Workbook

Sheet Summary
A1: =Data!$Q$2&" ("&Data!$Q$4&": "&Data!$Q$3&") — Equity Research Summary"
A2: ="Report date "&TEXT(Data!$Q$5,"d-mmm-yyyy")&" · Price $ per share · Financials $ in billions · Fiscal year ends "&Data!$Q$6
A4: VERDICT (MODEL VIEW) | B4: SHARE PRICE | E4: BASE-CASE FAIR VALUE | F4: FAIR-VALUE RANGE (BEAR – BULL)
A5: =IF(Scenarios!B14<-0.15,"Priced above model value",IF(Scenarios!B14>0.15,"Priced below model value","Near model value")) | B5: =DCF!B5 | E5: =Scenarios!C11 | F5: =TEXT(Scenarios!B11,"$0")&" – "&TEXT(Scenarios!D11,"$0")
A6: =IF(Scenarios!D12>0,"Only the bull case clears today's price",IF(Scenarios!B12>0,"Even the bear case is above the price","No scenario reaches today's price")) | B6: ="52-wk "&TEXT(Scenarios!B43,"$0")&"–"&TEXT(Scenarios!B44,"$0") | E6: =TEXT(Scenarios!C12,"+0%;-0%")&" vs price · prob-weighted "&TEXT(Scenarios!B13,"$0") | F6: ="Price needs "&IFERROR(TEXT(DCF!B82,"0%"),"n/a")&" op. margin (today "&TEXT(DCF!B39,"0%")&")"
A8: Market snapshot | E8: Intrinsic value (DCF)
A9: Share price | B9: =IFERROR(DCF!B5,"n/a") | F9: Bear | G9: Base | H9: Bull
A10: Market capitalisation ($B) | B10: =IFERROR(Multiples!B7,"n/a") | E10: Fair value / share | F10: =Scenarios!B11 | G10: =Scenarios!C11 | H10: =Scenarios!D11
A11: Enterprise value ($B) | B11: =IFERROR(Multiples!B9,"n/a") | E11: vs current price | F11: =Scenarios!B12 | G11: =Scenarios!C12 | H11: =Scenarios!D12
A12: 52-week low | B12: =IFERROR(Risk!B30,"n/a") | E12: Scenario weight | F12: =Scenarios!B10 | G12: =Scenarios!C10 | H12: =Scenarios!D10
A13: 52-week high | B13: =IFERROR(Risk!B29,"n/a") | E13: Probability-weighted value | F13: =Scenarios!B13
A14: =TEXT(Data!A1256,"yyyy")&" YTD total return" | B14: =Risk!C43 | E14: Upside / (downside) | F14: =Scenarios!B14
A15: Dividend yield | B15: =IFERROR(Multiples!B11,"n/a")
A16: ="Net cash ($B, "&TEXT(Financials!E16,"d-mmm-yy")&")" | B16: =IFERROR(Financials!C39,"n/a") | E16: What is the market pricing in? (reverse DCF)
E17: Implied year-1 revenue growth | F17: =DCF!B79
A18: Valuation multiples | E18: Implied 10-yr revenue CAGR | F18: =DCF!B80
B19: =IFERROR(Financials!K5,"n/a") | C19: TTM | E19: ="Actual 5-yr CAGR ("&Financials!F5&"–"&Financials!K5&")" | F19: =DCF!B83
A20: P/E (FY GAAP · TTM excl. gains) | B20: =IFERROR(Multiples!B15,"n/a") | C20: =IFERROR(Multiples!C16,"n/a") | E20: Implied long-run operating margin | F20: =DCF!B82 | G20: ="vs today "&IFERROR(TEXT(DCF!B39,"0%"),"n/a")&IFERROR(" · peers "&TEXT(MEDIAN(Peers!H7:H10),"0%"),"")
A21: Price / Sales | B21: =IFERROR(Multiples!B18,"n/a") | C21: =IFERROR(Multiples!C18,"n/a")
A22: EV / EBITDA | B22: =IFERROR(Multiples!B19,"n/a") | C22: =IFERROR(Multiples!C19,"n/a") | E22: Analyst view
A23: FCF yield | B23: =IFERROR(Multiples!B21,"n/a") | C23: =IFERROR(Multiples!C21,"n/a") | E23: ="At "&TEXT(B9,"$0")&", "&Data!$Q$2&IF(N(C20)>0," trades at "&TEXT(C20,"0.0x")&" trailing earnings"&IF(Financials!F19-Financials!F27>0.005," excluding one-off investment gains ("&TEXT(Multiples!C15,"0.0x")&" GAAP)","")&IFERROR(", vs a historical average of "&TEXT(Valuation_History!D17,"0.0x"),"")," has no trailing earnings to price")&". The base-case DCF ("&TEXT(G10,"$0")&", "&TEXT(G11,"+0%;-0%")&") assumes "&TEXT(DCF!B9,"0%")&" year-1 revenue growth fading to "&TEXT(DCF!B8,"0.0%")&", a "&TEXT(DCF!B10,"0%")&" operating margin, and capex "&IF(DCF!B19<DCF!B40,"easing","rising")&" from "&TEXT(DCF!B40,"0%")&" to "&TEXT(DCF!B19,"0%")&" of revenue. To justify the price the market needs "&IFERROR(TEXT(DCF!B79,"0%")&" year-1 growth","growth beyond the solvable range")&" or a "&IFERROR(TEXT(DCF!B82,"0%"),"n/a")&" long-run operating margin. "&IF(H11<0,"No scenario reaches the price.",IF(F11>0,"Even the bear case is above the price.","The price sits between the bear ("&TEXT(F10,"$0")&") and bull ("&TEXT(H10,"$0")&") cases; probability-weighted value "&TEXT(F13,"$0")&" ("&TEXT(F14,"+0%;-0%")&")."))
A24: FCF yield after stock comp | B24: =IFERROR(Multiples!B22,"n/a") | C24: =IFERROR(Multiples!C22,"n/a")
A26: Fundamentals
A27: ="Revenue, TTM to "&TEXT(Financials!E16,"mmm-yyyy")&" ($B)" | B27: =IFERROR(Financials!F17,"n/a")
A28: Revenue growth, last 3 qtrs avg y/y | B28: =IFERROR(DCF!B84,"n/a")
A29: Diluted EPS TTM ($) · GAAP / excl. gains | B29: =IFERROR(Financials!F19,"n/a") | C29: =IFERROR(Financials!F27,"n/a")
A30: Gross margin, TTM | B30: =IFERROR(Multiples!C28,"n/a") | C30: =IFERROR("to "&TEXT(Financials!E16,"d-mmm-yy"),"n/a")
A31: ="Free cash flow "&Financials!K5&" ($B)" | B31: =IFERROR(Financials!K10,"n/a") | E31: ="Stance: valuation view, no rating. Reference value = base case "&TEXT(Scenarios!C11,"$0")&" (probability-weighted "&TEXT(Scenarios!B13,"$0")&"). Not investment advice."
A32: ="9-year FCF CAGR ("&Financials!B5&"–"&Financials!K5&")" | B32: =IFERROR(Financials!L10,"n/a")
A34: Bull case, bear case, catalysts and risks
A35: Bull case | D35: Bear case
A36: ="• Revenue growth ran "&TEXT(MIN(Financials!C18:E18),"+0%;-0%")&" to "&TEXT(MAX(Financials!C18:E18),"+0%;-0%")&" y/y over the last three quarters"&IF(Data!$Q$9="","",", "&Data!$Q$9)&"." | D36: ="• "&Data!$Q$10
A37: ="• "&Data!$Q$8 | D37: =IF(Financials!C56>Financials!B56*1.005,"• Dilution: "&Data!$Q$11&" lifted the share count to "&TEXT(Financials!C56,"0.00")&"B from "&TEXT(Financials!B56,"0.00")&"B at "&Financials!K5&".",IF(Financials!C56<Financials!B56*0.995,"• Share count "&TEXT(Financials!C56,"0.00")&"B vs "&TEXT(Financials!B56,"0.00")&"B at "&Financials!K5&" — buybacks are shrinking the base.","• Share count steady at "&TEXT(Financials!C56,"0.00")&"B; "&Data!$Q$11&"."))
A38: =IFERROR("• Gross margin "&IF(Multiples!C28>=Multiples!B28,"widened","narrowed")&" to "&TEXT(Multiples!C28,"0.0%")&" TTM from "&TEXT(Multiples!B28,"0.0%")&" in "&Financials!K5&"; operating margin is "&TEXT(Financials!F23,"0.0%")&".","• Operating margin is "&TEXT(Financials!F23,"0.0%")&" over the last twelve months.") | D38: ="• Capex runs at "&TEXT(DCF!B40,"0%")&" of revenue"&IF(Data!$Q$12="",""," ("&Data!$Q$12&")")&"; the TTM FCF margin is "&TEXT(DCF!B38,"0.0%")&" vs "&TEXT(Financials!K11,"0.0%")&" in "&Financials!K5&"."
A39: ="• $"&TEXT(Financials!C35,"#,##0")&"B of cash and securities ("&IF(Financials!C39>=0,"net cash $"&TEXT(Financials!C39,"#,##0")&"B","net debt $"&TEXT(-Financials!C39,"#,##0")&"B")&")"&IF(Financials!C54>0," plus $"&TEXT(Financials!C54,"#,##0")&"B of private equity stakes not captured by FCF","")&"." | D39: ="• Stock-based pay of $"&TEXT(Financials!C44,"0.0")&"B ("&TEXT(Multiples!C35,"0%")&" of TTM FCF) is added back in reported free cash flow."
A41: Upcoming catalysts | D41: What drives the answer
A42: ="• "&Data!$Q$13 | D42: ="• The result rests on the long-run operating margin ("&TEXT(DCF!B10,"0.0%")&", "&DCF!B17&" anchor). Each +1 pt adds ~$"&TEXT((Scenarios!F31-Scenarios!E31)/((Scenarios!F28-Scenarios!E28)*100),"0")&" per share."
A43: ="• "&Data!$Q$14 | D43: ="• The terminal value implies "&TEXT(DCF!B96,"0.0x")&" EV/EBITDA — "&IF(DCF!B96<8,"conservative against the ~10–20x mature companies trade at, so the base case leans cautious.",IF(DCF!B96>25,"aggressive; the base case may be too generous.","within the normal range for mature companies."))
A44: ="• "&Data!$Q$15 | D44: ="• Model integrity: "&DCF!B109&" (DCF sanity checks, rows 91–109)."
A45: ="• "&Data!$Q$16 | D45: ="• Data: prices to "&TEXT(Data!A1256,"d-mmm-yyyy")&"; balance sheet "&TEXT(Financials!E16,"d-mmm-yyyy")&". "&IF(Financials!F19-Financials!F27>0.005,"TTM EPS excludes $"&TEXT(Financials!F19-Financials!F27,"0.00")&" of investment gains.","No investment-gain adjustment needed.")
A47: Contents — click to jump
A48: → Financials | B48: 10-year history + TTM | E48: → Risk | F48: Performance, drawdown, volatility
A49: → DCF | B49: Live model & reverse DCF | E49: → Catalysts_News | F49: Catalysts & filtered headlines
A50: → Scenarios | B50: Bear/base/bull & sensitivities | E50: → Methodology | F50: How every number is built
A51: → Multiples | B51: Valuation & quality ratios | E51: → Sources | F51: Every external figure, linked
A52: → Peers | B52: ="Valuation vs "&Data!$Q$7 | E52: → Capital_Returns | F52: Buybacks, dividends, SBC
A53: → Valuation_History | B53: P/E through the cycle | E53: → Segments | F53: Segments, SOTP & Street estimates
E54: → Valuation_Log | F54: Track record of every report
A56: What changed since the last report
A57: Metric | B57: Last report | C57: Now | F57: Change
A58: Report date | B58: =Valuation_Log!A6 | C58: =Valuation_Log!A5 | F58: =IF(N(B58)=0,"first report",TEXT(C58-B58,"0")&" days")
A59: Share price ($) | B59: =Valuation_Log!B6 | C59: =Valuation_Log!B5 | F59: =IFERROR(C59/B59-1,"–")
A60: Base-case fair value ($) | B60: =Valuation_Log!D6 | C60: =Valuation_Log!D5 | F60: =IFERROR(C60/B60-1,"–")
A61: Probability-weighted value ($) | B61: =Valuation_Log!F6 | C61: =Valuation_Log!F5 | F61: =IFERROR(C61/B61-1,"–")
A62: Verdict | B62: =IF(Valuation_Log!H6=Valuation_Log!H5,"Unchanged: "&Valuation_Log!H5,"CHANGED: "&Valuation_Log!H6&" → "&Valuation_Log!H5)
A63: =IF(ABS(N(F60))>=0.1,"⚠ Base case moved "&TEXT(F60,"+0%;-0%")&" since the last report — see Methodology (Model changes) for why.","")

Sheet Scenarios
A1: =Data!$Q$2&" ("&Data!$Q$3&") — Scenarios & Sensitivity"
A2: Every value on this tab is live: it recalculates from the DCF tab inputs · $ per share | G2: ← Back to Summary
A4: Bear / base / bull scenarios
B5: Bear | C5: Base | D5: Bull | F5: Bear / bull spread (±)
A6: Year-1 revenue growth (fades to terminal) | B6: =C6-$F6 | C6: =DCF!B9 | D6: =C6+$F6 | E6: Bear/bull = base ∓ the spread in column F (blue). Spreads scale with the company: the margin swing is a quarter of the base margin (1–5 points) and the growth swing 40% of base growth (2–6 points). Capex, D&A and timing follow the DCF tab. | F6: 0.02
A7: Long-run operating margin | B7: =C7-$F7 | C7: =DCF!B10 | D7: =C7+$F7 | F7: 0.02
A8: Discount rate (WACC) | B8: =C8+$F8 | C8: =DCF!B7 | D8: =C8-$F8 | F8: 0.01
A9: Terminal growth | B9: =C9-$F9 | C9: =DCF!B8 | D9: =C9+$F9 | F9: 0.005
A10: Scenario probability | B10: 0.25 | C10: 0.5 | D10: 0.25 | E10: =IF(ABS(SUM(B10:D10)-1)<0.0001,"✓ sums to 100%","⚠ must sum to 100%")
A11: Fair value per share ($) | B11: {=_xlfn.LET(_xlpm.gs,B6,_xlpm.om,B7,_xlpm.w,B8,_xlpm.tgr,B9,_xlpm.n,DCF!$B$11,_xlpm.lcx,DCF!$B$19,_xlpm.r0,DCF!$B$37,_xlpm.om0,DCF!$B$39,_xlpm.cx0,DCF!$B$40,_xlpm.da0,DCF!$B$41,_xlpm.dar,DCF!$B$20,_xlpm.tx,DCF!$B$31,_xlpm.sb,DCF!$B$43,_xlpm.nw,DCF!$B$21,_xlpm.gd,N(DCF!$B$22),_xlpm.nc,DCF!$B$47,_xlpm.shs,DCF!$B$6,_xlpm.m,DCF!$B$48,_xlpm.t,_xlfn.SEQUENCE(10),_xlpm.g,_xlpm.gs-(_xlpm.gs-_xlpm.tgr)*(_xlpm.t-1)/9,_xlpm.cum,MMULT(--(_xlpm.t>=TRANSPOSE(_xlpm.t)),LN(1+_xlpm.g)),_xlpm.rev,_xlpm.r0*EXP(_xlpm.cum),_xlpm.prv,_xlpm.r0*EXP(_xlpm.cum-LN(1+_xlpm.g)),_xlpm.lp,IF(_xlpm.t>=_xlpm.n,1,_xlpm.t/_xlpm.n),_xlpm.omt,_xlpm.om0+(_xlpm.om-_xlpm.om0)*_xlpm.lp,_xlpm.dat,_xlpm.da0+(_xlpm.lcx*_xlpm.dar-_xlpm.da0)*_xlpm.lp,_xlpm.cpx,IF((_xlpm.t=1)*(_xlpm.gd>0),_xlpm.gd/_xlpm.rev,_xlpm.cx0+(_xlpm.lcx-_xlpm.cx0)*_xlpm.lp),_xlpm.f,_xlpm.rev*(_xlpm.omt*(1-_xlpm.tx)+_xlpm.dat-_xlpm.cpx+_xlpm.sb)-_xlpm.nw*(_xlpm.rev-_xlpm.prv),_xlpm.pv,SUM(_xlpm.f/(1+_xlpm.w)^(_xlpm.t-0.5*_xlpm.m)),_xlpm.tv,INDEX(_xlpm.f,10)*(1+_xlpm.tgr)/(_xlpm.w-_xlpm.tgr)/(1+_xlpm.w)^10,(_xlpm.pv+_xlpm.tv+_xlpm.nc)/_xlpm.shs)} | C11: {=_xlfn.LET(_xlpm.gs,C6,_xlpm.om,C7,_xlpm.w,C8,_xlpm.tgr,C9,_xlpm.n,DCF!$B$11,_xlpm.lcx,DCF!$B$19,_xlpm.r0,DCF!$B$37,_xlpm.om0,DCF!$B$39,_xlpm.cx0,DCF!$B$40,_xlpm.da0,DCF!$B$41,_xlpm.dar,DCF!$B$20,_xlpm.tx,DCF!$B$31,_xlpm.sb,DCF!$B$43,_xlpm.nw,DCF!$B$21,_xlpm.gd,N(DCF!$B$22),_xlpm.nc,DCF!$B$47,_xlpm.shs,DCF!$B$6,_xlpm.m,DCF!$B$48,_xlpm.t,_xlfn.SEQUENCE(10),_xlpm.g,_xlpm.gs-(_xlpm.gs-_xlpm.tgr)*(_xlpm.t-1)/9,_xlpm.cum,MMULT(--(_xlpm.t>=TRANSPOSE(_xlpm.t)),LN(1+_xlpm.g)),_xlpm.rev,_xlpm.r0*EXP(_xlpm.cum),_xlpm.prv,_xlpm.r0*EXP(_xlpm.cum-LN(1+_xlpm.g)),_xlpm.lp,IF(_xlpm.t>=_xlpm.n,1,_xlpm.t/_xlpm.n),_xlpm.omt,_xlpm.om0+(_xlpm.om-_xlpm.om0)*_xlpm.lp,_xlpm.dat,_xlpm.da0+(_xlpm.lcx*_xlpm.dar-_xlpm.da0)*_xlpm.lp,_xlpm.cpx,IF((_xlpm.t=1)*(_xlpm.gd>0),_xlpm.gd/_xlpm.rev,_xlpm.cx0+(_xlpm.lcx-_xlpm.cx0)*_xlpm.lp),_xlpm.f,_xlpm.rev*(_xlpm.omt*(1-_xlpm.tx)+_xlpm.dat-_xlpm.cpx+_xlpm.sb)-_xlpm.nw*(_xlpm.rev-_xlpm.prv),_xlpm.pv,SUM(_xlpm.f/(1+_xlpm.w)^(_xlpm.t-0.5*_xlpm.m)),_xlpm.tv,INDEX(_xlpm.f,10)*(1+_xlpm.tgr)/(_xlpm.w-_xlpm.tgr)/(1+_xlpm.w)^10,(_xlpm.pv+_xlpm.tv+_xlpm.nc)/_xlpm.shs)} | D11: {=_xlfn.LET(_xlpm.gs,D6,_xlpm.om,D7,_xlpm.w,D8,_xlpm.tgr,D9,_xlpm.n,DCF!$B$11,_xlpm.lcx,DCF!$B$19,_xlpm.r0,DCF!$B$37,_xlpm.om0,DCF!$B$39,_xlpm.cx0,DCF!$B$40,_xlpm.da0,DCF!$B$41,_xlpm.dar,DCF!$B$20,_xlpm.tx,DCF!$B$31,_xlpm.sb,DCF!$B$43,_xlpm.nw,DCF!$B$21,_xlpm.gd,N(DCF!$B$22),_xlpm.nc,DCF!$B$47,_xlpm.shs,DCF!$B$6,_xlpm.m,DCF!$B$48,_xlpm.t,_xlfn.SEQUENCE(10),_xlpm.g,_xlpm.gs-(_xlpm.gs-_xlpm.tgr)*(_xlpm.t-1)/9,_xlpm.cum,MMULT(--(_xlpm.t>=TRANSPOSE(_xlpm.t)),LN(1+_xlpm.g)),_xlpm.rev,_xlpm.r0*EXP(_xlpm.cum),_xlpm.prv,_xlpm.r0*EXP(_xlpm.cum-LN(1+_xlpm.g)),_xlpm.lp,IF(_xlpm.t>=_xlpm.n,1,_xlpm.t/_xlpm.n),_xlpm.omt,_xlpm.om0+(_xlpm.om-_xlpm.om0)*_xlpm.lp,_xlpm.dat,_xlpm.da0+(_xlpm.lcx*_xlpm.dar-_xlpm.da0)*_xlpm.lp,_xlpm.cpx,IF((_xlpm.t=1)*(_xlpm.gd>0),_xlpm.gd/_xlpm.rev,_xlpm.cx0+(_xlpm.lcx-_xlpm.cx0)*_xlpm.lp),_xlpm.f,_xlpm.rev*(_xlpm.omt*(1-_xlpm.tx)+_xlpm.dat-_xlpm.cpx+_xlpm.sb)-_xlpm.nw*(_xlpm.rev-_xlpm.prv),_xlpm.pv,SUM(_xlpm.f/(1+_xlpm.w)^(_xlpm.t-0.5*_xlpm.m)),_xlpm.tv,INDEX(_xlpm.f,10)*(1+_xlpm.tgr)/(_xlpm.w-_xlpm.tgr)/(1+_xlpm.w)^10,(_xlpm.pv+_xlpm.tv+_xlpm.nc)/_xlpm.shs)}
A12: Upside / (downside) vs price | B12: =B11/DCF!$B$5-1 | C12: =C11/DCF!$B$5-1 | D12: =D11/DCF!$B$5-1
A13: Probability-weighted fair value ($) | B13: =SUMPRODUCT(B10:D10,B11:D11)
A14: Probability-weighted upside / (downside) | B14: =B13/DCF!B5-1
A15: What has to happen | B15: ="Growth slows: revenue "&TEXT(B6,"+0%;-0%")&" in year one, operating margin settles at "&TEXT(B7,"0%")&" (vs "&TEXT(DCF!$B$39,"0%")&" today) and a "&TEXT(B8,"0.0%")&" discount rate prices in more risk." | C15: ="Revenue "&TEXT(C6,"+0%;-0%")&" in year one, fading to "&TEXT(C9,"0.0%")&"; operating margin "&TEXT(C7,"0%")&" ("&DCF!$B$17&" anchor); capex "&IF(DCF!$B$19<DCF!$B$40,"falls","rises")&" from "&TEXT(DCF!$B$40,"0%")&" to "&TEXT(DCF!$B$19,"0%")&" of revenue by year "&DCF!$B$11&"." | D15: ="Momentum holds: revenue "&TEXT(D6,"+0%;-0%")&" in year one, operating margin expands to "&TEXT(D7,"0%")&" as investment pays off, with a "&TEXT(D8,"0.0%")&" WACC and "&TEXT(D9,"0.0%")&" terminal growth."
A19: Sensitivity 1 — fair value per share: WACC (rows) × terminal growth (columns), base-case growth and margin
B20: WACC ↓ · g → | C20: =DCF!$B$8+(-0.01) | D20: =DCF!$B$8+(-0.005) | E20: =DCF!$B$8+(0) | F20: =DCF!$B$8+(0.005) | G20: =DCF!$B$8+(0.01)
B21: =DCF!$B$7+(-0.01) | C21: {=_xlfn.LET(_xlpm.gs,DCF!$B$9,_xlpm.om,DCF!$B$10,_xlpm.w,$B21,_xlpm.tgr,C$20,_xlpm.n,DCF!$B$11,_xlpm.lcx,DCF!$B$19,_xlpm.r0,DCF!$B$37,_xlpm.om0,DCF!$B$39,_xlpm.cx0,DCF!$B$40,_xlpm.da0,DCF!$B$41,_xlpm.dar,DCF!$B$20,_xlpm.tx,DCF!$B$31,_xlpm.sb,DCF!$B$43,_xlpm.nw,DCF!$B$21,_xlpm.gd,N(DCF!$B$22),_xlpm.nc,DCF!$B$47,_xlpm.shs,DCF!$B$6,_xlpm.m,DCF!$B$48,_xlpm.t,_xlfn.SEQUENCE(10),_xlpm.g,_xlpm.gs-(_xlpm.gs-_xlpm.tgr)*(_xlpm.t-1)/9,_xlpm.cum,MMULT(--(_xlpm.t>=TRANSPOSE(_xlpm.t)),LN(1+_xlpm.g)),_xlpm.rev,_xlpm.r0*EXP(_xlpm.cum),_xlpm.prv,_xlpm.r0*EXP(_xlpm.cum-LN(1+_xlpm.g)),_xlpm.lp,IF(_xlpm.t>=_xlpm.n,1,_xlpm.t/_xlpm.n),_xlpm.omt,_xlpm.om0+(_xlpm.om-_xlpm.om0)*_xlpm.lp,_xlpm.dat,_xlpm.da0+(_xlpm.lcx*_xlpm.dar-_xlpm.da0)*_xlpm.lp,_xlpm.cpx,IF((_xlpm.t=1)*(_xlpm.gd>0),_xlpm.gd/_xlpm.rev,_xlpm.cx0+(_xlpm.lcx-_xlpm.cx0)*_xlpm.lp),_xlpm.f,_xlpm.rev*(_xlpm.omt*(1-_xlpm.tx)+_xlpm.dat-_xlpm.cpx+_xlpm.sb)-_xlpm.nw*(_xlpm.rev-_xlpm.prv),_xlpm.pv,SUM(_xlpm.f/(1+_xlpm.w)^(_xlpm.t-0.5*_xlpm.m)),_xlpm.tv,INDEX(_xlpm.f,10)*(1+_xlpm.tgr)/(_xlpm.w-_xlpm.tgr)/(1+_xlpm.w)^10,(_xlpm.pv+_xlpm.tv+_xlpm.nc)/_xlpm.shs)} | D21: {=_xlfn.LET(_xlpm.gs,DCF!$B$9,_xlpm.om,DCF!$B$10,_xlpm.w,$B21,_xlpm.tgr,D$20,_xlpm.n,DCF!$B$11,_xlpm.lcx,DCF!$B$19,_xlpm.r0,DCF!$B$37,_xlpm.om0,DCF!$B$39,_xlpm.cx0,DCF!$B$40,_xlpm.da0,DCF!$B$41,_xlpm.dar,DCF!$B$20,_xlpm.tx,DCF!$B$31,_xlpm.sb,DCF!$B$43,_xlpm.nw,DCF!$B$21,_xlpm.gd,N(DCF!$B$22),_xlpm.nc,DCF!$B$47,_xlpm.shs,DCF!$B$6,_xlpm.m,DCF!$B$48,_xlpm.t,_xlfn.SEQUENCE(10),_xlpm.g,_xlpm.gs-(_xlpm.gs-_xlpm.tgr)*(_xlpm.t-1)/9,_xlpm.cum,MMULT(--(_xlpm.t>=TRANSPOSE(_xlpm.t)),LN(1+_xlpm.g)),_xlpm.rev,_xlpm.r0*EXP(_xlpm.cum),_xlpm.prv,_xlpm.r0*EXP(_xlpm.cum-LN(1+_xlpm.g)),_xlpm.lp,IF(_xlpm.t>=_xlpm.n,1,_xlpm.t/_xlpm.n),_xlpm.omt,_xlpm.om0+(_xlpm.om-_xlpm.om0)*_xlpm.lp,_xlpm.dat,_xlpm.da0+(_xlpm.lcx*_xlpm.dar-_xlpm.da0)*_xlpm.lp,_xlpm.cpx,IF((_xlpm.t=1)*(_xlpm.gd>0),_xlpm.gd/_xlpm.rev,_xlpm.cx0+(_xlpm.lcx-_xlpm.cx0)*_xlpm.lp),_xlpm.f,_xlpm.rev*(_xlpm.omt*(1-_xlpm.tx)+_xlpm.dat-_xlpm.cpx+_xlpm.sb)-_xlpm.nw*(_xlpm.rev-_xlpm.prv),_xlpm.pv,SUM(_xlpm.f/(1+_xlpm.w)^(_xlpm.t-0.5*_xlpm.m)),_xlpm.tv,INDEX(_xlpm.f,10)*(1+_xlpm.tgr)/(_xlpm.w-_xlpm.tgr)/(1+_xlpm.w)^10,(_xlpm.pv+_xlpm.tv+_xlpm.nc)/_xlpm.shs)} | E21: {=_xlfn.LET(_xlpm.gs,DCF!$B$9,_xlpm.om,DCF!$B$10,_xlpm.w,$B21,_xlpm.tgr,E$20,_xlpm.n,DCF!$B$11,_xlpm.lcx,DCF!$B$19,_xlpm.r0,DCF!$B$37,_xlpm.om0,DCF!$B$39,_xlpm.cx0,DCF!$B$40,_xlpm.da0,DCF!$B$41,_xlpm.dar,DCF!$B$20,_xlpm.tx,DCF!$B$31,_xlpm.sb,DCF!$B$43,_xlpm.nw,DCF!$B$21,_xlpm.gd,N(DCF!$B$22),_xlpm.nc,DCF!$B$47,_xlpm.shs,DCF!$B$6,_xlpm.m,DCF!$B$48,_xlpm.t,_xlfn.SEQUENCE(10),_xlpm.g,_xlpm.gs-(_xlpm.gs-_xlpm.tgr)*(_xlpm.t-1)/9,_xlpm.cum,MMULT(--(_xlpm.t>=TRANSPOSE(_xlpm.t)),LN(1+_xlpm.g)),_xlpm.rev,_xlpm.r0*EXP(_xlpm.cum),_xlpm.prv,_xlpm.r0*EXP(_xlpm.cum-LN(1+_xlpm.g)),_xlpm.lp,IF(_xlpm.t>=_xlpm.n,1,_xlpm.t/_xlpm.n),_xlpm.omt,_xlpm.om0+(_xlpm.om-_xlpm.om0)*_xlpm.lp,_xlpm.dat,_xlpm.da0+(_xlpm.lcx*_xlpm.dar-_xlpm.da0)*_xlpm.lp,_xlpm.cpx,IF((_xlpm.t=1)*(_xlpm.gd>0),_xlpm.gd/_xlpm.rev,_xlpm.cx0+(_xlpm.lcx-_xlpm.cx0)*_xlpm.lp),_xlpm.f,_xlpm.rev*(_xlpm.omt*(1-_xlpm.tx)+_xlpm.dat-_xlpm.cpx+_xlpm.sb)-_xlpm.nw*(_xlpm.rev-_xlpm.prv),_xlpm.pv,SUM(_xlpm.f/(1+_xlpm.w)^(_xlpm.t-0.5*_xlpm.m)),_xlpm.tv,INDEX(_xlpm.f,10)*(1+_xlpm.tgr)/(_xlpm.w-_xlpm.tgr)/(1+_xlpm.w)^10,(_xlpm.pv+_xlpm.tv+_xlpm.nc)/_xlpm.shs)} | F21: {=_xlfn.LET(_xlpm.gs,DCF!$B$9,_xlpm.om,DCF!$B$10,_xlpm.w,$B21,_xlpm.tgr,F$20,_xlpm.n,DCF!$B$11,_xlpm.lcx,DCF!$B$19,_xlpm.r0,DCF!$B$37,_xlpm.om0,DCF!$B$39,_xlpm.cx0,DCF!$B$40,_xlpm.da0,DCF!$B$41,_xlpm.dar,DCF!$B$20,_xlpm.tx,DCF!$B$31,_xlpm.sb,DCF!$B$43,_xlpm.nw,DCF!$B$21,_xlpm.gd,N(DCF!$B$22),_xlpm.nc,DCF!$B$47,_xlpm.shs,DCF!$B$6,_xlpm.m,DCF!$B$48,_xlpm.t,_xlfn.SEQUENCE(10),_xlpm.g,_xlpm.gs-(_xlpm.gs-_xlpm.tgr)*(_xlpm.t-1)/9,_xlpm.cum,MMULT(--(_xlpm.t>=TRANSPOSE(_xlpm.t)),LN(1+_xlpm.g)),_xlpm.rev,_xlpm.r0*EXP(_xlpm.cum),_xlpm.prv,_xlpm.r0*EXP(_xlpm.cum-LN(1+_xlpm.g)),_xlpm.lp,IF(_xlpm.t>=_xlpm.n,1,_xlpm.t/_xlpm.n),_xlpm.omt,_xlpm.om0+(_xlpm.om-_xlpm.om0)*_xlpm.lp,_xlpm.dat,_xlpm.da0+(_xlpm.lcx*_xlpm.dar-_xlpm.da0)*_xlpm.lp,_xlpm.cpx,IF((_xlpm.t=1)*(_xlpm.gd>0),_xlpm.gd/_xlpm.rev,_xlpm.cx0+(_xlpm.lcx-_xlpm.cx0)*_xlpm.lp),_xlpm.f,_xlpm.rev*(_xlpm.omt*(1-_xlpm.tx)+_xlpm.dat-_xlpm.cpx+_xlpm.sb)-_xlpm.nw*(_xlpm.rev-_xlpm.prv),_xlpm.pv,SUM(_xlpm.f/(1+_xlpm.w)^(_xlpm.t-0.5*_xlpm.m)),_xlpm.tv,INDEX(_xlpm.f,10)*(1+_xlpm.tgr)/(_xlpm.w-_xlpm.tgr)/(1+_xlpm.w)^10,(_xlpm.pv+_xlpm.tv+_xlpm.nc)/_xlpm.shs)} | G21: {=_xlfn.LET(_xlpm.gs,DCF!$B$9,_xlpm.om,DCF!$B$10,_xlpm.w,$B21,_xlpm.tgr,G$20,_xlpm.n,DCF!$B$11,_xlpm.lcx,DCF!$B$19,_xlpm.r0,DCF!$B$37,_xlpm.om0,DCF!$B$39,_xlpm.cx0,DCF!$B$40,_xlpm.da0,DCF!$B$41,_xlpm.dar,DCF!$B$20,_xlpm.tx,DCF!$B$31,_xlpm.sb,DCF!$B$43,_xlpm.nw,DCF!$B$21,_xlpm.gd,N(DCF!$B$22),_xlpm.nc,DCF!$B$47,_xlpm.shs,DCF!$B$6,_xlpm.m,DCF!$B$48,_xlpm.t,_xlfn.SEQUENCE(10),_xlpm.g,_xlpm.gs-(_xlpm.gs-_xlpm.tgr)*(_xlpm.t-1)/9,_xlpm.cum,MMULT(--(_xlpm.t>=TRANSPOSE(_xlpm.t)),LN(1+_xlpm.g)),_xlpm.rev,_xlpm.r0*EXP(_xlpm.cum),_xlpm.prv,_xlpm.r0*EXP(_xlpm.cum-LN(1+_xlpm.g)),_xlpm.lp,IF(_xlpm.t>=_xlpm.n,1,_xlpm.t/_xlpm.n),_xlpm.omt,_xlpm.om0+(_xlpm.om-_xlpm.om0)*_xlpm.lp,_xlpm.dat,_xlpm.da0+(_xlpm.lcx*_xlpm.dar-_xlpm.da0)*_xlpm.lp,_xlpm.cpx,IF((_xlpm.t=1)*(_xlpm.gd>0),_xlpm.gd/_xlpm.rev,_xlpm.cx0+(_xlpm.lcx-_xlpm.cx0)*_xlpm.lp),_xlpm.f,_xlpm.rev*(_xlpm.omt*(1-_xlpm.tx)+_xlpm.dat-_xlpm.cpx+_xlpm.sb)-_xlpm.nw*(_xlpm.rev-_xlpm.prv),_xlpm.pv,SUM(_xlpm.f/(1+_xlpm.w)^(_xlpm.t-0.5*_xlpm.m)),_xlpm.tv,INDEX(_xlpm.f,10)*(1+_xlpm.tgr)/(_xlpm.w-_xlpm.tgr)/(1+_xlpm.w)^10,(_xlpm.pv+_xlpm.tv+_xlpm.nc)/_xlpm.shs)}
B22: =DCF!$B$7+(-0.005) | C22: {=_xlfn.LET(_xlpm.gs,DCF!$B$9,_xlpm.om,DCF!$B$10,_xlpm.w,$B22,_xlpm.tgr,C$20,_xlpm.n,DCF!$B$11,_xlpm.lcx,DCF!$B$19,_xlpm.r0,DCF!$B$37,_xlpm.om0,DCF!$B$39,_xlpm.cx0,DCF!$B$40,_xlpm.da0,DCF!$B$41,_xlpm.dar,DCF!$B$20,_xlpm.tx,DCF!$B$31,_xlpm.sb,DCF!$B$43,_xlpm.nw,DCF!$B$21,_xlpm.gd,N(DCF!$B$22),_xlpm.nc,DCF!$B$47,_xlpm.shs,DCF!$B$6,_xlpm.m,DCF!$B$48,_xlpm.t,_xlfn.SEQUENCE(10),_xlpm.g,_xlpm.gs-(_xlpm.gs-_xlpm.tgr)*(_xlpm.t-1)/9,_xlpm.cum,MMULT(--(_xlpm.t>=TRANSPOSE(_xlpm.t)),LN(1+_xlpm.g)),_xlpm.rev,_xlpm.r0*EXP(_xlpm.cum),_xlpm.prv,_xlpm.r0*EXP(_xlpm.cum-LN(1+_xlpm.g)),_xlpm.lp,IF(_xlpm.t>=_xlpm.n,1,_xlpm.t/_xlpm.n),_xlpm.omt,_xlpm.om0+(_xlpm.om-_xlpm.om0)*_xlpm.lp,_xlpm.dat,_xlpm.da0+(_xlpm.lcx*_xlpm.dar-_xlpm.da0)*_xlpm.lp,_xlpm.cpx,IF((_xlpm.t=1)*(_xlpm.gd>0),_xlpm.gd/_xlpm.rev,_xlpm.cx0+(_xlpm.lcx-_xlpm.cx0)*_xlpm.lp),_xlpm.f,_xlpm.rev*(_xlpm.omt*(1-_xlpm.tx)+_xlpm.dat-_xlpm.cpx+_xlpm.sb)-_xlpm.nw*(_xlpm.rev-_xlpm.prv),_xlpm.pv,SUM(_xlpm.f/(1+_xlpm.w)^(_xlpm.t-0.5*_xlpm.m)),_xlpm.tv,INDEX(_xlpm.f,10)*(1+_xlpm.tgr)/(_xlpm.w-_xlpm.tgr)/(1+_xlpm.w)^10,(_xlpm.pv+_xlpm.tv+_xlpm.nc)/_xlpm.shs)} | D22: {=_xlfn.LET(_xlpm.gs,DCF!$B$9,_xlpm.om,DCF!$B$10,_xlpm.w,$B22,_xlpm.tgr,D$20,_xlpm.n,DCF!$B$11,_xlpm.lcx,DCF!$B$19,_xlpm.r0,DCF!$B$37,_xlpm.om0,DCF!$B$39,_xlpm.cx0,DCF!$B$40,_xlpm.da0,DCF!$B$41,_xlpm.dar,DCF!$B$20,_xlpm.tx,DCF!$B$31,_xlpm.sb,DCF!$B$43,_xlpm.nw,DCF!$B$21,_xlpm.gd,N(DCF!$B$22),_xlpm.nc,DCF!$B$47,_xlpm.shs,DCF!$B$6,_xlpm.m,DCF!$B$48,_xlpm.t,_xlfn.SEQUENCE(10),_xlpm.g,_xlpm.gs-(_xlpm.gs-_xlpm.tgr)*(_xlpm.t-1)/9,_xlpm.cum,MMULT(--(_xlpm.t>=TRANSPOSE(_xlpm.t)),LN(1+_xlpm.g)),_xlpm.rev,_xlpm.r0*EXP(_xlpm.cum),_xlpm.prv,_xlpm.r0*EXP(_xlpm.cum-LN(1+_xlpm.g)),_xlpm.lp,IF(_xlpm.t>=_xlpm.n,1,_xlpm.t/_xlpm.n),_xlpm.omt,_xlpm.om0+(_xlpm.om-_xlpm.om0)*_xlpm.lp,_xlpm.dat,_xlpm.da0+(_xlpm.lcx*_xlpm.dar-_xlpm.da0)*_xlpm.lp,_xlpm.cpx,IF((_xlpm.t=1)*(_xlpm.gd>0),_xlpm.gd/_xlpm.rev,_xlpm.cx0+(_xlpm.lcx-_xlpm.cx0)*_xlpm.lp),_xlpm.f,_xlpm.rev*(_xlpm.omt*(1-_xlpm.tx)+_xlpm.dat-_xlpm.cpx+_xlpm.sb)-_xlpm.nw*(_xlpm.rev-_xlpm.prv),_xlpm.pv,SUM(_xlpm.f/(1+_xlpm.w)^(_xlpm.t-0.5*_xlpm.m)),_xlpm.tv,INDEX(_xlpm.f,10)*(1+_xlpm.tgr)/(_xlpm.w-_xlpm.tgr)/(1+_xlpm.w)^10,(_xlpm.pv+_xlpm.tv+_xlpm.nc)/_xlpm.shs)} | E22: {=_xlfn.LET(_xlpm.gs,DCF!$B$9,_xlpm.om,DCF!$B$10,_xlpm.w,$B22,_xlpm.tgr,E$20,_xlpm.n,DCF!$B$11,_xlpm.lcx,DCF!$B$19,_xlpm.r0,DCF!$B$37,_xlpm.om0,DCF!$B$39,_xlpm.cx0,DCF!$B$40,_xlpm.da0,DCF!$B$41,_xlpm.dar,DCF!$B$20,_xlpm.tx,DCF!$B$31,_xlpm.sb,DCF!$B$43,_xlpm.nw,DCF!$B$21,_xlpm.gd,N(DCF!$B$22),_xlpm.nc,DCF!$B$47,_xlpm.shs,DCF!$B$6,_xlpm.m,DCF!$B$48,_xlpm.t,_xlfn.SEQUENCE(10),_xlpm.g,_xlpm.gs-(_xlpm.gs-_xlpm.tgr)*(_xlpm.t-1)/9,_xlpm.cum,MMULT(--(_xlpm.t>=TRANSPOSE(_xlpm.t)),LN(1+_xlpm.g)),_xlpm.rev,_xlpm.r0*EXP(_xlpm.cum),_xlpm.prv,_xlpm.r0*EXP(_xlpm.cum-LN(1+_xlpm.g)),_xlpm.lp,IF(_xlpm.t>=_xlpm.n,1,_xlpm.t/_xlpm.n),_xlpm.omt,_xlpm.om0+(_xlpm.om-_xlpm.om0)*_xlpm.lp,_xlpm.dat,_xlpm.da0+(_xlpm.lcx*_xlpm.dar-_xlpm.da0)*_xlpm.lp,_xlpm.cpx,IF((_xlpm.t=1)*(_xlpm.gd>0),_xlpm.gd/_xlpm.rev,_xlpm.cx0+(_xlpm.lcx-_xlpm.cx0)*_xlpm.lp),_xlpm.f,_xlpm.rev*(_xlpm.omt*(1-_xlpm.tx)+_xlpm.dat-_xlpm.cpx+_xlpm.sb)-_xlpm.nw*(_xlpm.rev-_xlpm.prv),_xlpm.pv,SUM(_xlpm.f/(1+_xlpm.w)^(_xlpm.t-0.5*_xlpm.m)),_xlpm.tv,INDEX(_xlpm.f,10)*(1+_xlpm.tgr)/(_xlpm.w-_xlpm.tgr)/(1+_xlpm.w)^10,(_xlpm.pv+_xlpm.tv+_xlpm.nc)/_xlpm.shs)} | F22: {=_xlfn.LET(_xlpm.gs,DCF!$B$9,_xlpm.om,DCF!$B$10,_xlpm.w,$B22,_xlpm.tgr,F$20,_xlpm.n,DCF!$B$11,_xlpm.lcx,DCF!$B$19,_xlpm.r0,DCF!$B$37,_xlpm.om0,DCF!$B$39,_xlpm.cx0,DCF!$B$40,_xlpm.da0,DCF!$B$41,_xlpm.dar,DCF!$B$20,_xlpm.tx,DCF!$B$31,_xlpm.sb,DCF!$B$43,_xlpm.nw,DCF!$B$21,_xlpm.gd,N(DCF!$B$22),_xlpm.nc,DCF!$B$47,_xlpm.shs,DCF!$B$6,_xlpm.m,DCF!$B$48,_xlpm.t,_xlfn.SEQUENCE(10),_xlpm.g,_xlpm.gs-(_xlpm.gs-_xlpm.tgr)*(_xlpm.t-1)/9,_xlpm.cum,MMULT(--(_xlpm.t>=TRANSPOSE(_xlpm.t)),LN(1+_xlpm.g)),_xlpm.rev,_xlpm.r0*EXP(_xlpm.cum),_xlpm.prv,_xlpm.r0*EXP(_xlpm.cum-LN(1+_xlpm.g)),_xlpm.lp,IF(_xlpm.t>=_xlpm.n,1,_xlpm.t/_xlpm.n),_xlpm.omt,_xlpm.om0+(_xlpm.om-_xlpm.om0)*_xlpm.lp,_xlpm.dat,_xlpm.da0+(_xlpm.lcx*_xlpm.dar-_xlpm.da0)*_xlpm.lp,_xlpm.cpx,IF((_xlpm.t=1)*(_xlpm.gd>0),_xlpm.gd/_xlpm.rev,_xlpm.cx0+(_xlpm.lcx-_xlpm.cx0)*_xlpm.lp),_xlpm.f,_xlpm.rev*(_xlpm.omt*(1-_xlpm.tx)+_xlpm.dat-_xlpm.cpx+_xlpm.sb)-_xlpm.nw*(_xlpm.rev-_xlpm.prv),_xlpm.pv,SUM(_xlpm.f/(1+_xlpm.w)^(_xlpm.t-0.5*_xlpm.m)),_xlpm.tv,INDEX(_xlpm.f,10)*(1+_xlpm.tgr)/(_xlpm.w-_xlpm.tgr)/(1+_xlpm.w)^10,(_xlpm.pv+_xlpm.tv+_xlpm.nc)/_xlpm.shs)} | G22: {=_xlfn.LET(_xlpm.gs,DCF!$B$9,_xlpm.om,DCF!$B$10,_xlpm.w,$B22,_xlpm.tgr,G$20,_xlpm.n,DCF!$B$11,_xlpm.lcx,DCF!$B$19,_xlpm.r0,DCF!$B$37,_xlpm.om0,DCF!$B$39,_xlpm.cx0,DCF!$B$40,_xlpm.da0,DCF!$B$41,_xlpm.dar,DCF!$B$20,_xlpm.tx,DCF!$B$31,_xlpm.sb,DCF!$B$43,_xlpm.nw,DCF!$B$21,_xlpm.gd,N(DCF!$B$22),_xlpm.nc,DCF!$B$47,_xlpm.shs,DCF!$B$6,_xlpm.m,DCF!$B$48,_xlpm.t,_xlfn.SEQUENCE(10),_xlpm.g,_xlpm.gs-(_xlpm.gs-_xlpm.tgr)*(_xlpm.t-1)/9,_xlpm.cum,MMULT(--(_xlpm.t>=TRANSPOSE(_xlpm.t)),LN(1+_xlpm.g)),_xlpm.rev,_xlpm.r0*EXP(_xlpm.cum),_xlpm.prv,_xlpm.r0*EXP(_xlpm.cum-LN(1+_xlpm.g)),_xlpm.lp,IF(_xlpm.t>=_xlpm.n,1,_xlpm.t/_xlpm.n),_xlpm.omt,_xlpm.om0+(_xlpm.om-_xlpm.om0)*_xlpm.lp,_xlpm.dat,_xlpm.da0+(_xlpm.lcx*_xlpm.dar-_xlpm.da0)*_xlpm.lp,_xlpm.cpx,IF((_xlpm.t=1)*(_xlpm.gd>0),_xlpm.gd/_xlpm.rev,_xlpm.cx0+(_xlpm.lcx-_xlpm.cx0)*_xlpm.lp),_xlpm.f,_xlpm.rev*(_xlpm.omt*(1-_xlpm.tx)+_xlpm.dat-_xlpm.cpx+_xlpm.sb)-_xlpm.nw*(_xlpm.rev-_xlpm.prv),_xlpm.pv,SUM(_xlpm.f/(1+_xlpm.w)^(_xlpm.t-0.5*_xlpm.m)),_xlpm.tv,INDEX(_xlpm.f,10)*(1+_xlpm.tgr)/(_xlpm.w-_xlpm.tgr)/(1+_xlpm.w)^10,(_xlpm.pv+_xlpm.tv+_xlpm.nc)/_xlpm.shs)}
B23: =DCF!$B$7+(0) | C23: {=_xlfn.LET(_xlpm.gs,DCF!$B$9,_xlpm.om,DCF!$B$10,_xlpm.w,$B23,_xlpm.tgr,C$20,_xlpm.n,DCF!$B$11,_xlpm.lcx,DCF!$B$19,_xlpm.r0,DCF!$B$37,_xlpm.om0,DCF!$B$39,_xlpm.cx0,DCF!$B$40,_xlpm.da0,DCF!$B$41,_xlpm.dar,DCF!$B$20,_xlpm.tx,DCF!$B$31,_xlpm.sb,DCF!$B$43,_xlpm.nw,DCF!$B$21,_xlpm.gd,N(DCF!$B$22),_xlpm.nc,DCF!$B$47,_xlpm.shs,DCF!$B$6,_xlpm.m,DCF!$B$48,_xlpm.t,_xlfn.SEQUENCE(10),_xlpm.g,_xlpm.gs-(_xlpm.gs-_xlpm.tgr)*(_xlpm.t-1)/9,_xlpm.cum,MMULT(--(_xlpm.t>=TRANSPOSE(_xlpm.t)),LN(1+_xlpm.g)),_xlpm.rev,_xlpm.r0*EXP(_xlpm.cum),_xlpm.prv,_xlpm.r0*EXP(_xlpm.cum-LN(1+_xlpm.g)),_xlpm.lp,IF(_xlpm.t>=_xlpm.n,1,_xlpm.t/_xlpm.n),_xlpm.omt,_xlpm.om0+(_xlpm.om-_xlpm.om0)*_xlpm.lp,_xlpm.dat,_xlpm.da0+(_xlpm.lcx*_xlpm.dar-_xlpm.da0)*_xlpm.lp,_xlpm.cpx,IF((_xlpm.t=1)*(_xlpm.gd>0),_xlpm.gd/_xlpm.rev,_xlpm.cx0+(_xlpm.lcx-_xlpm.cx0)*_xlpm.lp),_xlpm.f,_xlpm.rev*(_xlpm.omt*(1-_xlpm.tx)+_xlpm.dat-_xlpm.cpx+_xlpm.sb)-_xlpm.nw*(_xlpm.rev-_xlpm.prv),_xlpm.pv,SUM(_xlpm.f/(1+_xlpm.w)^(_xlpm.t-0.5*_xlpm.m)),_xlpm.tv,INDEX(_xlpm.f,10)*(1+_xlpm.tgr)/(_xlpm.w-_xlpm.tgr)/(1+_xlpm.w)^10,(_xlpm.pv+_xlpm.tv+_xlpm.nc)/_xlpm.shs)} | D23: {=_xlfn.LET(_xlpm.gs,DCF!$B$9,_xlpm.om,DCF!$B$10,_xlpm.w,$B23,_xlpm.tgr,D$20,_xlpm.n,DCF!$B$11,_xlpm.lcx,DCF!$B$19,_xlpm.r0,DCF!$B$37,_xlpm.om0,DCF!$B$39,_xlpm.cx0,DCF!$B$40,_xlpm.da0,DCF!$B$41,_xlpm.dar,DCF!$B$20,_xlpm.tx,DCF!$B$31,_xlpm.sb,DCF!$B$43,_xlpm.nw,DCF!$B$21,_xlpm.gd,N(DCF!$B$22),_xlpm.nc,DCF!$B$47,_xlpm.shs,DCF!$B$6,_xlpm.m,DCF!$B$48,_xlpm.t,_xlfn.SEQUENCE(10),_xlpm.g,_xlpm.gs-(_xlpm.gs-_xlpm.tgr)*(_xlpm.t-1)/9,_xlpm.cum,MMULT(--(_xlpm.t>=TRANSPOSE(_xlpm.t)),LN(1+_xlpm.g)),_xlpm.rev,_xlpm.r0*EXP(_xlpm.cum),_xlpm.prv,_xlpm.r0*EXP(_xlpm.cum-LN(1+_xlpm.g)),_xlpm.lp,IF(_xlpm.t>=_xlpm.n,1,_xlpm.t/_xlpm.n),_xlpm.omt,_xlpm.om0+(_xlpm.om-_xlpm.om0)*_xlpm.lp,_xlpm.dat,_xlpm.da0+(_xlpm.lcx*_xlpm.dar-_xlpm.da0)*_xlpm.lp,_xlpm.cpx,IF((_xlpm.t=1)*(_xlpm.gd>0),_xlpm.gd/_xlpm.rev,_xlpm.cx0+(_xlpm.lcx-_xlpm.cx0)*_xlpm.lp),_xlpm.f,_xlpm.rev*(_xlpm.omt*(1-_xlpm.tx)+_xlpm.dat-_xlpm.cpx+_xlpm.sb)-_xlpm.nw*(_xlpm.rev-_xlpm.prv),_xlpm.pv,SUM(_xlpm.f/(1+_xlpm.w)^(_xlpm.t-0.5*_xlpm.m)),_xlpm.tv,INDEX(_xlpm.f,10)*(1+_xlpm.tgr)/(_xlpm.w-_xlpm.tgr)/(1+_xlpm.w)^10,(_xlpm.pv+_xlpm.tv+_xlpm.nc)/_xlpm.shs)} | E23: {=_xlfn.LET(_xlpm.gs,DCF!$B$9,_xlpm.om,DCF!$B$10,_xlpm.w,$B23,_xlpm.tgr,E$20,_xlpm.n,DCF!$B$11,_xlpm.lcx,DCF!$B$19,_xlpm.r0,DCF!$B$37,_xlpm.om0,DCF!$B$39,_xlpm.cx0,DCF!$B$40,_xlpm.da0,DCF!$B$41,_xlpm.dar,DCF!$B$20,_xlpm.tx,DCF!$B$31,_xlpm.sb,DCF!$B$43,_xlpm.nw,DCF!$B$21,_xlpm.gd,N(DCF!$B$22),_xlpm.nc,DCF!$B$47,_xlpm.shs,DCF!$B$6,_xlpm.m,DCF!$B$48,_xlpm.t,_xlfn.SEQUENCE(10),_xlpm.g,_xlpm.gs-(_xlpm.gs-_xlpm.tgr)*(_xlpm.t-1)/9,_xlpm.cum,MMULT(--(_xlpm.t>=TRANSPOSE(_xlpm.t)),LN(1+_xlpm.g)),_xlpm.rev,_xlpm.r0*EXP(_xlpm.cum),_xlpm.prv,_xlpm.r0*EXP(_xlpm.cum-LN(1+_xlpm.g)),_xlpm.lp,IF(_xlpm.t>=_xlpm.n,1,_xlpm.t/_xlpm.n),_xlpm.omt,_xlpm.om0+(_xlpm.om-_xlpm.om0)*_xlpm.lp,_xlpm.dat,_xlpm.da0+(_xlpm.lcx*_xlpm.dar-_xlpm.da0)*_xlpm.lp,_xlpm.cpx,IF((_xlpm.t=1)*(_xlpm.gd>0),_xlpm.gd/_xlpm.rev,_xlpm.cx0+(_xlpm.lcx-_xlpm.cx0)*_xlpm.lp),_xlpm.f,_xlpm.rev*(_xlpm.omt*(1-_xlpm.tx)+_xlpm.dat-_xlpm.cpx+_xlpm.sb)-_xlpm.nw*(_xlpm.rev-_xlpm.prv),_xlpm.pv,SUM(_xlpm.f/(1+_xlpm.w)^(_xlpm.t-0.5*_xlpm.m)),_xlpm.tv,INDEX(_xlpm.f,10)*(1+_xlpm.tgr)/(_xlpm.w-_xlpm.tgr)/(1+_xlpm.w)^10,(_xlpm.pv+_xlpm.tv+_xlpm.nc)/_xlpm.shs)} | F23: {=_xlfn.LET(_xlpm.gs,DCF!$B$9,_xlpm.om,DCF!$B$10,_xlpm.w,$B23,_xlpm.tgr,F$20,_xlpm.n,DCF!$B$11,_xlpm.lcx,DCF!$B$19,_xlpm.r0,DCF!$B$37,_xlpm.om0,DCF!$B$39,_xlpm.cx0,DCF!$B$40,_xlpm.da0,DCF!$B$41,_xlpm.dar,DCF!$B$20,_xlpm.tx,DCF!$B$31,_xlpm.sb,DCF!$B$43,_xlpm.nw,DCF!$B$21,_xlpm.gd,N(DCF!$B$22),_xlpm.nc,DCF!$B$47,_xlpm.shs,DCF!$B$6,_xlpm.m,DCF!$B$48,_xlpm.t,_xlfn.SEQUENCE(10),_xlpm.g,_xlpm.gs-(_xlpm.gs-_xlpm.tgr)*(_xlpm.t-1)/9,_xlpm.cum,MMULT(--(_xlpm.t>=TRANSPOSE(_xlpm.t)),LN(1+_xlpm.g)),_xlpm.rev,_xlpm.r0*EXP(_xlpm.cum),_xlpm.prv,_xlpm.r0*EXP(_xlpm.cum-LN(1+_xlpm.g)),_xlpm.lp,IF(_xlpm.t>=_xlpm.n,1,_xlpm.t/_xlpm.n),_xlpm.omt,_xlpm.om0+(_xlpm.om-_xlpm.om0)*_xlpm.lp,_xlpm.dat,_xlpm.da0+(_xlpm.lcx*_xlpm.dar-_xlpm.da0)*_xlpm.lp,_xlpm.cpx,IF((_xlpm.t=1)*(_xlpm.gd>0),_xlpm.gd/_xlpm.rev,_xlpm.cx0+(_xlpm.lcx-_xlpm.cx0)*_xlpm.lp),_xlpm.f,_xlpm.rev*(_xlpm.omt*(1-_xlpm.tx)+_xlpm.dat-_xlpm.cpx+_xlpm.sb)-_xlpm.nw*(_xlpm.rev-_xlpm.prv),_xlpm.pv,SUM(_xlpm.f/(1+_xlpm.w)^(_xlpm.t-0.5*_xlpm.m)),_xlpm.tv,INDEX(_xlpm.f,10)*(1+_xlpm.tgr)/(_xlpm.w-_xlpm.tgr)/(1+_xlpm.w)^10,(_xlpm.pv+_xlpm.tv+_xlpm.nc)/_xlpm.shs)} | G23: {=_xlfn.LET(_xlpm.gs,DCF!$B$9,_xlpm.om,DCF!$B$10,_xlpm.w,$B23,_xlpm.tgr,G$20,_xlpm.n,DCF!$B$11,_xlpm.lcx,DCF!$B$19,_xlpm.r0,DCF!$B$37,_xlpm.om0,DCF!$B$39,_xlpm.cx0,DCF!$B$40,_xlpm.da0,DCF!$B$41,_xlpm.dar,DCF!$B$20,_xlpm.tx,DCF!$B$31,_xlpm.sb,DCF!$B$43,_xlpm.nw,DCF!$B$21,_xlpm.gd,N(DCF!$B$22),_xlpm.nc,DCF!$B$47,_xlpm.shs,DCF!$B$6,_xlpm.m,DCF!$B$48,_xlpm.t,_xlfn.SEQUENCE(10),_xlpm.g,_xlpm.gs-(_xlpm.gs-_xlpm.tgr)*(_xlpm.t-1)/9,_xlpm.cum,MMULT(--(_xlpm.t>=TRANSPOSE(_xlpm.t)),LN(1+_xlpm.g)),_xlpm.rev,_xlpm.r0*EXP(_xlpm.cum),_xlpm.prv,_xlpm.r0*EXP(_xlpm.cum-LN(1+_xlpm.g)),_xlpm.lp,IF(_xlpm.t>=_xlpm.n,1,_xlpm.t/_xlpm.n),_xlpm.omt,_xlpm.om0+(_xlpm.om-_xlpm.om0)*_xlpm.lp,_xlpm.dat,_xlpm.da0+(_xlpm.lcx*_xlpm.dar-_xlpm.da0)*_xlpm.lp,_xlpm.cpx,IF((_xlpm.t=1)*(_xlpm.gd>0),_xlpm.gd/_xlpm.rev,_xlpm.cx0+(_xlpm.lcx-_xlpm.cx0)*_xlpm.lp),_xlpm.f,_xlpm.rev*(_xlpm.omt*(1-_xlpm.tx)+_xlpm.dat-_xlpm.cpx+_xlpm.sb)-_xlpm.nw*(_xlpm.rev-_xlpm.prv),_xlpm.pv,SUM(_xlpm.f/(1+_xlpm.w)^(_xlpm.t-0.5*_xlpm.m)),_xlpm.tv,INDEX(_xlpm.f,10)*(1+_xlpm.tgr)/(_xlpm.w-_xlpm.tgr)/(1+_xlpm.w)^10,(_xlpm.pv+_xlpm.tv+_xlpm.nc)/_xlpm.shs)}
B24: =DCF!$B$7+(0.005) | C24: {=_xlfn.LET(_xlpm.gs,DCF!$B$9,_xlpm.om,DCF!$B$10,_xlpm.w,$B24,_xlpm.tgr,C$20,_xlpm.n,DCF!$B$11,_xlpm.lcx,DCF!$B$19,_xlpm.r0,DCF!$B$37,_xlpm.om0,DCF!$B$39,_xlpm.cx0,DCF!$B$40,_xlpm.da0,DCF!$B$41,_xlpm.dar,DCF!$B$20,_xlpm.tx,DCF!$B$31,_xlpm.sb,DCF!$B$43,_xlpm.nw,DCF!$B$21,_xlpm.gd,N(DCF!$B$22),_xlpm.nc,DCF!$B$47,_xlpm.shs,DCF!$B$6,_xlpm.m,DCF!$B$48,_xlpm.t,_xlfn.SEQUENCE(10),_xlpm.g,_xlpm.gs-(_xlpm.gs-_xlpm.tgr)*(_xlpm.t-1)/9,_xlpm.cum,MMULT(--(_xlpm.t>=TRANSPOSE(_xlpm.t)),LN(1+_xlpm.g)),_xlpm.rev,_xlpm.r0*EXP(_xlpm.cum),_xlpm.prv,_xlpm.r0*EXP(_xlpm.cum-LN(1+_xlpm.g)),_xlpm.lp,IF(_xlpm.t>=_xlpm.n,1,_xlpm.t/_xlpm.n),_xlpm.omt,_xlpm.om0+(_xlpm.om-_xlpm.om0)*_xlpm.lp,_xlpm.dat,_xlpm.da0+(_xlpm.lcx*_xlpm.dar-_xlpm.da0)*_xlpm.lp,_xlpm.cpx,IF((_xlpm.t=1)*(_xlpm.gd>0),_xlpm.gd/_xlpm.rev,_xlpm.cx0+(_xlpm.lcx-_xlpm.cx0)*_xlpm.lp),_xlpm.f,_xlpm.rev*(_xlpm.omt*(1-_xlpm.tx)+_xlpm.dat-_xlpm.cpx+_xlpm.sb)-_xlpm.nw*(_xlpm.rev-_xlpm.prv),_xlpm.pv,SUM(_xlpm.f/(1+_xlpm.w)^(_xlpm.t-0.5*_xlpm.m)),_xlpm.tv,INDEX(_xlpm.f,10)*(1+_xlpm.tgr)/(_xlpm.w-_xlpm.tgr)/(1+_xlpm.w)^10,(_xlpm.pv+_xlpm.tv+_xlpm.nc)/_xlpm.shs)} | D24: {=_xlfn.LET(_xlpm.gs,DCF!$B$9,_xlpm.om,DCF!$B$10,_xlpm.w,$B24,_xlpm.tgr,D$20,_xlpm.n,DCF!$B$11,_xlpm.lcx,DCF!$B$19,_xlpm.r0,DCF!$B$37,_xlpm.om0,DCF!$B$39,_xlpm.cx0,DCF!$B$40,_xlpm.da0,DCF!$B$41,_xlpm.dar,DCF!$B$20,_xlpm.tx,DCF!$B$31,_xlpm.sb,DCF!$B$43,_xlpm.nw,DCF!$B$21,_xlpm.gd,N(DCF!$B$22),_xlpm.nc,DCF!$B$47,_xlpm.shs,DCF!$B$6,_xlpm.m,DCF!$B$48,_xlpm.t,_xlfn.SEQUENCE(10),_xlpm.g,_xlpm.gs-(_xlpm.gs-_xlpm.tgr)*(_xlpm.t-1)/9,_xlpm.cum,MMULT(--(_xlpm.t>=TRANSPOSE(_xlpm.t)),LN(1+_xlpm.g)),_xlpm.rev,_xlpm.r0*EXP(_xlpm.cum),_xlpm.prv,_xlpm.r0*EXP(_xlpm.cum-LN(1+_xlpm.g)),_xlpm.lp,IF(_xlpm.t>=_xlpm.n,1,_xlpm.t/_xlpm.n),_xlpm.omt,_xlpm.om0+(_xlpm.om-_xlpm.om0)*_xlpm.lp,_xlpm.dat,_xlpm.da0+(_xlpm.lcx*_xlpm.dar-_xlpm.da0)*_xlpm.lp,_xlpm.cpx,IF((_xlpm.t=1)*(_xlpm.gd>0),_xlpm.gd/_xlpm.rev,_xlpm.cx0+(_xlpm.lcx-_xlpm.cx0)*_xlpm.lp),_xlpm.f,_xlpm.rev*(_xlpm.omt*(1-_xlpm.tx)+_xlpm.dat-_xlpm.cpx+_xlpm.sb)-_xlpm.nw*(_xlpm.rev-_xlpm.prv),_xlpm.pv,SUM(_xlpm.f/(1+_xlpm.w)^(_xlpm.t-0.5*_xlpm.m)),_xlpm.tv,INDEX(_xlpm.f,10)*(1+_xlpm.tgr)/(_xlpm.w-_xlpm.tgr)/(1+_xlpm.w)^10,(_xlpm.pv+_xlpm.tv+_xlpm.nc)/_xlpm.shs)} | E24: {=_xlfn.LET(_xlpm.gs,DCF!$B$9,_xlpm.om,DCF!$B$10,_xlpm.w,$B24,_xlpm.tgr,E$20,_xlpm.n,DCF!$B$11,_xlpm.lcx,DCF!$B$19,_xlpm.r0,DCF!$B$37,_xlpm.om0,DCF!$B$39,_xlpm.cx0,DCF!$B$40,_xlpm.da0,DCF!$B$41,_xlpm.dar,DCF!$B$20,_xlpm.tx,DCF!$B$31,_xlpm.sb,DCF!$B$43,_xlpm.nw,DCF!$B$21,_xlpm.gd,N(DCF!$B$22),_xlpm.nc,DCF!$B$47,_xlpm.shs,DCF!$B$6,_xlpm.m,DCF!$B$48,_xlpm.t,_xlfn.SEQUENCE(10),_xlpm.g,_xlpm.gs-(_xlpm.gs-_xlpm.tgr)*(_xlpm.t-1)/9,_xlpm.cum,MMULT(--(_xlpm.t>=TRANSPOSE(_xlpm.t)),LN(1+_xlpm.g)),_xlpm.rev,_xlpm.r0*EXP(_xlpm.cum),_xlpm.prv,_xlpm.r0*EXP(_xlpm.cum-LN(1+_xlpm.g)),_xlpm.lp,IF(_xlpm.t>=_xlpm.n,1,_xlpm.t/_xlpm.n),_xlpm.omt,_xlpm.om0+(_xlpm.om-_xlpm.om0)*_xlpm.lp,_xlpm.dat,_xlpm.da0+(_xlpm.lcx*_xlpm.dar-_xlpm.da0)*_xlpm.lp,_xlpm.cpx,IF((_xlpm.t=1)*(_xlpm.gd>0),_xlpm.gd/_xlpm.rev,_xlpm.cx0+(_xlpm.lcx-_xlpm.cx0)*_xlpm.lp),_xlpm.f,_xlpm.rev*(_xlpm.omt*(1-_xlpm.tx)+_xlpm.dat-_xlpm.cpx+_xlpm.sb)-_xlpm.nw*(_xlpm.rev-_xlpm.prv),_xlpm.pv,SUM(_xlpm.f/(1+_xlpm.w)^(_xlpm.t-0.5*_xlpm.m)),_xlpm.tv,INDEX(_xlpm.f,10)*(1+_xlpm.tgr)/(_xlpm.w-_xlpm.tgr)/(1+_xlpm.w)^10,(_xlpm.pv+_xlpm.tv+_xlpm.nc)/_xlpm.shs)} | F24: {=_xlfn.LET(_xlpm.gs,DCF!$B$9,_xlpm.om,DCF!$B$10,_xlpm.w,$B24,_xlpm.tgr,F$20,_xlpm.n,DCF!$B$11,_xlpm.lcx,DCF!$B$19,_xlpm.r0,DCF!$B$37,_xlpm.om0,DCF!$B$39,_xlpm.cx0,DCF!$B$40,_xlpm.da0,DCF!$B$41,_xlpm.dar,DCF!$B$20,_xlpm.tx,DCF!$B$31,_xlpm.sb,DCF!$B$43,_xlpm.nw,DCF!$B$21,_xlpm.gd,N(DCF!$B$22),_xlpm.nc,DCF!$B$47,_xlpm.shs,DCF!$B$6,_xlpm.m,DCF!$B$48,_xlpm.t,_xlfn.SEQUENCE(10),_xlpm.g,_xlpm.gs-(_xlpm.gs-_xlpm.tgr)*(_xlpm.t-1)/9,_xlpm.cum,MMULT(--(_xlpm.t>=TRANSPOSE(_xlpm.t)),LN(1+_xlpm.g)),_xlpm.rev,_xlpm.r0*EXP(_xlpm.cum),_xlpm.prv,_xlpm.r0*EXP(_xlpm.cum-LN(1+_xlpm.g)),_xlpm.lp,IF(_xlpm.t>=_xlpm.n,1,_xlpm.t/_xlpm.n),_xlpm.omt,_xlpm.om0+(_xlpm.om-_xlpm.om0)*_xlpm.lp,_xlpm.dat,_xlpm.da0+(_xlpm.lcx*_xlpm.dar-_xlpm.da0)*_xlpm.lp,_xlpm.cpx,IF((_xlpm.t=1)*(_xlpm.gd>0),_xlpm.gd/_xlpm.rev,_xlpm.cx0+(_xlpm.lcx-_xlpm.cx0)*_xlpm.lp),_xlpm.f,_xlpm.rev*(_xlpm.omt*(1-_xlpm.tx)+_xlpm.dat-_xlpm.cpx+_xlpm.sb)-_xlpm.nw*(_xlpm.rev-_xlpm.prv),_xlpm.pv,SUM(_xlpm.f/(1+_xlpm.w)^(_xlpm.t-0.5*_xlpm.m)),_xlpm.tv,INDEX(_xlpm.f,10)*(1+_xlpm.tgr)/(_xlpm.w-_xlpm.tgr)/(1+_xlpm.w)^10,(_xlpm.pv+_xlpm.tv+_xlpm.nc)/_xlpm.shs)} | G24: {=_xlfn.LET(_xlpm.gs,DCF!$B$9,_xlpm.om,DCF!$B$10,_xlpm.w,$B24,_xlpm.tgr,G$20,_xlpm.n,DCF!$B$11,_xlpm.lcx,DCF!$B$19,_xlpm.r0,DCF!$B$37,_xlpm.om0,DCF!$B$39,_xlpm.cx0,DCF!$B$40,_xlpm.da0,DCF!$B$41,_xlpm.dar,DCF!$B$20,_xlpm.tx,DCF!$B$31,_xlpm.sb,DCF!$B$43,_xlpm.nw,DCF!$B$21,_xlpm.gd,N(DCF!$B$22),_xlpm.nc,DCF!$B$47,_xlpm.shs,DCF!$B$6,_xlpm.m,DCF!$B$48,_xlpm.t,_xlfn.SEQUENCE(10),_xlpm.g,_xlpm.gs-(_xlpm.gs-_xlpm.tgr)*(_xlpm.t-1)/9,_xlpm.cum,MMULT(--(_xlpm.t>=TRANSPOSE(_xlpm.t)),LN(1+_xlpm.g)),_xlpm.rev,_xlpm.r0*EXP(_xlpm.cum),_xlpm.prv,_xlpm.r0*EXP(_xlpm.cum-LN(1+_xlpm.g)),_xlpm.lp,IF(_xlpm.t>=_xlpm.n,1,_xlpm.t/_xlpm.n),_xlpm.omt,_xlpm.om0+(_xlpm.om-_xlpm.om0)*_xlpm.lp,_xlpm.dat,_xlpm.da0+(_xlpm.lcx*_xlpm.dar-_xlpm.da0)*_xlpm.lp,_xlpm.cpx,IF((_xlpm.t=1)*(_xlpm.gd>0),_xlpm.gd/_xlpm.rev,_xlpm.cx0+(_xlpm.lcx-_xlpm.cx0)*_xlpm.lp),_xlpm.f,_xlpm.rev*(_xlpm.omt*(1-_xlpm.tx)+_xlpm.dat-_xlpm.cpx+_xlpm.sb)-_xlpm.nw*(_xlpm.rev-_xlpm.prv),_xlpm.pv,SUM(_xlpm.f/(1+_xlpm.w)^(_xlpm.t-0.5*_xlpm.m)),_xlpm.tv,INDEX(_xlpm.f,10)*(1+_xlpm.tgr)/(_xlpm.w-_xlpm.tgr)/(1+_xlpm.w)^10,(_xlpm.pv+_xlpm.tv+_xlpm.nc)/_xlpm.shs)}
B25: =DCF!$B$7+(0.01) | C25: {=_xlfn.LET(_xlpm.gs,DCF!$B$9,_xlpm.om,DCF!$B$10,_xlpm.w,$B25,_xlpm.tgr,C$20,_xlpm.n,DCF!$B$11,_xlpm.lcx,DCF!$B$19,_xlpm.r0,DCF!$B$37,_xlpm.om0,DCF!$B$39,_xlpm.cx0,DCF!$B$40,_xlpm.da0,DCF!$B$41,_xlpm.dar,DCF!$B$20,_xlpm.tx,DCF!$B$31,_xlpm.sb,DCF!$B$43,_xlpm.nw,DCF!$B$21,_xlpm.gd,N(DCF!$B$22),_xlpm.nc,DCF!$B$47,_xlpm.shs,DCF!$B$6,_xlpm.m,DCF!$B$48,_xlpm.t,_xlfn.SEQUENCE(10),_xlpm.g,_xlpm.gs-(_xlpm.gs-_xlpm.tgr)*(_xlpm.t-1)/9,_xlpm.cum,MMULT(--(_xlpm.t>=TRANSPOSE(_xlpm.t)),LN(1+_xlpm.g)),_xlpm.rev,_xlpm.r0*EXP(_xlpm.cum),_xlpm.prv,_xlpm.r0*EXP(_xlpm.cum-LN(1+_xlpm.g)),_xlpm.lp,IF(_xlpm.t>=_xlpm.n,1,_xlpm.t/_xlpm.n),_xlpm.omt,_xlpm.om0+(_xlpm.om-_xlpm.om0)*_xlpm.lp,_xlpm.dat,_xlpm.da0+(_xlpm.lcx*_xlpm.dar-_xlpm.da0)*_xlpm.lp,_xlpm.cpx,IF((_xlpm.t=1)*(_xlpm.gd>0),_xlpm.gd/_xlpm.rev,_xlpm.cx0+(_xlpm.lcx-_xlpm.cx0)*_xlpm.lp),_xlpm.f,_xlpm.rev*(_xlpm.omt*(1-_xlpm.tx)+_xlpm.dat-_xlpm.cpx+_xlpm.sb)-_xlpm.nw*(_xlpm.rev-_xlpm.prv),_xlpm.pv,SUM(_xlpm.f/(1+_xlpm.w)^(_xlpm.t-0.5*_xlpm.m)),_xlpm.tv,INDEX(_xlpm.f,10)*(1+_xlpm.tgr)/(_xlpm.w-_xlpm.tgr)/(1+_xlpm.w)^10,(_xlpm.pv+_xlpm.tv+_xlpm.nc)/_xlpm.shs)} | D25: {=_xlfn.LET(_xlpm.gs,DCF!$B$9,_xlpm.om,DCF!$B$10,_xlpm.w,$B25,_xlpm.tgr,D$20,_xlpm.n,DCF!$B$11,_xlpm.lcx,DCF!$B$19,_xlpm.r0,DCF!$B$37,_xlpm.om0,DCF!$B$39,_xlpm.cx0,DCF!$B$40,_xlpm.da0,DCF!$B$41,_xlpm.dar,DCF!$B$20,_xlpm.tx,DCF!$B$31,_xlpm.sb,DCF!$B$43,_xlpm.nw,DCF!$B$21,_xlpm.gd,N(DCF!$B$22),_xlpm.nc,DCF!$B$47,_xlpm.shs,DCF!$B$6,_xlpm.m,DCF!$B$48,_xlpm.t,_xlfn.SEQUENCE(10),_xlpm.g,_xlpm.gs-(_xlpm.gs-_xlpm.tgr)*(_xlpm.t-1)/9,_xlpm.cum,MMULT(--(_xlpm.t>=TRANSPOSE(_xlpm.t)),LN(1+_xlpm.g)),_xlpm.rev,_xlpm.r0*EXP(_xlpm.cum),_xlpm.prv,_xlpm.r0*EXP(_xlpm.cum-LN(1+_xlpm.g)),_xlpm.lp,IF(_xlpm.t>=_xlpm.n,1,_xlpm.t/_xlpm.n),_xlpm.omt,_xlpm.om0+(_xlpm.om-_xlpm.om0)*_xlpm.lp,_xlpm.dat,_xlpm.da0+(_xlpm.lcx*_xlpm.dar-_xlpm.da0)*_xlpm.lp,_xlpm.cpx,IF((_xlpm.t=1)*(_xlpm.gd>0),_xlpm.gd/_xlpm.rev,_xlpm.cx0+(_xlpm.lcx-_xlpm.cx0)*_xlpm.lp),_xlpm.f,_xlpm.rev*(_xlpm.omt*(1-_xlpm.tx)+_xlpm.dat-_xlpm.cpx+_xlpm.sb)-_xlpm.nw*(_xlpm.rev-_xlpm.prv),_xlpm.pv,SUM(_xlpm.f/(1+_xlpm.w)^(_xlpm.t-0.5*_xlpm.m)),_xlpm.tv,INDEX(_xlpm.f,10)*(1+_xlpm.tgr)/(_xlpm.w-_xlpm.tgr)/(1+_xlpm.w)^10,(_xlpm.pv+_xlpm.tv+_xlpm.nc)/_xlpm.shs)} | E25: {=_xlfn.LET(_xlpm.gs,DCF!$B$9,_xlpm.om,DCF!$B$10,_xlpm.w,$B25,_xlpm.tgr,E$20,_xlpm.n,DCF!$B$11,_xlpm.lcx,DCF!$B$19,_xlpm.r0,DCF!$B$37,_xlpm.om0,DCF!$B$39,_xlpm.cx0,DCF!$B$40,_xlpm.da0,DCF!$B$41,_xlpm.dar,DCF!$B$20,_xlpm.tx,DCF!$B$31,_xlpm.sb,DCF!$B$43,_xlpm.nw,DCF!$B$21,_xlpm.gd,N(DCF!$B$22),_xlpm.nc,DCF!$B$47,_xlpm.shs,DCF!$B$6,_xlpm.m,DCF!$B$48,_xlpm.t,_xlfn.SEQUENCE(10),_xlpm.g,_xlpm.gs-(_xlpm.gs-_xlpm.tgr)*(_xlpm.t-1)/9,_xlpm.cum,MMULT(--(_xlpm.t>=TRANSPOSE(_xlpm.t)),LN(1+_xlpm.g)),_xlpm.rev,_xlpm.r0*EXP(_xlpm.cum),_xlpm.prv,_xlpm.r0*EXP(_xlpm.cum-LN(1+_xlpm.g)),_xlpm.lp,IF(_xlpm.t>=_xlpm.n,1,_xlpm.t/_xlpm.n),_xlpm.omt,_xlpm.om0+(_xlpm.om-_xlpm.om0)*_xlpm.lp,_xlpm.dat,_xlpm.da0+(_xlpm.lcx*_xlpm.dar-_xlpm.da0)*_xlpm.lp,_xlpm.cpx,IF((_xlpm.t=1)*(_xlpm.gd>0),_xlpm.gd/_xlpm.rev,_xlpm.cx0+(_xlpm.lcx-_xlpm.cx0)*_xlpm.lp),_xlpm.f,_xlpm.rev*(_xlpm.omt*(1-_xlpm.tx)+_xlpm.dat-_xlpm.cpx+_xlpm.sb)-_xlpm.nw*(_xlpm.rev-_xlpm.prv),_xlpm.pv,SUM(_xlpm.f/(1+_xlpm.w)^(_xlpm.t-0.5*_xlpm.m)),_xlpm.tv,INDEX(_xlpm.f,10)*(1+_xlpm.tgr)/(_xlpm.w-_xlpm.tgr)/(1+_xlpm.w)^10,(_xlpm.pv+_xlpm.tv+_xlpm.nc)/_xlpm.shs)} | F25: {=_xlfn.LET(_xlpm.gs,DCF!$B$9,_xlpm.om,DCF!$B$10,_xlpm.w,$B25,_xlpm.tgr,F$20,_xlpm.n,DCF!$B$11,_xlpm.lcx,DCF!$B$19,_xlpm.r0,DCF!$B$37,_xlpm.om0,DCF!$B$39,_xlpm.cx0,DCF!$B$40,_xlpm.da0,DCF!$B$41,_xlpm.dar,DCF!$B$20,_xlpm.tx,DCF!$B$31,_xlpm.sb,DCF!$B$43,_xlpm.nw,DCF!$B$21,_xlpm.gd,N(DCF!$B$22),_xlpm.nc,DCF!$B$47,_xlpm.shs,DCF!$B$6,_xlpm.m,DCF!$B$48,_xlpm.t,_xlfn.SEQUENCE(10),_xlpm.g,_xlpm.gs-(_xlpm.gs-_xlpm.tgr)*(_xlpm.t-1)/9,_xlpm.cum,MMULT(--(_xlpm.t>=TRANSPOSE(_xlpm.t)),LN(1+_xlpm.g)),_xlpm.rev,_xlpm.r0*EXP(_xlpm.cum),_xlpm.prv,_xlpm.r0*EXP(_xlpm.cum-LN(1+_xlpm.g)),_xlpm.lp,IF(_xlpm.t>=_xlpm.n,1,_xlpm.t/_xlpm.n),_xlpm.omt,_xlpm.om0+(_xlpm.om-_xlpm.om0)*_xlpm.lp,_xlpm.dat,_xlpm.da0+(_xlpm.lcx*_xlpm.dar-_xlpm.da0)*_xlpm.lp,_xlpm.cpx,IF((_xlpm.t=1)*(_xlpm.gd>0),_xlpm.gd/_xlpm.rev,_xlpm.cx0+(_xlpm.lcx-_xlpm.cx0)*_xlpm.lp),_xlpm.f,_xlpm.rev*(_xlpm.omt*(1-_xlpm.tx)+_xlpm.dat-_xlpm.cpx+_xlpm.sb)-_xlpm.nw*(_xlpm.rev-_xlpm.prv),_xlpm.pv,SUM(_xlpm.f/(1+_xlpm.w)^(_xlpm.t-0.5*_xlpm.m)),_xlpm.tv,INDEX(_xlpm.f,10)*(1+_xlpm.tgr)/(_xlpm.w-_xlpm.tgr)/(1+_xlpm.w)^10,(_xlpm.pv+_xlpm.tv+_xlpm.nc)/_xlpm.shs)} | G25: {=_xlfn.LET(_xlpm.gs,DCF!$B$9,_xlpm.om,DCF!$B$10,_xlpm.w,$B25,_xlpm.tgr,G$20,_xlpm.n,DCF!$B$11,_xlpm.lcx,DCF!$B$19,_xlpm.r0,DCF!$B$37,_xlpm.om0,DCF!$B$39,_xlpm.cx0,DCF!$B$40,_xlpm.da0,DCF!$B$41,_xlpm.dar,DCF!$B$20,_xlpm.tx,DCF!$B$31,_xlpm.sb,DCF!$B$43,_xlpm.nw,DCF!$B$21,_xlpm.gd,N(DCF!$B$22),_xlpm.nc,DCF!$B$47,_xlpm.shs,DCF!$B$6,_xlpm.m,DCF!$B$48,_xlpm.t,_xlfn.SEQUENCE(10),_xlpm.g,_xlpm.gs-(_xlpm.gs-_xlpm.tgr)*(_xlpm.t-1)/9,_xlpm.cum,MMULT(--(_xlpm.t>=TRANSPOSE(_xlpm.t)),LN(1+_xlpm.g)),_xlpm.rev,_xlpm.r0*EXP(_xlpm.cum),_xlpm.prv,_xlpm.r0*EXP(_xlpm.cum-LN(1+_xlpm.g)),_xlpm.lp,IF(_xlpm.t>=_xlpm.n,1,_xlpm.t/_xlpm.n),_xlpm.omt,_xlpm.om0+(_xlpm.om-_xlpm.om0)*_xlpm.lp,_xlpm.dat,_xlpm.da0+(_xlpm.lcx*_xlpm.dar-_xlpm.da0)*_xlpm.lp,_xlpm.cpx,IF((_xlpm.t=1)*(_xlpm.gd>0),_xlpm.gd/_xlpm.rev,_xlpm.cx0+(_xlpm.lcx-_xlpm.cx0)*_xlpm.lp),_xlpm.f,_xlpm.rev*(_xlpm.omt*(1-_xlpm.tx)+_xlpm.dat-_xlpm.cpx+_xlpm.sb)-_xlpm.nw*(_xlpm.rev-_xlpm.prv),_xlpm.pv,SUM(_xlpm.f/(1+_xlpm.w)^(_xlpm.t-0.5*_xlpm.m)),_xlpm.tv,INDEX(_xlpm.f,10)*(1+_xlpm.tgr)/(_xlpm.w-_xlpm.tgr)/(1+_xlpm.w)^10,(_xlpm.pv+_xlpm.tv+_xlpm.nc)/_xlpm.shs)}
A27: Sensitivity 2 — fair value per share: year-1 revenue growth (rows) × long-run operating margin (columns) | I27: Sensitivity 3 — long-run capex % of revenue (rows) × years to normalise (columns)
B28: Growth ↓ · margin → | C28: =DCF!$B$10+(-0.04) | D28: =DCF!$B$10+(-0.02) | E28: =DCF!$B$10+(0) | F28: =DCF!$B$10+(0.02) | G28: =DCF!$B$10+(0.04) | J28: Capex ↓ · years → | K28: =MAX(1,DCF!$B$11-2) | L28: =MAX(1,DCF!$B$11-1) | M28: =DCF!$B$11 | N28: =DCF!$B$11+1 | O28: =DCF!$B$11+2
B29: =DCF!$B$9+(-0.06) | C29: {=_xlfn.LET(_xlpm.gs,$B29,_xlpm.om,C$28,_xlpm.w,DCF!$B$7,_xlpm.tgr,DCF!$B$8,_xlpm.n,DCF!$B$11,_xlpm.lcx,DCF!$B$19,_xlpm.r0,DCF!$B$37,_xlpm.om0,DCF!$B$39,_xlpm.cx0,DCF!$B$40,_xlpm.da0,DCF!$B$41,_xlpm.dar,DCF!$B$20,_xlpm.tx,DCF!$B$31,_xlpm.sb,DCF!$B$43,_xlpm.nw,DCF!$B$21,_xlpm.gd,N(DCF!$B$22),_xlpm.nc,DCF!$B$47,_xlpm.shs,DCF!$B$6,_xlpm.m,DCF!$B$48,_xlpm.t,_xlfn.SEQUENCE(10),_xlpm.g,_xlpm.gs-(_xlpm.gs-_xlpm.tgr)*(_xlpm.t-1)/9,_xlpm.cum,MMULT(--(_xlpm.t>=TRANSPOSE(_xlpm.t)),LN(1+_xlpm.g)),_xlpm.rev,_xlpm.r0*EXP(_xlpm.cum),_xlpm.prv,_xlpm.r0*EXP(_xlpm.cum-LN(1+_xlpm.g)),_xlpm.lp,IF(_xlpm.t>=_xlpm.n,1,_xlpm.t/_xlpm.n),_xlpm.omt,_xlpm.om0+(_xlpm.om-_xlpm.om0)*_xlpm.lp,_xlpm.dat,_xlpm.da0+(_xlpm.lcx*_xlpm.dar-_xlpm.da0)*_xlpm.lp,_xlpm.cpx,IF((_xlpm.t=1)*(_xlpm.gd>0),_xlpm.gd/_xlpm.rev,_xlpm.cx0+(_xlpm.lcx-_xlpm.cx0)*_xlpm.lp),_xlpm.f,_xlpm.rev*(_xlpm.omt*(1-_xlpm.tx)+_xlpm.dat-_xlpm.cpx+_xlpm.sb)-_xlpm.nw*(_xlpm.rev-_xlpm.prv),_xlpm.pv,SUM(_xlpm.f/(1+_xlpm.w)^(_xlpm.t-0.5*_xlpm.m)),_xlpm.tv,INDEX(_xlpm.f,10)*(1+_xlpm.tgr)/(_xlpm.w-_xlpm.tgr)/(1+_xlpm.w)^10,(_xlpm.pv+_xlpm.tv+_xlpm.nc)/_xlpm.shs)} | D29: {=_xlfn.LET(_xlpm.gs,$B29,_xlpm.om,D$28,_xlpm.w,DCF!$B$7,_xlpm.tgr,DCF!$B$8,_xlpm.n,DCF!$B$11,_xlpm.lcx,DCF!$B$19,_xlpm.r0,DCF!$B$37,_xlpm.om0,DCF!$B$39,_xlpm.cx0,DCF!$B$40,_xlpm.da0,DCF!$B$41,_xlpm.dar,DCF!$B$20,_xlpm.tx,DCF!$B$31,_xlpm.sb,DCF!$B$43,_xlpm.nw,DCF!$B$21,_xlpm.gd,N(DCF!$B$22),_xlpm.nc,DCF!$B$47,_xlpm.shs,DCF!$B$6,_xlpm.m,DCF!$B$48,_xlpm.t,_xlfn.SEQUENCE(10),_xlpm.g,_xlpm.gs-(_xlpm.gs-_xlpm.tgr)*(_xlpm.t-1)/9,_xlpm.cum,MMULT(--(_xlpm.t>=TRANSPOSE(_xlpm.t)),LN(1+_xlpm.g)),_xlpm.rev,_xlpm.r0*EXP(_xlpm.cum),_xlpm.prv,_xlpm.r0*EXP(_xlpm.cum-LN(1+_xlpm.g)),_xlpm.lp,IF(_xlpm.t>=_xlpm.n,1,_xlpm.t/_xlpm.n),_xlpm.omt,_xlpm.om0+(_xlpm.om-_xlpm.om0)*_xlpm.lp,_xlpm.dat,_xlpm.da0+(_xlpm.lcx*_xlpm.dar-_xlpm.da0)*_xlpm.lp,_xlpm.cpx,IF((_xlpm.t=1)*(_xlpm.gd>0),_xlpm.gd/_xlpm.rev,_xlpm.cx0+(_xlpm.lcx-_xlpm.cx0)*_xlpm.lp),_xlpm.f,_xlpm.rev*(_xlpm.omt*(1-_xlpm.tx)+_xlpm.dat-_xlpm.cpx+_xlpm.sb)-_xlpm.nw*(_xlpm.rev-_xlpm.prv),_xlpm.pv,SUM(_xlpm.f/(1+_xlpm.w)^(_xlpm.t-0.5*_xlpm.m)),_xlpm.tv,INDEX(_xlpm.f,10)*(1+_xlpm.tgr)/(_xlpm.w-_xlpm.tgr)/(1+_xlpm.w)^10,(_xlpm.pv+_xlpm.tv+_xlpm.nc)/_xlpm.shs)} | E29: {=_xlfn.LET(_xlpm.gs,$B29,_xlpm.om,E$28,_xlpm.w,DCF!$B$7,_xlpm.tgr,DCF!$B$8,_xlpm.n,DCF!$B$11,_xlpm.lcx,DCF!$B$19,_xlpm.r0,DCF!$B$37,_xlpm.om0,DCF!$B$39,_xlpm.cx0,DCF!$B$40,_xlpm.da0,DCF!$B$41,_xlpm.dar,DCF!$B$20,_xlpm.tx,DCF!$B$31,_xlpm.sb,DCF!$B$43,_xlpm.nw,DCF!$B$21,_xlpm.gd,N(DCF!$B$22),_xlpm.nc,DCF!$B$47,_xlpm.shs,DCF!$B$6,_xlpm.m,DCF!$B$48,_xlpm.t,_xlfn.SEQUENCE(10),_xlpm.g,_xlpm.gs-(_xlpm.gs-_xlpm.tgr)*(_xlpm.t-1)/9,_xlpm.cum,MMULT(--(_xlpm.t>=TRANSPOSE(_xlpm.t)),LN(1+_xlpm.g)),_xlpm.rev,_xlpm.r0*EXP(_xlpm.cum),_xlpm.prv,_xlpm.r0*EXP(_xlpm.cum-LN(1+_xlpm.g)),_xlpm.lp,IF(_xlpm.t>=_xlpm.n,1,_xlpm.t/_xlpm.n),_xlpm.omt,_xlpm.om0+(_xlpm.om-_xlpm.om0)*_xlpm.lp,_xlpm.dat,_xlpm.da0+(_xlpm.lcx*_xlpm.dar-_xlpm.da0)*_xlpm.lp,_xlpm.cpx,IF((_xlpm.t=1)*(_xlpm.gd>0),_xlpm.gd/_xlpm.rev,_xlpm.cx0+(_xlpm.lcx-_xlpm.cx0)*_xlpm.lp),_xlpm.f,_xlpm.rev*(_xlpm.omt*(1-_xlpm.tx)+_xlpm.dat-_xlpm.cpx+_xlpm.sb)-_xlpm.nw*(_xlpm.rev-_xlpm.prv),_xlpm.pv,SUM(_xlpm.f/(1+_xlpm.w)^(_xlpm.t-0.5*_xlpm.m)),_xlpm.tv,INDEX(_xlpm.f,10)*(1+_xlpm.tgr)/(_xlpm.w-_xlpm.tgr)/(1+_xlpm.w)^10,(_xlpm.pv+_xlpm.tv+_xlpm.nc)/_xlpm.shs)} | F29: {=_xlfn.LET(_xlpm.gs,$B29,_xlpm.om,F$28,_xlpm.w,DCF!$B$7,_xlpm.tgr,DCF!$B$8,_xlpm.n,DCF!$B$11,_xlpm.lcx,DCF!$B$19,_xlpm.r0,DCF!$B$37,_xlpm.om0,DCF!$B$39,_xlpm.cx0,DCF!$B$40,_xlpm.da0,DCF!$B$41,_xlpm.dar,DCF!$B$20,_xlpm.tx,DCF!$B$31,_xlpm.sb,DCF!$B$43,_xlpm.nw,DCF!$B$21,_xlpm.gd,N(DCF!$B$22),_xlpm.nc,DCF!$B$47,_xlpm.shs,DCF!$B$6,_xlpm.m,DCF!$B$48,_xlpm.t,_xlfn.SEQUENCE(10),_xlpm.g,_xlpm.gs-(_xlpm.gs-_xlpm.tgr)*(_xlpm.t-1)/9,_xlpm.cum,MMULT(--(_xlpm.t>=TRANSPOSE(_xlpm.t)),LN(1+_xlpm.g)),_xlpm.rev,_xlpm.r0*EXP(_xlpm.cum),_xlpm.prv,_xlpm.r0*EXP(_xlpm.cum-LN(1+_xlpm.g)),_xlpm.lp,IF(_xlpm.t>=_xlpm.n,1,_xlpm.t/_xlpm.n),_xlpm.omt,_xlpm.om0+(_xlpm.om-_xlpm.om0)*_xlpm.lp,_xlpm.dat,_xlpm.da0+(_xlpm.lcx*_xlpm.dar-_xlpm.da0)*_xlpm.lp,_xlpm.cpx,IF((_xlpm.t=1)*(_xlpm.gd>0),_xlpm.gd/_xlpm.rev,_xlpm.cx0+(_xlpm.lcx-_xlpm.cx0)*_xlpm.lp),_xlpm.f,_xlpm.rev*(_xlpm.omt*(1-_xlpm.tx)+_xlpm.dat-_xlpm.cpx+_xlpm.sb)-_xlpm.nw*(_xlpm.rev-_xlpm.prv),_xlpm.pv,SUM(_xlpm.f/(1+_xlpm.w)^(_xlpm.t-0.5*_xlpm.m)),_xlpm.tv,INDEX(_xlpm.f,10)*(1+_xlpm.tgr)/(_xlpm.w-_xlpm.tgr)/(1+_xlpm.w)^10,(_xlpm.pv+_xlpm.tv+_xlpm.nc)/_xlpm.shs)} | G29: {=_xlfn.LET(_xlpm.gs,$B29,_xlpm.om,G$28,_xlpm.w,DCF!$B$7,_xlpm.tgr,DCF!$B$8,_xlpm.n,DCF!$B$11,_xlpm.lcx,DCF!$B$19,_xlpm.r0,DCF!$B$37,_xlpm.om0,DCF!$B$39,_xlpm.cx0,DCF!$B$40,_xlpm.da0,DCF!$B$41,_xlpm.dar,DCF!$B$20,_xlpm.tx,DCF!$B$31,_xlpm.sb,DCF!$B$43,_xlpm.nw,DCF!$B$21,_xlpm.gd,N(DCF!$B$22),_xlpm.nc,DCF!$B$47,_xlpm.shs,DCF!$B$6,_xlpm.m,DCF!$B$48,_xlpm.t,_xlfn.SEQUENCE(10),_xlpm.g,_xlpm.gs-(_xlpm.gs-_xlpm.tgr)*(_xlpm.t-1)/9,_xlpm.cum,MMULT(--(_xlpm.t>=TRANSPOSE(_xlpm.t)),LN(1+_xlpm.g)),_xlpm.rev,_xlpm.r0*EXP(_xlpm.cum),_xlpm.prv,_xlpm.r0*EXP(_xlpm.cum-LN(1+_xlpm.g)),_xlpm.lp,IF(_xlpm.t>=_xlpm.n,1,_xlpm.t/_xlpm.n),_xlpm.omt,_xlpm.om0+(_xlpm.om-_xlpm.om0)*_xlpm.lp,_xlpm.dat,_xlpm.da0+(_xlpm.lcx*_xlpm.dar-_xlpm.da0)*_xlpm.lp,_xlpm.cpx,IF((_xlpm.t=1)*(_xlpm.gd>0),_xlpm.gd/_xlpm.rev,_xlpm.cx0+(_xlpm.lcx-_xlpm.cx0)*_xlpm.lp),_xlpm.f,_xlpm.rev*(_xlpm.omt*(1-_xlpm.tx)+_xlpm.dat-_xlpm.cpx+_xlpm.sb)-_xlpm.nw*(_xlpm.rev-_xlpm.prv),_xlpm.pv,SUM(_xlpm.f/(1+_xlpm.w)^(_xlpm.t-0.5*_xlpm.m)),_xlpm.tv,INDEX(_xlpm.f,10)*(1+_xlpm.tgr)/(_xlpm.w-_xlpm.tgr)/(1+_xlpm.w)^10,(_xlpm.pv+_xlpm.tv+_xlpm.nc)/_xlpm.shs)} | J29: =DCF!$B$19-0.04 | K29: {=_xlfn.LET(_xlpm.gs,DCF!$B$9,_xlpm.om,DCF!$B$10,_xlpm.w,DCF!$B$7,_xlpm.tgr,DCF!$B$8,_xlpm.n,K$28,_xlpm.lcx,$J29,_xlpm.r0,DCF!$B$37,_xlpm.om0,DCF!$B$39,_xlpm.cx0,DCF!$B$40,_xlpm.da0,DCF!$B$41,_xlpm.dar,DCF!$B$20,_xlpm.tx,DCF!$B$31,_xlpm.sb,DCF!$B$43,_xlpm.nw,DCF!$B$21,_xlpm.gd,N(DCF!$B$22),_xlpm.nc,DCF!$B$47,_xlpm.shs,DCF!$B$6,_xlpm.m,DCF!$B$48,_xlpm.t,_xlfn.SEQUENCE(10),_xlpm.g,_xlpm.gs-(_xlpm.gs-_xlpm.tgr)*(_xlpm.t-1)/9,_xlpm.cum,MMULT(--(_xlpm.t>=TRANSPOSE(_xlpm.t)),LN(1+_xlpm.g)),_xlpm.rev,_xlpm.r0*EXP(_xlpm.cum),_xlpm.prv,_xlpm.r0*EXP(_xlpm.cum-LN(1+_xlpm.g)),_xlpm.lp,IF(_xlpm.t>=_xlpm.n,1,_xlpm.t/_xlpm.n),_xlpm.omt,_xlpm.om0+(_xlpm.om-_xlpm.om0)*_xlpm.lp,_xlpm.dat,_xlpm.da0+(_xlpm.lcx*_xlpm.dar-_xlpm.da0)*_xlpm.lp,_xlpm.cpx,IF((_xlpm.t=1)*(_xlpm.gd>0),_xlpm.gd/_xlpm.rev,_xlpm.cx0+(_xlpm.lcx-_xlpm.cx0)*_xlpm.lp),_xlpm.f,_xlpm.rev*(_xlpm.omt*(1-_xlpm.tx)+_xlpm.dat-_xlpm.cpx+_xlpm.sb)-_xlpm.nw*(_xlpm.rev-_xlpm.prv),_xlpm.pv,SUM(_xlpm.f/(1+_xlpm.w)^(_xlpm.t-0.5*_xlpm.m)),_xlpm.tv,INDEX(_xlpm.f,10)*(1+_xlpm.tgr)/(_xlpm.w-_xlpm.tgr)/(1+_xlpm.w)^10,(_xlpm.pv+_xlpm.tv+_xlpm.nc)/_xlpm.shs)} | L29: {=_xlfn.LET(_xlpm.gs,DCF!$B$9,_xlpm.om,DCF!$B$10,_xlpm.w,DCF!$B$7,_xlpm.tgr,DCF!$B$8,_xlpm.n,L$28,_xlpm.lcx,$J29,_xlpm.r0,DCF!$B$37,_xlpm.om0,DCF!$B$39,_xlpm.cx0,DCF!$B$40,_xlpm.da0,DCF!$B$41,_xlpm.dar,DCF!$B$20,_xlpm.tx,DCF!$B$31,_xlpm.sb,DCF!$B$43,_xlpm.nw,DCF!$B$21,_xlpm.gd,N(DCF!$B$22),_xlpm.nc,DCF!$B$47,_xlpm.shs,DCF!$B$6,_xlpm.m,DCF!$B$48,_xlpm.t,_xlfn.SEQUENCE(10),_xlpm.g,_xlpm.gs-(_xlpm.gs-_xlpm.tgr)*(_xlpm.t-1)/9,_xlpm.cum,MMULT(--(_xlpm.t>=TRANSPOSE(_xlpm.t)),LN(1+_xlpm.g)),_xlpm.rev,_xlpm.r0*EXP(_xlpm.cum),_xlpm.prv,_xlpm.r0*EXP(_xlpm.cum-LN(1+_xlpm.g)),_xlpm.lp,IF(_xlpm.t>=_xlpm.n,1,_xlpm.t/_xlpm.n),_xlpm.omt,_xlpm.om0+(_xlpm.om-_xlpm.om0)*_xlpm.lp,_xlpm.dat,_xlpm.da0+(_xlpm.lcx*_xlpm.dar-_xlpm.da0)*_xlpm.lp,_xlpm.cpx,IF((_xlpm.t=1)*(_xlpm.gd>0),_xlpm.gd/_xlpm.rev,_xlpm.cx0+(_xlpm.lcx-_xlpm.cx0)*_xlpm.lp),_xlpm.f,_xlpm.rev*(_xlpm.omt*(1-_xlpm.tx)+_xlpm.dat-_xlpm.cpx+_xlpm.sb)-_xlpm.nw*(_xlpm.rev-_xlpm.prv),_xlpm.pv,SUM(_xlpm.f/(1+_xlpm.w)^(_xlpm.t-0.5*_xlpm.m)),_xlpm.tv,INDEX(_xlpm.f,10)*(1+_xlpm.tgr)/(_xlpm.w-_xlpm.tgr)/(1+_xlpm.w)^10,(_xlpm.pv+_xlpm.tv+_xlpm.nc)/_xlpm.shs)} | M29: {=_xlfn.LET(_xlpm.gs,DCF!$B$9,_xlpm.om,DCF!$B$10,_xlpm.w,DCF!$B$7,_xlpm.tgr,DCF!$B$8,_xlpm.n,M$28,_xlpm.lcx,$J29,_xlpm.r0,DCF!$B$37,_xlpm.om0,DCF!$B$39,_xlpm.cx0,DCF!$B$40,_xlpm.da0,DCF!$B$41,_xlpm.dar,DCF!$B$20,_xlpm.tx,DCF!$B$31,_xlpm.sb,DCF!$B$43,_xlpm.nw,DCF!$B$21,_xlpm.gd,N(DCF!$B$22),_xlpm.nc,DCF!$B$47,_xlpm.shs,DCF!$B$6,_xlpm.m,DCF!$B$48,_xlpm.t,_xlfn.SEQUENCE(10),_xlpm.g,_xlpm.gs-(_xlpm.gs-_xlpm.tgr)*(_xlpm.t-1)/9,_xlpm.cum,MMULT(--(_xlpm.t>=TRANSPOSE(_xlpm.t)),LN(1+_xlpm.g)),_xlpm.rev,_xlpm.r0*EXP(_xlpm.cum),_xlpm.prv,_xlpm.r0*EXP(_xlpm.cum-LN(1+_xlpm.g)),_xlpm.lp,IF(_xlpm.t>=_xlpm.n,1,_xlpm.t/_xlpm.n),_xlpm.omt,_xlpm.om0+(_xlpm.om-_xlpm.om0)*_xlpm.lp,_xlpm.dat,_xlpm.da0+(_xlpm.lcx*_xlpm.dar-_xlpm.da0)*_xlpm.lp,_xlpm.cpx,IF((_xlpm.t=1)*(_xlpm.gd>0),_xlpm.gd/_xlpm.rev,_xlpm.cx0+(_xlpm.lcx-_xlpm.cx0)*_xlpm.lp),_xlpm.f,_xlpm.rev*(_xlpm.omt*(1-_xlpm.tx)+_xlpm.dat-_xlpm.cpx+_xlpm.sb)-_xlpm.nw*(_xlpm.rev-_xlpm.prv),_xlpm.pv,SUM(_xlpm.f/(1+_xlpm.w)^(_xlpm.t-0.5*_xlpm.m)),_xlpm.tv,INDEX(_xlpm.f,10)*(1+_xlpm.tgr)/(_xlpm.w-_xlpm.tgr)/(1+_xlpm.w)^10,(_xlpm.pv+_xlpm.tv+_xlpm.nc)/_xlpm.shs)} | N29: {=_xlfn.LET(_xlpm.gs,DCF!$B$9,_xlpm.om,DCF!$B$10,_xlpm.w,DCF!$B$7,_xlpm.tgr,DCF!$B$8,_xlpm.n,N$28,_xlpm.lcx,$J29,_xlpm.r0,DCF!$B$37,_xlpm.om0,DCF!$B$39,_xlpm.cx0,DCF!$B$40,_xlpm.da0,DCF!$B$41,_xlpm.dar,DCF!$B$20,_xlpm.tx,DCF!$B$31,_xlpm.sb,DCF!$B$43,_xlpm.nw,DCF!$B$21,_xlpm.gd,N(DCF!$B$22),_xlpm.nc,DCF!$B$47,_xlpm.shs,DCF!$B$6,_xlpm.m,DCF!$B$48,_xlpm.t,_xlfn.SEQUENCE(10),_xlpm.g,_xlpm.gs-(_xlpm.gs-_xlpm.tgr)*(_xlpm.t-1)/9,_xlpm.cum,MMULT(--(_xlpm.t>=TRANSPOSE(_xlpm.t)),LN(1+_xlpm.g)),_xlpm.rev,_xlpm.r0*EXP(_xlpm.cum),_xlpm.prv,_xlpm.r0*EXP(_xlpm.cum-LN(1+_xlpm.g)),_xlpm.lp,IF(_xlpm.t>=_xlpm.n,1,_xlpm.t/_xlpm.n),_xlpm.omt,_xlpm.om0+(_xlpm.om-_xlpm.om0)*_xlpm.lp,_xlpm.dat,_xlpm.da0+(_xlpm.lcx*_xlpm.dar-_xlpm.da0)*_xlpm.lp,_xlpm.cpx,IF((_xlpm.t=1)*(_xlpm.gd>0),_xlpm.gd/_xlpm.rev,_xlpm.cx0+(_xlpm.lcx-_xlpm.cx0)*_xlpm.lp),_xlpm.f,_xlpm.rev*(_xlpm.omt*(1-_xlpm.tx)+_xlpm.dat-_xlpm.cpx+_xlpm.sb)-_xlpm.nw*(_xlpm.rev-_xlpm.prv),_xlpm.pv,SUM(_xlpm.f/(1+_xlpm.w)^(_xlpm.t-0.5*_xlpm.m)),_xlpm.tv,INDEX(_xlpm.f,10)*(1+_xlpm.tgr)/(_xlpm.w-_xlpm.tgr)/(1+_xlpm.w)^10,(_xlpm.pv+_xlpm.tv+_xlpm.nc)/_xlpm.shs)} | O29: {=_xlfn.LET(_xlpm.gs,DCF!$B$9,_xlpm.om,DCF!$B$10,_xlpm.w,DCF!$B$7,_xlpm.tgr,DCF!$B$8,_xlpm.n,O$28,_xlpm.lcx,$J29,_xlpm.r0,DCF!$B$37,_xlpm.om0,DCF!$B$39,_xlpm.cx0,DCF!$B$40,_xlpm.da0,DCF!$B$41,_xlpm.dar,DCF!$B$20,_xlpm.tx,DCF!$B$31,_xlpm.sb,DCF!$B$43,_xlpm.nw,DCF!$B$21,_xlpm.gd,N(DCF!$B$22),_xlpm.nc,DCF!$B$47,_xlpm.shs,DCF!$B$6,_xlpm.m,DCF!$B$48,_xlpm.t,_xlfn.SEQUENCE(10),_xlpm.g,_xlpm.gs-(_xlpm.gs-_xlpm.tgr)*(_xlpm.t-1)/9,_xlpm.cum,MMULT(--(_xlpm.t>=TRANSPOSE(_xlpm.t)),LN(1+_xlpm.g)),_xlpm.rev,_xlpm.r0*EXP(_xlpm.cum),_xlpm.prv,_xlpm.r0*EXP(_xlpm.cum-LN(1+_xlpm.g)),_xlpm.lp,IF(_xlpm.t>=_xlpm.n,1,_xlpm.t/_xlpm.n),_xlpm.omt,_xlpm.om0+(_xlpm.om-_xlpm.om0)*_xlpm.lp,_xlpm.dat,_xlpm.da0+(_xlpm.lcx*_xlpm.dar-_xlpm.da0)*_xlpm.lp,_xlpm.cpx,IF((_xlpm.t=1)*(_xlpm.gd>0),_xlpm.gd/_xlpm.rev,_xlpm.cx0+(_xlpm.lcx-_xlpm.cx0)*_xlpm.lp),_xlpm.f,_xlpm.rev*(_xlpm.omt*(1-_xlpm.tx)+_xlpm.dat-_xlpm.cpx+_xlpm.sb)-_xlpm.nw*(_xlpm.rev-_xlpm.prv),_xlpm.pv,SUM(_xlpm.f/(1+_xlpm.w)^(_xlpm.t-0.5*_xlpm.m)),_xlpm.tv,INDEX(_xlpm.f,10)*(1+_xlpm.tgr)/(_xlpm.w-_xlpm.tgr)/(1+_xlpm.w)^10,(_xlpm.pv+_xlpm.tv+_xlpm.nc)/_xlpm.shs)}
B30: =DCF!$B$9+(-0.03) | C30: {=_xlfn.LET(_xlpm.gs,$B30,_xlpm.om,C$28,_xlpm.w,DCF!$B$7,_xlpm.tgr,DCF!$B$8,_xlpm.n,DCF!$B$11,_xlpm.lcx,DCF!$B$19,_xlpm.r0,DCF!$B$37,_xlpm.om0,DCF!$B$39,_xlpm.cx0,DCF!$B$40,_xlpm.da0,DCF!$B$41,_xlpm.dar,DCF!$B$20,_xlpm.tx,DCF!$B$31,_xlpm.sb,DCF!$B$43,_xlpm.nw,DCF!$B$21,_xlpm.gd,N(DCF!$B$22),_xlpm.nc,DCF!$B$47,_xlpm.shs,DCF!$B$6,_xlpm.m,DCF!$B$48,_xlpm.t,_xlfn.SEQUENCE(10),_xlpm.g,_xlpm.gs-(_xlpm.gs-_xlpm.tgr)*(_xlpm.t-1)/9,_xlpm.cum,MMULT(--(_xlpm.t>=TRANSPOSE(_xlpm.t)),LN(1+_xlpm.g)),_xlpm.rev,_xlpm.r0*EXP(_xlpm.cum),_xlpm.prv,_xlpm.r0*EXP(_xlpm.cum-LN(1+_xlpm.g)),_xlpm.lp,IF(_xlpm.t>=_xlpm.n,1,_xlpm.t/_xlpm.n),_xlpm.omt,_xlpm.om0+(_xlpm.om-_xlpm.om0)*_xlpm.lp,_xlpm.dat,_xlpm.da0+(_xlpm.lcx*_xlpm.dar-_xlpm.da0)*_xlpm.lp,_xlpm.cpx,IF((_xlpm.t=1)*(_xlpm.gd>0),_xlpm.gd/_xlpm.rev,_xlpm.cx0+(_xlpm.lcx-_xlpm.cx0)*_xlpm.lp),_xlpm.f,_xlpm.rev*(_xlpm.omt*(1-_xlpm.tx)+_xlpm.dat-_xlpm.cpx+_xlpm.sb)-_xlpm.nw*(_xlpm.rev-_xlpm.prv),_xlpm.pv,SUM(_xlpm.f/(1+_xlpm.w)^(_xlpm.t-0.5*_xlpm.m)),_xlpm.tv,INDEX(_xlpm.f,10)*(1+_xlpm.tgr)/(_xlpm.w-_xlpm.tgr)/(1+_xlpm.w)^10,(_xlpm.pv+_xlpm.tv+_xlpm.nc)/_xlpm.shs)} | D30: {=_xlfn.LET(_xlpm.gs,$B30,_xlpm.om,D$28,_xlpm.w,DCF!$B$7,_xlpm.tgr,DCF!$B$8,_xlpm.n,DCF!$B$11,_xlpm.lcx,DCF!$B$19,_xlpm.r0,DCF!$B$37,_xlpm.om0,DCF!$B$39,_xlpm.cx0,DCF!$B$40,_xlpm.da0,DCF!$B$41,_xlpm.dar,DCF!$B$20,_xlpm.tx,DCF!$B$31,_xlpm.sb,DCF!$B$43,_xlpm.nw,DCF!$B$21,_xlpm.gd,N(DCF!$B$22),_xlpm.nc,DCF!$B$47,_xlpm.shs,DCF!$B$6,_xlpm.m,DCF!$B$48,_xlpm.t,_xlfn.SEQUENCE(10),_xlpm.g,_xlpm.gs-(_xlpm.gs-_xlpm.tgr)*(_xlpm.t-1)/9,_xlpm.cum,MMULT(--(_xlpm.t>=TRANSPOSE(_xlpm.t)),LN(1+_xlpm.g)),_xlpm.rev,_xlpm.r0*EXP(_xlpm.cum),_xlpm.prv,_xlpm.r0*EXP(_xlpm.cum-LN(1+_xlpm.g)),_xlpm.lp,IF(_xlpm.t>=_xlpm.n,1,_xlpm.t/_xlpm.n),_xlpm.omt,_xlpm.om0+(_xlpm.om-_xlpm.om0)*_xlpm.lp,_xlpm.dat,_xlpm.da0+(_xlpm.lcx*_xlpm.dar-_xlpm.da0)*_xlpm.lp,_xlpm.cpx,IF((_xlpm.t=1)*(_xlpm.gd>0),_xlpm.gd/_xlpm.rev,_xlpm.cx0+(_xlpm.lcx-_xlpm.cx0)*_xlpm.lp),_xlpm.f,_xlpm.rev*(_xlpm.omt*(1-_xlpm.tx)+_xlpm.dat-_xlpm.cpx+_xlpm.sb)-_xlpm.nw*(_xlpm.rev-_xlpm.prv),_xlpm.pv,SUM(_xlpm.f/(1+_xlpm.w)^(_xlpm.t-0.5*_xlpm.m)),_xlpm.tv,INDEX(_xlpm.f,10)*(1+_xlpm.tgr)/(_xlpm.w-_xlpm.tgr)/(1+_xlpm.w)^10,(_xlpm.pv+_xlpm.tv+_xlpm.nc)/_xlpm.shs)} | E30: {=_xlfn.LET(_xlpm.gs,$B30,_xlpm.om,E$28,_xlpm.w,DCF!$B$7,_xlpm.tgr,DCF!$B$8,_xlpm.n,DCF!$B$11,_xlpm.lcx,DCF!$B$19,_xlpm.r0,DCF!$B$37,_xlpm.om0,DCF!$B$39,_xlpm.cx0,DCF!$B$40,_xlpm.da0,DCF!$B$41,_xlpm.dar,DCF!$B$20,_xlpm.tx,DCF!$B$31,_xlpm.sb,DCF!$B$43,_xlpm.nw,DCF!$B$21,_xlpm.gd,N(DCF!$B$22),_xlpm.nc,DCF!$B$47,_xlpm.shs,DCF!$B$6,_xlpm.m,DCF!$B$48,_xlpm.t,_xlfn.SEQUENCE(10),_xlpm.g,_xlpm.gs-(_xlpm.gs-_xlpm.tgr)*(_xlpm.t-1)/9,_xlpm.cum,MMULT(--(_xlpm.t>=TRANSPOSE(_xlpm.t)),LN(1+_xlpm.g)),_xlpm.rev,_xlpm.r0*EXP(_xlpm.cum),_xlpm.prv,_xlpm.r0*EXP(_xlpm.cum-LN(1+_xlpm.g)),_xlpm.lp,IF(_xlpm.t>=_xlpm.n,1,_xlpm.t/_xlpm.n),_xlpm.omt,_xlpm.om0+(_xlpm.om-_xlpm.om0)*_xlpm.lp,_xlpm.dat,_xlpm.da0+(_xlpm.lcx*_xlpm.dar-_xlpm.da0)*_xlpm.lp,_xlpm.cpx,IF((_xlpm.t=1)*(_xlpm.gd>0),_xlpm.gd/_xlpm.rev,_xlpm.cx0+(_xlpm.lcx-_xlpm.cx0)*_xlpm.lp),_xlpm.f,_xlpm.rev*(_xlpm.omt*(1-_xlpm.tx)+_xlpm.dat-_xlpm.cpx+_xlpm.sb)-_xlpm.nw*(_xlpm.rev-_xlpm.prv),_xlpm.pv,SUM(_xlpm.f/(1+_xlpm.w)^(_xlpm.t-0.5*_xlpm.m)),_xlpm.tv,INDEX(_xlpm.f,10)*(1+_xlpm.tgr)/(_xlpm.w-_xlpm.tgr)/(1+_xlpm.w)^10,(_xlpm.pv+_xlpm.tv+_xlpm.nc)/_xlpm.shs)} | F30: {=_xlfn.LET(_xlpm.gs,$B30,_xlpm.om,F$28,_xlpm.w,DCF!$B$7,_xlpm.tgr,DCF!$B$8,_xlpm.n,DCF!$B$11,_xlpm.lcx,DCF!$B$19,_xlpm.r0,DCF!$B$37,_xlpm.om0,DCF!$B$39,_xlpm.cx0,DCF!$B$40,_xlpm.da0,DCF!$B$41,_xlpm.dar,DCF!$B$20,_xlpm.tx,DCF!$B$31,_xlpm.sb,DCF!$B$43,_xlpm.nw,DCF!$B$21,_xlpm.gd,N(DCF!$B$22),_xlpm.nc,DCF!$B$47,_xlpm.shs,DCF!$B$6,_xlpm.m,DCF!$B$48,_xlpm.t,_xlfn.SEQUENCE(10),_xlpm.g,_xlpm.gs-(_xlpm.gs-_xlpm.tgr)*(_xlpm.t-1)/9,_xlpm.cum,MMULT(--(_xlpm.t>=TRANSPOSE(_xlpm.t)),LN(1+_xlpm.g)),_xlpm.rev,_xlpm.r0*EXP(_xlpm.cum),_xlpm.prv,_xlpm.r0*EXP(_xlpm.cum-LN(1+_xlpm.g)),_xlpm.lp,IF(_xlpm.t>=_xlpm.n,1,_xlpm.t/_xlpm.n),_xlpm.omt,_xlpm.om0+(_xlpm.om-_xlpm.om0)*_xlpm.lp,_xlpm.dat,_xlpm.da0+(_xlpm.lcx*_xlpm.dar-_xlpm.da0)*_xlpm.lp,_xlpm.cpx,IF((_xlpm.t=1)*(_xlpm.gd>0),_xlpm.gd/_xlpm.rev,_xlpm.cx0+(_xlpm.lcx-_xlpm.cx0)*_xlpm.lp),_xlpm.f,_xlpm.rev*(_xlpm.omt*(1-_xlpm.tx)+_xlpm.dat-_xlpm.cpx+_xlpm.sb)-_xlpm.nw*(_xlpm.rev-_xlpm.prv),_xlpm.pv,SUM(_xlpm.f/(1+_xlpm.w)^(_xlpm.t-0.5*_xlpm.m)),_xlpm.tv,INDEX(_xlpm.f,10)*(1+_xlpm.tgr)/(_xlpm.w-_xlpm.tgr)/(1+_xlpm.w)^10,(_xlpm.pv+_xlpm.tv+_xlpm.nc)/_xlpm.shs)} | G30: {=_xlfn.LET(_xlpm.gs,$B30,_xlpm.om,G$28,_xlpm.w,DCF!$B$7,_xlpm.tgr,DCF!$B$8,_xlpm.n,DCF!$B$11,_xlpm.lcx,DCF!$B$19,_xlpm.r0,DCF!$B$37,_xlpm.om0,DCF!$B$39,_xlpm.cx0,DCF!$B$40,_xlpm.da0,DCF!$B$41,_xlpm.dar,DCF!$B$20,_xlpm.tx,DCF!$B$31,_xlpm.sb,DCF!$B$43,_xlpm.nw,DCF!$B$21,_xlpm.gd,N(DCF!$B$22),_xlpm.nc,DCF!$B$47,_xlpm.shs,DCF!$B$6,_xlpm.m,DCF!$B$48,_xlpm.t,_xlfn.SEQUENCE(10),_xlpm.g,_xlpm.gs-(_xlpm.gs-_xlpm.tgr)*(_xlpm.t-1)/9,_xlpm.cum,MMULT(--(_xlpm.t>=TRANSPOSE(_xlpm.t)),LN(1+_xlpm.g)),_xlpm.rev,_xlpm.r0*EXP(_xlpm.cum),_xlpm.prv,_xlpm.r0*EXP(_xlpm.cum-LN(1+_xlpm.g)),_xlpm.lp,IF(_xlpm.t>=_xlpm.n,1,_xlpm.t/_xlpm.n),_xlpm.omt,_xlpm.om0+(_xlpm.om-_xlpm.om0)*_xlpm.lp,_xlpm.dat,_xlpm.da0+(_xlpm.lcx*_xlpm.dar-_xlpm.da0)*_xlpm.lp,_xlpm.cpx,IF((_xlpm.t=1)*(_xlpm.gd>0),_xlpm.gd/_xlpm.rev,_xlpm.cx0+(_xlpm.lcx-_xlpm.cx0)*_xlpm.lp),_xlpm.f,_xlpm.rev*(_xlpm.omt*(1-_xlpm.tx)+_xlpm.dat-_xlpm.cpx+_xlpm.sb)-_xlpm.nw*(_xlpm.rev-_xlpm.prv),_xlpm.pv,SUM(_xlpm.f/(1+_xlpm.w)^(_xlpm.t-0.5*_xlpm.m)),_xlpm.tv,INDEX(_xlpm.f,10)*(1+_xlpm.tgr)/(_xlpm.w-_xlpm.tgr)/(1+_xlpm.w)^10,(_xlpm.pv+_xlpm.tv+_xlpm.nc)/_xlpm.shs)} | J30: =DCF!$B$19-0.02 | K30: {=_xlfn.LET(_xlpm.gs,DCF!$B$9,_xlpm.om,DCF!$B$10,_xlpm.w,DCF!$B$7,_xlpm.tgr,DCF!$B$8,_xlpm.n,K$28,_xlpm.lcx,$J30,_xlpm.r0,DCF!$B$37,_xlpm.om0,DCF!$B$39,_xlpm.cx0,DCF!$B$40,_xlpm.da0,DCF!$B$41,_xlpm.dar,DCF!$B$20,_xlpm.tx,DCF!$B$31,_xlpm.sb,DCF!$B$43,_xlpm.nw,DCF!$B$21,_xlpm.gd,N(DCF!$B$22),_xlpm.nc,DCF!$B$47,_xlpm.shs,DCF!$B$6,_xlpm.m,DCF!$B$48,_xlpm.t,_xlfn.SEQUENCE(10),_xlpm.g,_xlpm.gs-(_xlpm.gs-_xlpm.tgr)*(_xlpm.t-1)/9,_xlpm.cum,MMULT(--(_xlpm.t>=TRANSPOSE(_xlpm.t)),LN(1+_xlpm.g)),_xlpm.rev,_xlpm.r0*EXP(_xlpm.cum),_xlpm.prv,_xlpm.r0*EXP(_xlpm.cum-LN(1+_xlpm.g)),_xlpm.lp,IF(_xlpm.t>=_xlpm.n,1,_xlpm.t/_xlpm.n),_xlpm.omt,_xlpm.om0+(_xlpm.om-_xlpm.om0)*_xlpm.lp,_xlpm.dat,_xlpm.da0+(_xlpm.lcx*_xlpm.dar-_xlpm.da0)*_xlpm.lp,_xlpm.cpx,IF((_xlpm.t=1)*(_xlpm.gd>0),_xlpm.gd/_xlpm.rev,_xlpm.cx0+(_xlpm.lcx-_xlpm.cx0)*_xlpm.lp),_xlpm.f,_xlpm.rev*(_xlpm.omt*(1-_xlpm.tx)+_xlpm.dat-_xlpm.cpx+_xlpm.sb)-_xlpm.nw*(_xlpm.rev-_xlpm.prv),_xlpm.pv,SUM(_xlpm.f/(1+_xlpm.w)^(_xlpm.t-0.5*_xlpm.m)),_xlpm.tv,INDEX(_xlpm.f,10)*(1+_xlpm.tgr)/(_xlpm.w-_xlpm.tgr)/(1+_xlpm.w)^10,(_xlpm.pv+_xlpm.tv+_xlpm.nc)/_xlpm.shs)} | L30: {=_xlfn.LET(_xlpm.gs,DCF!$B$9,_xlpm.om,DCF!$B$10,_xlpm.w,DCF!$B$7,_xlpm.tgr,DCF!$B$8,_xlpm.n,L$28,_xlpm.lcx,$J30,_xlpm.r0,DCF!$B$37,_xlpm.om0,DCF!$B$39,_xlpm.cx0,DCF!$B$40,_xlpm.da0,DCF!$B$41,_xlpm.dar,DCF!$B$20,_xlpm.tx,DCF!$B$31,_xlpm.sb,DCF!$B$43,_xlpm.nw,DCF!$B$21,_xlpm.gd,N(DCF!$B$22),_xlpm.nc,DCF!$B$47,_xlpm.shs,DCF!$B$6,_xlpm.m,DCF!$B$48,_xlpm.t,_xlfn.SEQUENCE(10),_xlpm.g,_xlpm.gs-(_xlpm.gs-_xlpm.tgr)*(_xlpm.t-1)/9,_xlpm.cum,MMULT(--(_xlpm.t>=TRANSPOSE(_xlpm.t)),LN(1+_xlpm.g)),_xlpm.rev,_xlpm.r0*EXP(_xlpm.cum),_xlpm.prv,_xlpm.r0*EXP(_xlpm.cum-LN(1+_xlpm.g)),_xlpm.lp,IF(_xlpm.t>=_xlpm.n,1,_xlpm.t/_xlpm.n),_xlpm.omt,_xlpm.om0+(_xlpm.om-_xlpm.om0)*_xlpm.lp,_xlpm.dat,_xlpm.da0+(_xlpm.lcx*_xlpm.dar-_xlpm.da0)*_xlpm.lp,_xlpm.cpx,IF((_xlpm.t=1)*(_xlpm.gd>0),_xlpm.gd/_xlpm.rev,_xlpm.cx0+(_xlpm.lcx-_xlpm.cx0)*_xlpm.lp),_xlpm.f,_xlpm.rev*(_xlpm.omt*(1-_xlpm.tx)+_xlpm.dat-_xlpm.cpx+_xlpm.sb)-_xlpm.nw*(_xlpm.rev-_xlpm.prv),_xlpm.pv,SUM(_xlpm.f/(1+_xlpm.w)^(_xlpm.t-0.5*_xlpm.m)),_xlpm.tv,INDEX(_xlpm.f,10)*(1+_xlpm.tgr)/(_xlpm.w-_xlpm.tgr)/(1+_xlpm.w)^10,(_xlpm.pv+_xlpm.tv+_xlpm.nc)/_xlpm.shs)} | M30: {=_xlfn.LET(_xlpm.gs,DCF!$B$9,_xlpm.om,DCF!$B$10,_xlpm.w,DCF!$B$7,_xlpm.tgr,DCF!$B$8,_xlpm.n,M$28,_xlpm.lcx,$J30,_xlpm.r0,DCF!$B$37,_xlpm.om0,DCF!$B$39,_xlpm.cx0,DCF!$B$40,_xlpm.da0,DCF!$B$41,_xlpm.dar,DCF!$B$20,_xlpm.tx,DCF!$B$31,_xlpm.sb,DCF!$B$43,_xlpm.nw,DCF!$B$21,_xlpm.gd,N(DCF!$B$22),_xlpm.nc,DCF!$B$47,_xlpm.shs,DCF!$B$6,_xlpm.m,DCF!$B$48,_xlpm.t,_xlfn.SEQUENCE(10),_xlpm.g,_xlpm.gs-(_xlpm.gs-_xlpm.tgr)*(_xlpm.t-1)/9,_xlpm.cum,MMULT(--(_xlpm.t>=TRANSPOSE(_xlpm.t)),LN(1+_xlpm.g)),_xlpm.rev,_xlpm.r0*EXP(_xlpm.cum),_xlpm.prv,_xlpm.r0*EXP(_xlpm.cum-LN(1+_xlpm.g)),_xlpm.lp,IF(_xlpm.t>=_xlpm.n,1,_xlpm.t/_xlpm.n),_xlpm.omt,_xlpm.om0+(_xlpm.om-_xlpm.om0)*_xlpm.lp,_xlpm.dat,_xlpm.da0+(_xlpm.lcx*_xlpm.dar-_xlpm.da0)*_xlpm.lp,_xlpm.cpx,IF((_xlpm.t=1)*(_xlpm.gd>0),_xlpm.gd/_xlpm.rev,_xlpm.cx0+(_xlpm.lcx-_xlpm.cx0)*_xlpm.lp),_xlpm.f,_xlpm.rev*(_xlpm.omt*(1-_xlpm.tx)+_xlpm.dat-_xlpm.cpx+_xlpm.sb)-_xlpm.nw*(_xlpm.rev-_xlpm.prv),_xlpm.pv,SUM(_xlpm.f/(1+_xlpm.w)^(_xlpm.t-0.5*_xlpm.m)),_xlpm.tv,INDEX(_xlpm.f,10)*(1+_xlpm.tgr)/(_xlpm.w-_xlpm.tgr)/(1+_xlpm.w)^10,(_xlpm.pv+_xlpm.tv+_xlpm.nc)/_xlpm.shs)} | N30: {=_xlfn.LET(_xlpm.gs,DCF!$B$9,_xlpm.om,DCF!$B$10,_xlpm.w,DCF!$B$7,_xlpm.tgr,DCF!$B$8,_xlpm.n,N$28,_xlpm.lcx,$J30,_xlpm.r0,DCF!$B$37,_xlpm.om0,DCF!$B$39,_xlpm.cx0,DCF!$B$40,_xlpm.da0,DCF!$B$41,_xlpm.dar,DCF!$B$20,_xlpm.tx,DCF!$B$31,_xlpm.sb,DCF!$B$43,_xlpm.nw,DCF!$B$21,_xlpm.gd,N(DCF!$B$22),_xlpm.nc,DCF!$B$47,_xlpm.shs,DCF!$B$6,_xlpm.m,DCF!$B$48,_xlpm.t,_xlfn.SEQUENCE(10),_xlpm.g,_xlpm.gs-(_xlpm.gs-_xlpm.tgr)*(_xlpm.t-1)/9,_xlpm.cum,MMULT(--(_xlpm.t>=TRANSPOSE(_xlpm.t)),LN(1+_xlpm.g)),_xlpm.rev,_xlpm.r0*EXP(_xlpm.cum),_xlpm.prv,_xlpm.r0*EXP(_xlpm.cum-LN(1+_xlpm.g)),_xlpm.lp,IF(_xlpm.t>=_xlpm.n,1,_xlpm.t/_xlpm.n),_xlpm.omt,_xlpm.om0+(_xlpm.om-_xlpm.om0)*_xlpm.lp,_xlpm.dat,_xlpm.da0+(_xlpm.lcx*_xlpm.dar-_xlpm.da0)*_xlpm.lp,_xlpm.cpx,IF((_xlpm.t=1)*(_xlpm.gd>0),_xlpm.gd/_xlpm.rev,_xlpm.cx0+(_xlpm.lcx-_xlpm.cx0)*_xlpm.lp),_xlpm.f,_xlpm.rev*(_xlpm.omt*(1-_xlpm.tx)+_xlpm.dat-_xlpm.cpx+_xlpm.sb)-_xlpm.nw*(_xlpm.rev-_xlpm.prv),_xlpm.pv,SUM(_xlpm.f/(1+_xlpm.w)^(_xlpm.t-0.5*_xlpm.m)),_xlpm.tv,INDEX(_xlpm.f,10)*(1+_xlpm.tgr)/(_xlpm.w-_xlpm.tgr)/(1+_xlpm.w)^10,(_xlpm.pv+_xlpm.tv+_xlpm.nc)/_xlpm.shs)} | O30: {=_xlfn.LET(_xlpm.gs,DCF!$B$9,_xlpm.om,DCF!$B$10,_xlpm.w,DCF!$B$7,_xlpm.tgr,DCF!$B$8,_xlpm.n,O$28,_xlpm.lcx,$J30,_xlpm.r0,DCF!$B$37,_xlpm.om0,DCF!$B$39,_xlpm.cx0,DCF!$B$40,_xlpm.da0,DCF!$B$41,_xlpm.dar,DCF!$B$20,_xlpm.tx,DCF!$B$31,_xlpm.sb,DCF!$B$43,_xlpm.nw,DCF!$B$21,_xlpm.gd,N(DCF!$B$22),_xlpm.nc,DCF!$B$47,_xlpm.shs,DCF!$B$6,_xlpm.m,DCF!$B$48,_xlpm.t,_xlfn.SEQUENCE(10),_xlpm.g,_xlpm.gs-(_xlpm.gs-_xlpm.tgr)*(_xlpm.t-1)/9,_xlpm.cum,MMULT(--(_xlpm.t>=TRANSPOSE(_xlpm.t)),LN(1+_xlpm.g)),_xlpm.rev,_xlpm.r0*EXP(_xlpm.cum),_xlpm.prv,_xlpm.r0*EXP(_xlpm.cum-LN(1+_xlpm.g)),_xlpm.lp,IF(_xlpm.t>=_xlpm.n,1,_xlpm.t/_xlpm.n),_xlpm.omt,_xlpm.om0+(_xlpm.om-_xlpm.om0)*_xlpm.lp,_xlpm.dat,_xlpm.da0+(_xlpm.lcx*_xlpm.dar-_xlpm.da0)*_xlpm.lp,_xlpm.cpx,IF((_xlpm.t=1)*(_xlpm.gd>0),_xlpm.gd/_xlpm.rev,_xlpm.cx0+(_xlpm.lcx-_xlpm.cx0)*_xlpm.lp),_xlpm.f,_xlpm.rev*(_xlpm.omt*(1-_xlpm.tx)+_xlpm.dat-_xlpm.cpx+_xlpm.sb)-_xlpm.nw*(_xlpm.rev-_xlpm.prv),_xlpm.pv,SUM(_xlpm.f/(1+_xlpm.w)^(_xlpm.t-0.5*_xlpm.m)),_xlpm.tv,INDEX(_xlpm.f,10)*(1+_xlpm.tgr)/(_xlpm.w-_xlpm.tgr)/(1+_xlpm.w)^10,(_xlpm.pv+_xlpm.tv+_xlpm.nc)/_xlpm.shs)}
B31: =DCF!$B$9+(0) | C31: {=_xlfn.LET(_xlpm.gs,$B31,_xlpm.om,C$28,_xlpm.w,DCF!$B$7,_xlpm.tgr,DCF!$B$8,_xlpm.n,DCF!$B$11,_xlpm.lcx,DCF!$B$19,_xlpm.r0,DCF!$B$37,_xlpm.om0,DCF!$B$39,_xlpm.cx0,DCF!$B$40,_xlpm.da0,DCF!$B$41,_xlpm.dar,DCF!$B$20,_xlpm.tx,DCF!$B$31,_xlpm.sb,DCF!$B$43,_xlpm.nw,DCF!$B$21,_xlpm.gd,N(DCF!$B$22),_xlpm.nc,DCF!$B$47,_xlpm.shs,DCF!$B$6,_xlpm.m,DCF!$B$48,_xlpm.t,_xlfn.SEQUENCE(10),_xlpm.g,_xlpm.gs-(_xlpm.gs-_xlpm.tgr)*(_xlpm.t-1)/9,_xlpm.cum,MMULT(--(_xlpm.t>=TRANSPOSE(_xlpm.t)),LN(1+_xlpm.g)),_xlpm.rev,_xlpm.r0*EXP(_xlpm.cum),_xlpm.prv,_xlpm.r0*EXP(_xlpm.cum-LN(1+_xlpm.g)),_xlpm.lp,IF(_xlpm.t>=_xlpm.n,1,_xlpm.t/_xlpm.n),_xlpm.omt,_xlpm.om0+(_xlpm.om-_xlpm.om0)*_xlpm.lp,_xlpm.dat,_xlpm.da0+(_xlpm.lcx*_xlpm.dar-_xlpm.da0)*_xlpm.lp,_xlpm.cpx,IF((_xlpm.t=1)*(_xlpm.gd>0),_xlpm.gd/_xlpm.rev,_xlpm.cx0+(_xlpm.lcx-_xlpm.cx0)*_xlpm.lp),_xlpm.f,_xlpm.rev*(_xlpm.omt*(1-_xlpm.tx)+_xlpm.dat-_xlpm.cpx+_xlpm.sb)-_xlpm.nw*(_xlpm.rev-_xlpm.prv),_xlpm.pv,SUM(_xlpm.f/(1+_xlpm.w)^(_xlpm.t-0.5*_xlpm.m)),_xlpm.tv,INDEX(_xlpm.f,10)*(1+_xlpm.tgr)/(_xlpm.w-_xlpm.tgr)/(1+_xlpm.w)^10,(_xlpm.pv+_xlpm.tv+_xlpm.nc)/_xlpm.shs)} | D31: {=_xlfn.LET(_xlpm.gs,$B31,_xlpm.om,D$28,_xlpm.w,DCF!$B$7,_xlpm.tgr,DCF!$B$8,_xlpm.n,DCF!$B$11,_xlpm.lcx,DCF!$B$19,_xlpm.r0,DCF!$B$37,_xlpm.om0,DCF!$B$39,_xlpm.cx0,DCF!$B$40,_xlpm.da0,DCF!$B$41,_xlpm.dar,DCF!$B$20,_xlpm.tx,DCF!$B$31,_xlpm.sb,DCF!$B$43,_xlpm.nw,DCF!$B$21,_xlpm.gd,N(DCF!$B$22),_xlpm.nc,DCF!$B$47,_xlpm.shs,DCF!$B$6,_xlpm.m,DCF!$B$48,_xlpm.t,_xlfn.SEQUENCE(10),_xlpm.g,_xlpm.gs-(_xlpm.gs-_xlpm.tgr)*(_xlpm.t-1)/9,_xlpm.cum,MMULT(--(_xlpm.t>=TRANSPOSE(_xlpm.t)),LN(1+_xlpm.g)),_xlpm.rev,_xlpm.r0*EXP(_xlpm.cum),_xlpm.prv,_xlpm.r0*EXP(_xlpm.cum-LN(1+_xlpm.g)),_xlpm.lp,IF(_xlpm.t>=_xlpm.n,1,_xlpm.t/_xlpm.n),_xlpm.omt,_xlpm.om0+(_xlpm.om-_xlpm.om0)*_xlpm.lp,_xlpm.dat,_xlpm.da0+(_xlpm.lcx*_xlpm.dar-_xlpm.da0)*_xlpm.lp,_xlpm.cpx,IF((_xlpm.t=1)*(_xlpm.gd>0),_xlpm.gd/_xlpm.rev,_xlpm.cx0+(_xlpm.lcx-_xlpm.cx0)*_xlpm.lp),_xlpm.f,_xlpm.rev*(_xlpm.omt*(1-_xlpm.tx)+_xlpm.dat-_xlpm.cpx+_xlpm.sb)-_xlpm.nw*(_xlpm.rev-_xlpm.prv),_xlpm.pv,SUM(_xlpm.f/(1+_xlpm.w)^(_xlpm.t-0.5*_xlpm.m)),_xlpm.tv,INDEX(_xlpm.f,10)*(1+_xlpm.tgr)/(_xlpm.w-_xlpm.tgr)/(1+_xlpm.w)^10,(_xlpm.pv+_xlpm.tv+_xlpm.nc)/_xlpm.shs)} | E31: {=_xlfn.LET(_xlpm.gs,$B31,_xlpm.om,E$28,_xlpm.w,DCF!$B$7,_xlpm.tgr,DCF!$B$8,_xlpm.n,DCF!$B$11,_xlpm.lcx,DCF!$B$19,_xlpm.r0,DCF!$B$37,_xlpm.om0,DCF!$B$39,_xlpm.cx0,DCF!$B$40,_xlpm.da0,DCF!$B$41,_xlpm.dar,DCF!$B$20,_xlpm.tx,DCF!$B$31,_xlpm.sb,DCF!$B$43,_xlpm.nw,DCF!$B$21,_xlpm.gd,N(DCF!$B$22),_xlpm.nc,DCF!$B$47,_xlpm.shs,DCF!$B$6,_xlpm.m,DCF!$B$48,_xlpm.t,_xlfn.SEQUENCE(10),_xlpm.g,_xlpm.gs-(_xlpm.gs-_xlpm.tgr)*(_xlpm.t-1)/9,_xlpm.cum,MMULT(--(_xlpm.t>=TRANSPOSE(_xlpm.t)),LN(1+_xlpm.g)),_xlpm.rev,_xlpm.r0*EXP(_xlpm.cum),_xlpm.prv,_xlpm.r0*EXP(_xlpm.cum-LN(1+_xlpm.g)),_xlpm.lp,IF(_xlpm.t>=_xlpm.n,1,_xlpm.t/_xlpm.n),_xlpm.omt,_xlpm.om0+(_xlpm.om-_xlpm.om0)*_xlpm.lp,_xlpm.dat,_xlpm.da0+(_xlpm.lcx*_xlpm.dar-_xlpm.da0)*_xlpm.lp,_xlpm.cpx,IF((_xlpm.t=1)*(_xlpm.gd>0),_xlpm.gd/_xlpm.rev,_xlpm.cx0+(_xlpm.lcx-_xlpm.cx0)*_xlpm.lp),_xlpm.f,_xlpm.rev*(_xlpm.omt*(1-_xlpm.tx)+_xlpm.dat-_xlpm.cpx+_xlpm.sb)-_xlpm.nw*(_xlpm.rev-_xlpm.prv),_xlpm.pv,SUM(_xlpm.f/(1+_xlpm.w)^(_xlpm.t-0.5*_xlpm.m)),_xlpm.tv,INDEX(_xlpm.f,10)*(1+_xlpm.tgr)/(_xlpm.w-_xlpm.tgr)/(1+_xlpm.w)^10,(_xlpm.pv+_xlpm.tv+_xlpm.nc)/_xlpm.shs)} | F31: {=_xlfn.LET(_xlpm.gs,$B31,_xlpm.om,F$28,_xlpm.w,DCF!$B$7,_xlpm.tgr,DCF!$B$8,_xlpm.n,DCF!$B$11,_xlpm.lcx,DCF!$B$19,_xlpm.r0,DCF!$B$37,_xlpm.om0,DCF!$B$39,_xlpm.cx0,DCF!$B$40,_xlpm.da0,DCF!$B$41,_xlpm.dar,DCF!$B$20,_xlpm.tx,DCF!$B$31,_xlpm.sb,DCF!$B$43,_xlpm.nw,DCF!$B$21,_xlpm.gd,N(DCF!$B$22),_xlpm.nc,DCF!$B$47,_xlpm.shs,DCF!$B$6,_xlpm.m,DCF!$B$48,_xlpm.t,_xlfn.SEQUENCE(10),_xlpm.g,_xlpm.gs-(_xlpm.gs-_xlpm.tgr)*(_xlpm.t-1)/9,_xlpm.cum,MMULT(--(_xlpm.t>=TRANSPOSE(_xlpm.t)),LN(1+_xlpm.g)),_xlpm.rev,_xlpm.r0*EXP(_xlpm.cum),_xlpm.prv,_xlpm.r0*EXP(_xlpm.cum-LN(1+_xlpm.g)),_xlpm.lp,IF(_xlpm.t>=_xlpm.n,1,_xlpm.t/_xlpm.n),_xlpm.omt,_xlpm.om0+(_xlpm.om-_xlpm.om0)*_xlpm.lp,_xlpm.dat,_xlpm.da0+(_xlpm.lcx*_xlpm.dar-_xlpm.da0)*_xlpm.lp,_xlpm.cpx,IF((_xlpm.t=1)*(_xlpm.gd>0),_xlpm.gd/_xlpm.rev,_xlpm.cx0+(_xlpm.lcx-_xlpm.cx0)*_xlpm.lp),_xlpm.f,_xlpm.rev*(_xlpm.omt*(1-_xlpm.tx)+_xlpm.dat-_xlpm.cpx+_xlpm.sb)-_xlpm.nw*(_xlpm.rev-_xlpm.prv),_xlpm.pv,SUM(_xlpm.f/(1+_xlpm.w)^(_xlpm.t-0.5*_xlpm.m)),_xlpm.tv,INDEX(_xlpm.f,10)*(1+_xlpm.tgr)/(_xlpm.w-_xlpm.tgr)/(1+_xlpm.w)^10,(_xlpm.pv+_xlpm.tv+_xlpm.nc)/_xlpm.shs)} | G31: {=_xlfn.LET(_xlpm.gs,$B31,_xlpm.om,G$28,_xlpm.w,DCF!$B$7,_xlpm.tgr,DCF!$B$8,_xlpm.n,DCF!$B$11,_xlpm.lcx,DCF!$B$19,_xlpm.r0,DCF!$B$37,_xlpm.om0,DCF!$B$39,_xlpm.cx0,DCF!$B$40,_xlpm.da0,DCF!$B$41,_xlpm.dar,DCF!$B$20,_xlpm.tx,DCF!$B$31,_xlpm.sb,DCF!$B$43,_xlpm.nw,DCF!$B$21,_xlpm.gd,N(DCF!$B$22),_xlpm.nc,DCF!$B$47,_xlpm.shs,DCF!$B$6,_xlpm.m,DCF!$B$48,_xlpm.t,_xlfn.SEQUENCE(10),_xlpm.g,_xlpm.gs-(_xlpm.gs-_xlpm.tgr)*(_xlpm.t-1)/9,_xlpm.cum,MMULT(--(_xlpm.t>=TRANSPOSE(_xlpm.t)),LN(1+_xlpm.g)),_xlpm.rev,_xlpm.r0*EXP(_xlpm.cum),_xlpm.prv,_xlpm.r0*EXP(_xlpm.cum-LN(1+_xlpm.g)),_xlpm.lp,IF(_xlpm.t>=_xlpm.n,1,_xlpm.t/_xlpm.n),_xlpm.omt,_xlpm.om0+(_xlpm.om-_xlpm.om0)*_xlpm.lp,_xlpm.dat,_xlpm.da0+(_xlpm.lcx*_xlpm.dar-_xlpm.da0)*_xlpm.lp,_xlpm.cpx,IF((_xlpm.t=1)*(_xlpm.gd>0),_xlpm.gd/_xlpm.rev,_xlpm.cx0+(_xlpm.lcx-_xlpm.cx0)*_xlpm.lp),_xlpm.f,_xlpm.rev*(_xlpm.omt*(1-_xlpm.tx)+_xlpm.dat-_xlpm.cpx+_xlpm.sb)-_xlpm.nw*(_xlpm.rev-_xlpm.prv),_xlpm.pv,SUM(_xlpm.f/(1+_xlpm.w)^(_xlpm.t-0.5*_xlpm.m)),_xlpm.tv,INDEX(_xlpm.f,10)*(1+_xlpm.tgr)/(_xlpm.w-_xlpm.tgr)/(1+_xlpm.w)^10,(_xlpm.pv+_xlpm.tv+_xlpm.nc)/_xlpm.shs)} | J31: =DCF!$B$19 | K31: {=_xlfn.LET(_xlpm.gs,DCF!$B$9,_xlpm.om,DCF!$B$10,_xlpm.w,DCF!$B$7,_xlpm.tgr,DCF!$B$8,_xlpm.n,K$28,_xlpm.lcx,$J31,_xlpm.r0,DCF!$B$37,_xlpm.om0,DCF!$B$39,_xlpm.cx0,DCF!$B$40,_xlpm.da0,DCF!$B$41,_xlpm.dar,DCF!$B$20,_xlpm.tx,DCF!$B$31,_xlpm.sb,DCF!$B$43,_xlpm.nw,DCF!$B$21,_xlpm.gd,N(DCF!$B$22),_xlpm.nc,DCF!$B$47,_xlpm.shs,DCF!$B$6,_xlpm.m,DCF!$B$48,_xlpm.t,_xlfn.SEQUENCE(10),_xlpm.g,_xlpm.gs-(_xlpm.gs-_xlpm.tgr)*(_xlpm.t-1)/9,_xlpm.cum,MMULT(--(_xlpm.t>=TRANSPOSE(_xlpm.t)),LN(1+_xlpm.g)),_xlpm.rev,_xlpm.r0*EXP(_xlpm.cum),_xlpm.prv,_xlpm.r0*EXP(_xlpm.cum-LN(1+_xlpm.g)),_xlpm.lp,IF(_xlpm.t>=_xlpm.n,1,_xlpm.t/_xlpm.n),_xlpm.omt,_xlpm.om0+(_xlpm.om-_xlpm.om0)*_xlpm.lp,_xlpm.dat,_xlpm.da0+(_xlpm.lcx*_xlpm.dar-_xlpm.da0)*_xlpm.lp,_xlpm.cpx,IF((_xlpm.t=1)*(_xlpm.gd>0),_xlpm.gd/_xlpm.rev,_xlpm.cx0+(_xlpm.lcx-_xlpm.cx0)*_xlpm.lp),_xlpm.f,_xlpm.rev*(_xlpm.omt*(1-_xlpm.tx)+_xlpm.dat-_xlpm.cpx+_xlpm.sb)-_xlpm.nw*(_xlpm.rev-_xlpm.prv),_xlpm.pv,SUM(_xlpm.f/(1+_xlpm.w)^(_xlpm.t-0.5*_xlpm.m)),_xlpm.tv,INDEX(_xlpm.f,10)*(1+_xlpm.tgr)/(_xlpm.w-_xlpm.tgr)/(1+_xlpm.w)^10,(_xlpm.pv+_xlpm.tv+_xlpm.nc)/_xlpm.shs)} | L31: {=_xlfn.LET(_xlpm.gs,DCF!$B$9,_xlpm.om,DCF!$B$10,_xlpm.w,DCF!$B$7,_xlpm.tgr,DCF!$B$8,_xlpm.n,L$28,_xlpm.lcx,$J31,_xlpm.r0,DCF!$B$37,_xlpm.om0,DCF!$B$39,_xlpm.cx0,DCF!$B$40,_xlpm.da0,DCF!$B$41,_xlpm.dar,DCF!$B$20,_xlpm.tx,DCF!$B$31,_xlpm.sb,DCF!$B$43,_xlpm.nw,DCF!$B$21,_xlpm.gd,N(DCF!$B$22),_xlpm.nc,DCF!$B$47,_xlpm.shs,DCF!$B$6,_xlpm.m,DCF!$B$48,_xlpm.t,_xlfn.SEQUENCE(10),_xlpm.g,_xlpm.gs-(_xlpm.gs-_xlpm.tgr)*(_xlpm.t-1)/9,_xlpm.cum,MMULT(--(_xlpm.t>=TRANSPOSE(_xlpm.t)),LN(1+_xlpm.g)),_xlpm.rev,_xlpm.r0*EXP(_xlpm.cum),_xlpm.prv,_xlpm.r0*EXP(_xlpm.cum-LN(1+_xlpm.g)),_xlpm.lp,IF(_xlpm.t>=_xlpm.n,1,_xlpm.t/_xlpm.n),_xlpm.omt,_xlpm.om0+(_xlpm.om-_xlpm.om0)*_xlpm.lp,_xlpm.dat,_xlpm.da0+(_xlpm.lcx*_xlpm.dar-_xlpm.da0)*_xlpm.lp,_xlpm.cpx,IF((_xlpm.t=1)*(_xlpm.gd>0),_xlpm.gd/_xlpm.rev,_xlpm.cx0+(_xlpm.lcx-_xlpm.cx0)*_xlpm.lp),_xlpm.f,_xlpm.rev*(_xlpm.omt*(1-_xlpm.tx)+_xlpm.dat-_xlpm.cpx+_xlpm.sb)-_xlpm.nw*(_xlpm.rev-_xlpm.prv),_xlpm.pv,SUM(_xlpm.f/(1+_xlpm.w)^(_xlpm.t-0.5*_xlpm.m)),_xlpm.tv,INDEX(_xlpm.f,10)*(1+_xlpm.tgr)/(_xlpm.w-_xlpm.tgr)/(1+_xlpm.w)^10,(_xlpm.pv+_xlpm.tv+_xlpm.nc)/_xlpm.shs)} | M31: {=_xlfn.LET(_xlpm.gs,DCF!$B$9,_xlpm.om,DCF!$B$10,_xlpm.w,DCF!$B$7,_xlpm.tgr,DCF!$B$8,_xlpm.n,M$28,_xlpm.lcx,$J31,_xlpm.r0,DCF!$B$37,_xlpm.om0,DCF!$B$39,_xlpm.cx0,DCF!$B$40,_xlpm.da0,DCF!$B$41,_xlpm.dar,DCF!$B$20,_xlpm.tx,DCF!$B$31,_xlpm.sb,DCF!$B$43,_xlpm.nw,DCF!$B$21,_xlpm.gd,N(DCF!$B$22),_xlpm.nc,DCF!$B$47,_xlpm.shs,DCF!$B$6,_xlpm.m,DCF!$B$48,_xlpm.t,_xlfn.SEQUENCE(10),_xlpm.g,_xlpm.gs-(_xlpm.gs-_xlpm.tgr)*(_xlpm.t-1)/9,_xlpm.cum,MMULT(--(_xlpm.t>=TRANSPOSE(_xlpm.t)),LN(1+_xlpm.g)),_xlpm.rev,_xlpm.r0*EXP(_xlpm.cum),_xlpm.prv,_xlpm.r0*EXP(_xlpm.cum-LN(1+_xlpm.g)),_xlpm.lp,IF(_xlpm.t>=_xlpm.n,1,_xlpm.t/_xlpm.n),_xlpm.omt,_xlpm.om0+(_xlpm.om-_xlpm.om0)*_xlpm.lp,_xlpm.dat,_xlpm.da0+(_xlpm.lcx*_xlpm.dar-_xlpm.da0)*_xlpm.lp,_xlpm.cpx,IF((_xlpm.t=1)*(_xlpm.gd>0),_xlpm.gd/_xlpm.rev,_xlpm.cx0+(_xlpm.lcx-_xlpm.cx0)*_xlpm.lp),_xlpm.f,_xlpm.rev*(_xlpm.omt*(1-_xlpm.tx)+_xlpm.dat-_xlpm.cpx+_xlpm.sb)-_xlpm.nw*(_xlpm.rev-_xlpm.prv),_xlpm.pv,SUM(_xlpm.f/(1+_xlpm.w)^(_xlpm.t-0.5*_xlpm.m)),_xlpm.tv,INDEX(_xlpm.f,10)*(1+_xlpm.tgr)/(_xlpm.w-_xlpm.tgr)/(1+_xlpm.w)^10,(_xlpm.pv+_xlpm.tv+_xlpm.nc)/_xlpm.shs)} | N31: {=_xlfn.LET(_xlpm.gs,DCF!$B$9,_xlpm.om,DCF!$B$10,_xlpm.w,DCF!$B$7,_xlpm.tgr,DCF!$B$8,_xlpm.n,N$28,_xlpm.lcx,$J31,_xlpm.r0,DCF!$B$37,_xlpm.om0,DCF!$B$39,_xlpm.cx0,DCF!$B$40,_xlpm.da0,DCF!$B$41,_xlpm.dar,DCF!$B$20,_xlpm.tx,DCF!$B$31,_xlpm.sb,DCF!$B$43,_xlpm.nw,DCF!$B$21,_xlpm.gd,N(DCF!$B$22),_xlpm.nc,DCF!$B$47,_xlpm.shs,DCF!$B$6,_xlpm.m,DCF!$B$48,_xlpm.t,_xlfn.SEQUENCE(10),_xlpm.g,_xlpm.gs-(_xlpm.gs-_xlpm.tgr)*(_xlpm.t-1)/9,_xlpm.cum,MMULT(--(_xlpm.t>=TRANSPOSE(_xlpm.t)),LN(1+_xlpm.g)),_xlpm.rev,_xlpm.r0*EXP(_xlpm.cum),_xlpm.prv,_xlpm.r0*EXP(_xlpm.cum-LN(1+_xlpm.g)),_xlpm.lp,IF(_xlpm.t>=_xlpm.n,1,_xlpm.t/_xlpm.n),_xlpm.omt,_xlpm.om0+(_xlpm.om-_xlpm.om0)*_xlpm.lp,_xlpm.dat,_xlpm.da0+(_xlpm.lcx*_xlpm.dar-_xlpm.da0)*_xlpm.lp,_xlpm.cpx,IF((_xlpm.t=1)*(_xlpm.gd>0),_xlpm.gd/_xlpm.rev,_xlpm.cx0+(_xlpm.lcx-_xlpm.cx0)*_xlpm.lp),_xlpm.f,_xlpm.rev*(_xlpm.omt*(1-_xlpm.tx)+_xlpm.dat-_xlpm.cpx+_xlpm.sb)-_xlpm.nw*(_xlpm.rev-_xlpm.prv),_xlpm.pv,SUM(_xlpm.f/(1+_xlpm.w)^(_xlpm.t-0.5*_xlpm.m)),_xlpm.tv,INDEX(_xlpm.f,10)*(1+_xlpm.tgr)/(_xlpm.w-_xlpm.tgr)/(1+_xlpm.w)^10,(_xlpm.pv+_xlpm.tv+_xlpm.nc)/_xlpm.shs)} | O31: {=_xlfn.LET(_xlpm.gs,DCF!$B$9,_xlpm.om,DCF!$B$10,_xlpm.w,DCF!$B$7,_xlpm.tgr,DCF!$B$8,_xlpm.n,O$28,_xlpm.lcx,$J31,_xlpm.r0,DCF!$B$37,_xlpm.om0,DCF!$B$39,_xlpm.cx0,DCF!$B$40,_xlpm.da0,DCF!$B$41,_xlpm.dar,DCF!$B$20,_xlpm.tx,DCF!$B$31,_xlpm.sb,DCF!$B$43,_xlpm.nw,DCF!$B$21,_xlpm.gd,N(DCF!$B$22),_xlpm.nc,DCF!$B$47,_xlpm.shs,DCF!$B$6,_xlpm.m,DCF!$B$48,_xlpm.t,_xlfn.SEQUENCE(10),_xlpm.g,_xlpm.gs-(_xlpm.gs-_xlpm.tgr)*(_xlpm.t-1)/9,_xlpm.cum,MMULT(--(_xlpm.t>=TRANSPOSE(_xlpm.t)),LN(1+_xlpm.g)),_xlpm.rev,_xlpm.r0*EXP(_xlpm.cum),_xlpm.prv,_xlpm.r0*EXP(_xlpm.cum-LN(1+_xlpm.g)),_xlpm.lp,IF(_xlpm.t>=_xlpm.n,1,_xlpm.t/_xlpm.n),_xlpm.omt,_xlpm.om0+(_xlpm.om-_xlpm.om0)*_xlpm.lp,_xlpm.dat,_xlpm.da0+(_xlpm.lcx*_xlpm.dar-_xlpm.da0)*_xlpm.lp,_xlpm.cpx,IF((_xlpm.t=1)*(_xlpm.gd>0),_xlpm.gd/_xlpm.rev,_xlpm.cx0+(_xlpm.lcx-_xlpm.cx0)*_xlpm.lp),_xlpm.f,_xlpm.rev*(_xlpm.omt*(1-_xlpm.tx)+_xlpm.dat-_xlpm.cpx+_xlpm.sb)-_xlpm.nw*(_xlpm.rev-_xlpm.prv),_xlpm.pv,SUM(_xlpm.f/(1+_xlpm.w)^(_xlpm.t-0.5*_xlpm.m)),_xlpm.tv,INDEX(_xlpm.f,10)*(1+_xlpm.tgr)/(_xlpm.w-_xlpm.tgr)/(1+_xlpm.w)^10,(_xlpm.pv+_xlpm.tv+_xlpm.nc)/_xlpm.shs)}
B32: =DCF!$B$9+(0.03) | C32: {=_xlfn.LET(_xlpm.gs,$B32,_xlpm.om,C$28,_xlpm.w,DCF!$B$7,_xlpm.tgr,DCF!$B$8,_xlpm.n,DCF!$B$11,_xlpm.lcx,DCF!$B$19,_xlpm.r0,DCF!$B$37,_xlpm.om0,DCF!$B$39,_xlpm.cx0,DCF!$B$40,_xlpm.da0,DCF!$B$41,_xlpm.dar,DCF!$B$20,_xlpm.tx,DCF!$B$31,_xlpm.sb,DCF!$B$43,_xlpm.nw,DCF!$B$21,_xlpm.gd,N(DCF!$B$22),_xlpm.nc,DCF!$B$47,_xlpm.shs,DCF!$B$6,_xlpm.m,DCF!$B$48,_xlpm.t,_xlfn.SEQUENCE(10),_xlpm.g,_xlpm.gs-(_xlpm.gs-_xlpm.tgr)*(_xlpm.t-1)/9,_xlpm.cum,MMULT(--(_xlpm.t>=TRANSPOSE(_xlpm.t)),LN(1+_xlpm.g)),_xlpm.rev,_xlpm.r0*EXP(_xlpm.cum),_xlpm.prv,_xlpm.r0*EXP(_xlpm.cum-LN(1+_xlpm.g)),_xlpm.lp,IF(_xlpm.t>=_xlpm.n,1,_xlpm.t/_xlpm.n),_xlpm.omt,_xlpm.om0+(_xlpm.om-_xlpm.om0)*_xlpm.lp,_xlpm.dat,_xlpm.da0+(_xlpm.lcx*_xlpm.dar-_xlpm.da0)*_xlpm.lp,_xlpm.cpx,IF((_xlpm.t=1)*(_xlpm.gd>0),_xlpm.gd/_xlpm.rev,_xlpm.cx0+(_xlpm.lcx-_xlpm.cx0)*_xlpm.lp),_xlpm.f,_xlpm.rev*(_xlpm.omt*(1-_xlpm.tx)+_xlpm.dat-_xlpm.cpx+_xlpm.sb)-_xlpm.nw*(_xlpm.rev-_xlpm.prv),_xlpm.pv,SUM(_xlpm.f/(1+_xlpm.w)^(_xlpm.t-0.5*_xlpm.m)),_xlpm.tv,INDEX(_xlpm.f,10)*(1+_xlpm.tgr)/(_xlpm.w-_xlpm.tgr)/(1+_xlpm.w)^10,(_xlpm.pv+_xlpm.tv+_xlpm.nc)/_xlpm.shs)} | D32: {=_xlfn.LET(_xlpm.gs,$B32,_xlpm.om,D$28,_xlpm.w,DCF!$B$7,_xlpm.tgr,DCF!$B$8,_xlpm.n,DCF!$B$11,_xlpm.lcx,DCF!$B$19,_xlpm.r0,DCF!$B$37,_xlpm.om0,DCF!$B$39,_xlpm.cx0,DCF!$B$40,_xlpm.da0,DCF!$B$41,_xlpm.dar,DCF!$B$20,_xlpm.tx,DCF!$B$31,_xlpm.sb,DCF!$B$43,_xlpm.nw,DCF!$B$21,_xlpm.gd,N(DCF!$B$22),_xlpm.nc,DCF!$B$47,_xlpm.shs,DCF!$B$6,_xlpm.m,DCF!$B$48,_xlpm.t,_xlfn.SEQUENCE(10),_xlpm.g,_xlpm.gs-(_xlpm.gs-_xlpm.tgr)*(_xlpm.t-1)/9,_xlpm.cum,MMULT(--(_xlpm.t>=TRANSPOSE(_xlpm.t)),LN(1+_xlpm.g)),_xlpm.rev,_xlpm.r0*EXP(_xlpm.cum),_xlpm.prv,_xlpm.r0*EXP(_xlpm.cum-LN(1+_xlpm.g)),_xlpm.lp,IF(_xlpm.t>=_xlpm.n,1,_xlpm.t/_xlpm.n),_xlpm.omt,_xlpm.om0+(_xlpm.om-_xlpm.om0)*_xlpm.lp,_xlpm.dat,_xlpm.da0+(_xlpm.lcx*_xlpm.dar-_xlpm.da0)*_xlpm.lp,_xlpm.cpx,IF((_xlpm.t=1)*(_xlpm.gd>0),_xlpm.gd/_xlpm.rev,_xlpm.cx0+(_xlpm.lcx-_xlpm.cx0)*_xlpm.lp),_xlpm.f,_xlpm.rev*(_xlpm.omt*(1-_xlpm.tx)+_xlpm.dat-_xlpm.cpx+_xlpm.sb)-_xlpm.nw*(_xlpm.rev-_xlpm.prv),_xlpm.pv,SUM(_xlpm.f/(1+_xlpm.w)^(_xlpm.t-0.5*_xlpm.m)),_xlpm.tv,INDEX(_xlpm.f,10)*(1+_xlpm.tgr)/(_xlpm.w-_xlpm.tgr)/(1+_xlpm.w)^10,(_xlpm.pv+_xlpm.tv+_xlpm.nc)/_xlpm.shs)} | E32: {=_xlfn.LET(_xlpm.gs,$B32,_xlpm.om,E$28,_xlpm.w,DCF!$B$7,_xlpm.tgr,DCF!$B$8,_xlpm.n,DCF!$B$11,_xlpm.lcx,DCF!$B$19,_xlpm.r0,DCF!$B$37,_xlpm.om0,DCF!$B$39,_xlpm.cx0,DCF!$B$40,_xlpm.da0,DCF!$B$41,_xlpm.dar,DCF!$B$20,_xlpm.tx,DCF!$B$31,_xlpm.sb,DCF!$B$43,_xlpm.nw,DCF!$B$21,_xlpm.gd,N(DCF!$B$22),_xlpm.nc,DCF!$B$47,_xlpm.shs,DCF!$B$6,_xlpm.m,DCF!$B$48,_xlpm.t,_xlfn.SEQUENCE(10),_xlpm.g,_xlpm.gs-(_xlpm.gs-_xlpm.tgr)*(_xlpm.t-1)/9,_xlpm.cum,MMULT(--(_xlpm.t>=TRANSPOSE(_xlpm.t)),LN(1+_xlpm.g)),_xlpm.rev,_xlpm.r0*EXP(_xlpm.cum),_xlpm.prv,_xlpm.r0*EXP(_xlpm.cum-LN(1+_xlpm.g)),_xlpm.lp,IF(_xlpm.t>=_xlpm.n,1,_xlpm.t/_xlpm.n),_xlpm.omt,_xlpm.om0+(_xlpm.om-_xlpm.om0)*_xlpm.lp,_xlpm.dat,_xlpm.da0+(_xlpm.lcx*_xlpm.dar-_xlpm.da0)*_xlpm.lp,_xlpm.cpx,IF((_xlpm.t=1)*(_xlpm.gd>0),_xlpm.gd/_xlpm.rev,_xlpm.cx0+(_xlpm.lcx-_xlpm.cx0)*_xlpm.lp),_xlpm.f,_xlpm.rev*(_xlpm.omt*(1-_xlpm.tx)+_xlpm.dat-_xlpm.cpx+_xlpm.sb)-_xlpm.nw*(_xlpm.rev-_xlpm.prv),_xlpm.pv,SUM(_xlpm.f/(1+_xlpm.w)^(_xlpm.t-0.5*_xlpm.m)),_xlpm.tv,INDEX(_xlpm.f,10)*(1+_xlpm.tgr)/(_xlpm.w-_xlpm.tgr)/(1+_xlpm.w)^10,(_xlpm.pv+_xlpm.tv+_xlpm.nc)/_xlpm.shs)} | F32: {=_xlfn.LET(_xlpm.gs,$B32,_xlpm.om,F$28,_xlpm.w,DCF!$B$7,_xlpm.tgr,DCF!$B$8,_xlpm.n,DCF!$B$11,_xlpm.lcx,DCF!$B$19,_xlpm.r0,DCF!$B$37,_xlpm.om0,DCF!$B$39,_xlpm.cx0,DCF!$B$40,_xlpm.da0,DCF!$B$41,_xlpm.dar,DCF!$B$20,_xlpm.tx,DCF!$B$31,_xlpm.sb,DCF!$B$43,_xlpm.nw,DCF!$B$21,_xlpm.gd,N(DCF!$B$22),_xlpm.nc,DCF!$B$47,_xlpm.shs,DCF!$B$6,_xlpm.m,DCF!$B$48,_xlpm.t,_xlfn.SEQUENCE(10),_xlpm.g,_xlpm.gs-(_xlpm.gs-_xlpm.tgr)*(_xlpm.t-1)/9,_xlpm.cum,MMULT(--(_xlpm.t>=TRANSPOSE(_xlpm.t)),LN(1+_xlpm.g)),_xlpm.rev,_xlpm.r0*EXP(_xlpm.cum),_xlpm.prv,_xlpm.r0*EXP(_xlpm.cum-LN(1+_xlpm.g)),_xlpm.lp,IF(_xlpm.t>=_xlpm.n,1,_xlpm.t/_xlpm.n),_xlpm.omt,_xlpm.om0+(_xlpm.om-_xlpm.om0)*_xlpm.lp,_xlpm.dat,_xlpm.da0+(_xlpm.lcx*_xlpm.dar-_xlpm.da0)*_xlpm.lp,_xlpm.cpx,IF((_xlpm.t=1)*(_xlpm.gd>0),_xlpm.gd/_xlpm.rev,_xlpm.cx0+(_xlpm.lcx-_xlpm.cx0)*_xlpm.lp),_xlpm.f,_xlpm.rev*(_xlpm.omt*(1-_xlpm.tx)+_xlpm.dat-_xlpm.cpx+_xlpm.sb)-_xlpm.nw*(_xlpm.rev-_xlpm.prv),_xlpm.pv,SUM(_xlpm.f/(1+_xlpm.w)^(_xlpm.t-0.5*_xlpm.m)),_xlpm.tv,INDEX(_xlpm.f,10)*(1+_xlpm.tgr)/(_xlpm.w-_xlpm.tgr)/(1+_xlpm.w)^10,(_xlpm.pv+_xlpm.tv+_xlpm.nc)/_xlpm.shs)} | G32: {=_xlfn.LET(_xlpm.gs,$B32,_xlpm.om,G$28,_xlpm.w,DCF!$B$7,_xlpm.tgr,DCF!$B$8,_xlpm.n,DCF!$B$11,_xlpm.lcx,DCF!$B$19,_xlpm.r0,DCF!$B$37,_xlpm.om0,DCF!$B$39,_xlpm.cx0,DCF!$B$40,_xlpm.da0,DCF!$B$41,_xlpm.dar,DCF!$B$20,_xlpm.tx,DCF!$B$31,_xlpm.sb,DCF!$B$43,_xlpm.nw,DCF!$B$21,_xlpm.gd,N(DCF!$B$22),_xlpm.nc,DCF!$B$47,_xlpm.shs,DCF!$B$6,_xlpm.m,DCF!$B$48,_xlpm.t,_xlfn.SEQUENCE(10),_xlpm.g,_xlpm.gs-(_xlpm.gs-_xlpm.tgr)*(_xlpm.t-1)/9,_xlpm.cum,MMULT(--(_xlpm.t>=TRANSPOSE(_xlpm.t)),LN(1+_xlpm.g)),_xlpm.rev,_xlpm.r0*EXP(_xlpm.cum),_xlpm.prv,_xlpm.r0*EXP(_xlpm.cum-LN(1+_xlpm.g)),_xlpm.lp,IF(_xlpm.t>=_xlpm.n,1,_xlpm.t/_xlpm.n),_xlpm.omt,_xlpm.om0+(_xlpm.om-_xlpm.om0)*_xlpm.lp,_xlpm.dat,_xlpm.da0+(_xlpm.lcx*_xlpm.dar-_xlpm.da0)*_xlpm.lp,_xlpm.cpx,IF((_xlpm.t=1)*(_xlpm.gd>0),_xlpm.gd/_xlpm.rev,_xlpm.cx0+(_xlpm.lcx-_xlpm.cx0)*_xlpm.lp),_xlpm.f,_xlpm.rev*(_xlpm.omt*(1-_xlpm.tx)+_xlpm.dat-_xlpm.cpx+_xlpm.sb)-_xlpm.nw*(_xlpm.rev-_xlpm.prv),_xlpm.pv,SUM(_xlpm.f/(1+_xlpm.w)^(_xlpm.t-0.5*_xlpm.m)),_xlpm.tv,INDEX(_xlpm.f,10)*(1+_xlpm.tgr)/(_xlpm.w-_xlpm.tgr)/(1+_xlpm.w)^10,(_xlpm.pv+_xlpm.tv+_xlpm.nc)/_xlpm.shs)} | J32: =DCF!$B$19+0.02 | K32: {=_xlfn.LET(_xlpm.gs,DCF!$B$9,_xlpm.om,DCF!$B$10,_xlpm.w,DCF!$B$7,_xlpm.tgr,DCF!$B$8,_xlpm.n,K$28,_xlpm.lcx,$J32,_xlpm.r0,DCF!$B$37,_xlpm.om0,DCF!$B$39,_xlpm.cx0,DCF!$B$40,_xlpm.da0,DCF!$B$41,_xlpm.dar,DCF!$B$20,_xlpm.tx,DCF!$B$31,_xlpm.sb,DCF!$B$43,_xlpm.nw,DCF!$B$21,_xlpm.gd,N(DCF!$B$22),_xlpm.nc,DCF!$B$47,_xlpm.shs,DCF!$B$6,_xlpm.m,DCF!$B$48,_xlpm.t,_xlfn.SEQUENCE(10),_xlpm.g,_xlpm.gs-(_xlpm.gs-_xlpm.tgr)*(_xlpm.t-1)/9,_xlpm.cum,MMULT(--(_xlpm.t>=TRANSPOSE(_xlpm.t)),LN(1+_xlpm.g)),_xlpm.rev,_xlpm.r0*EXP(_xlpm.cum),_xlpm.prv,_xlpm.r0*EXP(_xlpm.cum-LN(1+_xlpm.g)),_xlpm.lp,IF(_xlpm.t>=_xlpm.n,1,_xlpm.t/_xlpm.n),_xlpm.omt,_xlpm.om0+(_xlpm.om-_xlpm.om0)*_xlpm.lp,_xlpm.dat,_xlpm.da0+(_xlpm.lcx*_xlpm.dar-_xlpm.da0)*_xlpm.lp,_xlpm.cpx,IF((_xlpm.t=1)*(_xlpm.gd>0),_xlpm.gd/_xlpm.rev,_xlpm.cx0+(_xlpm.lcx-_xlpm.cx0)*_xlpm.lp),_xlpm.f,_xlpm.rev*(_xlpm.omt*(1-_xlpm.tx)+_xlpm.dat-_xlpm.cpx+_xlpm.sb)-_xlpm.nw*(_xlpm.rev-_xlpm.prv),_xlpm.pv,SUM(_xlpm.f/(1+_xlpm.w)^(_xlpm.t-0.5*_xlpm.m)),_xlpm.tv,INDEX(_xlpm.f,10)*(1+_xlpm.tgr)/(_xlpm.w-_xlpm.tgr)/(1+_xlpm.w)^10,(_xlpm.pv+_xlpm.tv+_xlpm.nc)/_xlpm.shs)} | L32: {=_xlfn.LET(_xlpm.gs,DCF!$B$9,_xlpm.om,DCF!$B$10,_xlpm.w,DCF!$B$7,_xlpm.tgr,DCF!$B$8,_xlpm.n,L$28,_xlpm.lcx,$J32,_xlpm.r0,DCF!$B$37,_xlpm.om0,DCF!$B$39,_xlpm.cx0,DCF!$B$40,_xlpm.da0,DCF!$B$41,_xlpm.dar,DCF!$B$20,_xlpm.tx,DCF!$B$31,_xlpm.sb,DCF!$B$43,_xlpm.nw,DCF!$B$21,_xlpm.gd,N(DCF!$B$22),_xlpm.nc,DCF!$B$47,_xlpm.shs,DCF!$B$6,_xlpm.m,DCF!$B$48,_xlpm.t,_xlfn.SEQUENCE(10),_xlpm.g,_xlpm.gs-(_xlpm.gs-_xlpm.tgr)*(_xlpm.t-1)/9,_xlpm.cum,MMULT(--(_xlpm.t>=TRANSPOSE(_xlpm.t)),LN(1+_xlpm.g)),_xlpm.rev,_xlpm.r0*EXP(_xlpm.cum),_xlpm.prv,_xlpm.r0*EXP(_xlpm.cum-LN(1+_xlpm.g)),_xlpm.lp,IF(_xlpm.t>=_xlpm.n,1,_xlpm.t/_xlpm.n),_xlpm.omt,_xlpm.om0+(_xlpm.om-_xlpm.om0)*_xlpm.lp,_xlpm.dat,_xlpm.da0+(_xlpm.lcx*_xlpm.dar-_xlpm.da0)*_xlpm.lp,_xlpm.cpx,IF((_xlpm.t=1)*(_xlpm.gd>0),_xlpm.gd/_xlpm.rev,_xlpm.cx0+(_xlpm.lcx-_xlpm.cx0)*_xlpm.lp),_xlpm.f,_xlpm.rev*(_xlpm.omt*(1-_xlpm.tx)+_xlpm.dat-_xlpm.cpx+_xlpm.sb)-_xlpm.nw*(_xlpm.rev-_xlpm.prv),_xlpm.pv,SUM(_xlpm.f/(1+_xlpm.w)^(_xlpm.t-0.5*_xlpm.m)),_xlpm.tv,INDEX(_xlpm.f,10)*(1+_xlpm.tgr)/(_xlpm.w-_xlpm.tgr)/(1+_xlpm.w)^10,(_xlpm.pv+_xlpm.tv+_xlpm.nc)/_xlpm.shs)} | M32: {=_xlfn.LET(_xlpm.gs,DCF!$B$9,_xlpm.om,DCF!$B$10,_xlpm.w,DCF!$B$7,_xlpm.tgr,DCF!$B$8,_xlpm.n,M$28,_xlpm.lcx,$J32,_xlpm.r0,DCF!$B$37,_xlpm.om0,DCF!$B$39,_xlpm.cx0,DCF!$B$40,_xlpm.da0,DCF!$B$41,_xlpm.dar,DCF!$B$20,_xlpm.tx,DCF!$B$31,_xlpm.sb,DCF!$B$43,_xlpm.nw,DCF!$B$21,_xlpm.gd,N(DCF!$B$22),_xlpm.nc,DCF!$B$47,_xlpm.shs,DCF!$B$6,_xlpm.m,DCF!$B$48,_xlpm.t,_xlfn.SEQUENCE(10),_xlpm.g,_xlpm.gs-(_xlpm.gs-_xlpm.tgr)*(_xlpm.t-1)/9,_xlpm.cum,MMULT(--(_xlpm.t>=TRANSPOSE(_xlpm.t)),LN(1+_xlpm.g)),_xlpm.rev,_xlpm.r0*EXP(_xlpm.cum),_xlpm.prv,_xlpm.r0*EXP(_xlpm.cum-LN(1+_xlpm.g)),_xlpm.lp,IF(_xlpm.t>=_xlpm.n,1,_xlpm.t/_xlpm.n),_xlpm.omt,_xlpm.om0+(_xlpm.om-_xlpm.om0)*_xlpm.lp,_xlpm.dat,_xlpm.da0+(_xlpm.lcx*_xlpm.dar-_xlpm.da0)*_xlpm.lp,_xlpm.cpx,IF((_xlpm.t=1)*(_xlpm.gd>0),_xlpm.gd/_xlpm.rev,_xlpm.cx0+(_xlpm.lcx-_xlpm.cx0)*_xlpm.lp),_xlpm.f,_xlpm.rev*(_xlpm.omt*(1-_xlpm.tx)+_xlpm.dat-_xlpm.cpx+_xlpm.sb)-_xlpm.nw*(_xlpm.rev-_xlpm.prv),_xlpm.pv,SUM(_xlpm.f/(1+_xlpm.w)^(_xlpm.t-0.5*_xlpm.m)),_xlpm.tv,INDEX(_xlpm.f,10)*(1+_xlpm.tgr)/(_xlpm.w-_xlpm.tgr)/(1+_xlpm.w)^10,(_xlpm.pv+_xlpm.tv+_xlpm.nc)/_xlpm.shs)} | N32: {=_xlfn.LET(_xlpm.gs,DCF!$B$9,_xlpm.om,DCF!$B$10,_xlpm.w,DCF!$B$7,_xlpm.tgr,DCF!$B$8,_xlpm.n,N$28,_xlpm.lcx,$J32,_xlpm.r0,DCF!$B$37,_xlpm.om0,DCF!$B$39,_xlpm.cx0,DCF!$B$40,_xlpm.da0,DCF!$B$41,_xlpm.dar,DCF!$B$20,_xlpm.tx,DCF!$B$31,_xlpm.sb,DCF!$B$43,_xlpm.nw,DCF!$B$21,_xlpm.gd,N(DCF!$B$22),_xlpm.nc,DCF!$B$47,_xlpm.shs,DCF!$B$6,_xlpm.m,DCF!$B$48,_xlpm.t,_xlfn.SEQUENCE(10),_xlpm.g,_xlpm.gs-(_xlpm.gs-_xlpm.tgr)*(_xlpm.t-1)/9,_xlpm.cum,MMULT(--(_xlpm.t>=TRANSPOSE(_xlpm.t)),LN(1+_xlpm.g)),_xlpm.rev,_xlpm.r0*EXP(_xlpm.cum),_xlpm.prv,_xlpm.r0*EXP(_xlpm.cum-LN(1+_xlpm.g)),_xlpm.lp,IF(_xlpm.t>=_xlpm.n,1,_xlpm.t/_xlpm.n),_xlpm.omt,_xlpm.om0+(_xlpm.om-_xlpm.om0)*_xlpm.lp,_xlpm.dat,_xlpm.da0+(_xlpm.lcx*_xlpm.dar-_xlpm.da0)*_xlpm.lp,_xlpm.cpx,IF((_xlpm.t=1)*(_xlpm.gd>0),_xlpm.gd/_xlpm.rev,_xlpm.cx0+(_xlpm.lcx-_xlpm.cx0)*_xlpm.lp),_xlpm.f,_xlpm.rev*(_xlpm.omt*(1-_xlpm.tx)+_xlpm.dat-_xlpm.cpx+_xlpm.sb)-_xlpm.nw*(_xlpm.rev-_xlpm.prv),_xlpm.pv,SUM(_xlpm.f/(1+_xlpm.w)^(_xlpm.t-0.5*_xlpm.m)),_xlpm.tv,INDEX(_xlpm.f,10)*(1+_xlpm.tgr)/(_xlpm.w-_xlpm.tgr)/(1+_xlpm.w)^10,(_xlpm.pv+_xlpm.tv+_xlpm.nc)/_xlpm.shs)} | O32: {=_xlfn.LET(_xlpm.gs,DCF!$B$9,_xlpm.om,DCF!$B$10,_xlpm.w,DCF!$B$7,_xlpm.tgr,DCF!$B$8,_xlpm.n,O$28,_xlpm.lcx,$J32,_xlpm.r0,DCF!$B$37,_xlpm.om0,DCF!$B$39,_xlpm.cx0,DCF!$B$40,_xlpm.da0,DCF!$B$41,_xlpm.dar,DCF!$B$20,_xlpm.tx,DCF!$B$31,_xlpm.sb,DCF!$B$43,_xlpm.nw,DCF!$B$21,_xlpm.gd,N(DCF!$B$22),_xlpm.nc,DCF!$B$47,_xlpm.shs,DCF!$B$6,_xlpm.m,DCF!$B$48,_xlpm.t,_xlfn.SEQUENCE(10),_xlpm.g,_xlpm.gs-(_xlpm.gs-_xlpm.tgr)*(_xlpm.t-1)/9,_xlpm.cum,MMULT(--(_xlpm.t>=TRANSPOSE(_xlpm.t)),LN(1+_xlpm.g)),_xlpm.rev,_xlpm.r0*EXP(_xlpm.cum),_xlpm.prv,_xlpm.r0*EXP(_xlpm.cum-LN(1+_xlpm.g)),_xlpm.lp,IF(_xlpm.t>=_xlpm.n,1,_xlpm.t/_xlpm.n),_xlpm.omt,_xlpm.om0+(_xlpm.om-_xlpm.om0)*_xlpm.lp,_xlpm.dat,_xlpm.da0+(_xlpm.lcx*_xlpm.dar-_xlpm.da0)*_xlpm.lp,_xlpm.cpx,IF((_xlpm.t=1)*(_xlpm.gd>0),_xlpm.gd/_xlpm.rev,_xlpm.cx0+(_xlpm.lcx-_xlpm.cx0)*_xlpm.lp),_xlpm.f,_xlpm.rev*(_xlpm.omt*(1-_xlpm.tx)+_xlpm.dat-_xlpm.cpx+_xlpm.sb)-_xlpm.nw*(_xlpm.rev-_xlpm.prv),_xlpm.pv,SUM(_xlpm.f/(1+_xlpm.w)^(_xlpm.t-0.5*_xlpm.m)),_xlpm.tv,INDEX(_xlpm.f,10)*(1+_xlpm.tgr)/(_xlpm.w-_xlpm.tgr)/(1+_xlpm.w)^10,(_xlpm.pv+_xlpm.tv+_xlpm.nc)/_xlpm.shs)}
B33: =DCF!$B$9+(0.06) | C33: {=_xlfn.LET(_xlpm.gs,$B33,_xlpm.om,C$28,_xlpm.w,DCF!$B$7,_xlpm.tgr,DCF!$B$8,_xlpm.n,DCF!$B$11,_xlpm.lcx,DCF!$B$19,_xlpm.r0,DCF!$B$37,_xlpm.om0,DCF!$B$39,_xlpm.cx0,DCF!$B$40,_xlpm.da0,DCF!$B$41,_xlpm.dar,DCF!$B$20,_xlpm.tx,DCF!$B$31,_xlpm.sb,DCF!$B$43,_xlpm.nw,DCF!$B$21,_xlpm.gd,N(DCF!$B$22),_xlpm.nc,DCF!$B$47,_xlpm.shs,DCF!$B$6,_xlpm.m,DCF!$B$48,_xlpm.t,_xlfn.SEQUENCE(10),_xlpm.g,_xlpm.gs-(_xlpm.gs-_xlpm.tgr)*(_xlpm.t-1)/9,_xlpm.cum,MMULT(--(_xlpm.t>=TRANSPOSE(_xlpm.t)),LN(1+_xlpm.g)),_xlpm.rev,_xlpm.r0*EXP(_xlpm.cum),_xlpm.prv,_xlpm.r0*EXP(_xlpm.cum-LN(1+_xlpm.g)),_xlpm.lp,IF(_xlpm.t>=_xlpm.n,1,_xlpm.t/_xlpm.n),_xlpm.omt,_xlpm.om0+(_xlpm.om-_xlpm.om0)*_xlpm.lp,_xlpm.dat,_xlpm.da0+(_xlpm.lcx*_xlpm.dar-_xlpm.da0)*_xlpm.lp,_xlpm.cpx,IF((_xlpm.t=1)*(_xlpm.gd>0),_xlpm.gd/_xlpm.rev,_xlpm.cx0+(_xlpm.lcx-_xlpm.cx0)*_xlpm.lp),_xlpm.f,_xlpm.rev*(_xlpm.omt*(1-_xlpm.tx)+_xlpm.dat-_xlpm.cpx+_xlpm.sb)-_xlpm.nw*(_xlpm.rev-_xlpm.prv),_xlpm.pv,SUM(_xlpm.f/(1+_xlpm.w)^(_xlpm.t-0.5*_xlpm.m)),_xlpm.tv,INDEX(_xlpm.f,10)*(1+_xlpm.tgr)/(_xlpm.w-_xlpm.tgr)/(1+_xlpm.w)^10,(_xlpm.pv+_xlpm.tv+_xlpm.nc)/_xlpm.shs)} | D33: {=_xlfn.LET(_xlpm.gs,$B33,_xlpm.om,D$28,_xlpm.w,DCF!$B$7,_xlpm.tgr,DCF!$B$8,_xlpm.n,DCF!$B$11,_xlpm.lcx,DCF!$B$19,_xlpm.r0,DCF!$B$37,_xlpm.om0,DCF!$B$39,_xlpm.cx0,DCF!$B$40,_xlpm.da0,DCF!$B$41,_xlpm.dar,DCF!$B$20,_xlpm.tx,DCF!$B$31,_xlpm.sb,DCF!$B$43,_xlpm.nw,DCF!$B$21,_xlpm.gd,N(DCF!$B$22),_xlpm.nc,DCF!$B$47,_xlpm.shs,DCF!$B$6,_xlpm.m,DCF!$B$48,_xlpm.t,_xlfn.SEQUENCE(10),_xlpm.g,_xlpm.gs-(_xlpm.gs-_xlpm.tgr)*(_xlpm.t-1)/9,_xlpm.cum,MMULT(--(_xlpm.t>=TRANSPOSE(_xlpm.t)),LN(1+_xlpm.g)),_xlpm.rev,_xlpm.r0*EXP(_xlpm.cum),_xlpm.prv,_xlpm.r0*EXP(_xlpm.cum-LN(1+_xlpm.g)),_xlpm.lp,IF(_xlpm.t>=_xlpm.n,1,_xlpm.t/_xlpm.n),_xlpm.omt,_xlpm.om0+(_xlpm.om-_xlpm.om0)*_xlpm.lp,_xlpm.dat,_xlpm.da0+(_xlpm.lcx*_xlpm.dar-_xlpm.da0)*_xlpm.lp,_xlpm.cpx,IF((_xlpm.t=1)*(_xlpm.gd>0),_xlpm.gd/_xlpm.rev,_xlpm.cx0+(_xlpm.lcx-_xlpm.cx0)*_xlpm.lp),_xlpm.f,_xlpm.rev*(_xlpm.omt*(1-_xlpm.tx)+_xlpm.dat-_xlpm.cpx+_xlpm.sb)-_xlpm.nw*(_xlpm.rev-_xlpm.prv),_xlpm.pv,SUM(_xlpm.f/(1+_xlpm.w)^(_xlpm.t-0.5*_xlpm.m)),_xlpm.tv,INDEX(_xlpm.f,10)*(1+_xlpm.tgr)/(_xlpm.w-_xlpm.tgr)/(1+_xlpm.w)^10,(_xlpm.pv+_xlpm.tv+_xlpm.nc)/_xlpm.shs)} | E33: {=_xlfn.LET(_xlpm.gs,$B33,_xlpm.om,E$28,_xlpm.w,DCF!$B$7,_xlpm.tgr,DCF!$B$8,_xlpm.n,DCF!$B$11,_xlpm.lcx,DCF!$B$19,_xlpm.r0,DCF!$B$37,_xlpm.om0,DCF!$B$39,_xlpm.cx0,DCF!$B$40,_xlpm.da0,DCF!$B$41,_xlpm.dar,DCF!$B$20,_xlpm.tx,DCF!$B$31,_xlpm.sb,DCF!$B$43,_xlpm.nw,DCF!$B$21,_xlpm.gd,N(DCF!$B$22),_xlpm.nc,DCF!$B$47,_xlpm.shs,DCF!$B$6,_xlpm.m,DCF!$B$48,_xlpm.t,_xlfn.SEQUENCE(10),_xlpm.g,_xlpm.gs-(_xlpm.gs-_xlpm.tgr)*(_xlpm.t-1)/9,_xlpm.cum,MMULT(--(_xlpm.t>=TRANSPOSE(_xlpm.t)),LN(1+_xlpm.g)),_xlpm.rev,_xlpm.r0*EXP(_xlpm.cum),_xlpm.prv,_xlpm.r0*EXP(_xlpm.cum-LN(1+_xlpm.g)),_xlpm.lp,IF(_xlpm.t>=_xlpm.n,1,_xlpm.t/_xlpm.n),_xlpm.omt,_xlpm.om0+(_xlpm.om-_xlpm.om0)*_xlpm.lp,_xlpm.dat,_xlpm.da0+(_xlpm.lcx*_xlpm.dar-_xlpm.da0)*_xlpm.lp,_xlpm.cpx,IF((_xlpm.t=1)*(_xlpm.gd>0),_xlpm.gd/_xlpm.rev,_xlpm.cx0+(_xlpm.lcx-_xlpm.cx0)*_xlpm.lp),_xlpm.f,_xlpm.rev*(_xlpm.omt*(1-_xlpm.tx)+_xlpm.dat-_xlpm.cpx+_xlpm.sb)-_xlpm.nw*(_xlpm.rev-_xlpm.prv),_xlpm.pv,SUM(_xlpm.f/(1+_xlpm.w)^(_xlpm.t-0.5*_xlpm.m)),_xlpm.tv,INDEX(_xlpm.f,10)*(1+_xlpm.tgr)/(_xlpm.w-_xlpm.tgr)/(1+_xlpm.w)^10,(_xlpm.pv+_xlpm.tv+_xlpm.nc)/_xlpm.shs)} | F33: {=_xlfn.LET(_xlpm.gs,$B33,_xlpm.om,F$28,_xlpm.w,DCF!$B$7,_xlpm.tgr,DCF!$B$8,_xlpm.n,DCF!$B$11,_xlpm.lcx,DCF!$B$19,_xlpm.r0,DCF!$B$37,_xlpm.om0,DCF!$B$39,_xlpm.cx0,DCF!$B$40,_xlpm.da0,DCF!$B$41,_xlpm.dar,DCF!$B$20,_xlpm.tx,DCF!$B$31,_xlpm.sb,DCF!$B$43,_xlpm.nw,DCF!$B$21,_xlpm.gd,N(DCF!$B$22),_xlpm.nc,DCF!$B$47,_xlpm.shs,DCF!$B$6,_xlpm.m,DCF!$B$48,_xlpm.t,_xlfn.SEQUENCE(10),_xlpm.g,_xlpm.gs-(_xlpm.gs-_xlpm.tgr)*(_xlpm.t-1)/9,_xlpm.cum,MMULT(--(_xlpm.t>=TRANSPOSE(_xlpm.t)),LN(1+_xlpm.g)),_xlpm.rev,_xlpm.r0*EXP(_xlpm.cum),_xlpm.prv,_xlpm.r0*EXP(_xlpm.cum-LN(1+_xlpm.g)),_xlpm.lp,IF(_xlpm.t>=_xlpm.n,1,_xlpm.t/_xlpm.n),_xlpm.omt,_xlpm.om0+(_xlpm.om-_xlpm.om0)*_xlpm.lp,_xlpm.dat,_xlpm.da0+(_xlpm.lcx*_xlpm.dar-_xlpm.da0)*_xlpm.lp,_xlpm.cpx,IF((_xlpm.t=1)*(_xlpm.gd>0),_xlpm.gd/_xlpm.rev,_xlpm.cx0+(_xlpm.lcx-_xlpm.cx0)*_xlpm.lp),_xlpm.f,_xlpm.rev*(_xlpm.omt*(1-_xlpm.tx)+_xlpm.dat-_xlpm.cpx+_xlpm.sb)-_xlpm.nw*(_xlpm.rev-_xlpm.prv),_xlpm.pv,SUM(_xlpm.f/(1+_xlpm.w)^(_xlpm.t-0.5*_xlpm.m)),_xlpm.tv,INDEX(_xlpm.f,10)*(1+_xlpm.tgr)/(_xlpm.w-_xlpm.tgr)/(1+_xlpm.w)^10,(_xlpm.pv+_xlpm.tv+_xlpm.nc)/_xlpm.shs)} | G33: {=_xlfn.LET(_xlpm.gs,$B33,_xlpm.om,G$28,_xlpm.w,DCF!$B$7,_xlpm.tgr,DCF!$B$8,_xlpm.n,DCF!$B$11,_xlpm.lcx,DCF!$B$19,_xlpm.r0,DCF!$B$37,_xlpm.om0,DCF!$B$39,_xlpm.cx0,DCF!$B$40,_xlpm.da0,DCF!$B$41,_xlpm.dar,DCF!$B$20,_xlpm.tx,DCF!$B$31,_xlpm.sb,DCF!$B$43,_xlpm.nw,DCF!$B$21,_xlpm.gd,N(DCF!$B$22),_xlpm.nc,DCF!$B$47,_xlpm.shs,DCF!$B$6,_xlpm.m,DCF!$B$48,_xlpm.t,_xlfn.SEQUENCE(10),_xlpm.g,_xlpm.gs-(_xlpm.gs-_xlpm.tgr)*(_xlpm.t-1)/9,_xlpm.cum,MMULT(--(_xlpm.t>=TRANSPOSE(_xlpm.t)),LN(1+_xlpm.g)),_xlpm.rev,_xlpm.r0*EXP(_xlpm.cum),_xlpm.prv,_xlpm.r0*EXP(_xlpm.cum-LN(1+_xlpm.g)),_xlpm.lp,IF(_xlpm.t>=_xlpm.n,1,_xlpm.t/_xlpm.n),_xlpm.omt,_xlpm.om0+(_xlpm.om-_xlpm.om0)*_xlpm.lp,_xlpm.dat,_xlpm.da0+(_xlpm.lcx*_xlpm.dar-_xlpm.da0)*_xlpm.lp,_xlpm.cpx,IF((_xlpm.t=1)*(_xlpm.gd>0),_xlpm.gd/_xlpm.rev,_xlpm.cx0+(_xlpm.lcx-_xlpm.cx0)*_xlpm.lp),_xlpm.f,_xlpm.rev*(_xlpm.omt*(1-_xlpm.tx)+_xlpm.dat-_xlpm.cpx+_xlpm.sb)-_xlpm.nw*(_xlpm.rev-_xlpm.prv),_xlpm.pv,SUM(_xlpm.f/(1+_xlpm.w)^(_xlpm.t-0.5*_xlpm.m)),_xlpm.tv,INDEX(_xlpm.f,10)*(1+_xlpm.tgr)/(_xlpm.w-_xlpm.tgr)/(1+_xlpm.w)^10,(_xlpm.pv+_xlpm.tv+_xlpm.nc)/_xlpm.shs)} | J33: =DCF!$B$19+0.04 | K33: {=_xlfn.LET(_xlpm.gs,DCF!$B$9,_xlpm.om,DCF!$B$10,_xlpm.w,DCF!$B$7,_xlpm.tgr,DCF!$B$8,_xlpm.n,K$28,_xlpm.lcx,$J33,_xlpm.r0,DCF!$B$37,_xlpm.om0,DCF!$B$39,_xlpm.cx0,DCF!$B$40,_xlpm.da0,DCF!$B$41,_xlpm.dar,DCF!$B$20,_xlpm.tx,DCF!$B$31,_xlpm.sb,DCF!$B$43,_xlpm.nw,DCF!$B$21,_xlpm.gd,N(DCF!$B$22),_xlpm.nc,DCF!$B$47,_xlpm.shs,DCF!$B$6,_xlpm.m,DCF!$B$48,_xlpm.t,_xlfn.SEQUENCE(10),_xlpm.g,_xlpm.gs-(_xlpm.gs-_xlpm.tgr)*(_xlpm.t-1)/9,_xlpm.cum,MMULT(--(_xlpm.t>=TRANSPOSE(_xlpm.t)),LN(1+_xlpm.g)),_xlpm.rev,_xlpm.r0*EXP(_xlpm.cum),_xlpm.prv,_xlpm.r0*EXP(_xlpm.cum-LN(1+_xlpm.g)),_xlpm.lp,IF(_xlpm.t>=_xlpm.n,1,_xlpm.t/_xlpm.n),_xlpm.omt,_xlpm.om0+(_xlpm.om-_xlpm.om0)*_xlpm.lp,_xlpm.dat,_xlpm.da0+(_xlpm.lcx*_xlpm.dar-_xlpm.da0)*_xlpm.lp,_xlpm.cpx,IF((_xlpm.t=1)*(_xlpm.gd>0),_xlpm.gd/_xlpm.rev,_xlpm.cx0+(_xlpm.lcx-_xlpm.cx0)*_xlpm.lp),_xlpm.f,_xlpm.rev*(_xlpm.omt*(1-_xlpm.tx)+_xlpm.dat-_xlpm.cpx+_xlpm.sb)-_xlpm.nw*(_xlpm.rev-_xlpm.prv),_xlpm.pv,SUM(_xlpm.f/(1+_xlpm.w)^(_xlpm.t-0.5*_xlpm.m)),_xlpm.tv,INDEX(_xlpm.f,10)*(1+_xlpm.tgr)/(_xlpm.w-_xlpm.tgr)/(1+_xlpm.w)^10,(_xlpm.pv+_xlpm.tv+_xlpm.nc)/_xlpm.shs)} | L33: {=_xlfn.LET(_xlpm.gs,DCF!$B$9,_xlpm.om,DCF!$B$10,_xlpm.w,DCF!$B$7,_xlpm.tgr,DCF!$B$8,_xlpm.n,L$28,_xlpm.lcx,$J33,_xlpm.r0,DCF!$B$37,_xlpm.om0,DCF!$B$39,_xlpm.cx0,DCF!$B$40,_xlpm.da0,DCF!$B$41,_xlpm.dar,DCF!$B$20,_xlpm.tx,DCF!$B$31,_xlpm.sb,DCF!$B$43,_xlpm.nw,DCF!$B$21,_xlpm.gd,N(DCF!$B$22),_xlpm.nc,DCF!$B$47,_xlpm.shs,DCF!$B$6,_xlpm.m,DCF!$B$48,_xlpm.t,_xlfn.SEQUENCE(10),_xlpm.g,_xlpm.gs-(_xlpm.gs-_xlpm.tgr)*(_xlpm.t-1)/9,_xlpm.cum,MMULT(--(_xlpm.t>=TRANSPOSE(_xlpm.t)),LN(1+_xlpm.g)),_xlpm.rev,_xlpm.r0*EXP(_xlpm.cum),_xlpm.prv,_xlpm.r0*EXP(_xlpm.cum-LN(1+_xlpm.g)),_xlpm.lp,IF(_xlpm.t>=_xlpm.n,1,_xlpm.t/_xlpm.n),_xlpm.omt,_xlpm.om0+(_xlpm.om-_xlpm.om0)*_xlpm.lp,_xlpm.dat,_xlpm.da0+(_xlpm.lcx*_xlpm.dar-_xlpm.da0)*_xlpm.lp,_xlpm.cpx,IF((_xlpm.t=1)*(_xlpm.gd>0),_xlpm.gd/_xlpm.rev,_xlpm.cx0+(_xlpm.lcx-_xlpm.cx0)*_xlpm.lp),_xlpm.f,_xlpm.rev*(_xlpm.omt*(1-_xlpm.tx)+_xlpm.dat-_xlpm.cpx+_xlpm.sb)-_xlpm.nw*(_xlpm.rev-_xlpm.prv),_xlpm.pv,SUM(_xlpm.f/(1+_xlpm.w)^(_xlpm.t-0.5*_xlpm.m)),_xlpm.tv,INDEX(_xlpm.f,10)*(1+_xlpm.tgr)/(_xlpm.w-_xlpm.tgr)/(1+_xlpm.w)^10,(_xlpm.pv+_xlpm.tv+_xlpm.nc)/_xlpm.shs)} | M33: {=_xlfn.LET(_xlpm.gs,DCF!$B$9,_xlpm.om,DCF!$B$10,_xlpm.w,DCF!$B$7,_xlpm.tgr,DCF!$B$8,_xlpm.n,M$28,_xlpm.lcx,$J33,_xlpm.r0,DCF!$B$37,_xlpm.om0,DCF!$B$39,_xlpm.cx0,DCF!$B$40,_xlpm.da0,DCF!$B$41,_xlpm.dar,DCF!$B$20,_xlpm.tx,DCF!$B$31,_xlpm.sb,DCF!$B$43,_xlpm.nw,DCF!$B$21,_xlpm.gd,N(DCF!$B$22),_xlpm.nc,DCF!$B$47,_xlpm.shs,DCF!$B$6,_xlpm.m,DCF!$B$48,_xlpm.t,_xlfn.SEQUENCE(10),_xlpm.g,_xlpm.gs-(_xlpm.gs-_xlpm.tgr)*(_xlpm.t-1)/9,_xlpm.cum,MMULT(--(_xlpm.t>=TRANSPOSE(_xlpm.t)),LN(1+_xlpm.g)),_xlpm.rev,_xlpm.r0*EXP(_xlpm.cum),_xlpm.prv,_xlpm.r0*EXP(_xlpm.cum-LN(1+_xlpm.g)),_xlpm.lp,IF(_xlpm.t>=_xlpm.n,1,_xlpm.t/_xlpm.n),_xlpm.omt,_xlpm.om0+(_xlpm.om-_xlpm.om0)*_xlpm.lp,_xlpm.dat,_xlpm.da0+(_xlpm.lcx*_xlpm.dar-_xlpm.da0)*_xlpm.lp,_xlpm.cpx,IF((_xlpm.t=1)*(_xlpm.gd>0),_xlpm.gd/_xlpm.rev,_xlpm.cx0+(_xlpm.lcx-_xlpm.cx0)*_xlpm.lp),_xlpm.f,_xlpm.rev*(_xlpm.omt*(1-_xlpm.tx)+_xlpm.dat-_xlpm.cpx+_xlpm.sb)-_xlpm.nw*(_xlpm.rev-_xlpm.prv),_xlpm.pv,SUM(_xlpm.f/(1+_xlpm.w)^(_xlpm.t-0.5*_xlpm.m)),_xlpm.tv,INDEX(_xlpm.f,10)*(1+_xlpm.tgr)/(_xlpm.w-_xlpm.tgr)/(1+_xlpm.w)^10,(_xlpm.pv+_xlpm.tv+_xlpm.nc)/_xlpm.shs)} | N33: {=_xlfn.LET(_xlpm.gs,DCF!$B$9,_xlpm.om,DCF!$B$10,_xlpm.w,DCF!$B$7,_xlpm.tgr,DCF!$B$8,_xlpm.n,N$28,_xlpm.lcx,$J33,_xlpm.r0,DCF!$B$37,_xlpm.om0,DCF!$B$39,_xlpm.cx0,DCF!$B$40,_xlpm.da0,DCF!$B$41,_xlpm.dar,DCF!$B$20,_xlpm.tx,DCF!$B$31,_xlpm.sb,DCF!$B$43,_xlpm.nw,DCF!$B$21,_xlpm.gd,N(DCF!$B$22),_xlpm.nc,DCF!$B$47,_xlpm.shs,DCF!$B$6,_xlpm.m,DCF!$B$48,_xlpm.t,_xlfn.SEQUENCE(10),_xlpm.g,_xlpm.gs-(_xlpm.gs-_xlpm.tgr)*(_xlpm.t-1)/9,_xlpm.cum,MMULT(--(_xlpm.t>=TRANSPOSE(_xlpm.t)),LN(1+_xlpm.g)),_xlpm.rev,_xlpm.r0*EXP(_xlpm.cum),_xlpm.prv,_xlpm.r0*EXP(_xlpm.cum-LN(1+_xlpm.g)),_xlpm.lp,IF(_xlpm.t>=_xlpm.n,1,_xlpm.t/_xlpm.n),_xlpm.omt,_xlpm.om0+(_xlpm.om-_xlpm.om0)*_xlpm.lp,_xlpm.dat,_xlpm.da0+(_xlpm.lcx*_xlpm.dar-_xlpm.da0)*_xlpm.lp,_xlpm.cpx,IF((_xlpm.t=1)*(_xlpm.gd>0),_xlpm.gd/_xlpm.rev,_xlpm.cx0+(_xlpm.lcx-_xlpm.cx0)*_xlpm.lp),_xlpm.f,_xlpm.rev*(_xlpm.omt*(1-_xlpm.tx)+_xlpm.dat-_xlpm.cpx+_xlpm.sb)-_xlpm.nw*(_xlpm.rev-_xlpm.prv),_xlpm.pv,SUM(_xlpm.f/(1+_xlpm.w)^(_xlpm.t-0.5*_xlpm.m)),_xlpm.tv,INDEX(_xlpm.f,10)*(1+_xlpm.tgr)/(_xlpm.w-_xlpm.tgr)/(1+_xlpm.w)^10,(_xlpm.pv+_xlpm.tv+_xlpm.nc)/_xlpm.shs)} | O33: {=_xlfn.LET(_xlpm.gs,DCF!$B$9,_xlpm.om,DCF!$B$10,_xlpm.w,DCF!$B$7,_xlpm.tgr,DCF!$B$8,_xlpm.n,O$28,_xlpm.lcx,$J33,_xlpm.r0,DCF!$B$37,_xlpm.om0,DCF!$B$39,_xlpm.cx0,DCF!$B$40,_xlpm.da0,DCF!$B$41,_xlpm.dar,DCF!$B$20,_xlpm.tx,DCF!$B$31,_xlpm.sb,DCF!$B$43,_xlpm.nw,DCF!$B$21,_xlpm.gd,N(DCF!$B$22),_xlpm.nc,DCF!$B$47,_xlpm.shs,DCF!$B$6,_xlpm.m,DCF!$B$48,_xlpm.t,_xlfn.SEQUENCE(10),_xlpm.g,_xlpm.gs-(_xlpm.gs-_xlpm.tgr)*(_xlpm.t-1)/9,_xlpm.cum,MMULT(--(_xlpm.t>=TRANSPOSE(_xlpm.t)),LN(1+_xlpm.g)),_xlpm.rev,_xlpm.r0*EXP(_xlpm.cum),_xlpm.prv,_xlpm.r0*EXP(_xlpm.cum-LN(1+_xlpm.g)),_xlpm.lp,IF(_xlpm.t>=_xlpm.n,1,_xlpm.t/_xlpm.n),_xlpm.omt,_xlpm.om0+(_xlpm.om-_xlpm.om0)*_xlpm.lp,_xlpm.dat,_xlpm.da0+(_xlpm.lcx*_xlpm.dar-_xlpm.da0)*_xlpm.lp,_xlpm.cpx,IF((_xlpm.t=1)*(_xlpm.gd>0),_xlpm.gd/_xlpm.rev,_xlpm.cx0+(_xlpm.lcx-_xlpm.cx0)*_xlpm.lp),_xlpm.f,_xlpm.rev*(_xlpm.omt*(1-_xlpm.tx)+_xlpm.dat-_xlpm.cpx+_xlpm.sb)-_xlpm.nw*(_xlpm.rev-_xlpm.prv),_xlpm.pv,SUM(_xlpm.f/(1+_xlpm.w)^(_xlpm.t-0.5*_xlpm.m)),_xlpm.tv,INDEX(_xlpm.f,10)*(1+_xlpm.tgr)/(_xlpm.w-_xlpm.tgr)/(1+_xlpm.w)^10,(_xlpm.pv+_xlpm.tv+_xlpm.nc)/_xlpm.shs)}
A35: ="Yellow = base case. Green = fair value at or above today's price of "&TEXT(DCF!B5,"$0.00")&". Base case: "&TEXT(DCF!B9,"0.0%")&" year-1 revenue growth and a "&TEXT(DCF!B10,"0.0%")&" long-run operating margin. Today's price implies "&IFERROR(TEXT(DCF!B79,"0.0%")&" year-1 growth (≈"&TEXT(DCF!B80,"0.0%")&" 10-yr CAGR)","growth outside the solvable range")&" or a "&IFERROR(TEXT(DCF!B82,"0.0%"),"n/a")&" operating margin."
A37: Valuation range (feeds the Summary chart)
A38: Measure | B38: $ per share
A39: DCF — bear | B39: =B11
A40: DCF — base | B40: =C11
A41: DCF — bull | B41: =D11
A42: DCF — probability-weighted | B42: =B13
A43: 52-week low | B43: =MIN(Data!D1004:D1256)
A44: 52-week high | B44: =MAX(Data!C1004:C1256)
A45: Current price | B45: =DCF!B5
A47: Football field — value ranges by method (feeds the Summary chart)
A48: Chart label | B48: Low ($) | C48: High ($) | D48: Bar length | E48: Method
A49: =E49&" "&TEXT(B49,"$0")&"–"&TEXT(C49,"$0") | B49: =Scenarios!B43 | C49: =Scenarios!B44 | D49: =C49-B49 | E49: 52-week trading range
A50: =E50&" "&TEXT(B50,"$0")&"–"&TEXT(C50,"$0") | B50: =B11 | C50: =D11 | D50: =C50-B50 | E50: DCF bear–bull
A51: =E51&" "&TEXT(B51,"$0")&"–"&TEXT(C51,"$0") | B51: =MIN(C21:G25) | C51: =MAX(C21:G25) | D51: =C51-B51 | E51: DCF: WACC × terminal g
A52: =E52&" "&TEXT(B52,"$0")&"–"&TEXT(C52,"$0") | B52: =MIN(C29:G33) | C52: =MAX(C29:G33) | D52: =C52-B52 | E52: DCF: growth × margin
A53: =E53&" "&TEXT(B53,"$0")&"–"&TEXT(C53,"$0") | B53: =IF(Financials!F27>0,MIN(Peers!C7:C10)*Financials!F27,"") | C53: =IF(Financials!F27>0,MAX(Peers!C7:C10)*Financials!F27,"") | D53: =IFERROR(C53-B53,"") | E53: Peer P/E range × clean EPS
A54: =E54&" "&TEXT(B54,"$0")&"–"&TEXT(C54,"$0") | B54: =IF(Financials!F27>0,MIN(Valuation_History!D6:D14)*Financials!F27,"") | C54: =IF(Financials!F27>0,MAX(Valuation_History!D6:D14)*Financials!F27,"") | D54: =IFERROR(C54-B54,"") | E54: Own P/E history × clean EPS
A55: =E55&" "&TEXT(B55,"$0")&"–"&TEXT(C55,"$0") | B55: =(Segments!J12*0.8+Segments!B17)/DCF!B6 | C55: =(Segments!J12*1.2+Segments!B17)/DCF!B6 | D55: =IFERROR(C55-B55,"") | E55: Sum-of-the-parts (segment multiples ±20%)
A56: =E56&" "&TEXT(B56,"$0")&"–"&TEXT(C56,"$0") | B56: =Risk!B48 | C56: =Risk!B49 | D56: =C56-B56 | E56: 1-yr price range, volatility (not a valuation)
A57: =E57&" "&TEXT(DCF!B5,"$0") | B57: =DCF!B5-2 | C57: =DCF!B5+2 | D57: =C57-B57 | E57: Current price
A58: Multiples rows apply the peer / own-history P/E range to EPS excluding investment gains (Financials F27). The volatility row is a statistical 1-year price range (Risk tab), not a valuation.

Sheet DCF
A1: =Data!$Q$2&" ("&Data!$Q$3&") — Discounted Cash Flow Valuation"
A2: Two-stage free-cash-flow DCF · $ in billions except per share · blue/yellow cells are editable inputs | G2: ← Back to Summary
A4: Inputs
A5: Current share price ($) | B5: =Data!E1256 | C5: Report price: close of 24-Sep-2026 (Yahoo Finance).
A6: Shares outstanding (B) | B6: =Financials!C56 | C6: All share classes, filing cover (08-Jul-2026).
A7: Discount rate (WACC) | B7: =B34 | C7: From the CAPM build below — edit its inputs, not this cell.
A8: Terminal growth rate | B8: 0.025 | C8: Perpetual growth after year 10. Must be below WACC; ~long-run nominal GDP.
A9: Year-1 revenue growth | B9: =IFERROR(MAX(-0.1,MIN(0.3,Financials!M6)),0.008216289449518577) | C9: Defaults to the 5-yr revenue CAGR (FY2021–FY2026), held between -10% and +30%; fades linearly to terminal growth by year 10. Overwrite to test.
A10: Target operating margin | B10: =CHOOSE(MATCH(B17,{"TTM","Last FY","Peer median","Custom"},0),Financials!F23,Financials!B47/Financials!K6,MEDIAN(Peers!H7:H10),B18) | C10: Set by the anchor in B17 (edit B17/B18, not this cell).
A11: Years to normalise margin & capex | B11: 5 | C11: Operating margin, capex and D&A move in a straight line from today's level to the long-run level over this many years.
A12: Deduct stock-based compensation? | B12: No | C12: Yes = treat SBC as a cash cost (more conservative). TTM SBC is shown below.
A13: Include non-marketable investments? | B13: Yes | C13: Private equity stakes on the balance sheet (not captured by FCF).
A14: Risk-free rate (3-month T-bill) | B14: 0.0419 | C14: Used for Sharpe / earnings-yield spread cross-checks only.
A15: Haircut on non-marketable investments | B15: 0.2 | C15: Discount for illiquidity and tax on unrealised gains.
A16: Mid-year discounting? | B16: Yes | C16: Yes = cash flows arrive mid-year on average (standard practice).
A17: Operating-margin anchor | B17: TTM | C17: Where the long-run operating margin settles: TTM / Last FY / Peer median / Custom.
A18: Custom operating margin | B18: 0.35 | C18: Used only when the anchor (B17) = Custom.
A19: Long-run capex, % of revenue | B19: 0.02 | C19: The company's median capex share of revenue over 10 filed fiscal years, to the nearest half point. Assumption; edit to test.
A20: Long-run D&A, % of capex | B20: 0.85 | C20: D&A below capex = the business keeps reinvesting for growth. Assumption.
A21: Working capital, % of revenue change | B21: 0 | C21: Cash tied up per $1 of new revenue. Near 0 for ad/software models.
A22: Next-year capex guidance ($B, optional) | C22: Company guidance midpoint; leave blank to glide from TTM capex instead.
A24: WACC build (CAPM)
A25: 10-year Treasury yield | B25: 0.0511 | C25: FRED DGS10 (see Sources).
A26: Raw beta vs S&P 500 | B26: =Risk!B25 | C26: Live regression of daily returns on SPY (Risk tab).
A27: Adjusted beta (Blume: ⅔ raw + ⅓) | B27: =2/3*B26+1/3 | C27: Pulls the raw estimate toward 1.0.
A28: Equity risk premium | B28: 0.05 | C28: Assumption.
A29: Cost of equity | B29: =B25+B27*B28 | C29: Risk-free + beta × ERP.
A30: Pre-tax cost of debt | B30: 0.0631 | C30: 10-year Treasury + 1.20% credit spread (stepped by leverage).
A31: Tax rate | B31: 0.20307692 | C31: Effective tax rate, trailing twelve months (held between 5% and 35%).
A32: Weight of debt | B32: =Financials!C38/(Financials!C38+B5*B6) | C32: Total debt ÷ (debt + market cap).
A33: Weight of equity | B33: =1-B32
A34: WACC | B34: =B33*B29+B32*B30*(1-B31) | C34: Feeds B7.
A36: Derived inputs
A37: Base revenue — TTM to May-2026 ($B) | B37: =Financials!F17 | C37: Sum of the last four quarters.
A38: Current FCF margin — TTM (reference) | B38: =(Financials!C42-Financials!C43)/Financials!F17 | C38: (CFO − capex) ÷ revenue, trailing twelve months.
A39: Current operating margin — TTM | B39: =Financials!F23 | C39: Starting point for the margin path.
A40: Current capex, % of revenue — TTM | B40: =Financials!C43/B37 | C40: Elevated by the AI build-out.
A41: Current D&A, % of revenue — TTM | B41: =Financials!C46/B37 | C41: D&A share of revenue, trailing twelve months.
A42: SBC as % of revenue — TTM | B42: =Financials!C44/Financials!F17
A43: SBC added back to FCF, % of revenue | B43: =IF(B12="Yes",0,B42) | C43: Reported FCF adds SBC back (non-cash). B12 = Yes treats it as a real cost instead.
A44: Net cash ($B) | B44: =Financials!C39 | C44: Cash + marketable securities − debt, 31-May-2026.
A45: Preferred stock ($B) | B45: =Financials!C55 | C45: A senior claim ahead of common shareholders; 0 when none is outstanding.
A46: Non-marketable investments after haircut ($B) | B46: =IF(B13="Yes",Financials!C54*(1-B15),0)
A47: Non-operating adjustments, net ($B) | B47: =B44-B45+B46 | C47: Added to enterprise value to reach equity value.
A48: Mid-year flag | B48: =IF(B16="Yes",1,0)
A50: 10-year projection — revenue → operating profit → cash flow ($B)
A51: Year | B51: 12 months to | C51: Revenue growth | D51: Revenue | E51: Operating margin | F51: NOPAT (after tax) | G51: + D&A | H51: − Capex | I51: − Working capital | J51: + SBC add-back | K51: Free cash flow | L51: FCF margin | M51: Discount period | N51: Discount factor | O51: PV of FCF | Q51: Yr-1 growth | R51: Fair value ($) | S51: Target op. margin | T51: Fair value ($) | U51: LR capex % | V51: Fair value ($)
A52: 1 | B52: =TEXT(EDATE(Financials!$E$16,12*A52),"mmm-yy") | C52: =$B$9-($B$9-$B$8)*(A52-1)/9 | D52: =IF(A52=1,$B$37,D51)*(1+C52) | E52: =$B$39+($B$10-$B$39)*MIN(1,A52/$B$11) | F52: =D52*E52*(1-$B$31) | G52: =D52*($B$41+($B$19*$B$20-$B$41)*MIN(1,A52/$B$11)) | H52: =IF(AND(A52=1,N($B$22)>0),$B$22,D52*($B$40+($B$19-$B$40)*MIN(1,A52/$B$11))) | I52: =$B$21*(D52-IF(A52=1,$B$37,D51)) | J52: =D52*$B$43 | K52: =F52+G52-H52-I52+J52 | L52: =K52/D52 | M52: =A52-0.5*$B$48 | N52: =1/(1+$B$7)^M52 | O52: =K52*N52 | Q52: -0.1 | R52: {=_xlfn.LET(_xlpm.gs,Q52,_xlpm.om,$B$10,_xlpm.w,$B$7,_xlpm.tgr,$B$8,_xlpm.n,$B$11,_xlpm.lcx,$B$19,_xlpm.r0,DCF!$B$37,_xlpm.om0,DCF!$B$39,_xlpm.cx0,DCF!$B$40,_xlpm.da0,DCF!$B$41,_xlpm.dar,DCF!$B$20,_xlpm.tx,DCF!$B$31,_xlpm.sb,DCF!$B$43,_xlpm.nw,DCF!$B$21,_xlpm.gd,N(DCF!$B$22),_xlpm.nc,DCF!$B$47,_xlpm.shs,DCF!$B$6,_xlpm.m,DCF!$B$48,_xlpm.t,_xlfn.SEQUENCE(10),_xlpm.g,_xlpm.gs-(_xlpm.gs-_xlpm.tgr)*(_xlpm.t-1)/9,_xlpm.cum,MMULT(--(_xlpm.t>=TRANSPOSE(_xlpm.t)),LN(1+_xlpm.g)),_xlpm.rev,_xlpm.r0*EXP(_xlpm.cum),_xlpm.prv,_xlpm.r0*EXP(_xlpm.cum-LN(1+_xlpm.g)),_xlpm.lp,IF(_xlpm.t>=_xlpm.n,1,_xlpm.t/_xlpm.n),_xlpm.omt,_xlpm.om0+(_xlpm.om-_xlpm.om0)*_xlpm.lp,_xlpm.dat,_xlpm.da0+(_xlpm.lcx*_xlpm.dar-_xlpm.da0)*_xlpm.lp,_xlpm.cpx,IF((_xlpm.t=1)*(_xlpm.gd>0),_xlpm.gd/_xlpm.rev,_xlpm.cx0+(_xlpm.lcx-_xlpm.cx0)*_xlpm.lp),_xlpm.f,_xlpm.rev*(_xlpm.omt*(1-_xlpm.tx)+_xlpm.dat-_xlpm.cpx+_xlpm.sb)-_xlpm.nw*(_xlpm.rev-_xlpm.prv),_xlpm.pv,SUM(_xlpm.f/(1+_xlpm.w)^(_xlpm.t-0.5*_xlpm.m)),_xlpm.tv,INDEX(_xlpm.f,10)*(1+_xlpm.tgr)/(_xlpm.w-_xlpm.tgr)/(1+_xlpm.w)^10,(_xlpm.pv+_xlpm.tv+_xlpm.nc)/_xlpm.shs)} | S52: 0.05 | T52: {=_xlfn.LET(_xlpm.gs,$B$9,_xlpm.om,S52,_xlpm.w,$B$7,_xlpm.tgr,$B$8,_xlpm.n,$B$11,_xlpm.lcx,$B$19,_xlpm.r0,DCF!$B$37,_xlpm.om0,DCF!$B$39,_xlpm.cx0,DCF!$B$40,_xlpm.da0,DCF!$B$41,_xlpm.dar,DCF!$B$20,_xlpm.tx,DCF!$B$31,_xlpm.sb,DCF!$B$43,_xlpm.nw,DCF!$B$21,_xlpm.gd,N(DCF!$B$22),_xlpm.nc,DCF!$B$47,_xlpm.shs,DCF!$B$6,_xlpm.m,DCF!$B$48,_xlpm.t,_xlfn.SEQUENCE(10),_xlpm.g,_xlpm.gs-(_xlpm.gs-_xlpm.tgr)*(_xlpm.t-1)/9,_xlpm.cum,MMULT(--(_xlpm.t>=TRANSPOSE(_xlpm.t)),LN(1+_xlpm.g)),_xlpm.rev,_xlpm.r0*EXP(_xlpm.cum),_xlpm.prv,_xlpm.r0*EXP(_xlpm.cum-LN(1+_xlpm.g)),_xlpm.lp,IF(_xlpm.t>=_xlpm.n,1,_xlpm.t/_xlpm.n),_xlpm.omt,_xlpm.om0+(_xlpm.om-_xlpm.om0)*_xlpm.lp,_xlpm.dat,_xlpm.da0+(_xlpm.lcx*_xlpm.dar-_xlpm.da0)*_xlpm.lp,_xlpm.cpx,IF((_xlpm.t=1)*(_xlpm.gd>0),_xlpm.gd/_xlpm.rev,_xlpm.cx0+(_xlpm.lcx-_xlpm.cx0)*_xlpm.lp),_xlpm.f,_xlpm.rev*(_xlpm.omt*(1-_xlpm.tx)+_xlpm.dat-_xlpm.cpx+_xlpm.sb)-_xlpm.nw*(_xlpm.rev-_xlpm.prv),_xlpm.pv,SUM(_xlpm.f/(1+_xlpm.w)^(_xlpm.t-0.5*_xlpm.m)),_xlpm.tv,INDEX(_xlpm.f,10)*(1+_xlpm.tgr)/(_xlpm.w-_xlpm.tgr)/(1+_xlpm.w)^10,(_xlpm.pv+_xlpm.tv+_xlpm.nc)/_xlpm.shs)} | U52: 0.4 | V52: {=_xlfn.LET(_xlpm.gs,$B$9,_xlpm.om,$B$10,_xlpm.w,$B$7,_xlpm.tgr,$B$8,_xlpm.n,$B$11,_xlpm.lcx,U52,_xlpm.r0,DCF!$B$37,_xlpm.om0,DCF!$B$39,_xlpm.cx0,DCF!$B$40,_xlpm.da0,DCF!$B$41,_xlpm.dar,DCF!$B$20,_xlpm.tx,DCF!$B$31,_xlpm.sb,DCF!$B$43,_xlpm.nw,DCF!$B$21,_xlpm.gd,N(DCF!$B$22),_xlpm.nc,DCF!$B$47,_xlpm.shs,DCF!$B$6,_xlpm.m,DCF!$B$48,_xlpm.t,_xlfn.SEQUENCE(10),_xlpm.g,_xlpm.gs-(_xlpm.gs-_xlpm.tgr)*(_xlpm.t-1)/9,_xlpm.cum,MMULT(--(_xlpm.t>=TRANSPOSE(_xlpm.t)),LN(1+_xlpm.g)),_xlpm.rev,_xlpm.r0*EXP(_xlpm.cum),_xlpm.prv,_xlpm.r0*EXP(_xlpm.cum-LN(1+_xlpm.g)),_xlpm.lp,IF(_xlpm.t>=_xlpm.n,1,_xlpm.t/_xlpm.n),_xlpm.omt,_xlpm.om0+(_xlpm.om-_xlpm.om0)*_xlpm.lp,_xlpm.dat,_xlpm.da0+(_xlpm.lcx*_xlpm.dar-_xlpm.da0)*_xlpm.lp,_xlpm.cpx,IF((_xlpm.t=1)*(_xlpm.gd>0),_xlpm.gd/_xlpm.rev,_xlpm.cx0+(_xlpm.lcx-_xlpm.cx0)*_xlpm.lp),_xlpm.f,_xlpm.rev*(_xlpm.omt*(1-_xlpm.tx)+_xlpm.dat-_xlpm.cpx+_xlpm.sb)-_xlpm.nw*(_xlpm.rev-_xlpm.prv),_xlpm.pv,SUM(_xlpm.f/(1+_xlpm.w)^(_xlpm.t-0.5*_xlpm.m)),_xlpm.tv,INDEX(_xlpm.f,10)*(1+_xlpm.tgr)/(_xlpm.w-_xlpm.tgr)/(1+_xlpm.w)^10,(_xlpm.pv+_xlpm.tv+_xlpm.nc)/_xlpm.shs)}
A53: 2 | B53: =TEXT(EDATE(Financials!$E$16,12*A53),"mmm-yy") | C53: =$B$9-($B$9-$B$8)*(A53-1)/9 | D53: =IF(A53=1,$B$37,D52)*(1+C53) | E53: =$B$39+($B$10-$B$39)*MIN(1,A53/$B$11) | F53: =D53*E53*(1-$B$31) | G53: =D53*($B$41+($B$19*$B$20-$B$41)*MIN(1,A53/$B$11)) | H53: =IF(AND(A53=1,N($B$22)>0),$B$22,D53*($B$40+($B$19-$B$40)*MIN(1,A53/$B$11))) | I53: =$B$21*(D53-IF(A53=1,$B$37,D52)) | J53: =D53*$B$43 | K53: =F53+G53-H53-I53+J53 | L53: =K53/D53 | M53: =A53-0.5*$B$48 | N53: =1/(1+$B$7)^M53 | O53: =K53*N53 | Q53: =Q52+0.005 | R53: {=_xlfn.LET(_xlpm.gs,Q53,_xlpm.om,$B$10,_xlpm.w,$B$7,_xlpm.tgr,$B$8,_xlpm.n,$B$11,_xlpm.lcx,$B$19,_xlpm.r0,DCF!$B$37,_xlpm.om0,DCF!$B$39,_xlpm.cx0,DCF!$B$40,_xlpm.da0,DCF!$B$41,_xlpm.dar,DCF!$B$20,_xlpm.tx,DCF!$B$31,_xlpm.sb,DCF!$B$43,_xlpm.nw,DCF!$B$21,_xlpm.gd,N(DCF!$B$22),_xlpm.nc,DCF!$B$47,_xlpm.shs,DCF!$B$6,_xlpm.m,DCF!$B$48,_xlpm.t,_xlfn.SEQUENCE(10),_xlpm.g,_xlpm.gs-(_xlpm.gs-_xlpm.tgr)*(_xlpm.t-1)/9,_xlpm.cum,MMULT(--(_xlpm.t>=TRANSPOSE(_xlpm.t)),LN(1+_xlpm.g)),_xlpm.rev,_xlpm.r0*EXP(_xlpm.cum),_xlpm.prv,_xlpm.r0*EXP(_xlpm.cum-LN(1+_xlpm.g)),_xlpm.lp,IF(_xlpm.t>=_xlpm.n,1,_xlpm.t/_xlpm.n),_xlpm.omt,_xlpm.om0+(_xlpm.om-_xlpm.om0)*_xlpm.lp,_xlpm.dat,_xlpm.da0+(_xlpm.lcx*_xlpm.dar-_xlpm.da0)*_xlpm.lp,_xlpm.cpx,IF((_xlpm.t=1)*(_xlpm.gd>0),_xlpm.gd/_xlpm.rev,_xlpm.cx0+(_xlpm.lcx-_xlpm.cx0)*_xlpm.lp),_xlpm.f,_xlpm.rev*(_xlpm.omt*(1-_xlpm.tx)+_xlpm.dat-_xlpm.cpx+_xlpm.sb)-_xlpm.nw*(_xlpm.rev-_xlpm.prv),_xlpm.pv,SUM(_xlpm.f/(1+_xlpm.w)^(_xlpm.t-0.5*_xlpm.m)),_xlpm.tv,INDEX(_xlpm.f,10)*(1+_xlpm.tgr)/(_xlpm.w-_xlpm.tgr)/(1+_xlpm.w)^10,(_xlpm.pv+_xlpm.tv+_xlpm.nc)/_xlpm.shs)} | S53: =S52+0.005 | T53: {=_xlfn.LET(_xlpm.gs,$B$9,_xlpm.om,S53,_xlpm.w,$B$7,_xlpm.tgr,$B$8,_xlpm.n,$B$11,_xlpm.lcx,$B$19,_xlpm.r0,DCF!$B$37,_xlpm.om0,DCF!$B$39,_xlpm.cx0,DCF!$B$40,_xlpm.da0,DCF!$B$41,_xlpm.dar,DCF!$B$20,_xlpm.tx,DCF!$B$31,_xlpm.sb,DCF!$B$43,_xlpm.nw,DCF!$B$21,_xlpm.gd,N(DCF!$B$22),_xlpm.nc,DCF!$B$47,_xlpm.shs,DCF!$B$6,_xlpm.m,DCF!$B$48,_xlpm.t,_xlfn.SEQUENCE(10),_xlpm.g,_xlpm.gs-(_xlpm.gs-_xlpm.tgr)*(_xlpm.t-1)/9,_xlpm.cum,MMULT(--(_xlpm.t>=TRANSPOSE(_xlpm.t)),LN(1+_xlpm.g)),_xlpm.rev,_xlpm.r0*EXP(_xlpm.cum),_xlpm.prv,_xlpm.r0*EXP(_xlpm.cum-LN(1+_xlpm.g)),_xlpm.lp,IF(_xlpm.t>=_xlpm.n,1,_xlpm.t/_xlpm.n),_xlpm.omt,_xlpm.om0+(_xlpm.om-_xlpm.om0)*_xlpm.lp,_xlpm.dat,_xlpm.da0+(_xlpm.lcx*_xlpm.dar-_xlpm.da0)*_xlpm.lp,_xlpm.cpx,IF((_xlpm.t=1)*(_xlpm.gd>0),_xlpm.gd/_xlpm.rev,_xlpm.cx0+(_xlpm.lcx-_xlpm.cx0)*_xlpm.lp),_xlpm.f,_xlpm.rev*(_xlpm.omt*(1-_xlpm.tx)+_xlpm.dat-_xlpm.cpx+_xlpm.sb)-_xlpm.nw*(_xlpm.rev-_xlpm.prv),_xlpm.pv,SUM(_xlpm.f/(1+_xlpm.w)^(_xlpm.t-0.5*_xlpm.m)),_xlpm.tv,INDEX(_xlpm.f,10)*(1+_xlpm.tgr)/(_xlpm.w-_xlpm.tgr)/(1+_xlpm.w)^10,(_xlpm.pv+_xlpm.tv+_xlpm.nc)/_xlpm.shs)} | U53: =U52-0.0025 | V53: {=_xlfn.LET(_xlpm.gs,$B$9,_xlpm.om,$B$10,_xlpm.w,$B$7,_xlpm.tgr,$B$8,_xlpm.n,$B$11,_xlpm.lcx,U53,_xlpm.r0,DCF!$B$37,_xlpm.om0,DCF!$B$39,_xlpm.cx0,DCF!$B$40,_xlpm.da0,DCF!$B$41,_xlpm.dar,DCF!$B$20,_xlpm.tx,DCF!$B$31,_xlpm.sb,DCF!$B$43,_xlpm.nw,DCF!$B$21,_xlpm.gd,N(DCF!$B$22),_xlpm.nc,DCF!$B$47,_xlpm.shs,DCF!$B$6,_xlpm.m,DCF!$B$48,_xlpm.t,_xlfn.SEQUENCE(10),_xlpm.g,_xlpm.gs-(_xlpm.gs-_xlpm.tgr)*(_xlpm.t-1)/9,_xlpm.cum,MMULT(--(_xlpm.t>=TRANSPOSE(_xlpm.t)),LN(1+_xlpm.g)),_xlpm.rev,_xlpm.r0*EXP(_xlpm.cum),_xlpm.prv,_xlpm.r0*EXP(_xlpm.cum-LN(1+_xlpm.g)),_xlpm.lp,IF(_xlpm.t>=_xlpm.n,1,_xlpm.t/_xlpm.n),_xlpm.omt,_xlpm.om0+(_xlpm.om-_xlpm.om0)*_xlpm.lp,_xlpm.dat,_xlpm.da0+(_xlpm.lcx*_xlpm.dar-_xlpm.da0)*_xlpm.lp,_xlpm.cpx,IF((_xlpm.t=1)*(_xlpm.gd>0),_xlpm.gd/_xlpm.rev,_xlpm.cx0+(_xlpm.lcx-_xlpm.cx0)*_xlpm.lp),_xlpm.f,_xlpm.rev*(_xlpm.omt*(1-_xlpm.tx)+_xlpm.dat-_xlpm.cpx+_xlpm.sb)-_xlpm.nw*(_xlpm.rev-_xlpm.prv),_xlpm.pv,SUM(_xlpm.f/(1+_xlpm.w)^(_xlpm.t-0.5*_xlpm.m)),_xlpm.tv,INDEX(_xlpm.f,10)*(1+_xlpm.tgr)/(_xlpm.w-_xlpm.tgr)/(1+_xlpm.w)^10,(_xlpm.pv+_xlpm.tv+_xlpm.nc)/_xlpm.shs)}
A54: 3 | B54: =TEXT(EDATE(Financials!$E$16,12*A54),"mmm-yy") | C54: =$B$9-($B$9-$B$8)*(A54-1)/9 | D54: =IF(A54=1,$B$37,D53)*(1+C54) | E54: =$B$39+($B$10-$B$39)*MIN(1,A54/$B$11) | F54: =D54*E54*(1-$B$31) | G54: =D54*($B$41+($B$19*$B$20-$B$41)*MIN(1,A54/$B$11)) | H54: =IF(AND(A54=1,N($B$22)>0),$B$22,D54*($B$40+($B$19-$B$40)*MIN(1,A54/$B$11))) | I54: =$B$21*(D54-IF(A54=1,$B$37,D53)) | J54: =D54*$B$43 | K54: =F54+G54-H54-I54+J54 | L54: =K54/D54 | M54: =A54-0.5*$B$48 | N54: =1/(1+$B$7)^M54 | O54: =K54*N54 | Q54: =Q53+0.005 | R54: {=_xlfn.LET(_xlpm.gs,Q54,_xlpm.om,$B$10,_xlpm.w,$B$7,_xlpm.tgr,$B$8,_xlpm.n,$B$11,_xlpm.lcx,$B$19,_xlpm.r0,DCF!$B$37,_xlpm.om0,DCF!$B$39,_xlpm.cx0,DCF!$B$40,_xlpm.da0,DCF!$B$41,_xlpm.dar,DCF!$B$20,_xlpm.tx,DCF!$B$31,_xlpm.sb,DCF!$B$43,_xlpm.nw,DCF!$B$21,_xlpm.gd,N(DCF!$B$22),_xlpm.nc,DCF!$B$47,_xlpm.shs,DCF!$B$6,_xlpm.m,DCF!$B$48,_xlpm.t,_xlfn.SEQUENCE(10),_xlpm.g,_xlpm.gs-(_xlpm.gs-_xlpm.tgr)*(_xlpm.t-1)/9,_xlpm.cum,MMULT(--(_xlpm.t>=TRANSPOSE(_xlpm.t)),LN(1+_xlpm.g)),_xlpm.rev,_xlpm.r0*EXP(_xlpm.cum),_xlpm.prv,_xlpm.r0*EXP(_xlpm.cum-LN(1+_xlpm.g)),_xlpm.lp,IF(_xlpm.t>=_xlpm.n,1,_xlpm.t/_xlpm.n),_xlpm.omt,_xlpm.om0+(_xlpm.om-_xlpm.om0)*_xlpm.lp,_xlpm.dat,_xlpm.da0+(_xlpm.lcx*_xlpm.dar-_xlpm.da0)*_xlpm.lp,_xlpm.cpx,IF((_xlpm.t=1)*(_xlpm.gd>0),_xlpm.gd/_xlpm.rev,_xlpm.cx0+(_xlpm.lcx-_xlpm.cx0)*_xlpm.lp),_xlpm.f,_xlpm.rev*(_xlpm.omt*(1-_xlpm.tx)+_xlpm.dat-_xlpm.cpx+_xlpm.sb)-_xlpm.nw*(_xlpm.rev-_xlpm.prv),_xlpm.pv,SUM(_xlpm.f/(1+_xlpm.w)^(_xlpm.t-0.5*_xlpm.m)),_xlpm.tv,INDEX(_xlpm.f,10)*(1+_xlpm.tgr)/(_xlpm.w-_xlpm.tgr)/(1+_xlpm.w)^10,(_xlpm.pv+_xlpm.tv+_xlpm.nc)/_xlpm.shs)} | S54: =S53+0.005 | T54: {=_xlfn.LET(_xlpm.gs,$B$9,_xlpm.om,S54,_xlpm.w,$B$7,_xlpm.tgr,$B$8,_xlpm.n,$B$11,_xlpm.lcx,$B$19,_xlpm.r0,DCF!$B$37,_xlpm.om0,DCF!$B$39,_xlpm.cx0,DCF!$B$40,_xlpm.da0,DCF!$B$41,_xlpm.dar,DCF!$B$20,_xlpm.tx,DCF!$B$31,_xlpm.sb,DCF!$B$43,_xlpm.nw,DCF!$B$21,_xlpm.gd,N(DCF!$B$22),_xlpm.nc,DCF!$B$47,_xlpm.shs,DCF!$B$6,_xlpm.m,DCF!$B$48,_xlpm.t,_xlfn.SEQUENCE(10),_xlpm.g,_xlpm.gs-(_xlpm.gs-_xlpm.tgr)*(_xlpm.t-1)/9,_xlpm.cum,MMULT(--(_xlpm.t>=TRANSPOSE(_xlpm.t)),LN(1+_xlpm.g)),_xlpm.rev,_xlpm.r0*EXP(_xlpm.cum),_xlpm.prv,_xlpm.r0*EXP(_xlpm.cum-LN(1+_xlpm.g)),_xlpm.lp,IF(_xlpm.t>=_xlpm.n,1,_xlpm.t/_xlpm.n),_xlpm.omt,_xlpm.om0+(_xlpm.om-_xlpm.om0)*_xlpm.lp,_xlpm.dat,_xlpm.da0+(_xlpm.lcx*_xlpm.dar-_xlpm.da0)*_xlpm.lp,_xlpm.cpx,IF((_xlpm.t=1)*(_xlpm.gd>0),_xlpm.gd/_xlpm.rev,_xlpm.cx0+(_xlpm.lcx-_xlpm.cx0)*_xlpm.lp),_xlpm.f,_xlpm.rev*(_xlpm.omt*(1-_xlpm.tx)+_xlpm.dat-_xlpm.cpx+_xlpm.sb)-_xlpm.nw*(_xlpm.rev-_xlpm.prv),_xlpm.pv,SUM(_xlpm.f/(1+_xlpm.w)^(_xlpm.t-0.5*_xlpm.m)),_xlpm.tv,INDEX(_xlpm.f,10)*(1+_xlpm.tgr)/(_xlpm.w-_xlpm.tgr)/(1+_xlpm.w)^10,(_xlpm.pv+_xlpm.tv+_xlpm.nc)/_xlpm.shs)} | U54: =U53-0.0025 | V54: {=_xlfn.LET(_xlpm.gs,$B$9,_xlpm.om,$B$10,_xlpm.w,$B$7,_xlpm.tgr,$B$8,_xlpm.n,$B$11,_xlpm.lcx,U54,_xlpm.r0,DCF!$B$37,_xlpm.om0,DCF!$B$39,_xlpm.cx0,DCF!$B$40,_xlpm.da0,DCF!$B$41,_xlpm.dar,DCF!$B$20,_xlpm.tx,DCF!$B$31,_xlpm.sb,DCF!$B$43,_xlpm.nw,DCF!$B$21,_xlpm.gd,N(DCF!$B$22),_xlpm.nc,DCF!$B$47,_xlpm.shs,DCF!$B$6,_xlpm.m,DCF!$B$48,_xlpm.t,_xlfn.SEQUENCE(10),_xlpm.g,_xlpm.gs-(_xlpm.gs-_xlpm.tgr)*(_xlpm.t-1)/9,_xlpm.cum,MMULT(--(_xlpm.t>=TRANSPOSE(_xlpm.t)),LN(1+_xlpm.g)),_xlpm.rev,_xlpm.r0*EXP(_xlpm.cum),_xlpm.prv,_xlpm.r0*EXP(_xlpm.cum-LN(1+_xlpm.g)),_xlpm.lp,IF(_xlpm.t>=_xlpm.n,1,_xlpm.t/_xlpm.n),_xlpm.omt,_xlpm.om0+(_xlpm.om-_xlpm.om0)*_xlpm.lp,_xlpm.dat,_xlpm.da0+(_xlpm.lcx*_xlpm.dar-_xlpm.da0)*_xlpm.lp,_xlpm.cpx,IF((_xlpm.t=1)*(_xlpm.gd>0),_xlpm.gd/_xlpm.rev,_xlpm.cx0+(_xlpm.lcx-_xlpm.cx0)*_xlpm.lp),_xlpm.f,_xlpm.rev*(_xlpm.omt*(1-_xlpm.tx)+_xlpm.dat-_xlpm.cpx+_xlpm.sb)-_xlpm.nw*(_xlpm.rev-_xlpm.prv),_xlpm.pv,SUM(_xlpm.f/(1+_xlpm.w)^(_xlpm.t-0.5*_xlpm.m)),_xlpm.tv,INDEX(_xlpm.f,10)*(1+_xlpm.tgr)/(_xlpm.w-_xlpm.tgr)/(1+_xlpm.w)^10,(_xlpm.pv+_xlpm.tv+_xlpm.nc)/_xlpm.shs)}
A55: 4 | B55: =TEXT(EDATE(Financials!$E$16,12*A55),"mmm-yy") | C55: =$B$9-($B$9-$B$8)*(A55-1)/9 | D55: =IF(A55=1,$B$37,D54)*(1+C55) | E55: =$B$39+($B$10-$B$39)*MIN(1,A55/$B$11) | F55: =D55*E55*(1-$B$31) | G55: =D55*($B$41+($B$19*$B$20-$B$41)*MIN(1,A55/$B$11)) | H55: =IF(AND(A55=1,N($B$22)>0),$B$22,D55*($B$40+($B$19-$B$40)*MIN(1,A55/$B$11))) | I55: =$B$21*(D55-IF(A55=1,$B$37,D54)) | J55: =D55*$B$43 | K55: =F55+G55-H55-I55+J55 | L55: =K55/D55 | M55: =A55-0.5*$B$48 | N55: =1/(1+$B$7)^M55 | O55: =K55*N55 | Q55: =Q54+0.005 | R55: {=_xlfn.LET(_xlpm.gs,Q55,_xlpm.om,$B$10,_xlpm.w,$B$7,_xlpm.tgr,$B$8,_xlpm.n,$B$11,_xlpm.lcx,$B$19,_xlpm.r0,DCF!$B$37,_xlpm.om0,DCF!$B$39,_xlpm.cx0,DCF!$B$40,_xlpm.da0,DCF!$B$41,_xlpm.dar,DCF!$B$20,_xlpm.tx,DCF!$B$31,_xlpm.sb,DCF!$B$43,_xlpm.nw,DCF!$B$21,_xlpm.gd,N(DCF!$B$22),_xlpm.nc,DCF!$B$47,_xlpm.shs,DCF!$B$6,_xlpm.m,DCF!$B$48,_xlpm.t,_xlfn.SEQUENCE(10),_xlpm.g,_xlpm.gs-(_xlpm.gs-_xlpm.tgr)*(_xlpm.t-1)/9,_xlpm.cum,MMULT(--(_xlpm.t>=TRANSPOSE(_xlpm.t)),LN(1+_xlpm.g)),_xlpm.rev,_xlpm.r0*EXP(_xlpm.cum),_xlpm.prv,_xlpm.r0*EXP(_xlpm.cum-LN(1+_xlpm.g)),_xlpm.lp,IF(_xlpm.t>=_xlpm.n,1,_xlpm.t/_xlpm.n),_xlpm.omt,_xlpm.om0+(_xlpm.om-_xlpm.om0)*_xlpm.lp,_xlpm.dat,_xlpm.da0+(_xlpm.lcx*_xlpm.dar-_xlpm.da0)*_xlpm.lp,_xlpm.cpx,IF((_xlpm.t=1)*(_xlpm.gd>0),_xlpm.gd/_xlpm.rev,_xlpm.cx0+(_xlpm.lcx-_xlpm.cx0)*_xlpm.lp),_xlpm.f,_xlpm.rev*(_xlpm.omt*(1-_xlpm.tx)+_xlpm.dat-_xlpm.cpx+_xlpm.sb)-_xlpm.nw*(_xlpm.rev-_xlpm.prv),_xlpm.pv,SUM(_xlpm.f/(1+_xlpm.w)^(_xlpm.t-0.5*_xlpm.m)),_xlpm.tv,INDEX(_xlpm.f,10)*(1+_xlpm.tgr)/(_xlpm.w-_xlpm.tgr)/(1+_xlpm.w)^10,(_xlpm.pv+_xlpm.tv+_xlpm.nc)/_xlpm.shs)} | S55: =S54+0.005 | T55: {=_xlfn.LET(_xlpm.gs,$B$9,_xlpm.om,S55,_xlpm.w,$B$7,_xlpm.tgr,$B$8,_xlpm.n,$B$11,_xlpm.lcx,$B$19,_xlpm.r0,DCF!$B$37,_xlpm.om0,DCF!$B$39,_xlpm.cx0,DCF!$B$40,_xlpm.da0,DCF!$B$41,_xlpm.dar,DCF!$B$20,_xlpm.tx,DCF!$B$31,_xlpm.sb,DCF!$B$43,_xlpm.nw,DCF!$B$21,_xlpm.gd,N(DCF!$B$22),_xlpm.nc,DCF!$B$47,_xlpm.shs,DCF!$B$6,_xlpm.m,DCF!$B$48,_xlpm.t,_xlfn.SEQUENCE(10),_xlpm.g,_xlpm.gs-(_xlpm.gs-_xlpm.tgr)*(_xlpm.t-1)/9,_xlpm.cum,MMULT(--(_xlpm.t>=TRANSPOSE(_xlpm.t)),LN(1+_xlpm.g)),_xlpm.rev,_xlpm.r0*EXP(_xlpm.cum),_xlpm.prv,_xlpm.r0*EXP(_xlpm.cum-LN(1+_xlpm.g)),_xlpm.lp,IF(_xlpm.t>=_xlpm.n,1,_xlpm.t/_xlpm.n),_xlpm.omt,_xlpm.om0+(_xlpm.om-_xlpm.om0)*_xlpm.lp,_xlpm.dat,_xlpm.da0+(_xlpm.lcx*_xlpm.dar-_xlpm.da0)*_xlpm.lp,_xlpm.cpx,IF((_xlpm.t=1)*(_xlpm.gd>0),_xlpm.gd/_xlpm.rev,_xlpm.cx0+(_xlpm.lcx-_xlpm.cx0)*_xlpm.lp),_xlpm.f,_xlpm.rev*(_xlpm.omt*(1-_xlpm.tx)+_xlpm.dat-_xlpm.cpx+_xlpm.sb)-_xlpm.nw*(_xlpm.rev-_xlpm.prv),_xlpm.pv,SUM(_xlpm.f/(1+_xlpm.w)^(_xlpm.t-0.5*_xlpm.m)),_xlpm.tv,INDEX(_xlpm.f,10)*(1+_xlpm.tgr)/(_xlpm.w-_xlpm.tgr)/(1+_xlpm.w)^10,(_xlpm.pv+_xlpm.tv+_xlpm.nc)/_xlpm.shs)} | U55: =U54-0.0025 | V55: {=_xlfn.LET(_xlpm.gs,$B$9,_xlpm.om,$B$10,_xlpm.w,$B$7,_xlpm.tgr,$B$8,_xlpm.n,$B$11,_xlpm.lcx,U55,_xlpm.r0,DCF!$B$37,_xlpm.om0,DCF!$B$39,_xlpm.cx0,DCF!$B$40,_xlpm.da0,DCF!$B$41,_xlpm.dar,DCF!$B$20,_xlpm.tx,DCF!$B$31,_xlpm.sb,DCF!$B$43,_xlpm.nw,DCF!$B$21,_xlpm.gd,N(DCF!$B$22),_xlpm.nc,DCF!$B$47,_xlpm.shs,DCF!$B$6,_xlpm.m,DCF!$B$48,_xlpm.t,_xlfn.SEQUENCE(10),_xlpm.g,_xlpm.gs-(_xlpm.gs-_xlpm.tgr)*(_xlpm.t-1)/9,_xlpm.cum,MMULT(--(_xlpm.t>=TRANSPOSE(_xlpm.t)),LN(1+_xlpm.g)),_xlpm.rev,_xlpm.r0*EXP(_xlpm.cum),_xlpm.prv,_xlpm.r0*EXP(_xlpm.cum-LN(1+_xlpm.g)),_xlpm.lp,IF(_xlpm.t>=_xlpm.n,1,_xlpm.t/_xlpm.n),_xlpm.omt,_xlpm.om0+(_xlpm.om-_xlpm.om0)*_xlpm.lp,_xlpm.dat,_xlpm.da0+(_xlpm.lcx*_xlpm.dar-_xlpm.da0)*_xlpm.lp,_xlpm.cpx,IF((_xlpm.t=1)*(_xlpm.gd>0),_xlpm.gd/_xlpm.rev,_xlpm.cx0+(_xlpm.lcx-_xlpm.cx0)*_xlpm.lp),_xlpm.f,_xlpm.rev*(_xlpm.omt*(1-_xlpm.tx)+_xlpm.dat-_xlpm.cpx+_xlpm.sb)-_xlpm.nw*(_xlpm.rev-_xlpm.prv),_xlpm.pv,SUM(_xlpm.f/(1+_xlpm.w)^(_xlpm.t-0.5*_xlpm.m)),_xlpm.tv,INDEX(_xlpm.f,10)*(1+_xlpm.tgr)/(_xlpm.w-_xlpm.tgr)/(1+_xlpm.w)^10,(_xlpm.pv+_xlpm.tv+_xlpm.nc)/_xlpm.shs)}
A56: 5 | B56: =TEXT(EDATE(Financials!$E$16,12*A56),"mmm-yy") | C56: =$B$9-($B$9-$B$8)*(A56-1)/9 | D56: =IF(A56=1,$B$37,D55)*(1+C56) | E56: =$B$39+($B$10-$B$39)*MIN(1,A56/$B$11) | F56: =D56*E56*(1-$B$31) | G56: =D56*($B$41+($B$19*$B$20-$B$41)*MIN(1,A56/$B$11)) | H56: =IF(AND(A56=1,N($B$22)>0),$B$22,D56*($B$40+($B$19-$B$40)*MIN(1,A56/$B$11))) | I56: =$B$21*(D56-IF(A56=1,$B$37,D55)) | J56: =D56*$B$43 | K56: =F56+G56-H56-I56+J56 | L56: =K56/D56 | M56: =A56-0.5*$B$48 | N56: =1/(1+$B$7)^M56 | O56: =K56*N56 | Q56: =Q55+0.005 | R56: {=_xlfn.LET(_xlpm.gs,Q56,_xlpm.om,$B$10,_xlpm.w,$B$7,_xlpm.tgr,$B$8,_xlpm.n,$B$11,_xlpm.lcx,$B$19,_xlpm.r0,DCF!$B$37,_xlpm.om0,DCF!$B$39,_xlpm.cx0,DCF!$B$40,_xlpm.da0,DCF!$B$41,_xlpm.dar,DCF!$B$20,_xlpm.tx,DCF!$B$31,_xlpm.sb,DCF!$B$43,_xlpm.nw,DCF!$B$21,_xlpm.gd,N(DCF!$B$22),_xlpm.nc,DCF!$B$47,_xlpm.shs,DCF!$B$6,_xlpm.m,DCF!$B$48,_xlpm.t,_xlfn.SEQUENCE(10),_xlpm.g,_xlpm.gs-(_xlpm.gs-_xlpm.tgr)*(_xlpm.t-1)/9,_xlpm.cum,MMULT(--(_xlpm.t>=TRANSPOSE(_xlpm.t)),LN(1+_xlpm.g)),_xlpm.rev,_xlpm.r0*EXP(_xlpm.cum),_xlpm.prv,_xlpm.r0*EXP(_xlpm.cum-LN(1+_xlpm.g)),_xlpm.lp,IF(_xlpm.t>=_xlpm.n,1,_xlpm.t/_xlpm.n),_xlpm.omt,_xlpm.om0+(_xlpm.om-_xlpm.om0)*_xlpm.lp,_xlpm.dat,_xlpm.da0+(_xlpm.lcx*_xlpm.dar-_xlpm.da0)*_xlpm.lp,_xlpm.cpx,IF((_xlpm.t=1)*(_xlpm.gd>0),_xlpm.gd/_xlpm.rev,_xlpm.cx0+(_xlpm.lcx-_xlpm.cx0)*_xlpm.lp),_xlpm.f,_xlpm.rev*(_xlpm.omt*(1-_xlpm.tx)+_xlpm.dat-_xlpm.cpx+_xlpm.sb)-_xlpm.nw*(_xlpm.rev-_xlpm.prv),_xlpm.pv,SUM(_xlpm.f/(1+_xlpm.w)^(_xlpm.t-0.5*_xlpm.m)),_xlpm.tv,INDEX(_xlpm.f,10)*(1+_xlpm.tgr)/(_xlpm.w-_xlpm.tgr)/(1+_xlpm.w)^10,(_xlpm.pv+_xlpm.tv+_xlpm.nc)/_xlpm.shs)} | S56: =S55+0.005 | T56: {=_xlfn.LET(_xlpm.gs,$B$9,_xlpm.om,S56,_xlpm.w,$B$7,_xlpm.tgr,$B$8,_xlpm.n,$B$11,_xlpm.lcx,$B$19,_xlpm.r0,DCF!$B$37,_xlpm.om0,DCF!$B$39,_xlpm.cx0,DCF!$B$40,_xlpm.da0,DCF!$B$41,_xlpm.dar,DCF!$B$20,_xlpm.tx,DCF!$B$31,_xlpm.sb,DCF!$B$43,_xlpm.nw,DCF!$B$21,_xlpm.gd,N(DCF!$B$22),_xlpm.nc,DCF!$B$47,_xlpm.shs,DCF!$B$6,_xlpm.m,DCF!$B$48,_xlpm.t,_xlfn.SEQUENCE(10),_xlpm.g,_xlpm.gs-(_xlpm.gs-_xlpm.tgr)*(_xlpm.t-1)/9,_xlpm.cum,MMULT(--(_xlpm.t>=TRANSPOSE(_xlpm.t)),LN(1+_xlpm.g)),_xlpm.rev,_xlpm.r0*EXP(_xlpm.cum),_xlpm.prv,_xlpm.r0*EXP(_xlpm.cum-LN(1+_xlpm.g)),_xlpm.lp,IF(_xlpm.t>=_xlpm.n,1,_xlpm.t/_xlpm.n),_xlpm.omt,_xlpm.om0+(_xlpm.om-_xlpm.om0)*_xlpm.lp,_xlpm.dat,_xlpm.da0+(_xlpm.lcx*_xlpm.dar-_xlpm.da0)*_xlpm.lp,_xlpm.cpx,IF((_xlpm.t=1)*(_xlpm.gd>0),_xlpm.gd/_xlpm.rev,_xlpm.cx0+(_xlpm.lcx-_xlpm.cx0)*_xlpm.lp),_xlpm.f,_xlpm.rev*(_xlpm.omt*(1-_xlpm.tx)+_xlpm.dat-_xlpm.cpx+_xlpm.sb)-_xlpm.nw*(_xlpm.rev-_xlpm.prv),_xlpm.pv,SUM(_xlpm.f/(1+_xlpm.w)^(_xlpm.t-0.5*_xlpm.m)),_xlpm.tv,INDEX(_xlpm.f,10)*(1+_xlpm.tgr)/(_xlpm.w-_xlpm.tgr)/(1+_xlpm.w)^10,(_xlpm.pv+_xlpm.tv+_xlpm.nc)/_xlpm.shs)} | U56: =U55-0.0025 | V56: {=_xlfn.LET(_xlpm.gs,$B$9,_xlpm.om,$B$10,_xlpm.w,$B$7,_xlpm.tgr,$B$8,_xlpm.n,$B$11,_xlpm.lcx,U56,_xlpm.r0,DCF!$B$37,_xlpm.om0,DCF!$B$39,_xlpm.cx0,DCF!$B$40,_xlpm.da0,DCF!$B$41,_xlpm.dar,DCF!$B$20,_xlpm.tx,DCF!$B$31,_xlpm.sb,DCF!$B$43,_xlpm.nw,DCF!$B$21,_xlpm.gd,N(DCF!$B$22),_xlpm.nc,DCF!$B$47,_xlpm.shs,DCF!$B$6,_xlpm.m,DCF!$B$48,_xlpm.t,_xlfn.SEQUENCE(10),_xlpm.g,_xlpm.gs-(_xlpm.gs-_xlpm.tgr)*(_xlpm.t-1)/9,_xlpm.cum,MMULT(--(_xlpm.t>=TRANSPOSE(_xlpm.t)),LN(1+_xlpm.g)),_xlpm.rev,_xlpm.r0*EXP(_xlpm.cum),_xlpm.prv,_xlpm.r0*EXP(_xlpm.cum-LN(1+_xlpm.g)),_xlpm.lp,IF(_xlpm.t>=_xlpm.n,1,_xlpm.t/_xlpm.n),_xlpm.omt,_xlpm.om0+(_xlpm.om-_xlpm.om0)*_xlpm.lp,_xlpm.dat,_xlpm.da0+(_xlpm.lcx*_xlpm.dar-_xlpm.da0)*_xlpm.lp,_xlpm.cpx,IF((_xlpm.t=1)*(_xlpm.gd>0),_xlpm.gd/_xlpm.rev,_xlpm.cx0+(_xlpm.lcx-_xlpm.cx0)*_xlpm.lp),_xlpm.f,_xlpm.rev*(_xlpm.omt*(1-_xlpm.tx)+_xlpm.dat-_xlpm.cpx+_xlpm.sb)-_xlpm.nw*(_xlpm.rev-_xlpm.prv),_xlpm.pv,SUM(_xlpm.f/(1+_xlpm.w)^(_xlpm.t-0.5*_xlpm.m)),_xlpm.tv,INDEX(_xlpm.f,10)*(1+_xlpm.tgr)/(_xlpm.w-_xlpm.tgr)/(1+_xlpm.w)^10,(_xlpm.pv+_xlpm.tv+_xlpm.nc)/_xlpm.shs)}
A57: 6 | B57: =TEXT(EDATE(Financials!$E$16,12*A57),"mmm-yy") | C57: =$B$9-($B$9-$B$8)*(A57-1)/9 | D57: =IF(A57=1,$B$37,D56)*(1+C57) | E57: =$B$39+($B$10-$B$39)*MIN(1,A57/$B$11) | F57: =D57*E57*(1-$B$31) | G57: =D57*($B$41+($B$19*$B$20-$B$41)*MIN(1,A57/$B$11)) | H57: =IF(AND(A57=1,N($B$22)>0),$B$22,D57*($B$40+($B$19-$B$40)*MIN(1,A57/$B$11))) | I57: =$B$21*(D57-IF(A57=1,$B$37,D56)) | J57: =D57*$B$43 | K57: =F57+G57-H57-I57+J57 | L57: =K57/D57 | M57: =A57-0.5*$B$48 | N57: =1/(1+$B$7)^M57 | O57: =K57*N57 | Q57: =Q56+0.005 | R57: {=_xlfn.LET(_xlpm.gs,Q57,_xlpm.om,$B$10,_xlpm.w,$B$7,_xlpm.tgr,$B$8,_xlpm.n,$B$11,_xlpm.lcx,$B$19,_xlpm.r0,DCF!$B$37,_xlpm.om0,DCF!$B$39,_xlpm.cx0,DCF!$B$40,_xlpm.da0,DCF!$B$41,_xlpm.dar,DCF!$B$20,_xlpm.tx,DCF!$B$31,_xlpm.sb,DCF!$B$43,_xlpm.nw,DCF!$B$21,_xlpm.gd,N(DCF!$B$22),_xlpm.nc,DCF!$B$47,_xlpm.shs,DCF!$B$6,_xlpm.m,DCF!$B$48,_xlpm.t,_xlfn.SEQUENCE(10),_xlpm.g,_xlpm.gs-(_xlpm.gs-_xlpm.tgr)*(_xlpm.t-1)/9,_xlpm.cum,MMULT(--(_xlpm.t>=TRANSPOSE(_xlpm.t)),LN(1+_xlpm.g)),_xlpm.rev,_xlpm.r0*EXP(_xlpm.cum),_xlpm.prv,_xlpm.r0*EXP(_xlpm.cum-LN(1+_xlpm.g)),_xlpm.lp,IF(_xlpm.t>=_xlpm.n,1,_xlpm.t/_xlpm.n),_xlpm.omt,_xlpm.om0+(_xlpm.om-_xlpm.om0)*_xlpm.lp,_xlpm.dat,_xlpm.da0+(_xlpm.lcx*_xlpm.dar-_xlpm.da0)*_xlpm.lp,_xlpm.cpx,IF((_xlpm.t=1)*(_xlpm.gd>0),_xlpm.gd/_xlpm.rev,_xlpm.cx0+(_xlpm.lcx-_xlpm.cx0)*_xlpm.lp),_xlpm.f,_xlpm.rev*(_xlpm.omt*(1-_xlpm.tx)+_xlpm.dat-_xlpm.cpx+_xlpm.sb)-_xlpm.nw*(_xlpm.rev-_xlpm.prv),_xlpm.pv,SUM(_xlpm.f/(1+_xlpm.w)^(_xlpm.t-0.5*_xlpm.m)),_xlpm.tv,INDEX(_xlpm.f,10)*(1+_xlpm.tgr)/(_xlpm.w-_xlpm.tgr)/(1+_xlpm.w)^10,(_xlpm.pv+_xlpm.tv+_xlpm.nc)/_xlpm.shs)} | S57: =S56+0.005 | T57: {=_xlfn.LET(_xlpm.gs,$B$9,_xlpm.om,S57,_xlpm.w,$B$7,_xlpm.tgr,$B$8,_xlpm.n,$B$11,_xlpm.lcx,$B$19,_xlpm.r0,DCF!$B$37,_xlpm.om0,DCF!$B$39,_xlpm.cx0,DCF!$B$40,_xlpm.da0,DCF!$B$41,_xlpm.dar,DCF!$B$20,_xlpm.tx,DCF!$B$31,_xlpm.sb,DCF!$B$43,_xlpm.nw,DCF!$B$21,_xlpm.gd,N(DCF!$B$22),_xlpm.nc,DCF!$B$47,_xlpm.shs,DCF!$B$6,_xlpm.m,DCF!$B$48,_xlpm.t,_xlfn.SEQUENCE(10),_xlpm.g,_xlpm.gs-(_xlpm.gs-_xlpm.tgr)*(_xlpm.t-1)/9,_xlpm.cum,MMULT(--(_xlpm.t>=TRANSPOSE(_xlpm.t)),LN(1+_xlpm.g)),_xlpm.rev,_xlpm.r0*EXP(_xlpm.cum),_xlpm.prv,_xlpm.r0*EXP(_xlpm.cum-LN(1+_xlpm.g)),_xlpm.lp,IF(_xlpm.t>=_xlpm.n,1,_xlpm.t/_xlpm.n),_xlpm.omt,_xlpm.om0+(_xlpm.om-_xlpm.om0)*_xlpm.lp,_xlpm.dat,_xlpm.da0+(_xlpm.lcx*_xlpm.dar-_xlpm.da0)*_xlpm.lp,_xlpm.cpx,IF((_xlpm.t=1)*(_xlpm.gd>0),_xlpm.gd/_xlpm.rev,_xlpm.cx0+(_xlpm.lcx-_xlpm.cx0)*_xlpm.lp),_xlpm.f,_xlpm.rev*(_xlpm.omt*(1-_xlpm.tx)+_xlpm.dat-_xlpm.cpx+_xlpm.sb)-_xlpm.nw*(_xlpm.rev-_xlpm.prv),_xlpm.pv,SUM(_xlpm.f/(1+_xlpm.w)^(_xlpm.t-0.5*_xlpm.m)),_xlpm.tv,INDEX(_xlpm.f,10)*(1+_xlpm.tgr)/(_xlpm.w-_xlpm.tgr)/(1+_xlpm.w)^10,(_xlpm.pv+_xlpm.tv+_xlpm.nc)/_xlpm.shs)} | U57: =U56-0.0025 | V57: {=_xlfn.LET(_xlpm.gs,$B$9,_xlpm.om,$B$10,_xlpm.w,$B$7,_xlpm.tgr,$B$8,_xlpm.n,$B$11,_xlpm.lcx,U57,_xlpm.r0,DCF!$B$37,_xlpm.om0,DCF!$B$39,_xlpm.cx0,DCF!$B$40,_xlpm.da0,DCF!$B$41,_xlpm.dar,DCF!$B$20,_xlpm.tx,DCF!$B$31,_xlpm.sb,DCF!$B$43,_xlpm.nw,DCF!$B$21,_xlpm.gd,N(DCF!$B$22),_xlpm.nc,DCF!$B$47,_xlpm.shs,DCF!$B$6,_xlpm.m,DCF!$B$48,_xlpm.t,_xlfn.SEQUENCE(10),_xlpm.g,_xlpm.gs-(_xlpm.gs-_xlpm.tgr)*(_xlpm.t-1)/9,_xlpm.cum,MMULT(--(_xlpm.t>=TRANSPOSE(_xlpm.t)),LN(1+_xlpm.g)),_xlpm.rev,_xlpm.r0*EXP(_xlpm.cum),_xlpm.prv,_xlpm.r0*EXP(_xlpm.cum-LN(1+_xlpm.g)),_xlpm.lp,IF(_xlpm.t>=_xlpm.n,1,_xlpm.t/_xlpm.n),_xlpm.omt,_xlpm.om0+(_xlpm.om-_xlpm.om0)*_xlpm.lp,_xlpm.dat,_xlpm.da0+(_xlpm.lcx*_xlpm.dar-_xlpm.da0)*_xlpm.lp,_xlpm.cpx,IF((_xlpm.t=1)*(_xlpm.gd>0),_xlpm.gd/_xlpm.rev,_xlpm.cx0+(_xlpm.lcx-_xlpm.cx0)*_xlpm.lp),_xlpm.f,_xlpm.rev*(_xlpm.omt*(1-_xlpm.tx)+_xlpm.dat-_xlpm.cpx+_xlpm.sb)-_xlpm.nw*(_xlpm.rev-_xlpm.prv),_xlpm.pv,SUM(_xlpm.f/(1+_xlpm.w)^(_xlpm.t-0.5*_xlpm.m)),_xlpm.tv,INDEX(_xlpm.f,10)*(1+_xlpm.tgr)/(_xlpm.w-_xlpm.tgr)/(1+_xlpm.w)^10,(_xlpm.pv+_xlpm.tv+_xlpm.nc)/_xlpm.shs)}
A58: 7 | B58: =TEXT(EDATE(Financials!$E$16,12*A58),"mmm-yy") | C58: =$B$9-($B$9-$B$8)*(A58-1)/9 | D58: =IF(A58=1,$B$37,D57)*(1+C58) | E58: =$B$39+($B$10-$B$39)*MIN(1,A58/$B$11) | F58: =D58*E58*(1-$B$31) | G58: =D58*($B$41+($B$19*$B$20-$B$41)*MIN(1,A58/$B$11)) | H58: =IF(AND(A58=1,N($B$22)>0),$B$22,D58*($B$40+($B$19-$B$40)*MIN(1,A58/$B$11))) | I58: =$B$21*(D58-IF(A58=1,$B$37,D57)) | J58: =D58*$B$43 | K58: =F58+G58-H58-I58+J58 | L58: =K58/D58 | M58: =A58-0.5*$B$48 | N58: =1/(1+$B$7)^M58 | O58: =K58*N58 | Q58: =Q57+0.005 | R58: {=_xlfn.LET(_xlpm.gs,Q58,_xlpm.om,$B$10,_xlpm.w,$B$7,_xlpm.tgr,$B$8,_xlpm.n,$B$11,_xlpm.lcx,$B$19,_xlpm.r0,DCF!$B$37,_xlpm.om0,DCF!$B$39,_xlpm.cx0,DCF!$B$40,_xlpm.da0,DCF!$B$41,_xlpm.dar,DCF!$B$20,_xlpm.tx,DCF!$B$31,_xlpm.sb,DCF!$B$43,_xlpm.nw,DCF!$B$21,_xlpm.gd,N(DCF!$B$22),_xlpm.nc,DCF!$B$47,_xlpm.shs,DCF!$B$6,_xlpm.m,DCF!$B$48,_xlpm.t,_xlfn.SEQUENCE(10),_xlpm.g,_xlpm.gs-(_xlpm.gs-_xlpm.tgr)*(_xlpm.t-1)/9,_xlpm.cum,MMULT(--(_xlpm.t>=TRANSPOSE(_xlpm.t)),LN(1+_xlpm.g)),_xlpm.rev,_xlpm.r0*EXP(_xlpm.cum),_xlpm.prv,_xlpm.r0*EXP(_xlpm.cum-LN(1+_xlpm.g)),_xlpm.lp,IF(_xlpm.t>=_xlpm.n,1,_xlpm.t/_xlpm.n),_xlpm.omt,_xlpm.om0+(_xlpm.om-_xlpm.om0)*_xlpm.lp,_xlpm.dat,_xlpm.da0+(_xlpm.lcx*_xlpm.dar-_xlpm.da0)*_xlpm.lp,_xlpm.cpx,IF((_xlpm.t=1)*(_xlpm.gd>0),_xlpm.gd/_xlpm.rev,_xlpm.cx0+(_xlpm.lcx-_xlpm.cx0)*_xlpm.lp),_xlpm.f,_xlpm.rev*(_xlpm.omt*(1-_xlpm.tx)+_xlpm.dat-_xlpm.cpx+_xlpm.sb)-_xlpm.nw*(_xlpm.rev-_xlpm.prv),_xlpm.pv,SUM(_xlpm.f/(1+_xlpm.w)^(_xlpm.t-0.5*_xlpm.m)),_xlpm.tv,INDEX(_xlpm.f,10)*(1+_xlpm.tgr)/(_xlpm.w-_xlpm.tgr)/(1+_xlpm.w)^10,(_xlpm.pv+_xlpm.tv+_xlpm.nc)/_xlpm.shs)} | S58: =S57+0.005 | T58: {=_xlfn.LET(_xlpm.gs,$B$9,_xlpm.om,S58,_xlpm.w,$B$7,_xlpm.tgr,$B$8,_xlpm.n,$B$11,_xlpm.lcx,$B$19,_xlpm.r0,DCF!$B$37,_xlpm.om0,DCF!$B$39,_xlpm.cx0,DCF!$B$40,_xlpm.da0,DCF!$B$41,_xlpm.dar,DCF!$B$20,_xlpm.tx,DCF!$B$31,_xlpm.sb,DCF!$B$43,_xlpm.nw,DCF!$B$21,_xlpm.gd,N(DCF!$B$22),_xlpm.nc,DCF!$B$47,_xlpm.shs,DCF!$B$6,_xlpm.m,DCF!$B$48,_xlpm.t,_xlfn.SEQUENCE(10),_xlpm.g,_xlpm.gs-(_xlpm.gs-_xlpm.tgr)*(_xlpm.t-1)/9,_xlpm.cum,MMULT(--(_xlpm.t>=TRANSPOSE(_xlpm.t)),LN(1+_xlpm.g)),_xlpm.rev,_xlpm.r0*EXP(_xlpm.cum),_xlpm.prv,_xlpm.r0*EXP(_xlpm.cum-LN(1+_xlpm.g)),_xlpm.lp,IF(_xlpm.t>=_xlpm.n,1,_xlpm.t/_xlpm.n),_xlpm.omt,_xlpm.om0+(_xlpm.om-_xlpm.om0)*_xlpm.lp,_xlpm.dat,_xlpm.da0+(_xlpm.lcx*_xlpm.dar-_xlpm.da0)*_xlpm.lp,_xlpm.cpx,IF((_xlpm.t=1)*(_xlpm.gd>0),_xlpm.gd/_xlpm.rev,_xlpm.cx0+(_xlpm.lcx-_xlpm.cx0)*_xlpm.lp),_xlpm.f,_xlpm.rev*(_xlpm.omt*(1-_xlpm.tx)+_xlpm.dat-_xlpm.cpx+_xlpm.sb)-_xlpm.nw*(_xlpm.rev-_xlpm.prv),_xlpm.pv,SUM(_xlpm.f/(1+_xlpm.w)^(_xlpm.t-0.5*_xlpm.m)),_xlpm.tv,INDEX(_xlpm.f,10)*(1+_xlpm.tgr)/(_xlpm.w-_xlpm.tgr)/(1+_xlpm.w)^10,(_xlpm.pv+_xlpm.tv+_xlpm.nc)/_xlpm.shs)} | U58: =U57-0.0025 | V58: {=_xlfn.LET(_xlpm.gs,$B$9,_xlpm.om,$B$10,_xlpm.w,$B$7,_xlpm.tgr,$B$8,_xlpm.n,$B$11,_xlpm.lcx,U58,_xlpm.r0,DCF!$B$37,_xlpm.om0,DCF!$B$39,_xlpm.cx0,DCF!$B$40,_xlpm.da0,DCF!$B$41,_xlpm.dar,DCF!$B$20,_xlpm.tx,DCF!$B$31,_xlpm.sb,DCF!$B$43,_xlpm.nw,DCF!$B$21,_xlpm.gd,N(DCF!$B$22),_xlpm.nc,DCF!$B$47,_xlpm.shs,DCF!$B$6,_xlpm.m,DCF!$B$48,_xlpm.t,_xlfn.SEQUENCE(10),_xlpm.g,_xlpm.gs-(_xlpm.gs-_xlpm.tgr)*(_xlpm.t-1)/9,_xlpm.cum,MMULT(--(_xlpm.t>=TRANSPOSE(_xlpm.t)),LN(1+_xlpm.g)),_xlpm.rev,_xlpm.r0*EXP(_xlpm.cum),_xlpm.prv,_xlpm.r0*EXP(_xlpm.cum-LN(1+_xlpm.g)),_xlpm.lp,IF(_xlpm.t>=_xlpm.n,1,_xlpm.t/_xlpm.n),_xlpm.omt,_xlpm.om0+(_xlpm.om-_xlpm.om0)*_xlpm.lp,_xlpm.dat,_xlpm.da0+(_xlpm.lcx*_xlpm.dar-_xlpm.da0)*_xlpm.lp,_xlpm.cpx,IF((_xlpm.t=1)*(_xlpm.gd>0),_xlpm.gd/_xlpm.rev,_xlpm.cx0+(_xlpm.lcx-_xlpm.cx0)*_xlpm.lp),_xlpm.f,_xlpm.rev*(_xlpm.omt*(1-_xlpm.tx)+_xlpm.dat-_xlpm.cpx+_xlpm.sb)-_xlpm.nw*(_xlpm.rev-_xlpm.prv),_xlpm.pv,SUM(_xlpm.f/(1+_xlpm.w)^(_xlpm.t-0.5*_xlpm.m)),_xlpm.tv,INDEX(_xlpm.f,10)*(1+_xlpm.tgr)/(_xlpm.w-_xlpm.tgr)/(1+_xlpm.w)^10,(_xlpm.pv+_xlpm.tv+_xlpm.nc)/_xlpm.shs)}
A59: 8 | B59: =TEXT(EDATE(Financials!$E$16,12*A59),"mmm-yy") | C59: =$B$9-($B$9-$B$8)*(A59-1)/9 | D59: =IF(A59=1,$B$37,D58)*(1+C59) | E59: =$B$39+($B$10-$B$39)*MIN(1,A59/$B$11) | F59: =D59*E59*(1-$B$31) | G59: =D59*($B$41+($B$19*$B$20-$B$41)*MIN(1,A59/$B$11)) | H59: =IF(AND(A59=1,N($B$22)>0),$B$22,D59*($B$40+($B$19-$B$40)*MIN(1,A59/$B$11))) | I59: =$B$21*(D59-IF(A59=1,$B$37,D58)) | J59: =D59*$B$43 | K59: =F59+G59-H59-I59+J59 | L59: =K59/D59 | M59: =A59-0.5*$B$48 | N59: =1/(1+$B$7)^M59 | O59: =K59*N59 | Q59: =Q58+0.005 | R59: {=_xlfn.LET(_xlpm.gs,Q59,_xlpm.om,$B$10,_xlpm.w,$B$7,_xlpm.tgr,$B$8,_xlpm.n,$B$11,_xlpm.lcx,$B$19,_xlpm.r0,DCF!$B$37,_xlpm.om0,DCF!$B$39,_xlpm.cx0,DCF!$B$40,_xlpm.da0,DCF!$B$41,_xlpm.dar,DCF!$B$20,_xlpm.tx,DCF!$B$31,_xlpm.sb,DCF!$B$43,_xlpm.nw,DCF!$B$21,_xlpm.gd,N(DCF!$B$22),_xlpm.nc,DCF!$B$47,_xlpm.shs,DCF!$B$6,_xlpm.m,DCF!$B$48,_xlpm.t,_xlfn.SEQUENCE(10),_xlpm.g,_xlpm.gs-(_xlpm.gs-_xlpm.tgr)*(_xlpm.t-1)/9,_xlpm.cum,MMULT(--(_xlpm.t>=TRANSPOSE(_xlpm.t)),LN(1+_xlpm.g)),_xlpm.rev,_xlpm.r0*EXP(_xlpm.cum),_xlpm.prv,_xlpm.r0*EXP(_xlpm.cum-LN(1+_xlpm.g)),_xlpm.lp,IF(_xlpm.t>=_xlpm.n,1,_xlpm.t/_xlpm.n),_xlpm.omt,_xlpm.om0+(_xlpm.om-_xlpm.om0)*_xlpm.lp,_xlpm.dat,_xlpm.da0+(_xlpm.lcx*_xlpm.dar-_xlpm.da0)*_xlpm.lp,_xlpm.cpx,IF((_xlpm.t=1)*(_xlpm.gd>0),_xlpm.gd/_xlpm.rev,_xlpm.cx0+(_xlpm.lcx-_xlpm.cx0)*_xlpm.lp),_xlpm.f,_xlpm.rev*(_xlpm.omt*(1-_xlpm.tx)+_xlpm.dat-_xlpm.cpx+_xlpm.sb)-_xlpm.nw*(_xlpm.rev-_xlpm.prv),_xlpm.pv,SUM(_xlpm.f/(1+_xlpm.w)^(_xlpm.t-0.5*_xlpm.m)),_xlpm.tv,INDEX(_xlpm.f,10)*(1+_xlpm.tgr)/(_xlpm.w-_xlpm.tgr)/(1+_xlpm.w)^10,(_xlpm.pv+_xlpm.tv+_xlpm.nc)/_xlpm.shs)} | S59: =S58+0.005 | T59: {=_xlfn.LET(_xlpm.gs,$B$9,_xlpm.om,S59,_xlpm.w,$B$7,_xlpm.tgr,$B$8,_xlpm.n,$B$11,_xlpm.lcx,$B$19,_xlpm.r0,DCF!$B$37,_xlpm.om0,DCF!$B$39,_xlpm.cx0,DCF!$B$40,_xlpm.da0,DCF!$B$41,_xlpm.dar,DCF!$B$20,_xlpm.tx,DCF!$B$31,_xlpm.sb,DCF!$B$43,_xlpm.nw,DCF!$B$21,_xlpm.gd,N(DCF!$B$22),_xlpm.nc,DCF!$B$47,_xlpm.shs,DCF!$B$6,_xlpm.m,DCF!$B$48,_xlpm.t,_xlfn.SEQUENCE(10),_xlpm.g,_xlpm.gs-(_xlpm.gs-_xlpm.tgr)*(_xlpm.t-1)/9,_xlpm.cum,MMULT(--(_xlpm.t>=TRANSPOSE(_xlpm.t)),LN(1+_xlpm.g)),_xlpm.rev,_xlpm.r0*EXP(_xlpm.cum),_xlpm.prv,_xlpm.r0*EXP(_xlpm.cum-LN(1+_xlpm.g)),_xlpm.lp,IF(_xlpm.t>=_xlpm.n,1,_xlpm.t/_xlpm.n),_xlpm.omt,_xlpm.om0+(_xlpm.om-_xlpm.om0)*_xlpm.lp,_xlpm.dat,_xlpm.da0+(_xlpm.lcx*_xlpm.dar-_xlpm.da0)*_xlpm.lp,_xlpm.cpx,IF((_xlpm.t=1)*(_xlpm.gd>0),_xlpm.gd/_xlpm.rev,_xlpm.cx0+(_xlpm.lcx-_xlpm.cx0)*_xlpm.lp),_xlpm.f,_xlpm.rev*(_xlpm.omt*(1-_xlpm.tx)+_xlpm.dat-_xlpm.cpx+_xlpm.sb)-_xlpm.nw*(_xlpm.rev-_xlpm.prv),_xlpm.pv,SUM(_xlpm.f/(1+_xlpm.w)^(_xlpm.t-0.5*_xlpm.m)),_xlpm.tv,INDEX(_xlpm.f,10)*(1+_xlpm.tgr)/(_xlpm.w-_xlpm.tgr)/(1+_xlpm.w)^10,(_xlpm.pv+_xlpm.tv+_xlpm.nc)/_xlpm.shs)} | U59: =U58-0.0025 | V59: {=_xlfn.LET(_xlpm.gs,$B$9,_xlpm.om,$B$10,_xlpm.w,$B$7,_xlpm.tgr,$B$8,_xlpm.n,$B$11,_xlpm.lcx,U59,_xlpm.r0,DCF!$B$37,_xlpm.om0,DCF!$B$39,_xlpm.cx0,DCF!$B$40,_xlpm.da0,DCF!$B$41,_xlpm.dar,DCF!$B$20,_xlpm.tx,DCF!$B$31,_xlpm.sb,DCF!$B$43,_xlpm.nw,DCF!$B$21,_xlpm.gd,N(DCF!$B$22),_xlpm.nc,DCF!$B$47,_xlpm.shs,DCF!$B$6,_xlpm.m,DCF!$B$48,_xlpm.t,_xlfn.SEQUENCE(10),_xlpm.g,_xlpm.gs-(_xlpm.gs-_xlpm.tgr)*(_xlpm.t-1)/9,_xlpm.cum,MMULT(--(_xlpm.t>=TRANSPOSE(_xlpm.t)),LN(1+_xlpm.g)),_xlpm.rev,_xlpm.r0*EXP(_xlpm.cum),_xlpm.prv,_xlpm.r0*EXP(_xlpm.cum-LN(1+_xlpm.g)),_xlpm.lp,IF(_xlpm.t>=_xlpm.n,1,_xlpm.t/_xlpm.n),_xlpm.omt,_xlpm.om0+(_xlpm.om-_xlpm.om0)*_xlpm.lp,_xlpm.dat,_xlpm.da0+(_xlpm.lcx*_xlpm.dar-_xlpm.da0)*_xlpm.lp,_xlpm.cpx,IF((_xlpm.t=1)*(_xlpm.gd>0),_xlpm.gd/_xlpm.rev,_xlpm.cx0+(_xlpm.lcx-_xlpm.cx0)*_xlpm.lp),_xlpm.f,_xlpm.rev*(_xlpm.omt*(1-_xlpm.tx)+_xlpm.dat-_xlpm.cpx+_xlpm.sb)-_xlpm.nw*(_xlpm.rev-_xlpm.prv),_xlpm.pv,SUM(_xlpm.f/(1+_xlpm.w)^(_xlpm.t-0.5*_xlpm.m)),_xlpm.tv,INDEX(_xlpm.f,10)*(1+_xlpm.tgr)/(_xlpm.w-_xlpm.tgr)/(1+_xlpm.w)^10,(_xlpm.pv+_xlpm.tv+_xlpm.nc)/_xlpm.shs)}
A60: 9 | B60: =TEXT(EDATE(Financials!$E$16,12*A60),"mmm-yy") | C60: =$B$9-($B$9-$B$8)*(A60-1)/9 | D60: =IF(A60=1,$B$37,D59)*(1+C60) | E60: =$B$39+($B$10-$B$39)*MIN(1,A60/$B$11) | F60: =D60*E60*(1-$B$31) | G60: =D60*($B$41+($B$19*$B$20-$B$41)*MIN(1,A60/$B$11)) | H60: =IF(AND(A60=1,N($B$22)>0),$B$22,D60*($B$40+($B$19-$B$40)*MIN(1,A60/$B$11))) | I60: =$B$21*(D60-IF(A60=1,$B$37,D59)) | J60: =D60*$B$43 | K60: =F60+G60-H60-I60+J60 | L60: =K60/D60 | M60: =A60-0.5*$B$48 | N60: =1/(1+$B$7)^M60 | O60: =K60*N60 | Q60: =Q59+0.005 | R60: {=_xlfn.LET(_xlpm.gs,Q60,_xlpm.om,$B$10,_xlpm.w,$B$7,_xlpm.tgr,$B$8,_xlpm.n,$B$11,_xlpm.lcx,$B$19,_xlpm.r0,DCF!$B$37,_xlpm.om0,DCF!$B$39,_xlpm.cx0,DCF!$B$40,_xlpm.da0,DCF!$B$41,_xlpm.dar,DCF!$B$20,_xlpm.tx,DCF!$B$31,_xlpm.sb,DCF!$B$43,_xlpm.nw,DCF!$B$21,_xlpm.gd,N(DCF!$B$22),_xlpm.nc,DCF!$B$47,_xlpm.shs,DCF!$B$6,_xlpm.m,DCF!$B$48,_xlpm.t,_xlfn.SEQUENCE(10),_xlpm.g,_xlpm.gs-(_xlpm.gs-_xlpm.tgr)*(_xlpm.t-1)/9,_xlpm.cum,MMULT(--(_xlpm.t>=TRANSPOSE(_xlpm.t)),LN(1+_xlpm.g)),_xlpm.rev,_xlpm.r0*EXP(_xlpm.cum),_xlpm.prv,_xlpm.r0*EXP(_xlpm.cum-LN(1+_xlpm.g)),_xlpm.lp,IF(_xlpm.t>=_xlpm.n,1,_xlpm.t/_xlpm.n),_xlpm.omt,_xlpm.om0+(_xlpm.om-_xlpm.om0)*_xlpm.lp,_xlpm.dat,_xlpm.da0+(_xlpm.lcx*_xlpm.dar-_xlpm.da0)*_xlpm.lp,_xlpm.cpx,IF((_xlpm.t=1)*(_xlpm.gd>0),_xlpm.gd/_xlpm.rev,_xlpm.cx0+(_xlpm.lcx-_xlpm.cx0)*_xlpm.lp),_xlpm.f,_xlpm.rev*(_xlpm.omt*(1-_xlpm.tx)+_xlpm.dat-_xlpm.cpx+_xlpm.sb)-_xlpm.nw*(_xlpm.rev-_xlpm.prv),_xlpm.pv,SUM(_xlpm.f/(1+_xlpm.w)^(_xlpm.t-0.5*_xlpm.m)),_xlpm.tv,INDEX(_xlpm.f,10)*(1+_xlpm.tgr)/(_xlpm.w-_xlpm.tgr)/(1+_xlpm.w)^10,(_xlpm.pv+_xlpm.tv+_xlpm.nc)/_xlpm.shs)} | S60: =S59+0.005 | T60: {=_xlfn.LET(_xlpm.gs,$B$9,_xlpm.om,S60,_xlpm.w,$B$7,_xlpm.tgr,$B$8,_xlpm.n,$B$11,_xlpm.lcx,$B$19,_xlpm.r0,DCF!$B$37,_xlpm.om0,DCF!$B$39,_xlpm.cx0,DCF!$B$40,_xlpm.da0,DCF!$B$41,_xlpm.dar,DCF!$B$20,_xlpm.tx,DCF!$B$31,_xlpm.sb,DCF!$B$43,_xlpm.nw,DCF!$B$21,_xlpm.gd,N(DCF!$B$22),_xlpm.nc,DCF!$B$47,_xlpm.shs,DCF!$B$6,_xlpm.m,DCF!$B$48,_xlpm.t,_xlfn.SEQUENCE(10),_xlpm.g,_xlpm.gs-(_xlpm.gs-_xlpm.tgr)*(_xlpm.t-1)/9,_xlpm.cum,MMULT(--(_xlpm.t>=TRANSPOSE(_xlpm.t)),LN(1+_xlpm.g)),_xlpm.rev,_xlpm.r0*EXP(_xlpm.cum),_xlpm.prv,_xlpm.r0*EXP(_xlpm.cum-LN(1+_xlpm.g)),_xlpm.lp,IF(_xlpm.t>=_xlpm.n,1,_xlpm.t/_xlpm.n),_xlpm.omt,_xlpm.om0+(_xlpm.om-_xlpm.om0)*_xlpm.lp,_xlpm.dat,_xlpm.da0+(_xlpm.lcx*_xlpm.dar-_xlpm.da0)*_xlpm.lp,_xlpm.cpx,IF((_xlpm.t=1)*(_xlpm.gd>0),_xlpm.gd/_xlpm.rev,_xlpm.cx0+(_xlpm.lcx-_xlpm.cx0)*_xlpm.lp),_xlpm.f,_xlpm.rev*(_xlpm.omt*(1-_xlpm.tx)+_xlpm.dat-_xlpm.cpx+_xlpm.sb)-_xlpm.nw*(_xlpm.rev-_xlpm.prv),_xlpm.pv,SUM(_xlpm.f/(1+_xlpm.w)^(_xlpm.t-0.5*_xlpm.m)),_xlpm.tv,INDEX(_xlpm.f,10)*(1+_xlpm.tgr)/(_xlpm.w-_xlpm.tgr)/(1+_xlpm.w)^10,(_xlpm.pv+_xlpm.tv+_xlpm.nc)/_xlpm.shs)} | U60: =U59-0.0025 | V60: {=_xlfn.LET(_xlpm.gs,$B$9,_xlpm.om,$B$10,_xlpm.w,$B$7,_xlpm.tgr,$B$8,_xlpm.n,$B$11,_xlpm.lcx,U60,_xlpm.r0,DCF!$B$37,_xlpm.om0,DCF!$B$39,_xlpm.cx0,DCF!$B$40,_xlpm.da0,DCF!$B$41,_xlpm.dar,DCF!$B$20,_xlpm.tx,DCF!$B$31,_xlpm.sb,DCF!$B$43,_xlpm.nw,DCF!$B$21,_xlpm.gd,N(DCF!$B$22),_xlpm.nc,DCF!$B$47,_xlpm.shs,DCF!$B$6,_xlpm.m,DCF!$B$48,_xlpm.t,_xlfn.SEQUENCE(10),_xlpm.g,_xlpm.gs-(_xlpm.gs-_xlpm.tgr)*(_xlpm.t-1)/9,_xlpm.cum,MMULT(--(_xlpm.t>=TRANSPOSE(_xlpm.t)),LN(1+_xlpm.g)),_xlpm.rev,_xlpm.r0*EXP(_xlpm.cum),_xlpm.prv,_xlpm.r0*EXP(_xlpm.cum-LN(1+_xlpm.g)),_xlpm.lp,IF(_xlpm.t>=_xlpm.n,1,_xlpm.t/_xlpm.n),_xlpm.omt,_xlpm.om0+(_xlpm.om-_xlpm.om0)*_xlpm.lp,_xlpm.dat,_xlpm.da0+(_xlpm.lcx*_xlpm.dar-_xlpm.da0)*_xlpm.lp,_xlpm.cpx,IF((_xlpm.t=1)*(_xlpm.gd>0),_xlpm.gd/_xlpm.rev,_xlpm.cx0+(_xlpm.lcx-_xlpm.cx0)*_xlpm.lp),_xlpm.f,_xlpm.rev*(_xlpm.omt*(1-_xlpm.tx)+_xlpm.dat-_xlpm.cpx+_xlpm.sb)-_xlpm.nw*(_xlpm.rev-_xlpm.prv),_xlpm.pv,SUM(_xlpm.f/(1+_xlpm.w)^(_xlpm.t-0.5*_xlpm.m)),_xlpm.tv,INDEX(_xlpm.f,10)*(1+_xlpm.tgr)/(_xlpm.w-_xlpm.tgr)/(1+_xlpm.w)^10,(_xlpm.pv+_xlpm.tv+_xlpm.nc)/_xlpm.shs)}
A61: 10 | B61: =TEXT(EDATE(Financials!$E$16,12*A61),"mmm-yy") | C61: =$B$9-($B$9-$B$8)*(A61-1)/9 | D61: =IF(A61=1,$B$37,D60)*(1+C61) | E61: =$B$39+($B$10-$B$39)*MIN(1,A61/$B$11) | F61: =D61*E61*(1-$B$31) | G61: =D61*($B$41+($B$19*$B$20-$B$41)*MIN(1,A61/$B$11)) | H61: =IF(AND(A61=1,N($B$22)>0),$B$22,D61*($B$40+($B$19-$B$40)*MIN(1,A61/$B$11))) | I61: =$B$21*(D61-IF(A61=1,$B$37,D60)) | J61: =D61*$B$43 | K61: =F61+G61-H61-I61+J61 | L61: =K61/D61 | M61: =A61-0.5*$B$48 | N61: =1/(1+$B$7)^M61 | O61: =K61*N61 | Q61: =Q60+0.005 | R61: {=_xlfn.LET(_xlpm.gs,Q61,_xlpm.om,$B$10,_xlpm.w,$B$7,_xlpm.tgr,$B$8,_xlpm.n,$B$11,_xlpm.lcx,$B$19,_xlpm.r0,DCF!$B$37,_xlpm.om0,DCF!$B$39,_xlpm.cx0,DCF!$B$40,_xlpm.da0,DCF!$B$41,_xlpm.dar,DCF!$B$20,_xlpm.tx,DCF!$B$31,_xlpm.sb,DCF!$B$43,_xlpm.nw,DCF!$B$21,_xlpm.gd,N(DCF!$B$22),_xlpm.nc,DCF!$B$47,_xlpm.shs,DCF!$B$6,_xlpm.m,DCF!$B$48,_xlpm.t,_xlfn.SEQUENCE(10),_xlpm.g,_xlpm.gs-(_xlpm.gs-_xlpm.tgr)*(_xlpm.t-1)/9,_xlpm.cum,MMULT(--(_xlpm.t>=TRANSPOSE(_xlpm.t)),LN(1+_xlpm.g)),_xlpm.rev,_xlpm.r0*EXP(_xlpm.cum),_xlpm.prv,_xlpm.r0*EXP(_xlpm.cum-LN(1+_xlpm.g)),_xlpm.lp,IF(_xlpm.t>=_xlpm.n,1,_xlpm.t/_xlpm.n),_xlpm.omt,_xlpm.om0+(_xlpm.om-_xlpm.om0)*_xlpm.lp,_xlpm.dat,_xlpm.da0+(_xlpm.lcx*_xlpm.dar-_xlpm.da0)*_xlpm.lp,_xlpm.cpx,IF((_xlpm.t=1)*(_xlpm.gd>0),_xlpm.gd/_xlpm.rev,_xlpm.cx0+(_xlpm.lcx-_xlpm.cx0)*_xlpm.lp),_xlpm.f,_xlpm.rev*(_xlpm.omt*(1-_xlpm.tx)+_xlpm.dat-_xlpm.cpx+_xlpm.sb)-_xlpm.nw*(_xlpm.rev-_xlpm.prv),_xlpm.pv,SUM(_xlpm.f/(1+_xlpm.w)^(_xlpm.t-0.5*_xlpm.m)),_xlpm.tv,INDEX(_xlpm.f,10)*(1+_xlpm.tgr)/(_xlpm.w-_xlpm.tgr)/(1+_xlpm.w)^10,(_xlpm.pv+_xlpm.tv+_xlpm.nc)/_xlpm.shs)} | S61: =S60+0.005 | T61: {=_xlfn.LET(_xlpm.gs,$B$9,_xlpm.om,S61,_xlpm.w,$B$7,_xlpm.tgr,$B$8,_xlpm.n,$B$11,_xlpm.lcx,$B$19,_xlpm.r0,DCF!$B$37,_xlpm.om0,DCF!$B$39,_xlpm.cx0,DCF!$B$40,_xlpm.da0,DCF!$B$41,_xlpm.dar,DCF!$B$20,_xlpm.tx,DCF!$B$31,_xlpm.sb,DCF!$B$43,_xlpm.nw,DCF!$B$21,_xlpm.gd,N(DCF!$B$22),_xlpm.nc,DCF!$B$47,_xlpm.shs,DCF!$B$6,_xlpm.m,DCF!$B$48,_xlpm.t,_xlfn.SEQUENCE(10),_xlpm.g,_xlpm.gs-(_xlpm.gs-_xlpm.tgr)*(_xlpm.t-1)/9,_xlpm.cum,MMULT(--(_xlpm.t>=TRANSPOSE(_xlpm.t)),LN(1+_xlpm.g)),_xlpm.rev,_xlpm.r0*EXP(_xlpm.cum),_xlpm.prv,_xlpm.r0*EXP(_xlpm.cum-LN(1+_xlpm.g)),_xlpm.lp,IF(_xlpm.t>=_xlpm.n,1,_xlpm.t/_xlpm.n),_xlpm.omt,_xlpm.om0+(_xlpm.om-_xlpm.om0)*_xlpm.lp,_xlpm.dat,_xlpm.da0+(_xlpm.lcx*_xlpm.dar-_xlpm.da0)*_xlpm.lp,_xlpm.cpx,IF((_xlpm.t=1)*(_xlpm.gd>0),_xlpm.gd/_xlpm.rev,_xlpm.cx0+(_xlpm.lcx-_xlpm.cx0)*_xlpm.lp),_xlpm.f,_xlpm.rev*(_xlpm.omt*(1-_xlpm.tx)+_xlpm.dat-_xlpm.cpx+_xlpm.sb)-_xlpm.nw*(_xlpm.rev-_xlpm.prv),_xlpm.pv,SUM(_xlpm.f/(1+_xlpm.w)^(_xlpm.t-0.5*_xlpm.m)),_xlpm.tv,INDEX(_xlpm.f,10)*(1+_xlpm.tgr)/(_xlpm.w-_xlpm.tgr)/(1+_xlpm.w)^10,(_xlpm.pv+_xlpm.tv+_xlpm.nc)/_xlpm.shs)} | U61: =U60-0.0025 | V61: {=_xlfn.LET(_xlpm.gs,$B$9,_xlpm.om,$B$10,_xlpm.w,$B$7,_xlpm.tgr,$B$8,_xlpm.n,$B$11,_xlpm.lcx,U61,_xlpm.r0,DCF!$B$37,_xlpm.om0,DCF!$B$39,_xlpm.cx0,DCF!$B$40,_xlpm.da0,DCF!$B$41,_xlpm.dar,DCF!$B$20,_xlpm.tx,DCF!$B$31,_xlpm.sb,DCF!$B$43,_xlpm.nw,DCF!$B$21,_xlpm.gd,N(DCF!$B$22),_xlpm.nc,DCF!$B$47,_xlpm.shs,DCF!$B$6,_xlpm.m,DCF!$B$48,_xlpm.t,_xlfn.SEQUENCE(10),_xlpm.g,_xlpm.gs-(_xlpm.gs-_xlpm.tgr)*(_xlpm.t-1)/9,_xlpm.cum,MMULT(--(_xlpm.t>=TRANSPOSE(_xlpm.t)),LN(1+_xlpm.g)),_xlpm.rev,_xlpm.r0*EXP(_xlpm.cum),_xlpm.prv,_xlpm.r0*EXP(_xlpm.cum-LN(1+_xlpm.g)),_xlpm.lp,IF(_xlpm.t>=_xlpm.n,1,_xlpm.t/_xlpm.n),_xlpm.omt,_xlpm.om0+(_xlpm.om-_xlpm.om0)*_xlpm.lp,_xlpm.dat,_xlpm.da0+(_xlpm.lcx*_xlpm.dar-_xlpm.da0)*_xlpm.lp,_xlpm.cpx,IF((_xlpm.t=1)*(_xlpm.gd>0),_xlpm.gd/_xlpm.rev,_xlpm.cx0+(_xlpm.lcx-_xlpm.cx0)*_xlpm.lp),_xlpm.f,_xlpm.rev*(_xlpm.omt*(1-_xlpm.tx)+_xlpm.dat-_xlpm.cpx+_xlpm.sb)-_xlpm.nw*(_xlpm.rev-_xlpm.prv),_xlpm.pv,SUM(_xlpm.f/(1+_xlpm.w)^(_xlpm.t-0.5*_xlpm.m)),_xlpm.tv,INDEX(_xlpm.f,10)*(1+_xlpm.tgr)/(_xlpm.w-_xlpm.tgr)/(1+_xlpm.w)^10,(_xlpm.pv+_xlpm.tv+_xlpm.nc)/_xlpm.shs)}
Q62: =Q61+0.005 | R62: {=_xlfn.LET(_xlpm.gs,Q62,_xlpm.om,$B$10,_xlpm.w,$B$7,_xlpm.tgr,$B$8,_xlpm.n,$B$11,_xlpm.lcx,$B$19,_xlpm.r0,DCF!$B$37,_xlpm.om0,DCF!$B$39,_xlpm.cx0,DCF!$B$40,_xlpm.da0,DCF!$B$41,_xlpm.dar,DCF!$B$20,_xlpm.tx,DCF!$B$31,_xlpm.sb,DCF!$B$43,_xlpm.nw,DCF!$B$21,_xlpm.gd,N(DCF!$B$22),_xlpm.nc,DCF!$B$47,_xlpm.shs,DCF!$B$6,_xlpm.m,DCF!$B$48,_xlpm.t,_xlfn.SEQUENCE(10),_xlpm.g,_xlpm.gs-(_xlpm.gs-_xlpm.tgr)*(_xlpm.t-1)/9,_xlpm.cum,MMULT(--(_xlpm.t>=TRANSPOSE(_xlpm.t)),LN(1+_xlpm.g)),_xlpm.rev,_xlpm.r0*EXP(_xlpm.cum),_xlpm.prv,_xlpm.r0*EXP(_xlpm.cum-LN(1+_xlpm.g)),_xlpm.lp,IF(_xlpm.t>=_xlpm.n,1,_xlpm.t/_xlpm.n),_xlpm.omt,_xlpm.om0+(_xlpm.om-_xlpm.om0)*_xlpm.lp,_xlpm.dat,_xlpm.da0+(_xlpm.lcx*_xlpm.dar-_xlpm.da0)*_xlpm.lp,_xlpm.cpx,IF((_xlpm.t=1)*(_xlpm.gd>0),_xlpm.gd/_xlpm.rev,_xlpm.cx0+(_xlpm.lcx-_xlpm.cx0)*_xlpm.lp),_xlpm.f,_xlpm.rev*(_xlpm.omt*(1-_xlpm.tx)+_xlpm.dat-_xlpm.cpx+_xlpm.sb)-_xlpm.nw*(_xlpm.rev-_xlpm.prv),_xlpm.pv,SUM(_xlpm.f/(1+_xlpm.w)^(_xlpm.t-0.5*_xlpm.m)),_xlpm.tv,INDEX(_xlpm.f,10)*(1+_xlpm.tgr)/(_xlpm.w-_xlpm.tgr)/(1+_xlpm.w)^10,(_xlpm.pv+_xlpm.tv+_xlpm.nc)/_xlpm.shs)} | S62: =S61+0.005 | T62: {=_xlfn.LET(_xlpm.gs,$B$9,_xlpm.om,S62,_xlpm.w,$B$7,_xlpm.tgr,$B$8,_xlpm.n,$B$11,_xlpm.lcx,$B$19,_xlpm.r0,DCF!$B$37,_xlpm.om0,DCF!$B$39,_xlpm.cx0,DCF!$B$40,_xlpm.da0,DCF!$B$41,_xlpm.dar,DCF!$B$20,_xlpm.tx,DCF!$B$31,_xlpm.sb,DCF!$B$43,_xlpm.nw,DCF!$B$21,_xlpm.gd,N(DCF!$B$22),_xlpm.nc,DCF!$B$47,_xlpm.shs,DCF!$B$6,_xlpm.m,DCF!$B$48,_xlpm.t,_xlfn.SEQUENCE(10),_xlpm.g,_xlpm.gs-(_xlpm.gs-_xlpm.tgr)*(_xlpm.t-1)/9,_xlpm.cum,MMULT(--(_xlpm.t>=TRANSPOSE(_xlpm.t)),LN(1+_xlpm.g)),_xlpm.rev,_xlpm.r0*EXP(_xlpm.cum),_xlpm.prv,_xlpm.r0*EXP(_xlpm.cum-LN(1+_xlpm.g)),_xlpm.lp,IF(_xlpm.t>=_xlpm.n,1,_xlpm.t/_xlpm.n),_xlpm.omt,_xlpm.om0+(_xlpm.om-_xlpm.om0)*_xlpm.lp,_xlpm.dat,_xlpm.da0+(_xlpm.lcx*_xlpm.dar-_xlpm.da0)*_xlpm.lp,_xlpm.cpx,IF((_xlpm.t=1)*(_xlpm.gd>0),_xlpm.gd/_xlpm.rev,_xlpm.cx0+(_xlpm.lcx-_xlpm.cx0)*_xlpm.lp),_xlpm.f,_xlpm.rev*(_xlpm.omt*(1-_xlpm.tx)+_xlpm.dat-_xlpm.cpx+_xlpm.sb)-_xlpm.nw*(_xlpm.rev-_xlpm.prv),_xlpm.pv,SUM(_xlpm.f/(1+_xlpm.w)^(_xlpm.t-0.5*_xlpm.m)),_xlpm.tv,INDEX(_xlpm.f,10)*(1+_xlpm.tgr)/(_xlpm.w-_xlpm.tgr)/(1+_xlpm.w)^10,(_xlpm.pv+_xlpm.tv+_xlpm.nc)/_xlpm.shs)} | U62: =U61-0.0025 | V62: {=_xlfn.LET(_xlpm.gs,$B$9,_xlpm.om,$B$10,_xlpm.w,$B$7,_xlpm.tgr,$B$8,_xlpm.n,$B$11,_xlpm.lcx,U62,_xlpm.r0,DCF!$B$37,_xlpm.om0,DCF!$B$39,_xlpm.cx0,DCF!$B$40,_xlpm.da0,DCF!$B$41,_xlpm.dar,DCF!$B$20,_xlpm.tx,DCF!$B$31,_xlpm.sb,DCF!$B$43,_xlpm.nw,DCF!$B$21,_xlpm.gd,N(DCF!$B$22),_xlpm.nc,DCF!$B$47,_xlpm.shs,DCF!$B$6,_xlpm.m,DCF!$B$48,_xlpm.t,_xlfn.SEQUENCE(10),_xlpm.g,_xlpm.gs-(_xlpm.gs-_xlpm.tgr)*(_xlpm.t-1)/9,_xlpm.cum,MMULT(--(_xlpm.t>=TRANSPOSE(_xlpm.t)),LN(1+_xlpm.g)),_xlpm.rev,_xlpm.r0*EXP(_xlpm.cum),_xlpm.prv,_xlpm.r0*EXP(_xlpm.cum-LN(1+_xlpm.g)),_xlpm.lp,IF(_xlpm.t>=_xlpm.n,1,_xlpm.t/_xlpm.n),_xlpm.omt,_xlpm.om0+(_xlpm.om-_xlpm.om0)*_xlpm.lp,_xlpm.dat,_xlpm.da0+(_xlpm.lcx*_xlpm.dar-_xlpm.da0)*_xlpm.lp,_xlpm.cpx,IF((_xlpm.t=1)*(_xlpm.gd>0),_xlpm.gd/_xlpm.rev,_xlpm.cx0+(_xlpm.lcx-_xlpm.cx0)*_xlpm.lp),_xlpm.f,_xlpm.rev*(_xlpm.omt*(1-_xlpm.tx)+_xlpm.dat-_xlpm.cpx+_xlpm.sb)-_xlpm.nw*(_xlpm.rev-_xlpm.prv),_xlpm.pv,SUM(_xlpm.f/(1+_xlpm.w)^(_xlpm.t-0.5*_xlpm.m)),_xlpm.tv,INDEX(_xlpm.f,10)*(1+_xlpm.tgr)/(_xlpm.w-_xlpm.tgr)/(1+_xlpm.w)^10,(_xlpm.pv+_xlpm.tv+_xlpm.nc)/_xlpm.shs)}
A63: Valuation bridge | Q63: =Q62+0.005 | R63: {=_xlfn.LET(_xlpm.gs,Q63,_xlpm.om,$B$10,_xlpm.w,$B$7,_xlpm.tgr,$B$8,_xlpm.n,$B$11,_xlpm.lcx,$B$19,_xlpm.r0,DCF!$B$37,_xlpm.om0,DCF!$B$39,_xlpm.cx0,DCF!$B$40,_xlpm.da0,DCF!$B$41,_xlpm.dar,DCF!$B$20,_xlpm.tx,DCF!$B$31,_xlpm.sb,DCF!$B$43,_xlpm.nw,DCF!$B$21,_xlpm.gd,N(DCF!$B$22),_xlpm.nc,DCF!$B$47,_xlpm.shs,DCF!$B$6,_xlpm.m,DCF!$B$48,_xlpm.t,_xlfn.SEQUENCE(10),_xlpm.g,_xlpm.gs-(_xlpm.gs-_xlpm.tgr)*(_xlpm.t-1)/9,_xlpm.cum,MMULT(--(_xlpm.t>=TRANSPOSE(_xlpm.t)),LN(1+_xlpm.g)),_xlpm.rev,_xlpm.r0*EXP(_xlpm.cum),_xlpm.prv,_xlpm.r0*EXP(_xlpm.cum-LN(1+_xlpm.g)),_xlpm.lp,IF(_xlpm.t>=_xlpm.n,1,_xlpm.t/_xlpm.n),_xlpm.omt,_xlpm.om0+(_xlpm.om-_xlpm.om0)*_xlpm.lp,_xlpm.dat,_xlpm.da0+(_xlpm.lcx*_xlpm.dar-_xlpm.da0)*_xlpm.lp,_xlpm.cpx,IF((_xlpm.t=1)*(_xlpm.gd>0),_xlpm.gd/_xlpm.rev,_xlpm.cx0+(_xlpm.lcx-_xlpm.cx0)*_xlpm.lp),_xlpm.f,_xlpm.rev*(_xlpm.omt*(1-_xlpm.tx)+_xlpm.dat-_xlpm.cpx+_xlpm.sb)-_xlpm.nw*(_xlpm.rev-_xlpm.prv),_xlpm.pv,SUM(_xlpm.f/(1+_xlpm.w)^(_xlpm.t-0.5*_xlpm.m)),_xlpm.tv,INDEX(_xlpm.f,10)*(1+_xlpm.tgr)/(_xlpm.w-_xlpm.tgr)/(1+_xlpm.w)^10,(_xlpm.pv+_xlpm.tv+_xlpm.nc)/_xlpm.shs)} | S63: =S62+0.005 | T63: {=_xlfn.LET(_xlpm.gs,$B$9,_xlpm.om,S63,_xlpm.w,$B$7,_xlpm.tgr,$B$8,_xlpm.n,$B$11,_xlpm.lcx,$B$19,_xlpm.r0,DCF!$B$37,_xlpm.om0,DCF!$B$39,_xlpm.cx0,DCF!$B$40,_xlpm.da0,DCF!$B$41,_xlpm.dar,DCF!$B$20,_xlpm.tx,DCF!$B$31,_xlpm.sb,DCF!$B$43,_xlpm.nw,DCF!$B$21,_xlpm.gd,N(DCF!$B$22),_xlpm.nc,DCF!$B$47,_xlpm.shs,DCF!$B$6,_xlpm.m,DCF!$B$48,_xlpm.t,_xlfn.SEQUENCE(10),_xlpm.g,_xlpm.gs-(_xlpm.gs-_xlpm.tgr)*(_xlpm.t-1)/9,_xlpm.cum,MMULT(--(_xlpm.t>=TRANSPOSE(_xlpm.t)),LN(1+_xlpm.g)),_xlpm.rev,_xlpm.r0*EXP(_xlpm.cum),_xlpm.prv,_xlpm.r0*EXP(_xlpm.cum-LN(1+_xlpm.g)),_xlpm.lp,IF(_xlpm.t>=_xlpm.n,1,_xlpm.t/_xlpm.n),_xlpm.omt,_xlpm.om0+(_xlpm.om-_xlpm.om0)*_xlpm.lp,_xlpm.dat,_xlpm.da0+(_xlpm.lcx*_xlpm.dar-_xlpm.da0)*_xlpm.lp,_xlpm.cpx,IF((_xlpm.t=1)*(_xlpm.gd>0),_xlpm.gd/_xlpm.rev,_xlpm.cx0+(_xlpm.lcx-_xlpm.cx0)*_xlpm.lp),_xlpm.f,_xlpm.rev*(_xlpm.omt*(1-_xlpm.tx)+_xlpm.dat-_xlpm.cpx+_xlpm.sb)-_xlpm.nw*(_xlpm.rev-_xlpm.prv),_xlpm.pv,SUM(_xlpm.f/(1+_xlpm.w)^(_xlpm.t-0.5*_xlpm.m)),_xlpm.tv,INDEX(_xlpm.f,10)*(1+_xlpm.tgr)/(_xlpm.w-_xlpm.tgr)/(1+_xlpm.w)^10,(_xlpm.pv+_xlpm.tv+_xlpm.nc)/_xlpm.shs)} | U63: =U62-0.0025 | V63: {=_xlfn.LET(_xlpm.gs,$B$9,_xlpm.om,$B$10,_xlpm.w,$B$7,_xlpm.tgr,$B$8,_xlpm.n,$B$11,_xlpm.lcx,U63,_xlpm.r0,DCF!$B$37,_xlpm.om0,DCF!$B$39,_xlpm.cx0,DCF!$B$40,_xlpm.da0,DCF!$B$41,_xlpm.dar,DCF!$B$20,_xlpm.tx,DCF!$B$31,_xlpm.sb,DCF!$B$43,_xlpm.nw,DCF!$B$21,_xlpm.gd,N(DCF!$B$22),_xlpm.nc,DCF!$B$47,_xlpm.shs,DCF!$B$6,_xlpm.m,DCF!$B$48,_xlpm.t,_xlfn.SEQUENCE(10),_xlpm.g,_xlpm.gs-(_xlpm.gs-_xlpm.tgr)*(_xlpm.t-1)/9,_xlpm.cum,MMULT(--(_xlpm.t>=TRANSPOSE(_xlpm.t)),LN(1+_xlpm.g)),_xlpm.rev,_xlpm.r0*EXP(_xlpm.cum),_xlpm.prv,_xlpm.r0*EXP(_xlpm.cum-LN(1+_xlpm.g)),_xlpm.lp,IF(_xlpm.t>=_xlpm.n,1,_xlpm.t/_xlpm.n),_xlpm.omt,_xlpm.om0+(_xlpm.om-_xlpm.om0)*_xlpm.lp,_xlpm.dat,_xlpm.da0+(_xlpm.lcx*_xlpm.dar-_xlpm.da0)*_xlpm.lp,_xlpm.cpx,IF((_xlpm.t=1)*(_xlpm.gd>0),_xlpm.gd/_xlpm.rev,_xlpm.cx0+(_xlpm.lcx-_xlpm.cx0)*_xlpm.lp),_xlpm.f,_xlpm.rev*(_xlpm.omt*(1-_xlpm.tx)+_xlpm.dat-_xlpm.cpx+_xlpm.sb)-_xlpm.nw*(_xlpm.rev-_xlpm.prv),_xlpm.pv,SUM(_xlpm.f/(1+_xlpm.w)^(_xlpm.t-0.5*_xlpm.m)),_xlpm.tv,INDEX(_xlpm.f,10)*(1+_xlpm.tgr)/(_xlpm.w-_xlpm.tgr)/(1+_xlpm.w)^10,(_xlpm.pv+_xlpm.tv+_xlpm.nc)/_xlpm.shs)}
A64: PV of forecast FCF ($B) | B64: =SUM(O52:O61) | Q64: =Q63+0.005 | R64: {=_xlfn.LET(_xlpm.gs,Q64,_xlpm.om,$B$10,_xlpm.w,$B$7,_xlpm.tgr,$B$8,_xlpm.n,$B$11,_xlpm.lcx,$B$19,_xlpm.r0,DCF!$B$37,_xlpm.om0,DCF!$B$39,_xlpm.cx0,DCF!$B$40,_xlpm.da0,DCF!$B$41,_xlpm.dar,DCF!$B$20,_xlpm.tx,DCF!$B$31,_xlpm.sb,DCF!$B$43,_xlpm.nw,DCF!$B$21,_xlpm.gd,N(DCF!$B$22),_xlpm.nc,DCF!$B$47,_xlpm.shs,DCF!$B$6,_xlpm.m,DCF!$B$48,_xlpm.t,_xlfn.SEQUENCE(10),_xlpm.g,_xlpm.gs-(_xlpm.gs-_xlpm.tgr)*(_xlpm.t-1)/9,_xlpm.cum,MMULT(--(_xlpm.t>=TRANSPOSE(_xlpm.t)),LN(1+_xlpm.g)),_xlpm.rev,_xlpm.r0*EXP(_xlpm.cum),_xlpm.prv,_xlpm.r0*EXP(_xlpm.cum-LN(1+_xlpm.g)),_xlpm.lp,IF(_xlpm.t>=_xlpm.n,1,_xlpm.t/_xlpm.n),_xlpm.omt,_xlpm.om0+(_xlpm.om-_xlpm.om0)*_xlpm.lp,_xlpm.dat,_xlpm.da0+(_xlpm.lcx*_xlpm.dar-_xlpm.da0)*_xlpm.lp,_xlpm.cpx,IF((_xlpm.t=1)*(_xlpm.gd>0),_xlpm.gd/_xlpm.rev,_xlpm.cx0+(_xlpm.lcx-_xlpm.cx0)*_xlpm.lp),_xlpm.f,_xlpm.rev*(_xlpm.omt*(1-_xlpm.tx)+_xlpm.dat-_xlpm.cpx+_xlpm.sb)-_xlpm.nw*(_xlpm.rev-_xlpm.prv),_xlpm.pv,SUM(_xlpm.f/(1+_xlpm.w)^(_xlpm.t-0.5*_xlpm.m)),_xlpm.tv,INDEX(_xlpm.f,10)*(1+_xlpm.tgr)/(_xlpm.w-_xlpm.tgr)/(1+_xlpm.w)^10,(_xlpm.pv+_xlpm.tv+_xlpm.nc)/_xlpm.shs)} | S64: =S63+0.005 | T64: {=_xlfn.LET(_xlpm.gs,$B$9,_xlpm.om,S64,_xlpm.w,$B$7,_xlpm.tgr,$B$8,_xlpm.n,$B$11,_xlpm.lcx,$B$19,_xlpm.r0,DCF!$B$37,_xlpm.om0,DCF!$B$39,_xlpm.cx0,DCF!$B$40,_xlpm.da0,DCF!$B$41,_xlpm.dar,DCF!$B$20,_xlpm.tx,DCF!$B$31,_xlpm.sb,DCF!$B$43,_xlpm.nw,DCF!$B$21,_xlpm.gd,N(DCF!$B$22),_xlpm.nc,DCF!$B$47,_xlpm.shs,DCF!$B$6,_xlpm.m,DCF!$B$48,_xlpm.t,_xlfn.SEQUENCE(10),_xlpm.g,_xlpm.gs-(_xlpm.gs-_xlpm.tgr)*(_xlpm.t-1)/9,_xlpm.cum,MMULT(--(_xlpm.t>=TRANSPOSE(_xlpm.t)),LN(1+_xlpm.g)),_xlpm.rev,_xlpm.r0*EXP(_xlpm.cum),_xlpm.prv,_xlpm.r0*EXP(_xlpm.cum-LN(1+_xlpm.g)),_xlpm.lp,IF(_xlpm.t>=_xlpm.n,1,_xlpm.t/_xlpm.n),_xlpm.omt,_xlpm.om0+(_xlpm.om-_xlpm.om0)*_xlpm.lp,_xlpm.dat,_xlpm.da0+(_xlpm.lcx*_xlpm.dar-_xlpm.da0)*_xlpm.lp,_xlpm.cpx,IF((_xlpm.t=1)*(_xlpm.gd>0),_xlpm.gd/_xlpm.rev,_xlpm.cx0+(_xlpm.lcx-_xlpm.cx0)*_xlpm.lp),_xlpm.f,_xlpm.rev*(_xlpm.omt*(1-_xlpm.tx)+_xlpm.dat-_xlpm.cpx+_xlpm.sb)-_xlpm.nw*(_xlpm.rev-_xlpm.prv),_xlpm.pv,SUM(_xlpm.f/(1+_xlpm.w)^(_xlpm.t-0.5*_xlpm.m)),_xlpm.tv,INDEX(_xlpm.f,10)*(1+_xlpm.tgr)/(_xlpm.w-_xlpm.tgr)/(1+_xlpm.w)^10,(_xlpm.pv+_xlpm.tv+_xlpm.nc)/_xlpm.shs)} | U64: =U63-0.0025 | V64: {=_xlfn.LET(_xlpm.gs,$B$9,_xlpm.om,$B$10,_xlpm.w,$B$7,_xlpm.tgr,$B$8,_xlpm.n,$B$11,_xlpm.lcx,U64,_xlpm.r0,DCF!$B$37,_xlpm.om0,DCF!$B$39,_xlpm.cx0,DCF!$B$40,_xlpm.da0,DCF!$B$41,_xlpm.dar,DCF!$B$20,_xlpm.tx,DCF!$B$31,_xlpm.sb,DCF!$B$43,_xlpm.nw,DCF!$B$21,_xlpm.gd,N(DCF!$B$22),_xlpm.nc,DCF!$B$47,_xlpm.shs,DCF!$B$6,_xlpm.m,DCF!$B$48,_xlpm.t,_xlfn.SEQUENCE(10),_xlpm.g,_xlpm.gs-(_xlpm.gs-_xlpm.tgr)*(_xlpm.t-1)/9,_xlpm.cum,MMULT(--(_xlpm.t>=TRANSPOSE(_xlpm.t)),LN(1+_xlpm.g)),_xlpm.rev,_xlpm.r0*EXP(_xlpm.cum),_xlpm.prv,_xlpm.r0*EXP(_xlpm.cum-LN(1+_xlpm.g)),_xlpm.lp,IF(_xlpm.t>=_xlpm.n,1,_xlpm.t/_xlpm.n),_xlpm.omt,_xlpm.om0+(_xlpm.om-_xlpm.om0)*_xlpm.lp,_xlpm.dat,_xlpm.da0+(_xlpm.lcx*_xlpm.dar-_xlpm.da0)*_xlpm.lp,_xlpm.cpx,IF((_xlpm.t=1)*(_xlpm.gd>0),_xlpm.gd/_xlpm.rev,_xlpm.cx0+(_xlpm.lcx-_xlpm.cx0)*_xlpm.lp),_xlpm.f,_xlpm.rev*(_xlpm.omt*(1-_xlpm.tx)+_xlpm.dat-_xlpm.cpx+_xlpm.sb)-_xlpm.nw*(_xlpm.rev-_xlpm.prv),_xlpm.pv,SUM(_xlpm.f/(1+_xlpm.w)^(_xlpm.t-0.5*_xlpm.m)),_xlpm.tv,INDEX(_xlpm.f,10)*(1+_xlpm.tgr)/(_xlpm.w-_xlpm.tgr)/(1+_xlpm.w)^10,(_xlpm.pv+_xlpm.tv+_xlpm.nc)/_xlpm.shs)}
A65: Terminal value at year 10 ($B) | B65: =K61*(1+B8)/(B7-B8) | C65: Gordon growth on year-11 FCF. | Q65: =Q64+0.005 | R65: {=_xlfn.LET(_xlpm.gs,Q65,_xlpm.om,$B$10,_xlpm.w,$B$7,_xlpm.tgr,$B$8,_xlpm.n,$B$11,_xlpm.lcx,$B$19,_xlpm.r0,DCF!$B$37,_xlpm.om0,DCF!$B$39,_xlpm.cx0,DCF!$B$40,_xlpm.da0,DCF!$B$41,_xlpm.dar,DCF!$B$20,_xlpm.tx,DCF!$B$31,_xlpm.sb,DCF!$B$43,_xlpm.nw,DCF!$B$21,_xlpm.gd,N(DCF!$B$22),_xlpm.nc,DCF!$B$47,_xlpm.shs,DCF!$B$6,_xlpm.m,DCF!$B$48,_xlpm.t,_xlfn.SEQUENCE(10),_xlpm.g,_xlpm.gs-(_xlpm.gs-_xlpm.tgr)*(_xlpm.t-1)/9,_xlpm.cum,MMULT(--(_xlpm.t>=TRANSPOSE(_xlpm.t)),LN(1+_xlpm.g)),_xlpm.rev,_xlpm.r0*EXP(_xlpm.cum),_xlpm.prv,_xlpm.r0*EXP(_xlpm.cum-LN(1+_xlpm.g)),_xlpm.lp,IF(_xlpm.t>=_xlpm.n,1,_xlpm.t/_xlpm.n),_xlpm.omt,_xlpm.om0+(_xlpm.om-_xlpm.om0)*_xlpm.lp,_xlpm.dat,_xlpm.da0+(_xlpm.lcx*_xlpm.dar-_xlpm.da0)*_xlpm.lp,_xlpm.cpx,IF((_xlpm.t=1)*(_xlpm.gd>0),_xlpm.gd/_xlpm.rev,_xlpm.cx0+(_xlpm.lcx-_xlpm.cx0)*_xlpm.lp),_xlpm.f,_xlpm.rev*(_xlpm.omt*(1-_xlpm.tx)+_xlpm.dat-_xlpm.cpx+_xlpm.sb)-_xlpm.nw*(_xlpm.rev-_xlpm.prv),_xlpm.pv,SUM(_xlpm.f/(1+_xlpm.w)^(_xlpm.t-0.5*_xlpm.m)),_xlpm.tv,INDEX(_xlpm.f,10)*(1+_xlpm.tgr)/(_xlpm.w-_xlpm.tgr)/(1+_xlpm.w)^10,(_xlpm.pv+_xlpm.tv+_xlpm.nc)/_xlpm.shs)} | S65: =S64+0.005 | T65: {=_xlfn.LET(_xlpm.gs,$B$9,_xlpm.om,S65,_xlpm.w,$B$7,_xlpm.tgr,$B$8,_xlpm.n,$B$11,_xlpm.lcx,$B$19,_xlpm.r0,DCF!$B$37,_xlpm.om0,DCF!$B$39,_xlpm.cx0,DCF!$B$40,_xlpm.da0,DCF!$B$41,_xlpm.dar,DCF!$B$20,_xlpm.tx,DCF!$B$31,_xlpm.sb,DCF!$B$43,_xlpm.nw,DCF!$B$21,_xlpm.gd,N(DCF!$B$22),_xlpm.nc,DCF!$B$47,_xlpm.shs,DCF!$B$6,_xlpm.m,DCF!$B$48,_xlpm.t,_xlfn.SEQUENCE(10),_xlpm.g,_xlpm.gs-(_xlpm.gs-_xlpm.tgr)*(_xlpm.t-1)/9,_xlpm.cum,MMULT(--(_xlpm.t>=TRANSPOSE(_xlpm.t)),LN(1+_xlpm.g)),_xlpm.rev,_xlpm.r0*EXP(_xlpm.cum),_xlpm.prv,_xlpm.r0*EXP(_xlpm.cum-LN(1+_xlpm.g)),_xlpm.lp,IF(_xlpm.t>=_xlpm.n,1,_xlpm.t/_xlpm.n),_xlpm.omt,_xlpm.om0+(_xlpm.om-_xlpm.om0)*_xlpm.lp,_xlpm.dat,_xlpm.da0+(_xlpm.lcx*_xlpm.dar-_xlpm.da0)*_xlpm.lp,_xlpm.cpx,IF((_xlpm.t=1)*(_xlpm.gd>0),_xlpm.gd/_xlpm.rev,_xlpm.cx0+(_xlpm.lcx-_xlpm.cx0)*_xlpm.lp),_xlpm.f,_xlpm.rev*(_xlpm.omt*(1-_xlpm.tx)+_xlpm.dat-_xlpm.cpx+_xlpm.sb)-_xlpm.nw*(_xlpm.rev-_xlpm.prv),_xlpm.pv,SUM(_xlpm.f/(1+_xlpm.w)^(_xlpm.t-0.5*_xlpm.m)),_xlpm.tv,INDEX(_xlpm.f,10)*(1+_xlpm.tgr)/(_xlpm.w-_xlpm.tgr)/(1+_xlpm.w)^10,(_xlpm.pv+_xlpm.tv+_xlpm.nc)/_xlpm.shs)} | U65: =U64-0.0025 | V65: {=_xlfn.LET(_xlpm.gs,$B$9,_xlpm.om,$B$10,_xlpm.w,$B$7,_xlpm.tgr,$B$8,_xlpm.n,$B$11,_xlpm.lcx,U65,_xlpm.r0,DCF!$B$37,_xlpm.om0,DCF!$B$39,_xlpm.cx0,DCF!$B$40,_xlpm.da0,DCF!$B$41,_xlpm.dar,DCF!$B$20,_xlpm.tx,DCF!$B$31,_xlpm.sb,DCF!$B$43,_xlpm.nw,DCF!$B$21,_xlpm.gd,N(DCF!$B$22),_xlpm.nc,DCF!$B$47,_xlpm.shs,DCF!$B$6,_xlpm.m,DCF!$B$48,_xlpm.t,_xlfn.SEQUENCE(10),_xlpm.g,_xlpm.gs-(_xlpm.gs-_xlpm.tgr)*(_xlpm.t-1)/9,_xlpm.cum,MMULT(--(_xlpm.t>=TRANSPOSE(_xlpm.t)),LN(1+_xlpm.g)),_xlpm.rev,_xlpm.r0*EXP(_xlpm.cum),_xlpm.prv,_xlpm.r0*EXP(_xlpm.cum-LN(1+_xlpm.g)),_xlpm.lp,IF(_xlpm.t>=_xlpm.n,1,_xlpm.t/_xlpm.n),_xlpm.omt,_xlpm.om0+(_xlpm.om-_xlpm.om0)*_xlpm.lp,_xlpm.dat,_xlpm.da0+(_xlpm.lcx*_xlpm.dar-_xlpm.da0)*_xlpm.lp,_xlpm.cpx,IF((_xlpm.t=1)*(_xlpm.gd>0),_xlpm.gd/_xlpm.rev,_xlpm.cx0+(_xlpm.lcx-_xlpm.cx0)*_xlpm.lp),_xlpm.f,_xlpm.rev*(_xlpm.omt*(1-_xlpm.tx)+_xlpm.dat-_xlpm.cpx+_xlpm.sb)-_xlpm.nw*(_xlpm.rev-_xlpm.prv),_xlpm.pv,SUM(_xlpm.f/(1+_xlpm.w)^(_xlpm.t-0.5*_xlpm.m)),_xlpm.tv,INDEX(_xlpm.f,10)*(1+_xlpm.tgr)/(_xlpm.w-_xlpm.tgr)/(1+_xlpm.w)^10,(_xlpm.pv+_xlpm.tv+_xlpm.nc)/_xlpm.shs)}
A66: PV of terminal value ($B) | B66: =B65/(1+B7)^A61 | C66: Discounted a full 10 years. | Q66: =Q65+0.005 | R66: {=_xlfn.LET(_xlpm.gs,Q66,_xlpm.om,$B$10,_xlpm.w,$B$7,_xlpm.tgr,$B$8,_xlpm.n,$B$11,_xlpm.lcx,$B$19,_xlpm.r0,DCF!$B$37,_xlpm.om0,DCF!$B$39,_xlpm.cx0,DCF!$B$40,_xlpm.da0,DCF!$B$41,_xlpm.dar,DCF!$B$20,_xlpm.tx,DCF!$B$31,_xlpm.sb,DCF!$B$43,_xlpm.nw,DCF!$B$21,_xlpm.gd,N(DCF!$B$22),_xlpm.nc,DCF!$B$47,_xlpm.shs,DCF!$B$6,_xlpm.m,DCF!$B$48,_xlpm.t,_xlfn.SEQUENCE(10),_xlpm.g,_xlpm.gs-(_xlpm.gs-_xlpm.tgr)*(_xlpm.t-1)/9,_xlpm.cum,MMULT(--(_xlpm.t>=TRANSPOSE(_xlpm.t)),LN(1+_xlpm.g)),_xlpm.rev,_xlpm.r0*EXP(_xlpm.cum),_xlpm.prv,_xlpm.r0*EXP(_xlpm.cum-LN(1+_xlpm.g)),_xlpm.lp,IF(_xlpm.t>=_xlpm.n,1,_xlpm.t/_xlpm.n),_xlpm.omt,_xlpm.om0+(_xlpm.om-_xlpm.om0)*_xlpm.lp,_xlpm.dat,_xlpm.da0+(_xlpm.lcx*_xlpm.dar-_xlpm.da0)*_xlpm.lp,_xlpm.cpx,IF((_xlpm.t=1)*(_xlpm.gd>0),_xlpm.gd/_xlpm.rev,_xlpm.cx0+(_xlpm.lcx-_xlpm.cx0)*_xlpm.lp),_xlpm.f,_xlpm.rev*(_xlpm.omt*(1-_xlpm.tx)+_xlpm.dat-_xlpm.cpx+_xlpm.sb)-_xlpm.nw*(_xlpm.rev-_xlpm.prv),_xlpm.pv,SUM(_xlpm.f/(1+_xlpm.w)^(_xlpm.t-0.5*_xlpm.m)),_xlpm.tv,INDEX(_xlpm.f,10)*(1+_xlpm.tgr)/(_xlpm.w-_xlpm.tgr)/(1+_xlpm.w)^10,(_xlpm.pv+_xlpm.tv+_xlpm.nc)/_xlpm.shs)} | S66: =S65+0.005 | T66: {=_xlfn.LET(_xlpm.gs,$B$9,_xlpm.om,S66,_xlpm.w,$B$7,_xlpm.tgr,$B$8,_xlpm.n,$B$11,_xlpm.lcx,$B$19,_xlpm.r0,DCF!$B$37,_xlpm.om0,DCF!$B$39,_xlpm.cx0,DCF!$B$40,_xlpm.da0,DCF!$B$41,_xlpm.dar,DCF!$B$20,_xlpm.tx,DCF!$B$31,_xlpm.sb,DCF!$B$43,_xlpm.nw,DCF!$B$21,_xlpm.gd,N(DCF!$B$22),_xlpm.nc,DCF!$B$47,_xlpm.shs,DCF!$B$6,_xlpm.m,DCF!$B$48,_xlpm.t,_xlfn.SEQUENCE(10),_xlpm.g,_xlpm.gs-(_xlpm.gs-_xlpm.tgr)*(_xlpm.t-1)/9,_xlpm.cum,MMULT(--(_xlpm.t>=TRANSPOSE(_xlpm.t)),LN(1+_xlpm.g)),_xlpm.rev,_xlpm.r0*EXP(_xlpm.cum),_xlpm.prv,_xlpm.r0*EXP(_xlpm.cum-LN(1+_xlpm.g)),_xlpm.lp,IF(_xlpm.t>=_xlpm.n,1,_xlpm.t/_xlpm.n),_xlpm.omt,_xlpm.om0+(_xlpm.om-_xlpm.om0)*_xlpm.lp,_xlpm.dat,_xlpm.da0+(_xlpm.lcx*_xlpm.dar-_xlpm.da0)*_xlpm.lp,_xlpm.cpx,IF((_xlpm.t=1)*(_xlpm.gd>0),_xlpm.gd/_xlpm.rev,_xlpm.cx0+(_xlpm.lcx-_xlpm.cx0)*_xlpm.lp),_xlpm.f,_xlpm.rev*(_xlpm.omt*(1-_xlpm.tx)+_xlpm.dat-_xlpm.cpx+_xlpm.sb)-_xlpm.nw*(_xlpm.rev-_xlpm.prv),_xlpm.pv,SUM(_xlpm.f/(1+_xlpm.w)^(_xlpm.t-0.5*_xlpm.m)),_xlpm.tv,INDEX(_xlpm.f,10)*(1+_xlpm.tgr)/(_xlpm.w-_xlpm.tgr)/(1+_xlpm.w)^10,(_xlpm.pv+_xlpm.tv+_xlpm.nc)/_xlpm.shs)} | U66: =U65-0.0025 | V66: {=_xlfn.LET(_xlpm.gs,$B$9,_xlpm.om,$B$10,_xlpm.w,$B$7,_xlpm.tgr,$B$8,_xlpm.n,$B$11,_xlpm.lcx,U66,_xlpm.r0,DCF!$B$37,_xlpm.om0,DCF!$B$39,_xlpm.cx0,DCF!$B$40,_xlpm.da0,DCF!$B$41,_xlpm.dar,DCF!$B$20,_xlpm.tx,DCF!$B$31,_xlpm.sb,DCF!$B$43,_xlpm.nw,DCF!$B$21,_xlpm.gd,N(DCF!$B$22),_xlpm.nc,DCF!$B$47,_xlpm.shs,DCF!$B$6,_xlpm.m,DCF!$B$48,_xlpm.t,_xlfn.SEQUENCE(10),_xlpm.g,_xlpm.gs-(_xlpm.gs-_xlpm.tgr)*(_xlpm.t-1)/9,_xlpm.cum,MMULT(--(_xlpm.t>=TRANSPOSE(_xlpm.t)),LN(1+_xlpm.g)),_xlpm.rev,_xlpm.r0*EXP(_xlpm.cum),_xlpm.prv,_xlpm.r0*EXP(_xlpm.cum-LN(1+_xlpm.g)),_xlpm.lp,IF(_xlpm.t>=_xlpm.n,1,_xlpm.t/_xlpm.n),_xlpm.omt,_xlpm.om0+(_xlpm.om-_xlpm.om0)*_xlpm.lp,_xlpm.dat,_xlpm.da0+(_xlpm.lcx*_xlpm.dar-_xlpm.da0)*_xlpm.lp,_xlpm.cpx,IF((_xlpm.t=1)*(_xlpm.gd>0),_xlpm.gd/_xlpm.rev,_xlpm.cx0+(_xlpm.lcx-_xlpm.cx0)*_xlpm.lp),_xlpm.f,_xlpm.rev*(_xlpm.omt*(1-_xlpm.tx)+_xlpm.dat-_xlpm.cpx+_xlpm.sb)-_xlpm.nw*(_xlpm.rev-_xlpm.prv),_xlpm.pv,SUM(_xlpm.f/(1+_xlpm.w)^(_xlpm.t-0.5*_xlpm.m)),_xlpm.tv,INDEX(_xlpm.f,10)*(1+_xlpm.tgr)/(_xlpm.w-_xlpm.tgr)/(1+_xlpm.w)^10,(_xlpm.pv+_xlpm.tv+_xlpm.nc)/_xlpm.shs)}
A67: Enterprise value ($B) | B67: =B64+B66 | Q67: =Q66+0.005 | R67: {=_xlfn.LET(_xlpm.gs,Q67,_xlpm.om,$B$10,_xlpm.w,$B$7,_xlpm.tgr,$B$8,_xlpm.n,$B$11,_xlpm.lcx,$B$19,_xlpm.r0,DCF!$B$37,_xlpm.om0,DCF!$B$39,_xlpm.cx0,DCF!$B$40,_xlpm.da0,DCF!$B$41,_xlpm.dar,DCF!$B$20,_xlpm.tx,DCF!$B$31,_xlpm.sb,DCF!$B$43,_xlpm.nw,DCF!$B$21,_xlpm.gd,N(DCF!$B$22),_xlpm.nc,DCF!$B$47,_xlpm.shs,DCF!$B$6,_xlpm.m,DCF!$B$48,_xlpm.t,_xlfn.SEQUENCE(10),_xlpm.g,_xlpm.gs-(_xlpm.gs-_xlpm.tgr)*(_xlpm.t-1)/9,_xlpm.cum,MMULT(--(_xlpm.t>=TRANSPOSE(_xlpm.t)),LN(1+_xlpm.g)),_xlpm.rev,_xlpm.r0*EXP(_xlpm.cum),_xlpm.prv,_xlpm.r0*EXP(_xlpm.cum-LN(1+_xlpm.g)),_xlpm.lp,IF(_xlpm.t>=_xlpm.n,1,_xlpm.t/_xlpm.n),_xlpm.omt,_xlpm.om0+(_xlpm.om-_xlpm.om0)*_xlpm.lp,_xlpm.dat,_xlpm.da0+(_xlpm.lcx*_xlpm.dar-_xlpm.da0)*_xlpm.lp,_xlpm.cpx,IF((_xlpm.t=1)*(_xlpm.gd>0),_xlpm.gd/_xlpm.rev,_xlpm.cx0+(_xlpm.lcx-_xlpm.cx0)*_xlpm.lp),_xlpm.f,_xlpm.rev*(_xlpm.omt*(1-_xlpm.tx)+_xlpm.dat-_xlpm.cpx+_xlpm.sb)-_xlpm.nw*(_xlpm.rev-_xlpm.prv),_xlpm.pv,SUM(_xlpm.f/(1+_xlpm.w)^(_xlpm.t-0.5*_xlpm.m)),_xlpm.tv,INDEX(_xlpm.f,10)*(1+_xlpm.tgr)/(_xlpm.w-_xlpm.tgr)/(1+_xlpm.w)^10,(_xlpm.pv+_xlpm.tv+_xlpm.nc)/_xlpm.shs)} | S67: =S66+0.005 | T67: {=_xlfn.LET(_xlpm.gs,$B$9,_xlpm.om,S67,_xlpm.w,$B$7,_xlpm.tgr,$B$8,_xlpm.n,$B$11,_xlpm.lcx,$B$19,_xlpm.r0,DCF!$B$37,_xlpm.om0,DCF!$B$39,_xlpm.cx0,DCF!$B$40,_xlpm.da0,DCF!$B$41,_xlpm.dar,DCF!$B$20,_xlpm.tx,DCF!$B$31,_xlpm.sb,DCF!$B$43,_xlpm.nw,DCF!$B$21,_xlpm.gd,N(DCF!$B$22),_xlpm.nc,DCF!$B$47,_xlpm.shs,DCF!$B$6,_xlpm.m,DCF!$B$48,_xlpm.t,_xlfn.SEQUENCE(10),_xlpm.g,_xlpm.gs-(_xlpm.gs-_xlpm.tgr)*(_xlpm.t-1)/9,_xlpm.cum,MMULT(--(_xlpm.t>=TRANSPOSE(_xlpm.t)),LN(1+_xlpm.g)),_xlpm.rev,_xlpm.r0*EXP(_xlpm.cum),_xlpm.prv,_xlpm.r0*EXP(_xlpm.cum-LN(1+_xlpm.g)),_xlpm.lp,IF(_xlpm.t>=_xlpm.n,1,_xlpm.t/_xlpm.n),_xlpm.omt,_xlpm.om0+(_xlpm.om-_xlpm.om0)*_xlpm.lp,_xlpm.dat,_xlpm.da0+(_xlpm.lcx*_xlpm.dar-_xlpm.da0)*_xlpm.lp,_xlpm.cpx,IF((_xlpm.t=1)*(_xlpm.gd>0),_xlpm.gd/_xlpm.rev,_xlpm.cx0+(_xlpm.lcx-_xlpm.cx0)*_xlpm.lp),_xlpm.f,_xlpm.rev*(_xlpm.omt*(1-_xlpm.tx)+_xlpm.dat-_xlpm.cpx+_xlpm.sb)-_xlpm.nw*(_xlpm.rev-_xlpm.prv),_xlpm.pv,SUM(_xlpm.f/(1+_xlpm.w)^(_xlpm.t-0.5*_xlpm.m)),_xlpm.tv,INDEX(_xlpm.f,10)*(1+_xlpm.tgr)/(_xlpm.w-_xlpm.tgr)/(1+_xlpm.w)^10,(_xlpm.pv+_xlpm.tv+_xlpm.nc)/_xlpm.shs)} | U67: =U66-0.0025 | V67: {=_xlfn.LET(_xlpm.gs,$B$9,_xlpm.om,$B$10,_xlpm.w,$B$7,_xlpm.tgr,$B$8,_xlpm.n,$B$11,_xlpm.lcx,U67,_xlpm.r0,DCF!$B$37,_xlpm.om0,DCF!$B$39,_xlpm.cx0,DCF!$B$40,_xlpm.da0,DCF!$B$41,_xlpm.dar,DCF!$B$20,_xlpm.tx,DCF!$B$31,_xlpm.sb,DCF!$B$43,_xlpm.nw,DCF!$B$21,_xlpm.gd,N(DCF!$B$22),_xlpm.nc,DCF!$B$47,_xlpm.shs,DCF!$B$6,_xlpm.m,DCF!$B$48,_xlpm.t,_xlfn.SEQUENCE(10),_xlpm.g,_xlpm.gs-(_xlpm.gs-_xlpm.tgr)*(_xlpm.t-1)/9,_xlpm.cum,MMULT(--(_xlpm.t>=TRANSPOSE(_xlpm.t)),LN(1+_xlpm.g)),_xlpm.rev,_xlpm.r0*EXP(_xlpm.cum),_xlpm.prv,_xlpm.r0*EXP(_xlpm.cum-LN(1+_xlpm.g)),_xlpm.lp,IF(_xlpm.t>=_xlpm.n,1,_xlpm.t/_xlpm.n),_xlpm.omt,_xlpm.om0+(_xlpm.om-_xlpm.om0)*_xlpm.lp,_xlpm.dat,_xlpm.da0+(_xlpm.lcx*_xlpm.dar-_xlpm.da0)*_xlpm.lp,_xlpm.cpx,IF((_xlpm.t=1)*(_xlpm.gd>0),_xlpm.gd/_xlpm.rev,_xlpm.cx0+(_xlpm.lcx-_xlpm.cx0)*_xlpm.lp),_xlpm.f,_xlpm.rev*(_xlpm.omt*(1-_xlpm.tx)+_xlpm.dat-_xlpm.cpx+_xlpm.sb)-_xlpm.nw*(_xlpm.rev-_xlpm.prv),_xlpm.pv,SUM(_xlpm.f/(1+_xlpm.w)^(_xlpm.t-0.5*_xlpm.m)),_xlpm.tv,INDEX(_xlpm.f,10)*(1+_xlpm.tgr)/(_xlpm.w-_xlpm.tgr)/(1+_xlpm.w)^10,(_xlpm.pv+_xlpm.tv+_xlpm.nc)/_xlpm.shs)}
A68: Add: net cash ($B) | B68: =B44 | Q68: =Q67+0.005 | R68: {=_xlfn.LET(_xlpm.gs,Q68,_xlpm.om,$B$10,_xlpm.w,$B$7,_xlpm.tgr,$B$8,_xlpm.n,$B$11,_xlpm.lcx,$B$19,_xlpm.r0,DCF!$B$37,_xlpm.om0,DCF!$B$39,_xlpm.cx0,DCF!$B$40,_xlpm.da0,DCF!$B$41,_xlpm.dar,DCF!$B$20,_xlpm.tx,DCF!$B$31,_xlpm.sb,DCF!$B$43,_xlpm.nw,DCF!$B$21,_xlpm.gd,N(DCF!$B$22),_xlpm.nc,DCF!$B$47,_xlpm.shs,DCF!$B$6,_xlpm.m,DCF!$B$48,_xlpm.t,_xlfn.SEQUENCE(10),_xlpm.g,_xlpm.gs-(_xlpm.gs-_xlpm.tgr)*(_xlpm.t-1)/9,_xlpm.cum,MMULT(--(_xlpm.t>=TRANSPOSE(_xlpm.t)),LN(1+_xlpm.g)),_xlpm.rev,_xlpm.r0*EXP(_xlpm.cum),_xlpm.prv,_xlpm.r0*EXP(_xlpm.cum-LN(1+_xlpm.g)),_xlpm.lp,IF(_xlpm.t>=_xlpm.n,1,_xlpm.t/_xlpm.n),_xlpm.omt,_xlpm.om0+(_xlpm.om-_xlpm.om0)*_xlpm.lp,_xlpm.dat,_xlpm.da0+(_xlpm.lcx*_xlpm.dar-_xlpm.da0)*_xlpm.lp,_xlpm.cpx,IF((_xlpm.t=1)*(_xlpm.gd>0),_xlpm.gd/_xlpm.rev,_xlpm.cx0+(_xlpm.lcx-_xlpm.cx0)*_xlpm.lp),_xlpm.f,_xlpm.rev*(_xlpm.omt*(1-_xlpm.tx)+_xlpm.dat-_xlpm.cpx+_xlpm.sb)-_xlpm.nw*(_xlpm.rev-_xlpm.prv),_xlpm.pv,SUM(_xlpm.f/(1+_xlpm.w)^(_xlpm.t-0.5*_xlpm.m)),_xlpm.tv,INDEX(_xlpm.f,10)*(1+_xlpm.tgr)/(_xlpm.w-_xlpm.tgr)/(1+_xlpm.w)^10,(_xlpm.pv+_xlpm.tv+_xlpm.nc)/_xlpm.shs)} | S68: =S67+0.005 | T68: {=_xlfn.LET(_xlpm.gs,$B$9,_xlpm.om,S68,_xlpm.w,$B$7,_xlpm.tgr,$B$8,_xlpm.n,$B$11,_xlpm.lcx,$B$19,_xlpm.r0,DCF!$B$37,_xlpm.om0,DCF!$B$39,_xlpm.cx0,DCF!$B$40,_xlpm.da0,DCF!$B$41,_xlpm.dar,DCF!$B$20,_xlpm.tx,DCF!$B$31,_xlpm.sb,DCF!$B$43,_xlpm.nw,DCF!$B$21,_xlpm.gd,N(DCF!$B$22),_xlpm.nc,DCF!$B$47,_xlpm.shs,DCF!$B$6,_xlpm.m,DCF!$B$48,_xlpm.t,_xlfn.SEQUENCE(10),_xlpm.g,_xlpm.gs-(_xlpm.gs-_xlpm.tgr)*(_xlpm.t-1)/9,_xlpm.cum,MMULT(--(_xlpm.t>=TRANSPOSE(_xlpm.t)),LN(1+_xlpm.g)),_xlpm.rev,_xlpm.r0*EXP(_xlpm.cum),_xlpm.prv,_xlpm.r0*EXP(_xlpm.cum-LN(1+_xlpm.g)),_xlpm.lp,IF(_xlpm.t>=_xlpm.n,1,_xlpm.t/_xlpm.n),_xlpm.omt,_xlpm.om0+(_xlpm.om-_xlpm.om0)*_xlpm.lp,_xlpm.dat,_xlpm.da0+(_xlpm.lcx*_xlpm.dar-_xlpm.da0)*_xlpm.lp,_xlpm.cpx,IF((_xlpm.t=1)*(_xlpm.gd>0),_xlpm.gd/_xlpm.rev,_xlpm.cx0+(_xlpm.lcx-_xlpm.cx0)*_xlpm.lp),_xlpm.f,_xlpm.rev*(_xlpm.omt*(1-_xlpm.tx)+_xlpm.dat-_xlpm.cpx+_xlpm.sb)-_xlpm.nw*(_xlpm.rev-_xlpm.prv),_xlpm.pv,SUM(_xlpm.f/(1+_xlpm.w)^(_xlpm.t-0.5*_xlpm.m)),_xlpm.tv,INDEX(_xlpm.f,10)*(1+_xlpm.tgr)/(_xlpm.w-_xlpm.tgr)/(1+_xlpm.w)^10,(_xlpm.pv+_xlpm.tv+_xlpm.nc)/_xlpm.shs)} | U68: =U67-0.0025 | V68: {=_xlfn.LET(_xlpm.gs,$B$9,_xlpm.om,$B$10,_xlpm.w,$B$7,_xlpm.tgr,$B$8,_xlpm.n,$B$11,_xlpm.lcx,U68,_xlpm.r0,DCF!$B$37,_xlpm.om0,DCF!$B$39,_xlpm.cx0,DCF!$B$40,_xlpm.da0,DCF!$B$41,_xlpm.dar,DCF!$B$20,_xlpm.tx,DCF!$B$31,_xlpm.sb,DCF!$B$43,_xlpm.nw,DCF!$B$21,_xlpm.gd,N(DCF!$B$22),_xlpm.nc,DCF!$B$47,_xlpm.shs,DCF!$B$6,_xlpm.m,DCF!$B$48,_xlpm.t,_xlfn.SEQUENCE(10),_xlpm.g,_xlpm.gs-(_xlpm.gs-_xlpm.tgr)*(_xlpm.t-1)/9,_xlpm.cum,MMULT(--(_xlpm.t>=TRANSPOSE(_xlpm.t)),LN(1+_xlpm.g)),_xlpm.rev,_xlpm.r0*EXP(_xlpm.cum),_xlpm.prv,_xlpm.r0*EXP(_xlpm.cum-LN(1+_xlpm.g)),_xlpm.lp,IF(_xlpm.t>=_xlpm.n,1,_xlpm.t/_xlpm.n),_xlpm.omt,_xlpm.om0+(_xlpm.om-_xlpm.om0)*_xlpm.lp,_xlpm.dat,_xlpm.da0+(_xlpm.lcx*_xlpm.dar-_xlpm.da0)*_xlpm.lp,_xlpm.cpx,IF((_xlpm.t=1)*(_xlpm.gd>0),_xlpm.gd/_xlpm.rev,_xlpm.cx0+(_xlpm.lcx-_xlpm.cx0)*_xlpm.lp),_xlpm.f,_xlpm.rev*(_xlpm.omt*(1-_xlpm.tx)+_xlpm.dat-_xlpm.cpx+_xlpm.sb)-_xlpm.nw*(_xlpm.rev-_xlpm.prv),_xlpm.pv,SUM(_xlpm.f/(1+_xlpm.w)^(_xlpm.t-0.5*_xlpm.m)),_xlpm.tv,INDEX(_xlpm.f,10)*(1+_xlpm.tgr)/(_xlpm.w-_xlpm.tgr)/(1+_xlpm.w)^10,(_xlpm.pv+_xlpm.tv+_xlpm.nc)/_xlpm.shs)}
A69: Less: preferred stock ($B) | B69: =-B45 | Q69: =Q68+0.005 | R69: {=_xlfn.LET(_xlpm.gs,Q69,_xlpm.om,$B$10,_xlpm.w,$B$7,_xlpm.tgr,$B$8,_xlpm.n,$B$11,_xlpm.lcx,$B$19,_xlpm.r0,DCF!$B$37,_xlpm.om0,DCF!$B$39,_xlpm.cx0,DCF!$B$40,_xlpm.da0,DCF!$B$41,_xlpm.dar,DCF!$B$20,_xlpm.tx,DCF!$B$31,_xlpm.sb,DCF!$B$43,_xlpm.nw,DCF!$B$21,_xlpm.gd,N(DCF!$B$22),_xlpm.nc,DCF!$B$47,_xlpm.shs,DCF!$B$6,_xlpm.m,DCF!$B$48,_xlpm.t,_xlfn.SEQUENCE(10),_xlpm.g,_xlpm.gs-(_xlpm.gs-_xlpm.tgr)*(_xlpm.t-1)/9,_xlpm.cum,MMULT(--(_xlpm.t>=TRANSPOSE(_xlpm.t)),LN(1+_xlpm.g)),_xlpm.rev,_xlpm.r0*EXP(_xlpm.cum),_xlpm.prv,_xlpm.r0*EXP(_xlpm.cum-LN(1+_xlpm.g)),_xlpm.lp,IF(_xlpm.t>=_xlpm.n,1,_xlpm.t/_xlpm.n),_xlpm.omt,_xlpm.om0+(_xlpm.om-_xlpm.om0)*_xlpm.lp,_xlpm.dat,_xlpm.da0+(_xlpm.lcx*_xlpm.dar-_xlpm.da0)*_xlpm.lp,_xlpm.cpx,IF((_xlpm.t=1)*(_xlpm.gd>0),_xlpm.gd/_xlpm.rev,_xlpm.cx0+(_xlpm.lcx-_xlpm.cx0)*_xlpm.lp),_xlpm.f,_xlpm.rev*(_xlpm.omt*(1-_xlpm.tx)+_xlpm.dat-_xlpm.cpx+_xlpm.sb)-_xlpm.nw*(_xlpm.rev-_xlpm.prv),_xlpm.pv,SUM(_xlpm.f/(1+_xlpm.w)^(_xlpm.t-0.5*_xlpm.m)),_xlpm.tv,INDEX(_xlpm.f,10)*(1+_xlpm.tgr)/(_xlpm.w-_xlpm.tgr)/(1+_xlpm.w)^10,(_xlpm.pv+_xlpm.tv+_xlpm.nc)/_xlpm.shs)} | S69: =S68+0.005 | T69: {=_xlfn.LET(_xlpm.gs,$B$9,_xlpm.om,S69,_xlpm.w,$B$7,_xlpm.tgr,$B$8,_xlpm.n,$B$11,_xlpm.lcx,$B$19,_xlpm.r0,DCF!$B$37,_xlpm.om0,DCF!$B$39,_xlpm.cx0,DCF!$B$40,_xlpm.da0,DCF!$B$41,_xlpm.dar,DCF!$B$20,_xlpm.tx,DCF!$B$31,_xlpm.sb,DCF!$B$43,_xlpm.nw,DCF!$B$21,_xlpm.gd,N(DCF!$B$22),_xlpm.nc,DCF!$B$47,_xlpm.shs,DCF!$B$6,_xlpm.m,DCF!$B$48,_xlpm.t,_xlfn.SEQUENCE(10),_xlpm.g,_xlpm.gs-(_xlpm.gs-_xlpm.tgr)*(_xlpm.t-1)/9,_xlpm.cum,MMULT(--(_xlpm.t>=TRANSPOSE(_xlpm.t)),LN(1+_xlpm.g)),_xlpm.rev,_xlpm.r0*EXP(_xlpm.cum),_xlpm.prv,_xlpm.r0*EXP(_xlpm.cum-LN(1+_xlpm.g)),_xlpm.lp,IF(_xlpm.t>=_xlpm.n,1,_xlpm.t/_xlpm.n),_xlpm.omt,_xlpm.om0+(_xlpm.om-_xlpm.om0)*_xlpm.lp,_xlpm.dat,_xlpm.da0+(_xlpm.lcx*_xlpm.dar-_xlpm.da0)*_xlpm.lp,_xlpm.cpx,IF((_xlpm.t=1)*(_xlpm.gd>0),_xlpm.gd/_xlpm.rev,_xlpm.cx0+(_xlpm.lcx-_xlpm.cx0)*_xlpm.lp),_xlpm.f,_xlpm.rev*(_xlpm.omt*(1-_xlpm.tx)+_xlpm.dat-_xlpm.cpx+_xlpm.sb)-_xlpm.nw*(_xlpm.rev-_xlpm.prv),_xlpm.pv,SUM(_xlpm.f/(1+_xlpm.w)^(_xlpm.t-0.5*_xlpm.m)),_xlpm.tv,INDEX(_xlpm.f,10)*(1+_xlpm.tgr)/(_xlpm.w-_xlpm.tgr)/(1+_xlpm.w)^10,(_xlpm.pv+_xlpm.tv+_xlpm.nc)/_xlpm.shs)} | U69: =U68-0.0025 | V69: {=_xlfn.LET(_xlpm.gs,$B$9,_xlpm.om,$B$10,_xlpm.w,$B$7,_xlpm.tgr,$B$8,_xlpm.n,$B$11,_xlpm.lcx,U69,_xlpm.r0,DCF!$B$37,_xlpm.om0,DCF!$B$39,_xlpm.cx0,DCF!$B$40,_xlpm.da0,DCF!$B$41,_xlpm.dar,DCF!$B$20,_xlpm.tx,DCF!$B$31,_xlpm.sb,DCF!$B$43,_xlpm.nw,DCF!$B$21,_xlpm.gd,N(DCF!$B$22),_xlpm.nc,DCF!$B$47,_xlpm.shs,DCF!$B$6,_xlpm.m,DCF!$B$48,_xlpm.t,_xlfn.SEQUENCE(10),_xlpm.g,_xlpm.gs-(_xlpm.gs-_xlpm.tgr)*(_xlpm.t-1)/9,_xlpm.cum,MMULT(--(_xlpm.t>=TRANSPOSE(_xlpm.t)),LN(1+_xlpm.g)),_xlpm.rev,_xlpm.r0*EXP(_xlpm.cum),_xlpm.prv,_xlpm.r0*EXP(_xlpm.cum-LN(1+_xlpm.g)),_xlpm.lp,IF(_xlpm.t>=_xlpm.n,1,_xlpm.t/_xlpm.n),_xlpm.omt,_xlpm.om0+(_xlpm.om-_xlpm.om0)*_xlpm.lp,_xlpm.dat,_xlpm.da0+(_xlpm.lcx*_xlpm.dar-_xlpm.da0)*_xlpm.lp,_xlpm.cpx,IF((_xlpm.t=1)*(_xlpm.gd>0),_xlpm.gd/_xlpm.rev,_xlpm.cx0+(_xlpm.lcx-_xlpm.cx0)*_xlpm.lp),_xlpm.f,_xlpm.rev*(_xlpm.omt*(1-_xlpm.tx)+_xlpm.dat-_xlpm.cpx+_xlpm.sb)-_xlpm.nw*(_xlpm.rev-_xlpm.prv),_xlpm.pv,SUM(_xlpm.f/(1+_xlpm.w)^(_xlpm.t-0.5*_xlpm.m)),_xlpm.tv,INDEX(_xlpm.f,10)*(1+_xlpm.tgr)/(_xlpm.w-_xlpm.tgr)/(1+_xlpm.w)^10,(_xlpm.pv+_xlpm.tv+_xlpm.nc)/_xlpm.shs)}
A70: Add: non-marketable investments, after haircut ($B) | B70: =B46 | C70: Toggle in B13; haircut in B15. | Q70: =Q69+0.005 | R70: {=_xlfn.LET(_xlpm.gs,Q70,_xlpm.om,$B$10,_xlpm.w,$B$7,_xlpm.tgr,$B$8,_xlpm.n,$B$11,_xlpm.lcx,$B$19,_xlpm.r0,DCF!$B$37,_xlpm.om0,DCF!$B$39,_xlpm.cx0,DCF!$B$40,_xlpm.da0,DCF!$B$41,_xlpm.dar,DCF!$B$20,_xlpm.tx,DCF!$B$31,_xlpm.sb,DCF!$B$43,_xlpm.nw,DCF!$B$21,_xlpm.gd,N(DCF!$B$22),_xlpm.nc,DCF!$B$47,_xlpm.shs,DCF!$B$6,_xlpm.m,DCF!$B$48,_xlpm.t,_xlfn.SEQUENCE(10),_xlpm.g,_xlpm.gs-(_xlpm.gs-_xlpm.tgr)*(_xlpm.t-1)/9,_xlpm.cum,MMULT(--(_xlpm.t>=TRANSPOSE(_xlpm.t)),LN(1+_xlpm.g)),_xlpm.rev,_xlpm.r0*EXP(_xlpm.cum),_xlpm.prv,_xlpm.r0*EXP(_xlpm.cum-LN(1+_xlpm.g)),_xlpm.lp,IF(_xlpm.t>=_xlpm.n,1,_xlpm.t/_xlpm.n),_xlpm.omt,_xlpm.om0+(_xlpm.om-_xlpm.om0)*_xlpm.lp,_xlpm.dat,_xlpm.da0+(_xlpm.lcx*_xlpm.dar-_xlpm.da0)*_xlpm.lp,_xlpm.cpx,IF((_xlpm.t=1)*(_xlpm.gd>0),_xlpm.gd/_xlpm.rev,_xlpm.cx0+(_xlpm.lcx-_xlpm.cx0)*_xlpm.lp),_xlpm.f,_xlpm.rev*(_xlpm.omt*(1-_xlpm.tx)+_xlpm.dat-_xlpm.cpx+_xlpm.sb)-_xlpm.nw*(_xlpm.rev-_xlpm.prv),_xlpm.pv,SUM(_xlpm.f/(1+_xlpm.w)^(_xlpm.t-0.5*_xlpm.m)),_xlpm.tv,INDEX(_xlpm.f,10)*(1+_xlpm.tgr)/(_xlpm.w-_xlpm.tgr)/(1+_xlpm.w)^10,(_xlpm.pv+_xlpm.tv+_xlpm.nc)/_xlpm.shs)} | S70: =S69+0.005 | T70: {=_xlfn.LET(_xlpm.gs,$B$9,_xlpm.om,S70,_xlpm.w,$B$7,_xlpm.tgr,$B$8,_xlpm.n,$B$11,_xlpm.lcx,$B$19,_xlpm.r0,DCF!$B$37,_xlpm.om0,DCF!$B$39,_xlpm.cx0,DCF!$B$40,_xlpm.da0,DCF!$B$41,_xlpm.dar,DCF!$B$20,_xlpm.tx,DCF!$B$31,_xlpm.sb,DCF!$B$43,_xlpm.nw,DCF!$B$21,_xlpm.gd,N(DCF!$B$22),_xlpm.nc,DCF!$B$47,_xlpm.shs,DCF!$B$6,_xlpm.m,DCF!$B$48,_xlpm.t,_xlfn.SEQUENCE(10),_xlpm.g,_xlpm.gs-(_xlpm.gs-_xlpm.tgr)*(_xlpm.t-1)/9,_xlpm.cum,MMULT(--(_xlpm.t>=TRANSPOSE(_xlpm.t)),LN(1+_xlpm.g)),_xlpm.rev,_xlpm.r0*EXP(_xlpm.cum),_xlpm.prv,_xlpm.r0*EXP(_xlpm.cum-LN(1+_xlpm.g)),_xlpm.lp,IF(_xlpm.t>=_xlpm.n,1,_xlpm.t/_xlpm.n),_xlpm.omt,_xlpm.om0+(_xlpm.om-_xlpm.om0)*_xlpm.lp,_xlpm.dat,_xlpm.da0+(_xlpm.lcx*_xlpm.dar-_xlpm.da0)*_xlpm.lp,_xlpm.cpx,IF((_xlpm.t=1)*(_xlpm.gd>0),_xlpm.gd/_xlpm.rev,_xlpm.cx0+(_xlpm.lcx-_xlpm.cx0)*_xlpm.lp),_xlpm.f,_xlpm.rev*(_xlpm.omt*(1-_xlpm.tx)+_xlpm.dat-_xlpm.cpx+_xlpm.sb)-_xlpm.nw*(_xlpm.rev-_xlpm.prv),_xlpm.pv,SUM(_xlpm.f/(1+_xlpm.w)^(_xlpm.t-0.5*_xlpm.m)),_xlpm.tv,INDEX(_xlpm.f,10)*(1+_xlpm.tgr)/(_xlpm.w-_xlpm.tgr)/(1+_xlpm.w)^10,(_xlpm.pv+_xlpm.tv+_xlpm.nc)/_xlpm.shs)} | U70: =U69-0.0025 | V70: {=_xlfn.LET(_xlpm.gs,$B$9,_xlpm.om,$B$10,_xlpm.w,$B$7,_xlpm.tgr,$B$8,_xlpm.n,$B$11,_xlpm.lcx,U70,_xlpm.r0,DCF!$B$37,_xlpm.om0,DCF!$B$39,_xlpm.cx0,DCF!$B$40,_xlpm.da0,DCF!$B$41,_xlpm.dar,DCF!$B$20,_xlpm.tx,DCF!$B$31,_xlpm.sb,DCF!$B$43,_xlpm.nw,DCF!$B$21,_xlpm.gd,N(DCF!$B$22),_xlpm.nc,DCF!$B$47,_xlpm.shs,DCF!$B$6,_xlpm.m,DCF!$B$48,_xlpm.t,_xlfn.SEQUENCE(10),_xlpm.g,_xlpm.gs-(_xlpm.gs-_xlpm.tgr)*(_xlpm.t-1)/9,_xlpm.cum,MMULT(--(_xlpm.t>=TRANSPOSE(_xlpm.t)),LN(1+_xlpm.g)),_xlpm.rev,_xlpm.r0*EXP(_xlpm.cum),_xlpm.prv,_xlpm.r0*EXP(_xlpm.cum-LN(1+_xlpm.g)),_xlpm.lp,IF(_xlpm.t>=_xlpm.n,1,_xlpm.t/_xlpm.n),_xlpm.omt,_xlpm.om0+(_xlpm.om-_xlpm.om0)*_xlpm.lp,_xlpm.dat,_xlpm.da0+(_xlpm.lcx*_xlpm.dar-_xlpm.da0)*_xlpm.lp,_xlpm.cpx,IF((_xlpm.t=1)*(_xlpm.gd>0),_xlpm.gd/_xlpm.rev,_xlpm.cx0+(_xlpm.lcx-_xlpm.cx0)*_xlpm.lp),_xlpm.f,_xlpm.rev*(_xlpm.omt*(1-_xlpm.tx)+_xlpm.dat-_xlpm.cpx+_xlpm.sb)-_xlpm.nw*(_xlpm.rev-_xlpm.prv),_xlpm.pv,SUM(_xlpm.f/(1+_xlpm.w)^(_xlpm.t-0.5*_xlpm.m)),_xlpm.tv,INDEX(_xlpm.f,10)*(1+_xlpm.tgr)/(_xlpm.w-_xlpm.tgr)/(1+_xlpm.w)^10,(_xlpm.pv+_xlpm.tv+_xlpm.nc)/_xlpm.shs)}
A71: Equity value ($B) | B71: =SUM(B67:B70) | Q71: =Q70+0.005 | R71: {=_xlfn.LET(_xlpm.gs,Q71,_xlpm.om,$B$10,_xlpm.w,$B$7,_xlpm.tgr,$B$8,_xlpm.n,$B$11,_xlpm.lcx,$B$19,_xlpm.r0,DCF!$B$37,_xlpm.om0,DCF!$B$39,_xlpm.cx0,DCF!$B$40,_xlpm.da0,DCF!$B$41,_xlpm.dar,DCF!$B$20,_xlpm.tx,DCF!$B$31,_xlpm.sb,DCF!$B$43,_xlpm.nw,DCF!$B$21,_xlpm.gd,N(DCF!$B$22),_xlpm.nc,DCF!$B$47,_xlpm.shs,DCF!$B$6,_xlpm.m,DCF!$B$48,_xlpm.t,_xlfn.SEQUENCE(10),_xlpm.g,_xlpm.gs-(_xlpm.gs-_xlpm.tgr)*(_xlpm.t-1)/9,_xlpm.cum,MMULT(--(_xlpm.t>=TRANSPOSE(_xlpm.t)),LN(1+_xlpm.g)),_xlpm.rev,_xlpm.r0*EXP(_xlpm.cum),_xlpm.prv,_xlpm.r0*EXP(_xlpm.cum-LN(1+_xlpm.g)),_xlpm.lp,IF(_xlpm.t>=_xlpm.n,1,_xlpm.t/_xlpm.n),_xlpm.omt,_xlpm.om0+(_xlpm.om-_xlpm.om0)*_xlpm.lp,_xlpm.dat,_xlpm.da0+(_xlpm.lcx*_xlpm.dar-_xlpm.da0)*_xlpm.lp,_xlpm.cpx,IF((_xlpm.t=1)*(_xlpm.gd>0),_xlpm.gd/_xlpm.rev,_xlpm.cx0+(_xlpm.lcx-_xlpm.cx0)*_xlpm.lp),_xlpm.f,_xlpm.rev*(_xlpm.omt*(1-_xlpm.tx)+_xlpm.dat-_xlpm.cpx+_xlpm.sb)-_xlpm.nw*(_xlpm.rev-_xlpm.prv),_xlpm.pv,SUM(_xlpm.f/(1+_xlpm.w)^(_xlpm.t-0.5*_xlpm.m)),_xlpm.tv,INDEX(_xlpm.f,10)*(1+_xlpm.tgr)/(_xlpm.w-_xlpm.tgr)/(1+_xlpm.w)^10,(_xlpm.pv+_xlpm.tv+_xlpm.nc)/_xlpm.shs)} | S71: =S70+0.005 | T71: {=_xlfn.LET(_xlpm.gs,$B$9,_xlpm.om,S71,_xlpm.w,$B$7,_xlpm.tgr,$B$8,_xlpm.n,$B$11,_xlpm.lcx,$B$19,_xlpm.r0,DCF!$B$37,_xlpm.om0,DCF!$B$39,_xlpm.cx0,DCF!$B$40,_xlpm.da0,DCF!$B$41,_xlpm.dar,DCF!$B$20,_xlpm.tx,DCF!$B$31,_xlpm.sb,DCF!$B$43,_xlpm.nw,DCF!$B$21,_xlpm.gd,N(DCF!$B$22),_xlpm.nc,DCF!$B$47,_xlpm.shs,DCF!$B$6,_xlpm.m,DCF!$B$48,_xlpm.t,_xlfn.SEQUENCE(10),_xlpm.g,_xlpm.gs-(_xlpm.gs-_xlpm.tgr)*(_xlpm.t-1)/9,_xlpm.cum,MMULT(--(_xlpm.t>=TRANSPOSE(_xlpm.t)),LN(1+_xlpm.g)),_xlpm.rev,_xlpm.r0*EXP(_xlpm.cum),_xlpm.prv,_xlpm.r0*EXP(_xlpm.cum-LN(1+_xlpm.g)),_xlpm.lp,IF(_xlpm.t>=_xlpm.n,1,_xlpm.t/_xlpm.n),_xlpm.omt,_xlpm.om0+(_xlpm.om-_xlpm.om0)*_xlpm.lp,_xlpm.dat,_xlpm.da0+(_xlpm.lcx*_xlpm.dar-_xlpm.da0)*_xlpm.lp,_xlpm.cpx,IF((_xlpm.t=1)*(_xlpm.gd>0),_xlpm.gd/_xlpm.rev,_xlpm.cx0+(_xlpm.lcx-_xlpm.cx0)*_xlpm.lp),_xlpm.f,_xlpm.rev*(_xlpm.omt*(1-_xlpm.tx)+_xlpm.dat-_xlpm.cpx+_xlpm.sb)-_xlpm.nw*(_xlpm.rev-_xlpm.prv),_xlpm.pv,SUM(_xlpm.f/(1+_xlpm.w)^(_xlpm.t-0.5*_xlpm.m)),_xlpm.tv,INDEX(_xlpm.f,10)*(1+_xlpm.tgr)/(_xlpm.w-_xlpm.tgr)/(1+_xlpm.w)^10,(_xlpm.pv+_xlpm.tv+_xlpm.nc)/_xlpm.shs)} | U71: =U70-0.0025 | V71: {=_xlfn.LET(_xlpm.gs,$B$9,_xlpm.om,$B$10,_xlpm.w,$B$7,_xlpm.tgr,$B$8,_xlpm.n,$B$11,_xlpm.lcx,U71,_xlpm.r0,DCF!$B$37,_xlpm.om0,DCF!$B$39,_xlpm.cx0,DCF!$B$40,_xlpm.da0,DCF!$B$41,_xlpm.dar,DCF!$B$20,_xlpm.tx,DCF!$B$31,_xlpm.sb,DCF!$B$43,_xlpm.nw,DCF!$B$21,_xlpm.gd,N(DCF!$B$22),_xlpm.nc,DCF!$B$47,_xlpm.shs,DCF!$B$6,_xlpm.m,DCF!$B$48,_xlpm.t,_xlfn.SEQUENCE(10),_xlpm.g,_xlpm.gs-(_xlpm.gs-_xlpm.tgr)*(_xlpm.t-1)/9,_xlpm.cum,MMULT(--(_xlpm.t>=TRANSPOSE(_xlpm.t)),LN(1+_xlpm.g)),_xlpm.rev,_xlpm.r0*EXP(_xlpm.cum),_xlpm.prv,_xlpm.r0*EXP(_xlpm.cum-LN(1+_xlpm.g)),_xlpm.lp,IF(_xlpm.t>=_xlpm.n,1,_xlpm.t/_xlpm.n),_xlpm.omt,_xlpm.om0+(_xlpm.om-_xlpm.om0)*_xlpm.lp,_xlpm.dat,_xlpm.da0+(_xlpm.lcx*_xlpm.dar-_xlpm.da0)*_xlpm.lp,_xlpm.cpx,IF((_xlpm.t=1)*(_xlpm.gd>0),_xlpm.gd/_xlpm.rev,_xlpm.cx0+(_xlpm.lcx-_xlpm.cx0)*_xlpm.lp),_xlpm.f,_xlpm.rev*(_xlpm.omt*(1-_xlpm.tx)+_xlpm.dat-_xlpm.cpx+_xlpm.sb)-_xlpm.nw*(_xlpm.rev-_xlpm.prv),_xlpm.pv,SUM(_xlpm.f/(1+_xlpm.w)^(_xlpm.t-0.5*_xlpm.m)),_xlpm.tv,INDEX(_xlpm.f,10)*(1+_xlpm.tgr)/(_xlpm.w-_xlpm.tgr)/(1+_xlpm.w)^10,(_xlpm.pv+_xlpm.tv+_xlpm.nc)/_xlpm.shs)}
A72: Fair value per share ($) | B72: =B71/B6 | Q72: =Q71+0.005 | R72: {=_xlfn.LET(_xlpm.gs,Q72,_xlpm.om,$B$10,_xlpm.w,$B$7,_xlpm.tgr,$B$8,_xlpm.n,$B$11,_xlpm.lcx,$B$19,_xlpm.r0,DCF!$B$37,_xlpm.om0,DCF!$B$39,_xlpm.cx0,DCF!$B$40,_xlpm.da0,DCF!$B$41,_xlpm.dar,DCF!$B$20,_xlpm.tx,DCF!$B$31,_xlpm.sb,DCF!$B$43,_xlpm.nw,DCF!$B$21,_xlpm.gd,N(DCF!$B$22),_xlpm.nc,DCF!$B$47,_xlpm.shs,DCF!$B$6,_xlpm.m,DCF!$B$48,_xlpm.t,_xlfn.SEQUENCE(10),_xlpm.g,_xlpm.gs-(_xlpm.gs-_xlpm.tgr)*(_xlpm.t-1)/9,_xlpm.cum,MMULT(--(_xlpm.t>=TRANSPOSE(_xlpm.t)),LN(1+_xlpm.g)),_xlpm.rev,_xlpm.r0*EXP(_xlpm.cum),_xlpm.prv,_xlpm.r0*EXP(_xlpm.cum-LN(1+_xlpm.g)),_xlpm.lp,IF(_xlpm.t>=_xlpm.n,1,_xlpm.t/_xlpm.n),_xlpm.omt,_xlpm.om0+(_xlpm.om-_xlpm.om0)*_xlpm.lp,_xlpm.dat,_xlpm.da0+(_xlpm.lcx*_xlpm.dar-_xlpm.da0)*_xlpm.lp,_xlpm.cpx,IF((_xlpm.t=1)*(_xlpm.gd>0),_xlpm.gd/_xlpm.rev,_xlpm.cx0+(_xlpm.lcx-_xlpm.cx0)*_xlpm.lp),_xlpm.f,_xlpm.rev*(_xlpm.omt*(1-_xlpm.tx)+_xlpm.dat-_xlpm.cpx+_xlpm.sb)-_xlpm.nw*(_xlpm.rev-_xlpm.prv),_xlpm.pv,SUM(_xlpm.f/(1+_xlpm.w)^(_xlpm.t-0.5*_xlpm.m)),_xlpm.tv,INDEX(_xlpm.f,10)*(1+_xlpm.tgr)/(_xlpm.w-_xlpm.tgr)/(1+_xlpm.w)^10,(_xlpm.pv+_xlpm.tv+_xlpm.nc)/_xlpm.shs)} | S72: =S71+0.005 | T72: {=_xlfn.LET(_xlpm.gs,$B$9,_xlpm.om,S72,_xlpm.w,$B$7,_xlpm.tgr,$B$8,_xlpm.n,$B$11,_xlpm.lcx,$B$19,_xlpm.r0,DCF!$B$37,_xlpm.om0,DCF!$B$39,_xlpm.cx0,DCF!$B$40,_xlpm.da0,DCF!$B$41,_xlpm.dar,DCF!$B$20,_xlpm.tx,DCF!$B$31,_xlpm.sb,DCF!$B$43,_xlpm.nw,DCF!$B$21,_xlpm.gd,N(DCF!$B$22),_xlpm.nc,DCF!$B$47,_xlpm.shs,DCF!$B$6,_xlpm.m,DCF!$B$48,_xlpm.t,_xlfn.SEQUENCE(10),_xlpm.g,_xlpm.gs-(_xlpm.gs-_xlpm.tgr)*(_xlpm.t-1)/9,_xlpm.cum,MMULT(--(_xlpm.t>=TRANSPOSE(_xlpm.t)),LN(1+_xlpm.g)),_xlpm.rev,_xlpm.r0*EXP(_xlpm.cum),_xlpm.prv,_xlpm.r0*EXP(_xlpm.cum-LN(1+_xlpm.g)),_xlpm.lp,IF(_xlpm.t>=_xlpm.n,1,_xlpm.t/_xlpm.n),_xlpm.omt,_xlpm.om0+(_xlpm.om-_xlpm.om0)*_xlpm.lp,_xlpm.dat,_xlpm.da0+(_xlpm.lcx*_xlpm.dar-_xlpm.da0)*_xlpm.lp,_xlpm.cpx,IF((_xlpm.t=1)*(_xlpm.gd>0),_xlpm.gd/_xlpm.rev,_xlpm.cx0+(_xlpm.lcx-_xlpm.cx0)*_xlpm.lp),_xlpm.f,_xlpm.rev*(_xlpm.omt*(1-_xlpm.tx)+_xlpm.dat-_xlpm.cpx+_xlpm.sb)-_xlpm.nw*(_xlpm.rev-_xlpm.prv),_xlpm.pv,SUM(_xlpm.f/(1+_xlpm.w)^(_xlpm.t-0.5*_xlpm.m)),_xlpm.tv,INDEX(_xlpm.f,10)*(1+_xlpm.tgr)/(_xlpm.w-_xlpm.tgr)/(1+_xlpm.w)^10,(_xlpm.pv+_xlpm.tv+_xlpm.nc)/_xlpm.shs)} | U72: =U71-0.0025 | V72: {=_xlfn.LET(_xlpm.gs,$B$9,_xlpm.om,$B$10,_xlpm.w,$B$7,_xlpm.tgr,$B$8,_xlpm.n,$B$11,_xlpm.lcx,U72,_xlpm.r0,DCF!$B$37,_xlpm.om0,DCF!$B$39,_xlpm.cx0,DCF!$B$40,_xlpm.da0,DCF!$B$41,_xlpm.dar,DCF!$B$20,_xlpm.tx,DCF!$B$31,_xlpm.sb,DCF!$B$43,_xlpm.nw,DCF!$B$21,_xlpm.gd,N(DCF!$B$22),_xlpm.nc,DCF!$B$47,_xlpm.shs,DCF!$B$6,_xlpm.m,DCF!$B$48,_xlpm.t,_xlfn.SEQUENCE(10),_xlpm.g,_xlpm.gs-(_xlpm.gs-_xlpm.tgr)*(_xlpm.t-1)/9,_xlpm.cum,MMULT(--(_xlpm.t>=TRANSPOSE(_xlpm.t)),LN(1+_xlpm.g)),_xlpm.rev,_xlpm.r0*EXP(_xlpm.cum),_xlpm.prv,_xlpm.r0*EXP(_xlpm.cum-LN(1+_xlpm.g)),_xlpm.lp,IF(_xlpm.t>=_xlpm.n,1,_xlpm.t/_xlpm.n),_xlpm.omt,_xlpm.om0+(_xlpm.om-_xlpm.om0)*_xlpm.lp,_xlpm.dat,_xlpm.da0+(_xlpm.lcx*_xlpm.dar-_xlpm.da0)*_xlpm.lp,_xlpm.cpx,IF((_xlpm.t=1)*(_xlpm.gd>0),_xlpm.gd/_xlpm.rev,_xlpm.cx0+(_xlpm.lcx-_xlpm.cx0)*_xlpm.lp),_xlpm.f,_xlpm.rev*(_xlpm.omt*(1-_xlpm.tx)+_xlpm.dat-_xlpm.cpx+_xlpm.sb)-_xlpm.nw*(_xlpm.rev-_xlpm.prv),_xlpm.pv,SUM(_xlpm.f/(1+_xlpm.w)^(_xlpm.t-0.5*_xlpm.m)),_xlpm.tv,INDEX(_xlpm.f,10)*(1+_xlpm.tgr)/(_xlpm.w-_xlpm.tgr)/(1+_xlpm.w)^10,(_xlpm.pv+_xlpm.tv+_xlpm.nc)/_xlpm.shs)}
A73: Current share price ($) | B73: =B5 | Q73: =Q72+0.005 | R73: {=_xlfn.LET(_xlpm.gs,Q73,_xlpm.om,$B$10,_xlpm.w,$B$7,_xlpm.tgr,$B$8,_xlpm.n,$B$11,_xlpm.lcx,$B$19,_xlpm.r0,DCF!$B$37,_xlpm.om0,DCF!$B$39,_xlpm.cx0,DCF!$B$40,_xlpm.da0,DCF!$B$41,_xlpm.dar,DCF!$B$20,_xlpm.tx,DCF!$B$31,_xlpm.sb,DCF!$B$43,_xlpm.nw,DCF!$B$21,_xlpm.gd,N(DCF!$B$22),_xlpm.nc,DCF!$B$47,_xlpm.shs,DCF!$B$6,_xlpm.m,DCF!$B$48,_xlpm.t,_xlfn.SEQUENCE(10),_xlpm.g,_xlpm.gs-(_xlpm.gs-_xlpm.tgr)*(_xlpm.t-1)/9,_xlpm.cum,MMULT(--(_xlpm.t>=TRANSPOSE(_xlpm.t)),LN(1+_xlpm.g)),_xlpm.rev,_xlpm.r0*EXP(_xlpm.cum),_xlpm.prv,_xlpm.r0*EXP(_xlpm.cum-LN(1+_xlpm.g)),_xlpm.lp,IF(_xlpm.t>=_xlpm.n,1,_xlpm.t/_xlpm.n),_xlpm.omt,_xlpm.om0+(_xlpm.om-_xlpm.om0)*_xlpm.lp,_xlpm.dat,_xlpm.da0+(_xlpm.lcx*_xlpm.dar-_xlpm.da0)*_xlpm.lp,_xlpm.cpx,IF((_xlpm.t=1)*(_xlpm.gd>0),_xlpm.gd/_xlpm.rev,_xlpm.cx0+(_xlpm.lcx-_xlpm.cx0)*_xlpm.lp),_xlpm.f,_xlpm.rev*(_xlpm.omt*(1-_xlpm.tx)+_xlpm.dat-_xlpm.cpx+_xlpm.sb)-_xlpm.nw*(_xlpm.rev-_xlpm.prv),_xlpm.pv,SUM(_xlpm.f/(1+_xlpm.w)^(_xlpm.t-0.5*_xlpm.m)),_xlpm.tv,INDEX(_xlpm.f,10)*(1+_xlpm.tgr)/(_xlpm.w-_xlpm.tgr)/(1+_xlpm.w)^10,(_xlpm.pv+_xlpm.tv+_xlpm.nc)/_xlpm.shs)} | S73: =S72+0.005 | T73: {=_xlfn.LET(_xlpm.gs,$B$9,_xlpm.om,S73,_xlpm.w,$B$7,_xlpm.tgr,$B$8,_xlpm.n,$B$11,_xlpm.lcx,$B$19,_xlpm.r0,DCF!$B$37,_xlpm.om0,DCF!$B$39,_xlpm.cx0,DCF!$B$40,_xlpm.da0,DCF!$B$41,_xlpm.dar,DCF!$B$20,_xlpm.tx,DCF!$B$31,_xlpm.sb,DCF!$B$43,_xlpm.nw,DCF!$B$21,_xlpm.gd,N(DCF!$B$22),_xlpm.nc,DCF!$B$47,_xlpm.shs,DCF!$B$6,_xlpm.m,DCF!$B$48,_xlpm.t,_xlfn.SEQUENCE(10),_xlpm.g,_xlpm.gs-(_xlpm.gs-_xlpm.tgr)*(_xlpm.t-1)/9,_xlpm.cum,MMULT(--(_xlpm.t>=TRANSPOSE(_xlpm.t)),LN(1+_xlpm.g)),_xlpm.rev,_xlpm.r0*EXP(_xlpm.cum),_xlpm.prv,_xlpm.r0*EXP(_xlpm.cum-LN(1+_xlpm.g)),_xlpm.lp,IF(_xlpm.t>=_xlpm.n,1,_xlpm.t/_xlpm.n),_xlpm.omt,_xlpm.om0+(_xlpm.om-_xlpm.om0)*_xlpm.lp,_xlpm.dat,_xlpm.da0+(_xlpm.lcx*_xlpm.dar-_xlpm.da0)*_xlpm.lp,_xlpm.cpx,IF((_xlpm.t=1)*(_xlpm.gd>0),_xlpm.gd/_xlpm.rev,_xlpm.cx0+(_xlpm.lcx-_xlpm.cx0)*_xlpm.lp),_xlpm.f,_xlpm.rev*(_xlpm.omt*(1-_xlpm.tx)+_xlpm.dat-_xlpm.cpx+_xlpm.sb)-_xlpm.nw*(_xlpm.rev-_xlpm.prv),_xlpm.pv,SUM(_xlpm.f/(1+_xlpm.w)^(_xlpm.t-0.5*_xlpm.m)),_xlpm.tv,INDEX(_xlpm.f,10)*(1+_xlpm.tgr)/(_xlpm.w-_xlpm.tgr)/(1+_xlpm.w)^10,(_xlpm.pv+_xlpm.tv+_xlpm.nc)/_xlpm.shs)} | U73: =U72-0.0025 | V73: {=_xlfn.LET(_xlpm.gs,$B$9,_xlpm.om,$B$10,_xlpm.w,$B$7,_xlpm.tgr,$B$8,_xlpm.n,$B$11,_xlpm.lcx,U73,_xlpm.r0,DCF!$B$37,_xlpm.om0,DCF!$B$39,_xlpm.cx0,DCF!$B$40,_xlpm.da0,DCF!$B$41,_xlpm.dar,DCF!$B$20,_xlpm.tx,DCF!$B$31,_xlpm.sb,DCF!$B$43,_xlpm.nw,DCF!$B$21,_xlpm.gd,N(DCF!$B$22),_xlpm.nc,DCF!$B$47,_xlpm.shs,DCF!$B$6,_xlpm.m,DCF!$B$48,_xlpm.t,_xlfn.SEQUENCE(10),_xlpm.g,_xlpm.gs-(_xlpm.gs-_xlpm.tgr)*(_xlpm.t-1)/9,_xlpm.cum,MMULT(--(_xlpm.t>=TRANSPOSE(_xlpm.t)),LN(1+_xlpm.g)),_xlpm.rev,_xlpm.r0*EXP(_xlpm.cum),_xlpm.prv,_xlpm.r0*EXP(_xlpm.cum-LN(1+_xlpm.g)),_xlpm.lp,IF(_xlpm.t>=_xlpm.n,1,_xlpm.t/_xlpm.n),_xlpm.omt,_xlpm.om0+(_xlpm.om-_xlpm.om0)*_xlpm.lp,_xlpm.dat,_xlpm.da0+(_xlpm.lcx*_xlpm.dar-_xlpm.da0)*_xlpm.lp,_xlpm.cpx,IF((_xlpm.t=1)*(_xlpm.gd>0),_xlpm.gd/_xlpm.rev,_xlpm.cx0+(_xlpm.lcx-_xlpm.cx0)*_xlpm.lp),_xlpm.f,_xlpm.rev*(_xlpm.omt*(1-_xlpm.tx)+_xlpm.dat-_xlpm.cpx+_xlpm.sb)-_xlpm.nw*(_xlpm.rev-_xlpm.prv),_xlpm.pv,SUM(_xlpm.f/(1+_xlpm.w)^(_xlpm.t-0.5*_xlpm.m)),_xlpm.tv,INDEX(_xlpm.f,10)*(1+_xlpm.tgr)/(_xlpm.w-_xlpm.tgr)/(1+_xlpm.w)^10,(_xlpm.pv+_xlpm.tv+_xlpm.nc)/_xlpm.shs)}
A74: Upside / (downside) | B74: =B72/B73-1 | Q74: =Q73+0.005 | R74: {=_xlfn.LET(_xlpm.gs,Q74,_xlpm.om,$B$10,_xlpm.w,$B$7,_xlpm.tgr,$B$8,_xlpm.n,$B$11,_xlpm.lcx,$B$19,_xlpm.r0,DCF!$B$37,_xlpm.om0,DCF!$B$39,_xlpm.cx0,DCF!$B$40,_xlpm.da0,DCF!$B$41,_xlpm.dar,DCF!$B$20,_xlpm.tx,DCF!$B$31,_xlpm.sb,DCF!$B$43,_xlpm.nw,DCF!$B$21,_xlpm.gd,N(DCF!$B$22),_xlpm.nc,DCF!$B$47,_xlpm.shs,DCF!$B$6,_xlpm.m,DCF!$B$48,_xlpm.t,_xlfn.SEQUENCE(10),_xlpm.g,_xlpm.gs-(_xlpm.gs-_xlpm.tgr)*(_xlpm.t-1)/9,_xlpm.cum,MMULT(--(_xlpm.t>=TRANSPOSE(_xlpm.t)),LN(1+_xlpm.g)),_xlpm.rev,_xlpm.r0*EXP(_xlpm.cum),_xlpm.prv,_xlpm.r0*EXP(_xlpm.cum-LN(1+_xlpm.g)),_xlpm.lp,IF(_xlpm.t>=_xlpm.n,1,_xlpm.t/_xlpm.n),_xlpm.omt,_xlpm.om0+(_xlpm.om-_xlpm.om0)*_xlpm.lp,_xlpm.dat,_xlpm.da0+(_xlpm.lcx*_xlpm.dar-_xlpm.da0)*_xlpm.lp,_xlpm.cpx,IF((_xlpm.t=1)*(_xlpm.gd>0),_xlpm.gd/_xlpm.rev,_xlpm.cx0+(_xlpm.lcx-_xlpm.cx0)*_xlpm.lp),_xlpm.f,_xlpm.rev*(_xlpm.omt*(1-_xlpm.tx)+_xlpm.dat-_xlpm.cpx+_xlpm.sb)-_xlpm.nw*(_xlpm.rev-_xlpm.prv),_xlpm.pv,SUM(_xlpm.f/(1+_xlpm.w)^(_xlpm.t-0.5*_xlpm.m)),_xlpm.tv,INDEX(_xlpm.f,10)*(1+_xlpm.tgr)/(_xlpm.w-_xlpm.tgr)/(1+_xlpm.w)^10,(_xlpm.pv+_xlpm.tv+_xlpm.nc)/_xlpm.shs)} | S74: =S73+0.005 | T74: {=_xlfn.LET(_xlpm.gs,$B$9,_xlpm.om,S74,_xlpm.w,$B$7,_xlpm.tgr,$B$8,_xlpm.n,$B$11,_xlpm.lcx,$B$19,_xlpm.r0,DCF!$B$37,_xlpm.om0,DCF!$B$39,_xlpm.cx0,DCF!$B$40,_xlpm.da0,DCF!$B$41,_xlpm.dar,DCF!$B$20,_xlpm.tx,DCF!$B$31,_xlpm.sb,DCF!$B$43,_xlpm.nw,DCF!$B$21,_xlpm.gd,N(DCF!$B$22),_xlpm.nc,DCF!$B$47,_xlpm.shs,DCF!$B$6,_xlpm.m,DCF!$B$48,_xlpm.t,_xlfn.SEQUENCE(10),_xlpm.g,_xlpm.gs-(_xlpm.gs-_xlpm.tgr)*(_xlpm.t-1)/9,_xlpm.cum,MMULT(--(_xlpm.t>=TRANSPOSE(_xlpm.t)),LN(1+_xlpm.g)),_xlpm.rev,_xlpm.r0*EXP(_xlpm.cum),_xlpm.prv,_xlpm.r0*EXP(_xlpm.cum-LN(1+_xlpm.g)),_xlpm.lp,IF(_xlpm.t>=_xlpm.n,1,_xlpm.t/_xlpm.n),_xlpm.omt,_xlpm.om0+(_xlpm.om-_xlpm.om0)*_xlpm.lp,_xlpm.dat,_xlpm.da0+(_xlpm.lcx*_xlpm.dar-_xlpm.da0)*_xlpm.lp,_xlpm.cpx,IF((_xlpm.t=1)*(_xlpm.gd>0),_xlpm.gd/_xlpm.rev,_xlpm.cx0+(_xlpm.lcx-_xlpm.cx0)*_xlpm.lp),_xlpm.f,_xlpm.rev*(_xlpm.omt*(1-_xlpm.tx)+_xlpm.dat-_xlpm.cpx+_xlpm.sb)-_xlpm.nw*(_xlpm.rev-_xlpm.prv),_xlpm.pv,SUM(_xlpm.f/(1+_xlpm.w)^(_xlpm.t-0.5*_xlpm.m)),_xlpm.tv,INDEX(_xlpm.f,10)*(1+_xlpm.tgr)/(_xlpm.w-_xlpm.tgr)/(1+_xlpm.w)^10,(_xlpm.pv+_xlpm.tv+_xlpm.nc)/_xlpm.shs)} | U74: =U73-0.0025 | V74: {=_xlfn.LET(_xlpm.gs,$B$9,_xlpm.om,$B$10,_xlpm.w,$B$7,_xlpm.tgr,$B$8,_xlpm.n,$B$11,_xlpm.lcx,U74,_xlpm.r0,DCF!$B$37,_xlpm.om0,DCF!$B$39,_xlpm.cx0,DCF!$B$40,_xlpm.da0,DCF!$B$41,_xlpm.dar,DCF!$B$20,_xlpm.tx,DCF!$B$31,_xlpm.sb,DCF!$B$43,_xlpm.nw,DCF!$B$21,_xlpm.gd,N(DCF!$B$22),_xlpm.nc,DCF!$B$47,_xlpm.shs,DCF!$B$6,_xlpm.m,DCF!$B$48,_xlpm.t,_xlfn.SEQUENCE(10),_xlpm.g,_xlpm.gs-(_xlpm.gs-_xlpm.tgr)*(_xlpm.t-1)/9,_xlpm.cum,MMULT(--(_xlpm.t>=TRANSPOSE(_xlpm.t)),LN(1+_xlpm.g)),_xlpm.rev,_xlpm.r0*EXP(_xlpm.cum),_xlpm.prv,_xlpm.r0*EXP(_xlpm.cum-LN(1+_xlpm.g)),_xlpm.lp,IF(_xlpm.t>=_xlpm.n,1,_xlpm.t/_xlpm.n),_xlpm.omt,_xlpm.om0+(_xlpm.om-_xlpm.om0)*_xlpm.lp,_xlpm.dat,_xlpm.da0+(_xlpm.lcx*_xlpm.dar-_xlpm.da0)*_xlpm.lp,_xlpm.cpx,IF((_xlpm.t=1)*(_xlpm.gd>0),_xlpm.gd/_xlpm.rev,_xlpm.cx0+(_xlpm.lcx-_xlpm.cx0)*_xlpm.lp),_xlpm.f,_xlpm.rev*(_xlpm.omt*(1-_xlpm.tx)+_xlpm.dat-_xlpm.cpx+_xlpm.sb)-_xlpm.nw*(_xlpm.rev-_xlpm.prv),_xlpm.pv,SUM(_xlpm.f/(1+_xlpm.w)^(_xlpm.t-0.5*_xlpm.m)),_xlpm.tv,INDEX(_xlpm.f,10)*(1+_xlpm.tgr)/(_xlpm.w-_xlpm.tgr)/(1+_xlpm.w)^10,(_xlpm.pv+_xlpm.tv+_xlpm.nc)/_xlpm.shs)}
A75: Terminal value as % of EV | B75: =B66/B67 | C75: Above ~75% means the valuation rests mostly on the perpetuity assumption. | Q75: =Q74+0.005 | R75: {=_xlfn.LET(_xlpm.gs,Q75,_xlpm.om,$B$10,_xlpm.w,$B$7,_xlpm.tgr,$B$8,_xlpm.n,$B$11,_xlpm.lcx,$B$19,_xlpm.r0,DCF!$B$37,_xlpm.om0,DCF!$B$39,_xlpm.cx0,DCF!$B$40,_xlpm.da0,DCF!$B$41,_xlpm.dar,DCF!$B$20,_xlpm.tx,DCF!$B$31,_xlpm.sb,DCF!$B$43,_xlpm.nw,DCF!$B$21,_xlpm.gd,N(DCF!$B$22),_xlpm.nc,DCF!$B$47,_xlpm.shs,DCF!$B$6,_xlpm.m,DCF!$B$48,_xlpm.t,_xlfn.SEQUENCE(10),_xlpm.g,_xlpm.gs-(_xlpm.gs-_xlpm.tgr)*(_xlpm.t-1)/9,_xlpm.cum,MMULT(--(_xlpm.t>=TRANSPOSE(_xlpm.t)),LN(1+_xlpm.g)),_xlpm.rev,_xlpm.r0*EXP(_xlpm.cum),_xlpm.prv,_xlpm.r0*EXP(_xlpm.cum-LN(1+_xlpm.g)),_xlpm.lp,IF(_xlpm.t>=_xlpm.n,1,_xlpm.t/_xlpm.n),_xlpm.omt,_xlpm.om0+(_xlpm.om-_xlpm.om0)*_xlpm.lp,_xlpm.dat,_xlpm.da0+(_xlpm.lcx*_xlpm.dar-_xlpm.da0)*_xlpm.lp,_xlpm.cpx,IF((_xlpm.t=1)*(_xlpm.gd>0),_xlpm.gd/_xlpm.rev,_xlpm.cx0+(_xlpm.lcx-_xlpm.cx0)*_xlpm.lp),_xlpm.f,_xlpm.rev*(_xlpm.omt*(1-_xlpm.tx)+_xlpm.dat-_xlpm.cpx+_xlpm.sb)-_xlpm.nw*(_xlpm.rev-_xlpm.prv),_xlpm.pv,SUM(_xlpm.f/(1+_xlpm.w)^(_xlpm.t-0.5*_xlpm.m)),_xlpm.tv,INDEX(_xlpm.f,10)*(1+_xlpm.tgr)/(_xlpm.w-_xlpm.tgr)/(1+_xlpm.w)^10,(_xlpm.pv+_xlpm.tv+_xlpm.nc)/_xlpm.shs)} | S75: =S74+0.005 | T75: {=_xlfn.LET(_xlpm.gs,$B$9,_xlpm.om,S75,_xlpm.w,$B$7,_xlpm.tgr,$B$8,_xlpm.n,$B$11,_xlpm.lcx,$B$19,_xlpm.r0,DCF!$B$37,_xlpm.om0,DCF!$B$39,_xlpm.cx0,DCF!$B$40,_xlpm.da0,DCF!$B$41,_xlpm.dar,DCF!$B$20,_xlpm.tx,DCF!$B$31,_xlpm.sb,DCF!$B$43,_xlpm.nw,DCF!$B$21,_xlpm.gd,N(DCF!$B$22),_xlpm.nc,DCF!$B$47,_xlpm.shs,DCF!$B$6,_xlpm.m,DCF!$B$48,_xlpm.t,_xlfn.SEQUENCE(10),_xlpm.g,_xlpm.gs-(_xlpm.gs-_xlpm.tgr)*(_xlpm.t-1)/9,_xlpm.cum,MMULT(--(_xlpm.t>=TRANSPOSE(_xlpm.t)),LN(1+_xlpm.g)),_xlpm.rev,_xlpm.r0*EXP(_xlpm.cum),_xlpm.prv,_xlpm.r0*EXP(_xlpm.cum-LN(1+_xlpm.g)),_xlpm.lp,IF(_xlpm.t>=_xlpm.n,1,_xlpm.t/_xlpm.n),_xlpm.omt,_xlpm.om0+(_xlpm.om-_xlpm.om0)*_xlpm.lp,_xlpm.dat,_xlpm.da0+(_xlpm.lcx*_xlpm.dar-_xlpm.da0)*_xlpm.lp,_xlpm.cpx,IF((_xlpm.t=1)*(_xlpm.gd>0),_xlpm.gd/_xlpm.rev,_xlpm.cx0+(_xlpm.lcx-_xlpm.cx0)*_xlpm.lp),_xlpm.f,_xlpm.rev*(_xlpm.omt*(1-_xlpm.tx)+_xlpm.dat-_xlpm.cpx+_xlpm.sb)-_xlpm.nw*(_xlpm.rev-_xlpm.prv),_xlpm.pv,SUM(_xlpm.f/(1+_xlpm.w)^(_xlpm.t-0.5*_xlpm.m)),_xlpm.tv,INDEX(_xlpm.f,10)*(1+_xlpm.tgr)/(_xlpm.w-_xlpm.tgr)/(1+_xlpm.w)^10,(_xlpm.pv+_xlpm.tv+_xlpm.nc)/_xlpm.shs)} | U75: =U74-0.0025 | V75: {=_xlfn.LET(_xlpm.gs,$B$9,_xlpm.om,$B$10,_xlpm.w,$B$7,_xlpm.tgr,$B$8,_xlpm.n,$B$11,_xlpm.lcx,U75,_xlpm.r0,DCF!$B$37,_xlpm.om0,DCF!$B$39,_xlpm.cx0,DCF!$B$40,_xlpm.da0,DCF!$B$41,_xlpm.dar,DCF!$B$20,_xlpm.tx,DCF!$B$31,_xlpm.sb,DCF!$B$43,_xlpm.nw,DCF!$B$21,_xlpm.gd,N(DCF!$B$22),_xlpm.nc,DCF!$B$47,_xlpm.shs,DCF!$B$6,_xlpm.m,DCF!$B$48,_xlpm.t,_xlfn.SEQUENCE(10),_xlpm.g,_xlpm.gs-(_xlpm.gs-_xlpm.tgr)*(_xlpm.t-1)/9,_xlpm.cum,MMULT(--(_xlpm.t>=TRANSPOSE(_xlpm.t)),LN(1+_xlpm.g)),_xlpm.rev,_xlpm.r0*EXP(_xlpm.cum),_xlpm.prv,_xlpm.r0*EXP(_xlpm.cum-LN(1+_xlpm.g)),_xlpm.lp,IF(_xlpm.t>=_xlpm.n,1,_xlpm.t/_xlpm.n),_xlpm.omt,_xlpm.om0+(_xlpm.om-_xlpm.om0)*_xlpm.lp,_xlpm.dat,_xlpm.da0+(_xlpm.lcx*_xlpm.dar-_xlpm.da0)*_xlpm.lp,_xlpm.cpx,IF((_xlpm.t=1)*(_xlpm.gd>0),_xlpm.gd/_xlpm.rev,_xlpm.cx0+(_xlpm.lcx-_xlpm.cx0)*_xlpm.lp),_xlpm.f,_xlpm.rev*(_xlpm.omt*(1-_xlpm.tx)+_xlpm.dat-_xlpm.cpx+_xlpm.sb)-_xlpm.nw*(_xlpm.rev-_xlpm.prv),_xlpm.pv,SUM(_xlpm.f/(1+_xlpm.w)^(_xlpm.t-0.5*_xlpm.m)),_xlpm.tv,INDEX(_xlpm.f,10)*(1+_xlpm.tgr)/(_xlpm.w-_xlpm.tgr)/(1+_xlpm.w)^10,(_xlpm.pv+_xlpm.tv+_xlpm.nc)/_xlpm.shs)}
A76: Model check (closed-form recompute − table) | B76: {=_xlfn.LET(_xlpm.gs,$B$9,_xlpm.om,$B$10,_xlpm.w,$B$7,_xlpm.tgr,$B$8,_xlpm.n,$B$11,_xlpm.lcx,$B$19,_xlpm.r0,DCF!$B$37,_xlpm.om0,DCF!$B$39,_xlpm.cx0,DCF!$B$40,_xlpm.da0,DCF!$B$41,_xlpm.dar,DCF!$B$20,_xlpm.tx,DCF!$B$31,_xlpm.sb,DCF!$B$43,_xlpm.nw,DCF!$B$21,_xlpm.gd,N(DCF!$B$22),_xlpm.nc,DCF!$B$47,_xlpm.shs,DCF!$B$6,_xlpm.m,DCF!$B$48,_xlpm.t,_xlfn.SEQUENCE(10),_xlpm.g,_xlpm.gs-(_xlpm.gs-_xlpm.tgr)*(_xlpm.t-1)/9,_xlpm.cum,MMULT(--(_xlpm.t>=TRANSPOSE(_xlpm.t)),LN(1+_xlpm.g)),_xlpm.rev,_xlpm.r0*EXP(_xlpm.cum),_xlpm.prv,_xlpm.r0*EXP(_xlpm.cum-LN(1+_xlpm.g)),_xlpm.lp,IF(_xlpm.t>=_xlpm.n,1,_xlpm.t/_xlpm.n),_xlpm.omt,_xlpm.om0+(_xlpm.om-_xlpm.om0)*_xlpm.lp,_xlpm.dat,_xlpm.da0+(_xlpm.lcx*_xlpm.dar-_xlpm.da0)*_xlpm.lp,_xlpm.cpx,IF((_xlpm.t=1)*(_xlpm.gd>0),_xlpm.gd/_xlpm.rev,_xlpm.cx0+(_xlpm.lcx-_xlpm.cx0)*_xlpm.lp),_xlpm.f,_xlpm.rev*(_xlpm.omt*(1-_xlpm.tx)+_xlpm.dat-_xlpm.cpx+_xlpm.sb)-_xlpm.nw*(_xlpm.rev-_xlpm.prv),_xlpm.pv,SUM(_xlpm.f/(1+_xlpm.w)^(_xlpm.t-0.5*_xlpm.m)),_xlpm.tv,INDEX(_xlpm.f,10)*(1+_xlpm.tgr)/(_xlpm.w-_xlpm.tgr)/(1+_xlpm.w)^10,(_xlpm.pv+_xlpm.tv+_xlpm.nc)/_xlpm.shs)-B72} | C76: Should be 0.00 — the Scenarios and sensitivity grids use this closed form. | Q76: =Q75+0.005 | R76: {=_xlfn.LET(_xlpm.gs,Q76,_xlpm.om,$B$10,_xlpm.w,$B$7,_xlpm.tgr,$B$8,_xlpm.n,$B$11,_xlpm.lcx,$B$19,_xlpm.r0,DCF!$B$37,_xlpm.om0,DCF!$B$39,_xlpm.cx0,DCF!$B$40,_xlpm.da0,DCF!$B$41,_xlpm.dar,DCF!$B$20,_xlpm.tx,DCF!$B$31,_xlpm.sb,DCF!$B$43,_xlpm.nw,DCF!$B$21,_xlpm.gd,N(DCF!$B$22),_xlpm.nc,DCF!$B$47,_xlpm.shs,DCF!$B$6,_xlpm.m,DCF!$B$48,_xlpm.t,_xlfn.SEQUENCE(10),_xlpm.g,_xlpm.gs-(_xlpm.gs-_xlpm.tgr)*(_xlpm.t-1)/9,_xlpm.cum,MMULT(--(_xlpm.t>=TRANSPOSE(_xlpm.t)),LN(1+_xlpm.g)),_xlpm.rev,_xlpm.r0*EXP(_xlpm.cum),_xlpm.prv,_xlpm.r0*EXP(_xlpm.cum-LN(1+_xlpm.g)),_xlpm.lp,IF(_xlpm.t>=_xlpm.n,1,_xlpm.t/_xlpm.n),_xlpm.omt,_xlpm.om0+(_xlpm.om-_xlpm.om0)*_xlpm.lp,_xlpm.dat,_xlpm.da0+(_xlpm.lcx*_xlpm.dar-_xlpm.da0)*_xlpm.lp,_xlpm.cpx,IF((_xlpm.t=1)*(_xlpm.gd>0),_xlpm.gd/_xlpm.rev,_xlpm.cx0+(_xlpm.lcx-_xlpm.cx0)*_xlpm.lp),_xlpm.f,_xlpm.rev*(_xlpm.omt*(1-_xlpm.tx)+_xlpm.dat-_xlpm.cpx+_xlpm.sb)-_xlpm.nw*(_xlpm.rev-_xlpm.prv),_xlpm.pv,SUM(_xlpm.f/(1+_xlpm.w)^(_xlpm.t-0.5*_xlpm.m)),_xlpm.tv,INDEX(_xlpm.f,10)*(1+_xlpm.tgr)/(_xlpm.w-_xlpm.tgr)/(1+_xlpm.w)^10,(_xlpm.pv+_xlpm.tv+_xlpm.nc)/_xlpm.shs)} | S76: =S75+0.005 | T76: {=_xlfn.LET(_xlpm.gs,$B$9,_xlpm.om,S76,_xlpm.w,$B$7,_xlpm.tgr,$B$8,_xlpm.n,$B$11,_xlpm.lcx,$B$19,_xlpm.r0,DCF!$B$37,_xlpm.om0,DCF!$B$39,_xlpm.cx0,DCF!$B$40,_xlpm.da0,DCF!$B$41,_xlpm.dar,DCF!$B$20,_xlpm.tx,DCF!$B$31,_xlpm.sb,DCF!$B$43,_xlpm.nw,DCF!$B$21,_xlpm.gd,N(DCF!$B$22),_xlpm.nc,DCF!$B$47,_xlpm.shs,DCF!$B$6,_xlpm.m,DCF!$B$48,_xlpm.t,_xlfn.SEQUENCE(10),_xlpm.g,_xlpm.gs-(_xlpm.gs-_xlpm.tgr)*(_xlpm.t-1)/9,_xlpm.cum,MMULT(--(_xlpm.t>=TRANSPOSE(_xlpm.t)),LN(1+_xlpm.g)),_xlpm.rev,_xlpm.r0*EXP(_xlpm.cum),_xlpm.prv,_xlpm.r0*EXP(_xlpm.cum-LN(1+_xlpm.g)),_xlpm.lp,IF(_xlpm.t>=_xlpm.n,1,_xlpm.t/_xlpm.n),_xlpm.omt,_xlpm.om0+(_xlpm.om-_xlpm.om0)*_xlpm.lp,_xlpm.dat,_xlpm.da0+(_xlpm.lcx*_xlpm.dar-_xlpm.da0)*_xlpm.lp,_xlpm.cpx,IF((_xlpm.t=1)*(_xlpm.gd>0),_xlpm.gd/_xlpm.rev,_xlpm.cx0+(_xlpm.lcx-_xlpm.cx0)*_xlpm.lp),_xlpm.f,_xlpm.rev*(_xlpm.omt*(1-_xlpm.tx)+_xlpm.dat-_xlpm.cpx+_xlpm.sb)-_xlpm.nw*(_xlpm.rev-_xlpm.prv),_xlpm.pv,SUM(_xlpm.f/(1+_xlpm.w)^(_xlpm.t-0.5*_xlpm.m)),_xlpm.tv,INDEX(_xlpm.f,10)*(1+_xlpm.tgr)/(_xlpm.w-_xlpm.tgr)/(1+_xlpm.w)^10,(_xlpm.pv+_xlpm.tv+_xlpm.nc)/_xlpm.shs)} | U76: =U75-0.0025 | V76: {=_xlfn.LET(_xlpm.gs,$B$9,_xlpm.om,$B$10,_xlpm.w,$B$7,_xlpm.tgr,$B$8,_xlpm.n,$B$11,_xlpm.lcx,U76,_xlpm.r0,DCF!$B$37,_xlpm.om0,DCF!$B$39,_xlpm.cx0,DCF!$B$40,_xlpm.da0,DCF!$B$41,_xlpm.dar,DCF!$B$20,_xlpm.tx,DCF!$B$31,_xlpm.sb,DCF!$B$43,_xlpm.nw,DCF!$B$21,_xlpm.gd,N(DCF!$B$22),_xlpm.nc,DCF!$B$47,_xlpm.shs,DCF!$B$6,_xlpm.m,DCF!$B$48,_xlpm.t,_xlfn.SEQUENCE(10),_xlpm.g,_xlpm.gs-(_xlpm.gs-_xlpm.tgr)*(_xlpm.t-1)/9,_xlpm.cum,MMULT(--(_xlpm.t>=TRANSPOSE(_xlpm.t)),LN(1+_xlpm.g)),_xlpm.rev,_xlpm.r0*EXP(_xlpm.cum),_xlpm.prv,_xlpm.r0*EXP(_xlpm.cum-LN(1+_xlpm.g)),_xlpm.lp,IF(_xlpm.t>=_xlpm.n,1,_xlpm.t/_xlpm.n),_xlpm.omt,_xlpm.om0+(_xlpm.om-_xlpm.om0)*_xlpm.lp,_xlpm.dat,_xlpm.da0+(_xlpm.lcx*_xlpm.dar-_xlpm.da0)*_xlpm.lp,_xlpm.cpx,IF((_xlpm.t=1)*(_xlpm.gd>0),_xlpm.gd/_xlpm.rev,_xlpm.cx0+(_xlpm.lcx-_xlpm.cx0)*_xlpm.lp),_xlpm.f,_xlpm.rev*(_xlpm.omt*(1-_xlpm.tx)+_xlpm.dat-_xlpm.cpx+_xlpm.sb)-_xlpm.nw*(_xlpm.rev-_xlpm.prv),_xlpm.pv,SUM(_xlpm.f/(1+_xlpm.w)^(_xlpm.t-0.5*_xlpm.m)),_xlpm.tv,INDEX(_xlpm.f,10)*(1+_xlpm.tgr)/(_xlpm.w-_xlpm.tgr)/(1+_xlpm.w)^10,(_xlpm.pv+_xlpm.tv+_xlpm.nc)/_xlpm.shs)}
